Workbook
Name ds: OFFSET(#REF!,0,0,COUNTA(#REF!)-1)
Name ds: OFFSET(#REF!,0,0,COUNTA(#REF!)-1)
Name ds: OFFSET(#REF!,0,0,COUNTA(#REF!)-1)
Name ds: OFFSET(#REF!,0,0,COUNTA(#REF!)-1)
Name ds: OFFSET(#REF!,0,0,COUNTA(#REF!)-1)
Name F: #N/A
Name GraphAA: OFFSET(#REF!,0,0,COUNTA(#REF!)-1)
Name GraphAA: OFFSET(#REF!,0,0,COUNTA(#REF!)-1)
Name GraphAA: OFFSET(#REF!,0,0,COUNTA(#REF!)-1)
Name GraphAA: OFFSET(#REF!,0,0,COUNTA(#REF!)-1)
Name GraphAA: OFFSET(#REF!,0,0,COUNTA(#REF!)-1)
Name GraphBB: OFFSET(#REF!,0,0,COUNTA(#REF!)-1)
Name GraphBB: OFFSET(#REF!,0,0,COUNTA(#REF!)-1)
Name GraphBB: OFFSET(#REF!,0,0,COUNTA(#REF!)-1)
Name GraphBB: OFFSET(#REF!,0,0,COUNTA(#REF!)-1)
Name GraphBB: OFFSET(#REF!,0,0,COUNTA(#REF!)-1)
Name GraphCC: OFFSET(#REF!,0,0,COUNTA(#REF!)-1)
Name GraphCC: OFFSET(#REF!,0,0,COUNTA(#REF!)-1)
Name GraphCC: OFFSET(#REF!,0,0,COUNTA(#REF!)-1)
Name GraphCC: OFFSET(#REF!,0,0,COUNTA(#REF!)-1)
Name GraphCC: OFFSET(#REF!,0,0,COUNTA(#REF!)-1)
Name GraphDD: OFFSET(#REF!,0,0,COUNTA(#REF!)-1)
Name GraphDD: OFFSET(#REF!,0,0,COUNTA(#REF!)-1)
Name GraphDD: OFFSET(#REF!,0,0,COUNTA(#REF!)-1)
Name GraphDD: OFFSET(#REF!,0,0,COUNTA(#REF!)-1)
Name GraphDD: OFFSET(#REF!,0,0,COUNTA(#REF!)-1)
Name GraphEE: OFFSET(#REF!,0,0,COUNTA(#REF!)-1)
Name GraphEE: OFFSET(#REF!,0,0,COUNTA(#REF!)-1)
Name GraphEE: OFFSET(#REF!,0,0,COUNTA(#REF!)-1)
Name GraphEE: OFFSET(#REF!,0,0,COUNTA(#REF!)-1)
Name GraphEE: OFFSET(#REF!,0,0,COUNTA(#REF!)-1)
Name GraphFF: OFFSET(#REF!,0,0,COUNTA(#REF!)-1)
Name GraphFF: OFFSET(#REF!,0,0,COUNTA(#REF!)-1)
Name GraphFF: OFFSET(#REF!,0,0,COUNTA(#REF!)-1)
Name GraphFF: OFFSET(#REF!,0,0,COUNTA(#REF!)-1)
Name GraphFF: OFFSET(#REF!,0,0,COUNTA(#REF!)-1)
Name GraphGG: OFFSET(#REF!,0,0,COUNTA(#REF!)-1)
Name GraphGG: OFFSET(#REF!,0,0,COUNTA(#REF!)-1)
Name GraphGG: OFFSET(#REF!,0,0,COUNTA(#REF!)-1)
Name GraphGG: OFFSET(#REF!,0,0,COUNTA(#REF!)-1)
Name GraphGG: OFFSET(#REF!,0,0,COUNTA(#REF!)-1)
Name GraphHH: OFFSET(#REF!,0,0,COUNTA(#REF!)-1)
Name GraphHH: OFFSET(#REF!,0,0,COUNTA(#REF!)-1)
Name GraphHH: OFFSET(#REF!,0,0,COUNTA(#REF!)-1)
Name GraphHH: OFFSET(#REF!,0,0,COUNTA(#REF!)-1)
Name GraphHH: OFFSET(#REF!,0,0,COUNTA(#REF!)-1)
Name GraphII: OFFSET(#REF!,0,0,COUNTA(#REF!)-1)
Name GraphII: OFFSET(#REF!,0,0,COUNTA(#REF!)-1)
Name GraphII: OFFSET(#REF!,0,0,COUNTA(#REF!)-1)
Name GraphII: OFFSET(#REF!,0,0,COUNTA(#REF!)-1)
Name GraphII: OFFSET(#REF!,0,0,COUNTA(#REF!)-1)
Name GraphJJ: OFFSET(#REF!,0,0,COUNTA(#REF!)-1)
Name GraphJJ: OFFSET(#REF!,0,0,COUNTA(#REF!)-1)
Name GraphJJ: OFFSET(#REF!,0,0,COUNTA(#REF!)-1)
Name GraphJJ: OFFSET(#REF!,0,0,COUNTA(#REF!)-1)
Name GraphJJ: OFFSET(#REF!,0,0,COUNTA(#REF!)-1)
Name GraphKK: OFFSET(#REF!,0,0,COUNTA(#REF!)-1)
Name GraphKK: OFFSET(#REF!,0,0,COUNTA(#REF!)-1)
Name GraphKK: OFFSET(#REF!,0,0,COUNTA(#REF!)-1)
Name GraphKK: OFFSET(#REF!,0,0,COUNTA(#REF!)-1)

Sheet IC&CF&BS
B1: איי.סי.אל (כימיקלים לישראל)
A2: רוה"ס | C2: FY 2024 | D2: FY 2023 | E2: FY 2022 | F2: FY 2021 | G2: FY 2020 | H2: FY 2019 | I2: FY 2018 | J2: FY 2017 | K2: FY 2016 | L2: FY 2015 | M2: FY 2014 | O2: Q2 2025 | P2: Q1 2025 | Q2: Q4 2024 | R2: Q3 2024 | S2: Q2 2024 | T2: Q1 2024 | U2: Q4 2023 | V2: Q3 2023 | W2: Q2 2023 | X2: Q1 2023 | Y2: Q4 2022 | Z2: Q3 2022 | AA2: Q2 2022 | AB2: Q1 2022 | AC2: Q4 2021 | AD2: Q3 2021 | AE2: Q2 2021 | AF2: Q1 2021 | AG2: Q4 2020 | AH2: Q3 2020 | AI2: Q2 2020 | AJ2: Q1 2020 | AK2: Q4 2019 | AL2: Q3 2019 | AM2: Q2 2019 | AN2: Q1 2019 | AO2: Q4 2018 | AP2: Q3 2018 | AQ2: Q2 2018 | AR2: Q1 2018
B3: הכנסות מביצוע עבודות, ממכירות וממתן שירותים | C3: 6841 | D3: 7536 | E3: 10015 | F3: 6955 | G3: 5043 | H3: 5271 | I3: 5556 | J3: 5418 | K3: 5363 | L3: 5405 | M3: 6111 | O3: 1832 | P3: 1767 | Q3: =C3-R3-S3-T3 -> 1601 | R3: 1753 | S3: 1752 | T3: 1735 | U3: =D3-V3-W3-X3 -> 1742 | V3: 1862 | W3: 1834 | X3: 2098 | Y3: =E3-Z3-AA3-AB3 -> 2091 | Z3: 2519 | AA3: 2880 | AB3: 2525 | AC3: =F3-AD3-AE3-AF3 -> 2038 | AD3: 1790 | AE3: 1617 | AF3: 1510 | AG3: =G3-AH3-AI3-AJ3 -> 1317 | AH3: 1204 | AI3: 1203 | AJ3: 1319 | AK3: =H3-AL3-AM3-AN3 -> 1106 | AL3: 1325 | AM3: 1425 | AN3: 1415 | AO3: =I3-AP3-AQ3-AR3 -> 1410 | AP3: 1371 | AQ3: 1371 | AR3: 1404
B4: עלות העבודות השירותים ומתן המכירות, העבודות | C4: -4585 | D4: -4865 | E4: -4983 | F4: -4344 | G4: -3553 | H4: -3454 | I4: -3702 | J4: -3746 | K4: -3703 | L4: -3602 | M4: -3915 | O4: -1278 | P4: -1207 | Q4: =C4-R4-S4-T4 -> -1066 | R4: -1157 | S4: -1184 | T4: -1178 | U4: =D4-V4-W4-X4 -> -1130 | V4: -1276 | W4: -1189 | X4: -1270 | Y4: =E4-Z4-AA4-AB4 -> -1158 | Z4: -1204 | AA4: -1341 | AB4: -1280 | AC4: =F4-AD4-AE4-AF4 -> -1181 | AD4: -1101 | AE4: -1047 | AF4: -1015 | AG4: =G4-AH4-AI4-AJ4 -> -912 | AH4: -839 | AI4: -883 | AJ4: -919 | AK4: =H4-AL4-AM4-AN4 -> -770 | AL4: -853 | AM4: -917 | AN4: -914 | AO4: =I4-AP4-AQ4-AR4 -> -903 | AP4: -913 | AQ4: -913 | AR4: -973
B5: רווח גולמי | C5: =C3+C4 -> 2256 | D5: =D3+D4 -> 2671 | E5: =E3+E4 -> 5032 | F5: =F3+F4 -> 2611 | G5: =G3+G4 -> 1490 | H5: =H3+H4 -> 1817 | I5: =I3+I4 -> 1854 | J5: =J3+J4 -> 1672 | ... M5: =M3+M4 -> 2196 | O5: =O3+O4 -> 554 | P5: =P3+P4 -> 560 | Q5: =Q3+Q4 -> 535 | R5: =R3+R4 -> 596 | S5: =S3+S4 -> 568 | T5: =T3+T4 -> 557 | U5: =U3+U4 -> 612 | V5: =V3+V4 -> 586 | ... AR5: =AR3+AR4 -> 431
B6: הוצאות מכירה ושיווק | C6: -1114 | D6: -1093 | E6: -1181 | F6: -1067 | G6: -766 | H6: -767 | I6: -798 | J6: -746 | K6: -722 | L6: -653 | M6: -839 | O6: -274 | P6: -268 | Q6: =C6-R6-S6-T6 -> -281 | R6: -280 | S6: -280 | T6: -273 | U6: =D6-V6-W6-X6 -> -286 | V6: -264 | W6: -279 | X6: -264 | Y6: =E6-Z6-AA6-AB6 -> -281 | Z6: -300 | AA6: -321 | AB6: -279 | AC6: =F6-AD6-AE6-AF6 -> -304 | AD6: -288 | AE6: -246 | AF6: -229 | AG6: =G6-AH6-AI6-AJ6 -> -204 | AH6: -191 | AI6: -183 | AJ6: -188 | AK6: =H6-AL6-AM6-AN6 -> -177 | AL6: -199 | AM6: -196 | AN6: -195 | AO6: =I6-AP6-AQ6-AR6 -> -210 | AP6: -191 | AQ6: -197 | AR6: -200
B7: הוצאות הנהלה וכלליות ואחרות | C7: -259 | D7: -260 | E7: -291 | F7: -276 | G7: -232 | H7: -254 | I7: -257 | J7: -261 | K7: -321 | L7: -350 | M7: -306 | O7: -72 | P7: -77 | Q7: =C7-R7-S7-T7 -> -68 | R7: -63 | S7: -64 | T7: -64 | U7: =D7-V7-W7-X7 -> -71 | V7: -66 | W7: -55 | X7: -68 | Y7: =E7-Z7-AA7-AB7 -> -78 | Z7: -70 | AA7: -74 | AB7: -69 | AC7: =F7-AD7-AE7-AF7 -> -78 | AD7: -69 | AE7: -67 | AF7: -62 | AG7: =G7-AH7-AI7-AJ7 -> -57 | AH7: -55 | AI7: -56 | AJ7: -64 | AK7: =H7-AL7-AM7-AN7 -> -64 | AL7: -62 | AM7: -65 | AN7: -63 | AO7: =I7-AP7-AQ7-AR7 -> -62 | AP7: -63 | AQ7: -62 | AR7: -70
B8: הוצאות מחקר ופיתוח | C8: -69 | D8: -71 | E8: -68 | F8: -64 | G8: -54 | H8: -50 | I8: -55 | J8: -55 | K8: -73 | L8: -74 | M8: -87 | O8: -19 | P8: -18 | Q8: =C8-R8-S8-T8 -> -19 | R8: -19 | S8: -14 | T8: -17 | U8: =D8-V8-W8-X8 -> -17 | V8: -17 | W8: -19 | X8: -18 | Y8: =E8-Z8-AA8-AB8 -> -15 | Z8: -18 | AA8: -17 | AB8: -18 | AC8: =F8-AD8-AE8-AF8 -> -19 | AD8: -16 | AE8: -14 | AF8: -15 | AG8: =G8-AH8-AI8-AJ8 -> -17 | AH8: -13 | AI8: -10 | AJ8: -14 | AK8: =H8-AL8-AM8-AN8 -> -12 | AL8: -13 | AM8: -12 | AN8: -13 | AO8: =I8-AP8-AQ8-AR8 -> -13 | AP8: -13 | AQ8: -15 | AR8: -14
B9: רווח תפעולי לפני הוצאות אחרות | C9: =SUM(C5:C8) -> 814 | D9: =SUM(D5:D8) -> 1247 | E9: =SUM(E5:E8) -> 3492 | F9: =SUM(F5:F8) -> 1204 | G9: =SUM(G5:G8) -> 438 | H9: =SUM(H5:H8) -> 746 | I9: =SUM(I5:I8) -> 744 | J9: =SUM(J5:J8) -> 610 | ... M9: =SUM(M5:M8) -> 964 | O9: =SUM(O5:O8) -> 189 | P9: =SUM(P5:P8) -> 197 | Q9: =SUM(Q5:Q8) -> 167 | R9: =SUM(R5:R8) -> 234 | S9: =SUM(S5:S8) -> 210 | T9: =SUM(T5:T8) -> 203 | U9: =SUM(U5:U8) -> 238 | V9: =SUM(V5:V8) -> 239 | ... AR9: =SUM(AR5:AR8) -> 147
B10: הכנסות (הוצאות) אחרות נטו | C10: =21-60 -> -39 | D10: =22-128 -> -106 | E10: =54-30 -> 24 | F10: =63-57 -> 6 | G10: =-256+20 -> -236 | H10: 10 | I10: =859-84 -> 775 | J10: =109-90 -> 19 | K10: =-618+71 -> -547 | L10: =250-211 -> 39 | M10: =-259+53 -> -206 | O10: =-11+3 -> -8 | P10: =-16+4 -> -12 | Q10: =C10-R10-S10-T10 -> -20 | R10: =-22+2 -> -20 | S10: =-2+3 -> 1 | T10: =3-3 -> 0 | U10: =D10-V10-W10-X10 -> -89 | V10: =2-14 -> -12 | W10: =10-2 -> 8 | X10: =3-16 -> -13 | Y10: =E10-Z10-AA10-AB10 -> -19 | Z10: 8 | AA10: =18-6 -> 12 | AB10: 23 | AC10: =F10-AD10-AE10-AF10 -> 5 | AD10: =14-9 -> 5 | AE10: =25-25 -> 0 | AF10: =-5+1 -> -4 | AG10: =G10-AH10-AI10-AJ10 -> 12 | AH10: -6 | AI10: =-244+4 -> -240 | AJ10: -2 | AK10: =H10-AL10-AM10-AN10 -> 5 | AL10: =5-2 -> 3 | AM10: =10-5 -> 5 | AN10: =13-16 -> -3 | AO10: =I10-AP10-AQ10-AR10 -> -56 | AP10: =19-14 -> 5 | AQ10: =-16+4 -> -12 | AR10: =846-8 -> 838
B11: הוצאות מימון | C11: -181 | D11: -259 | E11: -327 | F11: -216 | G11: -219 | H11: -220 | I11: -214 | J11: -229 | K11: -157 | L11: -160 | M11: -279 | O11: -98 | P11: -62 | Q11: =C11-R11-S11-T11 -> -16 | R11: -46 | S11: -59 | T11: -60 | U11: =D11-V11-W11-X11 -> -4 | V11: -79 | W11: =-89 -> -89 | X11: -87 | Y11: =E11-Z11-AA11-AB11 -> -65 | Z11: -57 | AA11: -138 | AB11: -67 | AC11: =F11-AD11-AE11-AF11 -> -38 | AD11: -54 | AE11: -64 | AF11: -60 | AG11: =G11-AH11-AI11-AJ11 -> -40 | AH11: -52 | AI11: -54 | AJ11: -73 | AK11: =H11-AL11-AM11-AN11 -> -25 | AL11: -67 | AM11: -49 | AN11: -79 | AO11: =I11-AP11-AQ11-AR11 -> -56 | AP11: -42 | AQ11: -76 | AR11: -40
B12: הכנסות מימון | C12: 41 | D12: 91 | E12: 214 | F12: 94 | G12: 61 | H12: 91 | I12: 56 | J12: 105 | K12: 25 | L12: 52 | M12: 122 | O12: 85 | P12: 25 | Q12: =C12-R12-S12-T12 -> -17 | R12: 7 | S12: 26 | T12: 25 | U12: =D12-V12-W12-X12 -> -29 | V12: 37 | W12: 40 | X12: 43 | Y12: =E12-Z12-AA12-AB12 -> 24 | Z12: 33 | AA12: 124 | AB12: 33 | AC12: =F12-AD12-AE12-AF12 -> 0 | AD12: 20 | AE12: 34 | AF12: 40 | AG12: =G12-AH12-AI12-AJ12 -> -6 | AH12: 23 | AI12: 23 | AJ12: 21 | AK12: =H12-AL12-AM12-AN12 -> 0 | AL12: 35 | AM12: 12 | AN12: 44 | AO12: =I12-AP12-AQ12-AR12 -> -10 | AP12: 19 | AQ12: 22 | AR12: 25
B13: הוצאות הכנסות מימון, נטו | C13: =SUM(C11:C12) -> -140 | D13: =SUM(D11:D12) -> -168 | E13: =SUM(E11:E12) -> -113 | F13: =SUM(F11:F12) -> -122 | G13: =SUM(G11:G12) -> -158 | H13: =SUM(H11:H12) -> -129 | I13: =SUM(I11:I12) -> -158 | J13: =SUM(J11:J12) -> -124 | ... M13: =SUM(M11:M12) -> -157 | O13: =SUM(O11:O12) -> -13 | P13: =SUM(P11:P12) -> -37 | Q13: =SUM(Q11:Q12) -> -33 | R13: =SUM(R11:R12) -> -39 | S13: =SUM(S11:S12) -> -33 | T13: =SUM(T11:T12) -> -35 | U13: =SUM(U11:U12) -> -33 | V13: =SUM(V11:V12) -> -42 | ... AR13: =SUM(AR11:AR12) -> -15
B14: חלק ברווחי כלולות | C14: 1 | D14: 1 | E14: 1 | F14: 4 | G14: 5 | H14: 1 | I14: 3 | J14: 0 | K14: 18 | L14: 11 | M14: 31 | O14: 0 | P14: 0 | Q14: =C14-R14-S14-T14 -> 0 | R14: 1 | S14: 0 | T14: 0 | U14: =D14-V14-W14-X14 -> 1 | V14: 0 | W14: 0 | X14: 0 | Y14: =E14-Z14-AA14-AB14 -> 1 | Z14: 0 | AA14: 0 | AB14: 0 | AC14: =F14-AD14-AE14-AF14 -> 3 | AD14: 0 | AE14: 1 | AF14: 0 | AG14: =G14-AH14-AI14-AJ14 -> 1 | AH14: 2 | AI14: 1 | AJ14: 1 | AL14: 0 | AM14: 1 | AN14: 0 | AP14: -1 | AQ14: 0 | AR14: 1
B15: רווח לפני מיסים | C15: =C9+C10+C13+C14 -> 636 | D15: =D9+D10+D13+D14 -> 974 | E15: =E9+E10+E13+E14 -> 3404 | F15: =F9+F10+F13+F14 -> 1092 | G15: =G9+G10+G13+G14 -> 49 | H15: =H9+H10+H13+H14 -> 628 | I15: =I9+I10+I13+I14 -> 1364 | J15: =J9+J10+J13+J14 -> 505 | ... M15: =M9+M10+M13+M14 -> 632 | O15: =O9+O10+O13+O14 -> 168 | P15: =P9+P10+P13+P14 -> 148 | Q15: =Q9+Q10+Q13+Q14 -> 114 | R15: =R9+R10+R13+R14 -> 176 | S15: =S9+S10+S13+S14 -> 178 | T15: =T9+T10+T13+T14 -> 168 | U15: =U9+U10+U13+U14 -> 117 | V15: =V9+V10+V13+V14 -> 185 | ... AR15: =AR9+AR10+AR13+AR14 -> 971
B16: מיסים על הכנסה | C16: -172 | D16: -287 | E16: -1185 | F16: -260 | G16: -25 | H16: -147 | I16: -129 | J16: -158 | K16: -55 | L16: -162 | M16: -166 | O16: -60 | P16: -42 | Q16: =C16-R16-S16-T16 -> -33 | R16: -49 | S16: -48 | T16: -42 | U16: =D16-V16-W16-X16 -> -33 | V16: -43 | W16: -84 | X16: -127 | Y16: =E16-Z16-AA16-AB16 -> -158 | Z16: -276 | AA16: -540 | AB16: -211 | AC16: =F16-AD16-AE16-AF16 -> -128 | AD16: -45 | AE16: -64 | AF16: -23 | AG16: =G16-AH16-AI16-AJ16 -> -24 | AH16: -14 | AI16: 33 | AJ16: -20 | AK16: =H16-AL16-AM16-AN16 -> -15 | AL16: -35 | AM16: -46 | AN16: -51 | AO16: =I16-AP16-AQ16-AR16 -> -19 | AP16: -45 | AQ16: -20 | AR16: -45
B17: רווח נקי | C17: =SUM(C15:C16) -> 464 | D17: =SUM(D15:D16) -> 687 | E17: =SUM(E15:E16) -> 2219 | F17: =SUM(F15:F16) -> 832 | G17: =SUM(G15:G16) -> 24 | H17: =SUM(H15:H16) -> 481 | I17: =SUM(I15:I16) -> 1235 | J17: =SUM(J15:J16) -> 347 | ... M17: =SUM(M15:M16) -> 466 | O17: =SUM(O15:O16) -> 108 | P17: =SUM(P15:P16) -> 106 | Q17: =SUM(Q15:Q16) -> 81 | R17: =SUM(R15:R16) -> 127 | S17: =SUM(S15:S16) -> 130 | T17: =SUM(T15:T16) -> 126 | U17: =SUM(U15:U16) -> 84 | V17: =SUM(V15:V16) -> 142 | ... AR17: =SUM(AR15:AR16) -> 926
B19: רווח נקי המיוחס לבעלי המניות | C19: =C17-C20 -> 407 | D19: =D17-D20 -> 647 | E19: =E17-E20 -> 2159 | F19: =F17-F20 -> 783 | G19: =G17-G20 -> 11 | H19: =H17-H20 -> 475 | I19: =I17-I20 -> 1240 | J19: =J17-J20 -> 364 | ... M19: =M17-M20 -> 464 | O19: =O17-O20 -> 93 | P19: =P17-P20 -> 91 | Q19: =C19-R19-S19-T19 -> 70 | R19: =R17-R20 -> 113 | S19: =S17-S20 -> 115 | T19: =T17-T20 -> 109 | U19: =#REF!-V19-W19-X19 -> #REF! | V19: =V17-V20 -> 137 | W19: =W17-W20 -> 163 | X19: =X17-X20 -> 269 | Y19: =E19-Z19-AA19-AB19 -> 331 | Z19: =Z17-Z20 -> 633 | AA19: =AA17-AA20 -> 563 | AB19: =AB17-AB20 -> 632 | AC19: =F19-AD19-AE19-AF19 -> 283 | AD19: =AD17-AD20 -> 225 | AE19: =AE17-AE20 -> 140 | AF19: =AF17-AF20 -> 135 | AG19: =G19-AH19-AI19-AJ19 -> 65 | AH19: =AH17-AH20 -> 54 | AI19: =AI17-AI20 -> -168 | AJ19: =AJ17-AJ20 -> 60 | AK19: =AK17-AK20 -> 48 | AL19: =AL17-AL20 -> 130 | AM19: =AM17-AM20 -> 158 | AN19: =AN17-AN20 -> 139 | AO19: =AO17-AO20 -> 79 | ... AR19: =AR17-AR20 -> 928
B20: רווח נקי המיוחס לזכויות שאינם מקנות שליטה | C20: 57 | D20: 40 | E20: 60 | F20: 49 | G20: 13 | H20: 6 | I20: -5 | J20: -17 | K20: -50 | L20: -3 | M20: 2 | O20: 15 | P20: 15 | Q20: =C20-R20-S20-T20 -> 11 | R20: 14 | S20: 15 | T20: 17 | U20: =#REF!-V20-W20-X20 -> #REF! | V20: 5 | W20: 4 | X20: 25 | Y20: =E20-Z20-AA20-AB20 -> 11 | Z20: 2 | AA20: 22 | AB20: 25 | AC20: =F20-AD20-AE20-AF20 -> 15 | AD20: 17 | AE20: 10 | AF20: 7 | AG20: =G20-AH20-AI20-AJ20 -> 5 | AH20: 5 | AI20: 2 | AJ20: 1 | AK20: =H20-AL20-AM20-AN20 -> 0 | AL20: 4 | AM20: 0 | AN20: 2 | AO20: =I20-AP20-AQ20-AR20 -> 2 | AP20: -2 | AQ20: -3 | AR20: -2
B22: צמיחה בהכנסות | C22: =C3/D3-1 -> -0.092223992 | D22: =D3/E3-1 -> -0.24752871 | E22: =E3/F3-1 -> 0.43997124 | F22: =F3/G3-1 -> 0.3791394 | G22: =G3/H3-1 -> -0.043255549 | H22: =H3/I3-1 -> -0.051295896 | I22: =I3/J3-1 -> 0.025470653 | J22: =J3/K3-1 -> 0.010255454 | ... L22: =L3/M3-1 -> -0.11552937 | O22: =O3/P3-1 -> 0.036785512 | P22: =P3/Q3-1 -> 0.1036852 | Q22: =Q3/R3-1 -> -0.0867085 | R22: =R3/S3-1 -> 0.00057077626 | S22: =S3/T3-1 -> 0.0097982709 | T22: =T3/U3-1 -> -0.0040183697 | U22: =U3/V3-1 -> -0.064446831 | V22: =V3/W3-1 -> 0.015267176 | ... AQ22: =AQ3/AR3-1 -> -0.023504274
B24: שיעור מסך הכנסות
B25: =B4 -> עלות העבודות השירותים ומתן המכירות, העבודות | C25: =IFERROR(IF(-C4/C$3<0,C4/C$3,-C4/C$3),"") -> 0.67022365 | D25: =IFERROR(IF(-D4/D$3<0,D4/D$3,-D4/D$3),"") -> 0.64556794 | E25: =IFERROR(IF(-E4/E$3<0,E4/E$3,-E4/E$3),"") -> 0.49755367 | F25: =IFERROR(IF(-F4/F$3<0,F4/F$3,-F4/F$3),"") -> 0.62458663 | G25: =IFERROR(IF(-G4/G$3<0,G4/G$3,-G4/G$3),"") -> 0.70454095 | H25: =IFERROR(IF(-H4/H$3<0,H4/H$3,-H4/H$3),"") -> 0.65528363 | I25: =IFERROR(IF(-I4/I$3<0,I4/I$3,-I4/I$3),"") -> 0.6663067 | J25: =IFERROR(IF(-J4/J$3<0,J4/J$3,-J4/J$3),"") -> 0.69139904 | ... M25: =IFERROR(IF(-M4/M$3<0,M4/M$3,-M4/M$3),"") -> 0.64064801 | O25: =IFERROR(IF(-O4/O$3<0,O4/O$3,-O4/O$3),"") -> 0.69759825 | P25: =IFERROR(IF(-P4/P$3<0,P4/P$3,-P4/P$3),"") -> 0.68307866 | Q25: =IFERROR(IF(-Q4/Q$3<0,Q4/Q$3,-Q4/Q$3),"") -> 0.66583385 | R25: =IFERROR(IF(-R4/R$3<0,R4/R$3,-R4/R$3),"") -> 0.66001141 | S25: =IFERROR(IF(-S4/S$3<0,S4/S$3,-S4/S$3),"") -> 0.67579909 | T25: =IFERROR(IF(-T4/T$3<0,T4/T$3,-T4/T$3),"") -> 0.67896254 | U25: =IFERROR(IF(-U4/U$3<0,U4/U$3,-U4/U$3),"") -> 0.64867968 | V25: =IFERROR(IF(-V4/V$3<0,V4/V$3,-V4/V$3),"") -> 0.68528464 | ... AR25: =IFERROR(IF(-AR4/AR$3<0,AR4/AR$3,-AR4/AR$3),"") -> 0.69301994
B26: =B5 -> רווח גולמי | C26: =IFERROR(IF(-C5/C$3<0,C5/C$3,-C5/C$3),"") -> 0.32977635 | D26: =IFERROR(IF(-D5/D$3<0,D5/D$3,-D5/D$3),"") -> 0.35443206 | E26: =IFERROR(IF(-E5/E$3<0,E5/E$3,-E5/E$3),"") -> 0.50244633 | F26: =IFERROR(IF(-F5/F$3<0,F5/F$3,-F5/F$3),"") -> 0.37541337 | G26: =IFERROR(IF(-G5/G$3<0,G5/G$3,-G5/G$3),"") -> 0.29545905 | H26: =IFERROR(IF(-H5/H$3<0,H5/H$3,-H5/H$3),"") -> 0.34471637 | I26: =IFERROR(IF(-I5/I$3<0,I5/I$3,-I5/I$3),"") -> 0.3336933 | J26: =IFERROR(IF(-J5/J$3<0,J5/J$3,-J5/J$3),"") -> 0.30860096 | ... M26: =IFERROR(IF(-M5/M$3<0,M5/M$3,-M5/M$3),"") -> 0.35935199 | O26: =IFERROR(IF(-O5/O$3<0,O5/O$3,-O5/O$3),"") -> 0.30240175 | P26: =IFERROR(IF(-P5/P$3<0,P5/P$3,-P5/P$3),"") -> 0.31692134 | Q26: =IFERROR(IF(-Q5/Q$3<0,Q5/Q$3,-Q5/Q$3),"") -> 0.33416615 | R26: =IFERROR(IF(-R5/R$3<0,R5/R$3,-R5/R$3),"") -> 0.33998859 | S26: =IFERROR(IF(-S5/S$3<0,S5/S$3,-S5/S$3),"") -> 0.32420091 | T26: =IFERROR(IF(-T5/T$3<0,T5/T$3,-T5/T$3),"") -> 0.32103746 | U26: =IFERROR(IF(-U5/U$3<0,U5/U$3,-U5/U$3),"") -> 0.35132032 | V26: =IFERROR(IF(-V5/V$3<0,V5/V$3,-V5/V$3),"") -> 0.31471536 | ... AR26: =IFERROR(IF(-AR5/AR$3<0,AR5/AR$3,-AR5/AR$3),"") -> 0.30698006
B27: =B6 -> הוצאות מכירה ושיווק | C27: =IFERROR(IF(-C6/C$3<0,C6/C$3,-C6/C$3),"") -> 0.16284169 | D27: =IFERROR(IF(-D6/D$3<0,D6/D$3,-D6/D$3),"") -> 0.14503715 | E27: =IFERROR(IF(-E6/E$3<0,E6/E$3,-E6/E$3),"") -> 0.11792312 | F27: =IFERROR(IF(-F6/F$3<0,F6/F$3,-F6/F$3),"") -> 0.15341481 | G27: =IFERROR(IF(-G6/G$3<0,G6/G$3,-G6/G$3),"") -> 0.15189371 | H27: =IFERROR(IF(-H6/H$3<0,H6/H$3,-H6/H$3),"") -> 0.14551319 | I27: =IFERROR(IF(-I6/I$3<0,I6/I$3,-I6/I$3),"") -> 0.14362851 | J27: =IFERROR(IF(-J6/J$3<0,J6/J$3,-J6/J$3),"") -> 0.13768918 | ... M27: =IFERROR(IF(-M6/M$3<0,M6/M$3,-M6/M$3),"") -> 0.13729341 | O27: =IFERROR(IF(-O6/O$3<0,O6/O$3,-O6/O$3),"") -> 0.14956332 | P27: =IFERROR(IF(-P6/P$3<0,P6/P$3,-P6/P$3),"") -> 0.1516695 | Q27: =IFERROR(IF(-Q6/Q$3<0,Q6/Q$3,-Q6/Q$3),"") -> 0.1755153 | R27: =IFERROR(IF(-R6/R$3<0,R6/R$3,-R6/R$3),"") -> 0.15972618 | S27: =IFERROR(IF(-S6/S$3<0,S6/S$3,-S6/S$3),"") -> 0.15981735 | T27: =IFERROR(IF(-T6/T$3<0,T6/T$3,-T6/T$3),"") -> 0.1573487 | U27: =IFERROR(IF(-U6/U$3<0,U6/U$3,-U6/U$3),"") -> 0.1641791 | V27: =IFERROR(IF(-V6/V$3<0,V6/V$3,-V6/V$3),"") -> 0.14178303 | ... AR27: =IFERROR(IF(-AR6/AR$3<0,AR6/AR$3,-AR6/AR$3),"") -> 0.14245014
B28: =B7 -> הוצאות הנהלה וכלליות ואחרות | C28: =IFERROR(IF(-C7/C$3<0,C7/C$3,-C7/C$3),"") -> 0.037859962 | D28: =IFERROR(IF(-D7/D$3<0,D7/D$3,-D7/D$3),"") -> 0.034501062 | E28: =IFERROR(IF(-E7/E$3<0,E7/E$3,-E7/E$3),"") -> 0.029056415 | F28: =IFERROR(IF(-F7/F$3<0,F7/F$3,-F7/F$3),"") -> 0.039683681 | G28: =IFERROR(IF(-G7/G$3<0,G7/G$3,-G7/G$3),"") -> 0.046004362 | H28: =IFERROR(IF(-H7/H$3<0,H7/H$3,-H7/H$3),"") -> 0.0481882 | I28: =IFERROR(IF(-I7/I$3<0,I7/I$3,-I7/I$3),"") -> 0.046256299 | J28: =IFERROR(IF(-J7/J$3<0,J7/J$3,-J7/J$3),"") -> 0.048172757 | ... M28: =IFERROR(IF(-M7/M$3<0,M7/M$3,-M7/M$3),"") -> 0.050073638 | O28: =IFERROR(IF(-O7/O$3<0,O7/O$3,-O7/O$3),"") -> 0.03930131 | P28: =IFERROR(IF(-P7/P$3<0,P7/P$3,-P7/P$3),"") -> 0.043576684 | Q28: =IFERROR(IF(-Q7/Q$3<0,Q7/Q$3,-Q7/Q$3),"") -> 0.042473454 | R28: =IFERROR(IF(-R7/R$3<0,R7/R$3,-R7/R$3),"") -> 0.035938391 | S28: =IFERROR(IF(-S7/S$3<0,S7/S$3,-S7/S$3),"") -> 0.03652968 | T28: =IFERROR(IF(-T7/T$3<0,T7/T$3,-T7/T$3),"") -> 0.036887608 | U28: =IFERROR(IF(-U7/U$3<0,U7/U$3,-U7/U$3),"") -> 0.04075775 | V28: =IFERROR(IF(-V7/V$3<0,V7/V$3,-V7/V$3),"") -> 0.035445757 | ... AR28: =IFERROR(IF(-AR7/AR$3<0,AR7/AR$3,-AR7/AR$3),"") -> 0.04985755
B29: =B8 -> הוצאות מחקר ופיתוח | C29: =IFERROR(IF(-C8/C$3<0,C8/C$3,-C8/C$3),"") -> 0.010086245 | D29: =IFERROR(IF(-D8/D$3<0,D8/D$3,-D8/D$3),"") -> 0.0094214437 | E29: =IFERROR(IF(-E8/E$3<0,E8/E$3,-E8/E$3),"") -> 0.0067898153 | F29: =IFERROR(IF(-F8/F$3<0,F8/F$3,-F8/F$3),"") -> 0.0092020129 | G29: =IFERROR(IF(-G8/G$3<0,G8/G$3,-G8/G$3),"") -> 0.010707912 | H29: =IFERROR(IF(-H8/H$3<0,H8/H$3,-H8/H$3),"") -> 0.0094858661 | I29: =IFERROR(IF(-I8/I$3<0,I8/I$3,-I8/I$3),"") -> 0.0098992081 | J29: =IFERROR(IF(-J8/J$3<0,J8/J$3,-J8/J$3),"") -> 0.010151347 | ... M29: =IFERROR(IF(-M8/M$3<0,M8/M$3,-M8/M$3),"") -> 0.014236622 | O29: =IFERROR(IF(-O8/O$3<0,O8/O$3,-O8/O$3),"") -> 0.010371179 | P29: =IFERROR(IF(-P8/P$3<0,P8/P$3,-P8/P$3),"") -> 0.010186757 | Q29: =IFERROR(IF(-Q8/Q$3<0,Q8/Q$3,-Q8/Q$3),"") -> 0.011867583 | R29: =IFERROR(IF(-R8/R$3<0,R8/R$3,-R8/R$3),"") -> 0.010838562 | S29: =IFERROR(IF(-S8/S$3<0,S8/S$3,-S8/S$3),"") -> 0.0079908676 | T29: =IFERROR(IF(-T8/T$3<0,T8/T$3,-T8/T$3),"") -> 0.0097982709 | U29: =IFERROR(IF(-U8/U$3<0,U8/U$3,-U8/U$3),"") -> 0.0097588978 | V29: =IFERROR(IF(-V8/V$3<0,V8/V$3,-V8/V$3),"") -> 0.0091299678 | ... AR29: =IFERROR(IF(-AR8/AR$3<0,AR8/AR$3,-AR8/AR$3),"") -> 0.00997151
B30: =B10 -> הכנסות (הוצאות) אחרות נטו | C30: =IFERROR(IF(-C10/C$3<0,C10/C$3,-C10/C$3),"") -> 0.0057009209 | D30: =IFERROR(IF(-D10/D$3<0,D10/D$3,-D10/D$3),"") -> 0.014065817 | E30: =IFERROR(IF(-E10/E$3<0,E10/E$3,-E10/E$3),"") -> 0.0023964054 | F30: =IFERROR(IF(-F10/F$3<0,F10/F$3,-F10/F$3),"") -> 0.00086268871 | G30: =IFERROR(IF(-G10/G$3<0,G10/G$3,-G10/G$3),"") -> 0.046797541 | H30: =IFERROR(IF(-H10/H$3<0,H10/H$3,-H10/H$3),"") -> 0.0018971732 | I30: =IFERROR(IF(-I10/I$3<0,I10/I$3,-I10/I$3),"") -> 0.13948884 | J30: =IFERROR(IF(-J10/J$3<0,J10/J$3,-J10/J$3),"") -> 0.0035068291 | ... M30: =IFERROR(IF(-M10/M$3<0,M10/M$3,-M10/M$3),"") -> 0.033709704 | O30: =IFERROR(IF(-O10/O$3<0,O10/O$3,-O10/O$3),"") -> 0.0043668122 | P30: =IFERROR(IF(-P10/P$3<0,P10/P$3,-P10/P$3),"") -> 0.0067911715 | Q30: =IFERROR(IF(-Q10/Q$3<0,Q10/Q$3,-Q10/Q$3),"") -> 0.012492192 | R30: =IFERROR(IF(-R10/R$3<0,R10/R$3,-R10/R$3),"") -> 0.011409013 | S30: =IFERROR(IF(-S10/S$3<0,S10/S$3,-S10/S$3),"") -> 0.00057077626 | T30: =IFERROR(IF(-T10/T$3<0,T10/T$3,-T10/T$3),"") -> 0 | U30: =IFERROR(IF(-U10/U$3<0,U10/U$3,-U10/U$3),"") -> 0.0510907 | V30: =IFERROR(IF(-V10/V$3<0,V10/V$3,-V10/V$3),"") -> 0.0064446831 | ... AR30: =IFERROR(IF(-AR10/AR$3<0,AR10/AR$3,-AR10/AR$3),"") -> 0.5968661
C31: =IFERROR(IF(-#REF!/C$3<0,#REF!/C$3,-#REF!/C$3),"") | D31: =IFERROR(IF(-#REF!/D$3<0,#REF!/D$3,-#REF!/D$3),"") | E31: =IFERROR(IF(-#REF!/E$3<0,#REF!/E$3,-#REF!/E$3),"") | F31: =IFERROR(IF(-#REF!/F$3<0,#REF!/F$3,-#REF!/F$3),"") | G31: =IFERROR(IF(-#REF!/G$3<0,#REF!/G$3,-#REF!/G$3),"") | H31: =IFERROR(IF(-#REF!/H$3<0,#REF!/H$3,-#REF!/H$3),"") | I31: =IFERROR(IF(-#REF!/I$3<0,#REF!/I$3,-#REF!/I$3),"") | J31: =IFERROR(IF(-#REF!/J$3<0,#REF!/J$3,-#REF!/J$3),"") | ... M31: =IFERROR(IF(-#REF!/M$3<0,#REF!/M$3,-#REF!/M$3),"") | O31: =IFERROR(IF(-#REF!/O$3<0,#REF!/O$3,-#REF!/O$3),"") | P31: =IFERROR(IF(-#REF!/P$3<0,#REF!/P$3,-#REF!/P$3),"") | Q31: =IFERROR(IF(-#REF!/Q$3<0,#REF!/Q$3,-#REF!/Q$3),"") | R31: =IFERROR(IF(-#REF!/R$3<0,#REF!/R$3,-#REF!/R$3),"") | S31: =IFERROR(IF(-#REF!/S$3<0,#REF!/S$3,-#REF!/S$3),"") | T31: =IFERROR(IF(-#REF!/T$3<0,#REF!/T$3,-#REF!/T$3),"") | U31: =IFERROR(IF(-#REF!/U$3<0,#REF!/U$3,-#REF!/U$3),"") | V31: =IFERROR(IF(-#REF!/V$3<0,#REF!/V$3,-#REF!/V$3),"") | ... AR31: =IFERROR(IF(-#REF!/AR$3<0,#REF!/AR$3,-#REF!/AR$3),"")
B32: =B9 -> רווח תפעולי לפני הוצאות אחרות | C32: =IFERROR(IF(-C9/C$3<0,C9/C$3,-C9/C$3),"") -> 0.11898845 | D32: =IFERROR(IF(-D9/D$3<0,D9/D$3,-D9/D$3),"") -> 0.1654724 | E32: =IFERROR(IF(-E9/E$3<0,E9/E$3,-E9/E$3),"") -> 0.34867698 | F32: =IFERROR(IF(-F9/F$3<0,F9/F$3,-F9/F$3),"") -> 0.17311287 | G32: =IFERROR(IF(-G9/G$3<0,G9/G$3,-G9/G$3),"") -> 0.086853064 | H32: =IFERROR(IF(-H9/H$3<0,H9/H$3,-H9/H$3),"") -> 0.14152912 | I32: =IFERROR(IF(-I9/I$3<0,I9/I$3,-I9/I$3),"") -> 0.13390929 | J32: =IFERROR(IF(-J9/J$3<0,J9/J$3,-J9/J$3),"") -> 0.11258767 | ... M32: =IFERROR(IF(-M9/M$3<0,M9/M$3,-M9/M$3),"") -> 0.15774832 | O32: =IFERROR(IF(-O9/O$3<0,O9/O$3,-O9/O$3),"") -> 0.10316594 | P32: =IFERROR(IF(-P9/P$3<0,P9/P$3,-P9/P$3),"") -> 0.1114884 | Q32: =IFERROR(IF(-Q9/Q$3<0,Q9/Q$3,-Q9/Q$3),"") -> 0.10430981 | R32: =IFERROR(IF(-R9/R$3<0,R9/R$3,-R9/R$3),"") -> 0.13348545 | S32: =IFERROR(IF(-S9/S$3<0,S9/S$3,-S9/S$3),"") -> 0.11986301 | T32: =IFERROR(IF(-T9/T$3<0,T9/T$3,-T9/T$3),"") -> 0.11700288 | U32: =IFERROR(IF(-U9/U$3<0,U9/U$3,-U9/U$3),"") -> 0.13662457 | V32: =IFERROR(IF(-V9/V$3<0,V9/V$3,-V9/V$3),"") -> 0.12835661 | ... AR32: =IFERROR(IF(-AR9/AR$3<0,AR9/AR$3,-AR9/AR$3),"") -> 0.10470085
C33: =IFERROR(IF(-#REF!/C$3<0,#REF!/C$3,-#REF!/C$3),"") | D33: =IFERROR(IF(-#REF!/D$3<0,#REF!/D$3,-#REF!/D$3),"") | E33: =IFERROR(IF(-#REF!/E$3<0,#REF!/E$3,-#REF!/E$3),"") | F33: =IFERROR(IF(-#REF!/F$3<0,#REF!/F$3,-#REF!/F$3),"") | G33: =IFERROR(IF(-#REF!/G$3<0,#REF!/G$3,-#REF!/G$3),"") | H33: =IFERROR(IF(-#REF!/H$3<0,#REF!/H$3,-#REF!/H$3),"") | I33: =IFERROR(IF(-#REF!/I$3<0,#REF!/I$3,-#REF!/I$3),"") | J33: =IFERROR(IF(-#REF!/J$3<0,#REF!/J$3,-#REF!/J$3),"") | ... M33: =IFERROR(IF(-#REF!/M$3<0,#REF!/M$3,-#REF!/M$3),"") | O33: =IFERROR(IF(-#REF!/O$3<0,#REF!/O$3,-#REF!/O$3),"") | P33: =IFERROR(IF(-#REF!/P$3<0,#REF!/P$3,-#REF!/P$3),"") | Q33: =IFERROR(IF(-#REF!/Q$3<0,#REF!/Q$3,-#REF!/Q$3),"") | R33: =IFERROR(IF(-#REF!/R$3<0,#REF!/R$3,-#REF!/R$3),"") | S33: =IFERROR(IF(-#REF!/S$3<0,#REF!/S$3,-#REF!/S$3),"") | T33: =IFERROR(IF(-#REF!/T$3<0,#REF!/T$3,-#REF!/T$3),"") | U33: =IFERROR(IF(-#REF!/U$3<0,#REF!/U$3,-#REF!/U$3),"") | V33: =IFERROR(IF(-#REF!/V$3<0,#REF!/V$3,-#REF!/V$3),"") | ... AR33: =IFERROR(IF(-#REF!/AR$3<0,#REF!/AR$3,-#REF!/AR$3),"")
B34: =B11 -> הוצאות מימון | C34: =IFERROR(IF(-C11/C$3<0,C11/C$3,-C11/C$3),"") -> 0.02645812 | D34: =IFERROR(IF(-D11/D$3<0,D11/D$3,-D11/D$3),"") -> 0.034368365 | E34: =IFERROR(IF(-E11/E$3<0,E11/E$3,-E11/E$3),"") -> 0.032651023 | F34: =IFERROR(IF(-F11/F$3<0,F11/F$3,-F11/F$3),"") -> 0.031056794 | G34: =IFERROR(IF(-G11/G$3<0,G11/G$3,-G11/G$3),"") -> 0.043426532 | H34: =IFERROR(IF(-H11/H$3<0,H11/H$3,-H11/H$3),"") -> 0.041737811 | I34: =IFERROR(IF(-I11/I$3<0,I11/I$3,-I11/I$3),"") -> 0.038516919 | J34: =IFERROR(IF(-J11/J$3<0,J11/J$3,-J11/J$3),"") -> 0.042266519 | ... M34: =IFERROR(IF(-M11/M$3<0,M11/M$3,-M11/M$3),"") -> 0.045655376 | O34: =IFERROR(IF(-O11/O$3<0,O11/O$3,-O11/O$3),"") -> 0.05349345 | P34: =IFERROR(IF(-P11/P$3<0,P11/P$3,-P11/P$3),"") -> 0.035087719 | Q34: =IFERROR(IF(-Q11/Q$3<0,Q11/Q$3,-Q11/Q$3),"") -> 0.0099937539 | R34: =IFERROR(IF(-R11/R$3<0,R11/R$3,-R11/R$3),"") -> 0.02624073 | S34: =IFERROR(IF(-S11/S$3<0,S11/S$3,-S11/S$3),"") -> 0.033675799 | T34: =IFERROR(IF(-T11/T$3<0,T11/T$3,-T11/T$3),"") -> 0.034582133 | U34: =IFERROR(IF(-U11/U$3<0,U11/U$3,-U11/U$3),"") -> 0.0022962113 | V34: =IFERROR(IF(-V11/V$3<0,V11/V$3,-V11/V$3),"") -> 0.042427497 | ... AR34: =IFERROR(IF(-AR11/AR$3<0,AR11/AR$3,-AR11/AR$3),"") -> 0.028490028
B35: =B12 -> הכנסות מימון | C35: =IFERROR(IF(-C12/C$3<0,C12/C$3,-C12/C$3),"") -> 0.0059932758 | D35: =IFERROR(IF(-D12/D$3<0,D12/D$3,-D12/D$3),"") -> 0.012075372 | E35: =IFERROR(IF(-E12/E$3<0,E12/E$3,-E12/E$3),"") -> 0.021367948 | F35: =IFERROR(IF(-F12/F$3<0,F12/F$3,-F12/F$3),"") -> 0.013515457 | G35: =IFERROR(IF(-G12/G$3<0,G12/G$3,-G12/G$3),"") -> 0.012095975 | H35: =IFERROR(IF(-H12/H$3<0,H12/H$3,-H12/H$3),"") -> 0.017264276 | I35: =IFERROR(IF(-I12/I$3<0,I12/I$3,-I12/I$3),"") -> 0.010079194 | J35: =IFERROR(IF(-J12/J$3<0,J12/J$3,-J12/J$3),"") -> 0.019379845 | ... M35: =IFERROR(IF(-M12/M$3<0,M12/M$3,-M12/M$3),"") -> 0.019963999 | O35: =IFERROR(IF(-O12/O$3<0,O12/O$3,-O12/O$3),"") -> 0.04639738 | P35: =IFERROR(IF(-P12/P$3<0,P12/P$3,-P12/P$3),"") -> 0.014148274 | Q35: =IFERROR(IF(-Q12/Q$3<0,Q12/Q$3,-Q12/Q$3),"") -> 0.010618364 | R35: =IFERROR(IF(-R12/R$3<0,R12/R$3,-R12/R$3),"") -> 0.0039931546 | S35: =IFERROR(IF(-S12/S$3<0,S12/S$3,-S12/S$3),"") -> 0.014840183 | T35: =IFERROR(IF(-T12/T$3<0,T12/T$3,-T12/T$3),"") -> 0.014409222 | U35: =IFERROR(IF(-U12/U$3<0,U12/U$3,-U12/U$3),"") -> 0.016647532 | V35: =IFERROR(IF(-V12/V$3<0,V12/V$3,-V12/V$3),"") -> 0.019871106 | ... AR35: =IFERROR(IF(-AR12/AR$3<0,AR12/AR$3,-AR12/AR$3),"") -> 0.017806268
B36: =B13 -> הוצאות הכנסות מימון, נטו | C36: =IFERROR(IF(-C13/C$3<0,C13/C$3,-C13/C$3),"") -> 0.020464844 | D36: =IFERROR(IF(-D13/D$3<0,D13/D$3,-D13/D$3),"") -> 0.022292994 | E36: =IFERROR(IF(-E13/E$3<0,E13/E$3,-E13/E$3),"") -> 0.011283075 | F36: =IFERROR(IF(-F13/F$3<0,F13/F$3,-F13/F$3),"") -> 0.017541337 | G36: =IFERROR(IF(-G13/G$3<0,G13/G$3,-G13/G$3),"") -> 0.031330557 | H36: =IFERROR(IF(-H13/H$3<0,H13/H$3,-H13/H$3),"") -> 0.024473534 | I36: =IFERROR(IF(-I13/I$3<0,I13/I$3,-I13/I$3),"") -> 0.028437725 | J36: =IFERROR(IF(-J13/J$3<0,J13/J$3,-J13/J$3),"") -> 0.022886674 | ... M36: =IFERROR(IF(-M13/M$3<0,M13/M$3,-M13/M$3),"") -> 0.025691376 | O36: =IFERROR(IF(-O13/O$3<0,O13/O$3,-O13/O$3),"") -> 0.0070960699 | P36: =IFERROR(IF(-P13/P$3<0,P13/P$3,-P13/P$3),"") -> 0.020939445 | Q36: =IFERROR(IF(-Q13/Q$3<0,Q13/Q$3,-Q13/Q$3),"") -> 0.020612117 | R36: =IFERROR(IF(-R13/R$3<0,R13/R$3,-R13/R$3),"") -> 0.022247576 | S36: =IFERROR(IF(-S13/S$3<0,S13/S$3,-S13/S$3),"") -> 0.018835616 | T36: =IFERROR(IF(-T13/T$3<0,T13/T$3,-T13/T$3),"") -> 0.020172911 | U36: =IFERROR(IF(-U13/U$3<0,U13/U$3,-U13/U$3),"") -> 0.018943743 | V36: =IFERROR(IF(-V13/V$3<0,V13/V$3,-V13/V$3),"") -> 0.022556391 | ... AR36: =IFERROR(IF(-AR13/AR$3<0,AR13/AR$3,-AR13/AR$3),"") -> 0.010683761
B37: =B15 -> רווח לפני מיסים | C37: =IFERROR(IF(-C15/C$3<0,C15/C$3,-C15/C$3),"") -> 0.092968864 | D37: =IFERROR(IF(-D15/D$3<0,D15/D$3,-D15/D$3),"") -> 0.12924628 | E37: =IFERROR(IF(-E15/E$3<0,E15/E$3,-E15/E$3),"") -> 0.33989016 | F37: =IFERROR(IF(-F15/F$3<0,F15/F$3,-F15/F$3),"") -> 0.15700935 | G37: =IFERROR(IF(-G15/G$3<0,G15/G$3,-G15/G$3),"") -> 0.0097164386 | H37: =IFERROR(IF(-H15/H$3<0,H15/H$3,-H15/H$3),"") -> 0.11914248 | I37: =IFERROR(IF(-I15/I$3<0,I15/I$3,-I15/I$3),"") -> 0.24550036 | J37: =IFERROR(IF(-J15/J$3<0,J15/J$3,-J15/J$3),"") -> 0.093207826 | ... M37: =IFERROR(IF(-M15/M$3<0,M15/M$3,-M15/M$3),"") -> 0.10342006 | O37: =IFERROR(IF(-O15/O$3<0,O15/O$3,-O15/O$3),"") -> 0.091703057 | P37: =IFERROR(IF(-P15/P$3<0,P15/P$3,-P15/P$3),"") -> 0.083757782 | Q37: =IFERROR(IF(-Q15/Q$3<0,Q15/Q$3,-Q15/Q$3),"") -> 0.071205497 | R37: =IFERROR(IF(-R15/R$3<0,R15/R$3,-R15/R$3),"") -> 0.10039932 | S37: =IFERROR(IF(-S15/S$3<0,S15/S$3,-S15/S$3),"") -> 0.10159817 | T37: =IFERROR(IF(-T15/T$3<0,T15/T$3,-T15/T$3),"") -> 0.096829971 | U37: =IFERROR(IF(-U15/U$3<0,U15/U$3,-U15/U$3),"") -> 0.067164179 | V37: =IFERROR(IF(-V15/V$3<0,V15/V$3,-V15/V$3),"") -> 0.099355532 | ... AR37: =IFERROR(IF(-AR15/AR$3<0,AR15/AR$3,-AR15/AR$3),"") -> 0.69159544
B38: =B16 -> מיסים על הכנסה | C38: =IFERROR(IF(-C16/C$3<0,C16/C$3,-C16/C$3),"") -> 0.025142523 | D38: =IFERROR(IF(-D16/D$3<0,D16/D$3,-D16/D$3),"") -> 0.038083864 | E38: =IFERROR(IF(-E16/E$3<0,E16/E$3,-E16/E$3),"") -> 0.11832252 | F38: =IFERROR(IF(-F16/F$3<0,F16/F$3,-F16/F$3),"") -> 0.037383178 | G38: =IFERROR(IF(-G16/G$3<0,G16/G$3,-G16/G$3),"") -> 0.0049573666 | H38: =IFERROR(IF(-H16/H$3<0,H16/H$3,-H16/H$3),"") -> 0.027888446 | I38: =IFERROR(IF(-I16/I$3<0,I16/I$3,-I16/I$3),"") -> 0.023218143 | J38: =IFERROR(IF(-J16/J$3<0,J16/J$3,-J16/J$3),"") -> 0.029162052 | ... M38: =IFERROR(IF(-M16/M$3<0,M16/M$3,-M16/M$3),"") -> 0.02716413 | O38: =IFERROR(IF(-O16/O$3<0,O16/O$3,-O16/O$3),"") -> 0.032751092 | P38: =IFERROR(IF(-P16/P$3<0,P16/P$3,-P16/P$3),"") -> 0.0237691 | Q38: =IFERROR(IF(-Q16/Q$3<0,Q16/Q$3,-Q16/Q$3),"") -> 0.020612117 | R38: =IFERROR(IF(-R16/R$3<0,R16/R$3,-R16/R$3),"") -> 0.027952082 | S38: =IFERROR(IF(-S16/S$3<0,S16/S$3,-S16/S$3),"") -> 0.02739726 | T38: =IFERROR(IF(-T16/T$3<0,T16/T$3,-T16/T$3),"") -> 0.024207493 | U38: =IFERROR(IF(-U16/U$3<0,U16/U$3,-U16/U$3),"") -> 0.018943743 | V38: =IFERROR(IF(-V16/V$3<0,V16/V$3,-V16/V$3),"") -> 0.023093448 | ... AR38: =IFERROR(IF(-AR16/AR$3<0,AR16/AR$3,-AR16/AR$3),"") -> 0.032051282
B39: =B17 -> רווח נקי | C39: =IFERROR(IF(-C17/C$3<0,C17/C$3,-C17/C$3),"") -> 0.067826341 | D39: =IFERROR(IF(-D17/D$3<0,D17/D$3,-D17/D$3),"") -> 0.09116242 | E39: =IFERROR(IF(-E17/E$3<0,E17/E$3,-E17/E$3),"") -> 0.22156765 | F39: =IFERROR(IF(-F17/F$3<0,F17/F$3,-F17/F$3),"") -> 0.11962617 | G39: =IFERROR(IF(-G17/G$3<0,G17/G$3,-G17/G$3),"") -> 0.004759072 | H39: =IFERROR(IF(-H17/H$3<0,H17/H$3,-H17/H$3),"") -> 0.091254031 | I39: =IFERROR(IF(-I17/I$3<0,I17/I$3,-I17/I$3),"") -> 0.22228222 | J39: =IFERROR(IF(-J17/J$3<0,J17/J$3,-J17/J$3),"") -> 0.064045773 | ... M39: =IFERROR(IF(-M17/M$3<0,M17/M$3,-M17/M$3),"") -> 0.076255932 | O39: =IFERROR(IF(-O17/O$3<0,O17/O$3,-O17/O$3),"") -> 0.058951965 | P39: =IFERROR(IF(-P17/P$3<0,P17/P$3,-P17/P$3),"") -> 0.059988681 | Q39: =IFERROR(IF(-Q17/Q$3<0,Q17/Q$3,-Q17/Q$3),"") -> 0.050593379 | R39: =IFERROR(IF(-R17/R$3<0,R17/R$3,-R17/R$3),"") -> 0.072447233 | S39: =IFERROR(IF(-S17/S$3<0,S17/S$3,-S17/S$3),"") -> 0.074200913 | T39: =IFERROR(IF(-T17/T$3<0,T17/T$3,-T17/T$3),"") -> 0.072622478 | U39: =IFERROR(IF(-U17/U$3<0,U17/U$3,-U17/U$3),"") -> 0.048220436 | V39: =IFERROR(IF(-V17/V$3<0,V17/V$3,-V17/V$3),"") -> 0.076262084 | ... AR39: =IFERROR(IF(-AR17/AR$3<0,AR17/AR$3,-AR17/AR$3),"") -> 0.65954416
A43: תזרים מזומנים | C43: =C$2 -> FY 2024 | D43: =D$2 -> FY 2023 | E43: =E$2 -> FY 2022 | F43: =F$2 -> FY 2021 | G43: =G$2 -> FY 2020 | H43: =H$2 -> FY 2019 | I43: =I$2 -> FY 2018 | J43: =J$2 -> FY 2017 | ... M43: =M$2 -> FY 2014 | O43: =O$2 -> Q2 2025 | P43: =P$2 -> Q1 2025 | Q43: =Q$2 -> Q4 2024 | R43: =R$2 -> Q3 2024 | S43: =S$2 -> Q2 2024 | T43: =T$2 -> Q1 2024 | U43: =U$2 -> Q4 2023 | V43: =V$2 -> Q3 2023 | ... AR43: =AR$2 -> Q1 2018
B45: רווח נקי | C45: =C17 -> 464 | D45: =D17 -> 687 | E45: =E17 -> 2219 | F45: =F17 -> 832 | G45: =G17 -> 24 | H45: =H17 -> 481 | I45: =I17 -> 1235 | J45: =J17 -> 347 | ... M45: =M17 -> 466 | O45: =O17 -> 108 | P45: =P17 -> 106 | Q45: =Q17 -> 81 | R45: =R17 -> 127 | S45: =S17 -> 130 | T45: =T17 -> 126 | U45: =U17 -> 84 | V45: =V17 -> 142 | ... AR45: =AR17 -> 926
B46: פחת והפחתות | C46: 596 | D46: 536 | E46: 498 | F46: 490 | G46: 489 | H46: 443 | I46: 403 | J46: 390 | K46: 401 | L46: 430 | M46: 427 | O46: 150 | P46: 151 | Q46: =C46-R46-S46-T46 -> 157 | R46: 140 | S46: 152 | T46: 147 | U46: =D46-V46-W46-X46 -> 146 | V46: 119 | W46: 141 | X46: 130 | Y46: =E46-Z46-AA46-AB46 -> 136 | Z46: 121 | AA46: 119 | AB46: 122 | AC46: =F46-AD46-AE46-AF46 -> 126 | AD46: 123 | AE46: 124 | AF46: 117 | AG46: =G46-AH46-AI46-AJ46 -> 170 | AH46: 82 | AI46: 119 | AJ46: 118 | AK46: =H46-AL46-AM46-AN46 -> 113 | AL46: 110 | AM46: 109 | AN46: 111 | AP46: 94 | AQ46: 105 | AR46: 97
B47: (ביטול) הפסד מירידת ערך רכוש קבוע | C47: 14 | D47: 0 | E47: 0 | F47: -6 | G47: 90 | H47: -10 | I47: 17 | J47: 28 | K47: 5 | L47: -162 | M47: -23 | O47: 0 | P47: 0 | Q47: =C47-R47-S47-T47 -> 7 | R47: 7 | S47: 0 | T47: 0 | U47: =D47-V47-W47-X47 -> 0 | V47: 0 | W47: 0 | X47: 0 | Y47: =E47-Z47-AA47-AB47 -> 0 | Z47: 0 | AA47: 0 | AB47: 0 | AC47: =F47-AD47-AE47-AF47 -> 3 | AD47: 0 | AE47: -9 | AF47: 0 | AG47: =G47-AH47-AI47-AJ47 -> -41 | AH47: 0 | AI47: 131 | AJ47: 0 | AK47: =H47-AL47-AM47-AN47 -> 0 | AL47: 0 | AM47: -10 | AN47: 0 | AP47: 3 | AQ47: 14 | AR47: 0
B48: שערוך יתרות מוסדות פיננסים והוצאות ריבית נטו | C48: 152 | D48: 24 | E48: 157 | F48: 99 | G48: 88 | H48: 109 | I48: 35 | J48: 137 | K48: 76 | L48: 0 | M48: 0 | O48: -84 | P48: 44 | Q48: =C48-R48-S48-T48 -> 47 | R48: 9 | S48: 37 | T48: 59 | U48: =D48-V48-W48-X48 -> -51 | V48: 27 | W48: 30 | X48: 18 | Y48: =E48-Z48-AA48-AB48 -> -4 | Z48: 45 | AA48: 75 | AB48: 41 | AC48: =F48-AD48-AE48-AF48 -> 17 | AD48: 29 | AE48: 0 | AF48: 53 | AG48: =G48-AH48-AI48-AJ48 -> 32 | AH48: -7 | AI48: 32 | AJ48: 31 | AK48: =H48-AL48-AM48-AN48 -> -37 | AL48: 68 | AM48: 24 | AN48: 54 | AP48: 35 | AQ48: 38 | AR48: 0
B49: חלק ברווחי חברות מוחזקות (רווחי אקוויטי) | C49: 0 | D49: 0 | E49: 0 | F49: 0 | G49: 0 | H49: 0 | I49: -3 | J49: 0 | K49: -18 | L49: 0 | M49: 0 | O49: 0 | P49: 0 | Q49: =C49-R49-S49-T49 -> 0 | R49: 0 | S49: 0 | T49: 0 | U49: =D49-V49-W49-X49 -> 0 | V49: 0 | W49: 0 | X49: 0 | Y49: =E49-Z49-AA49-AB49 -> 0 | Z49: 0 | AA49: 0 | AB49: 0 | AC49: =F49-AD49-AE49-AF49 -> 0 | AD49: 0 | AE49: 0 | AF49: 0 | AG49: =G49-AH49-AI49-AJ49 -> 4 | AH49: -2 | AI49: -1 | AJ49: -1 | AK49: =H49-AL49-AM49-AN49 -> 1 | AL49: 0 | AM49: -1 | AN49: 0 | AP49: 1 | AQ49: 0 | AR49: -1
B50: רווח ממכירת עסקים | C50: 0 | D50: 0 | E50: 0 | F50: 0 | G50: 0 | H50: 0 | I50: -841 | J50: 0 | K50: 1 | L50: 0 | M50: 0 | O50: 0 | P50: 0 | Q50: =C50-R50-S50-T50 -> 0 | R50: 0 | S50: 0 | T50: 0 | U50: =D50-V50-W50-X50 -> 0 | V50: 0 | W50: 0 | X50: 0 | Y50: =E50-Z50-AA50-AB50 -> 0 | Z50: 0 | AA50: 0 | AB50: 0 | AC50: =F50-AD50-AE50-AF50 -> 0 | AD50: 0 | AE50: 0 | AF50: 0 | AG50: =G50-AH50-AI50-AJ50 -> -4 | AH50: 0 | AI50: 2 | AJ50: 2 | AK50: =H50-AL50-AM50-AN50 -> 0 | AL50: 0 | AM50: 0 | AN50: 0 | AP50: 0 | AQ50: 0 | AR50: -841
B51: רווח הון | C51: 0 | D51: 0 | E51: 0 | F51: 0 | G51: 0 | H51: 0 | I51: 0 | J51: -54 | K51: 432 | L51: 0 | M51: 0 | O51: 0 | P51: 0 | Q51: =C51-R51-S51-T51 -> 0 | R51: 0 | S51: 0 | T51: 0 | U51: =D51-V51-W51-X51 -> 0 | V51: 0 | W51: 0 | X51: 0 | Y51: =E51-Z51-AA51-AB51 -> 0 | Z51: 0 | AA51: 0 | AB51: 0 | AC51: =F51-AD51-AE51-AF51 -> 0 | AD51: 0 | AE51: 0 | AF51: 0 | AG51: =G51-AH51-AI51-AJ51 -> -1 | AH51: 0 | AI51: 1 | AJ51: 0 | AK51: =H51-AL51-AM51-AN51 -> 12 | AL51: 0 | AM51: 0 | AN51: -12 | AP51: 0 | AQ51: 0 | AR51: 0
B52: תשלום מבוסס מניות | C52: 0 | D52: 0 | E52: 0 | F52: 0 | G52: 0 | H52: 0 | I52: 19 | J52: 16 | K52: 15 | L52: 0 | M52: 0 | O52: 0 | P52: 0 | Q52: =C52-R52-S52-T52 -> 0 | R52: 0 | S52: 0 | T52: 0 | U52: =D52-V52-W52-X52 -> 0 | V52: 0 | W52: 0 | X52: 0 | Y52: =E52-Z52-AA52-AB52 -> 0 | Z52: 0 | AA52: 0 | AB52: 0 | AC52: =F52-AD52-AE52-AF52 -> 0 | AD52: 0 | AE52: 0 | AF52: 0 | AG52: =G52-AH52-AI52-AJ52 -> -7 | AH52: 2 | AI52: 2 | AJ52: 3 | AK52: =H52-AL52-AM52-AN52 -> -9 | AL52: 3 | AM52: 4 | AN52: 2 | AP52: 4 | AQ52: 5 | AR52: 8
B53: הוצאות מיסים נדחים | C53: 172 | D53: 287 | E53: 1185 | F53: 260 | G53: 25 | H53: 147 | I53: 76 | J53: -46 | K53: -2 | L53: 162 | M53: 166 | O53: 60 | P53: 42 | Q53: =C53-R53-S53-T53 -> 33 | R53: 49 | S53: 48 | T53: 42 | U53: =D53-V53-W53-X53 -> 33 | V53: 43 | W53: 84 | X53: 127 | Y53: =E53-Z53-AA53-AB53 -> 158 | Z53: 276 | AA53: 540 | AB53: 211 | AC53: =F53-AD53-AE53-AF53 -> 128 | AD53: 45 | AE53: 64 | AF53: 23 | AG53: =G53-AH53-AI53-AJ53 -> 67 | AH53: 0 | AI53: -48 | AJ53: 6 | AK53: =H53-AL53-AM53-AN53 -> 57 | AL53: 14 | AM53: 35 | AN53: 41 | AP53: 37 | AQ53: -1 | AR53: 28
B54: שינוי בהפרשות | C54: -50 | D54: -32 | E54: -83 | F54: -4 | G54: 113 | H54: -21 | I54: 0 | J54: 0 | K54: 0 | L54: 0 | O54: 7 | P54: -5 | Q54: =C54-R54-S54-T54 -> 3 | R54: 0 | S54: -11 | T54: -42 | U54: =D54-V54-W54-X54 -> 9 | V54: -13 | W54: -13 | X54: -15 | Y54: =E54-Z54-AA54-AB54 -> -8 | Z54: -16 | AA54: -41 | AB54: -18 | AC54: =F54-AD54-AE54-AF54 -> 9 | AD54: -4 | AE54: 12 | AF54: -21 | AG54: =G54-AH54-AI54-AJ54 -> 113
B55: אחר | C55: 13 | D55: 29 | E55: -15 | F55: -21 | G55: 5 | H55: -1 | I55: 0 | O55: 8 | P55: 3 | Q55: =C55-R55-S55-T55 -> 7 | R55: 2 | S55: 2 | T55: 2 | U55: =D55-V55-W55-X55 -> 22 | V55: 1 | W55: 2 | X55: 4 | Y55: =E55-Z55-AA55-AB55 -> 4 | Z55: -5 | AA55: 6 | AB55: -20 | AC55: =F55-AD55-AE55-AF55 -> -19 | AD55: -12 | AE55: 8 | AF55: 2 | AG55: =G55-AH55-AI55-AJ55 -> 5
B56: ריבית ששולמה | C56: =-122+17 -> -105 | D56: -115 | E56: -106 | F56: -89 | G56: -107 | H56: -114 | I56: 0 | J56: 0 | K56: 0 | L56: -86 | M56: -47 | O56: =-42+4 -> -38 | P56: =-16+3 -> -13 | Q56: =C56-R56-S56-T56 -> -40 | R56: =-16+4 -> -12 | S56: =-43+3 -> -40 | T56: -13 | U56: =D56-V56-W56-X56 -> -37 | V56: -19 | W56: -42 | X56: -17 | Y56: =E56-Z56-AA56-AB56 -> -38 | Z56: -13 | AA56: -39 | AB56: -16 | AC56: =F56-AD56-AE56-AF56 -> -16 | AD56: -18 | AE56: -37 | AF56: -18 | AG56: =G56-AH56-AI56-AJ56 -> -107
B57: מס הכנסה שהתקבל (שולם), נטו | C57: -98 | D57: -253 | E57: -1107 | F57: -193 | G57: -31 | H57: -120 | I57: 0 | J57: 0 | K57: 0 | L57: -20 | M57: -159 | O57: -37 | P57: -36 | Q57: =C57-R57-S57-T57 -> -41 | R57: -22 | S57: -29 | T57: -6 | U57: =D57-V57-W57-X57 -> -7 | V57: -32 | W57: -105 | X57: -109 | Y57: =E57-Z57-AA57-AB57 -> -160 | Z57: -420 | AA57: -395 | AB57: -132 | AC57: =F57-AD57-AE57-AF57 -> -105 | AD57: -67 | AE57: -28 | AF57: 7 | AG57: =G57-AH57-AI57-AJ57 -> -31
B58: תזרים מזומנים מפעילות שוטפת לפני תנועות בהון חוזר | C58: =SUM(C46:C57) -> 694 | D58: =SUM(D46:D57) -> 476 | E58: =SUM(E46:E57) -> 529 | F58: =SUM(F46:F57) -> 536 | G58: =SUM(G46:G57) -> 672 | H58: =SUM(H46:H57) -> 433 | I58: =SUM(I46:I57) -> -294 | J58: =SUM(J46:J57) -> 471 | ... M58: =SUM(M46:M57) -> 364 | O58: =SUM(O46:O57) -> 66 | P58: =SUM(P46:P57) -> 186 | Q58: =SUM(Q46:Q57) -> 173 | R58: =SUM(R46:R57) -> 173 | S58: =SUM(S46:S57) -> 159 | T58: =SUM(T46:T57) -> 189 | U58: =D58-V58-W58-X58 -> 115 | V58: =SUM(V46:V57) -> 126 | W58: =SUM(W46:W57) -> 97 | X58: =SUM(X46:X57) -> 138 | Y58: =SUM(Y46:Y57) -> 88 | Z58: =SUM(Z46:Z57) -> -12 | AA58: =SUM(AA46:AA57) -> 265 | AB58: =SUM(AB46:AB57) -> 188 | AC58: =SUM(AC46:AC57) -> 143 | ... AG58: =SUM(AG46:AG57) -> 200 | AH58: =SUM(AH46:AH53) -> 75 | AI58: =SUM(AI46:AI53) -> 238 | AJ58: =SUM(AJ46:AJ53) -> 159 | AK58: =SUM(AK46:AK53) -> 137 | AL58: =SUM(AL46:AL53) -> 195 | AM58: =SUM(AM46:AM53) -> 161 | AN58: =SUM(AN46:AN53) -> 196 | AO58: =SUM(AO46:AO53) -> 0 | ... AR58: =SUM(AR46:AR53) -> -709
B60: FFO תזרים מזומנים | C60: =C45+C58 -> 1158 | D60: =D45+D58 -> 1163 | E60: =E45+E58 -> 2748 | F60: =F45+F58 -> 1368 | G60: =G45+G58 -> 696 | H60: =H45+H58 -> 914 | I60: =I45+I58 -> 941 | J60: =J45+J58 -> 818 | ... M60: =M45+M58 -> 830 | O60: =O45+O58 -> 174 | P60: =P45+P58 -> 292 | Q60: =Q45+Q58 -> 254 | R60: =R45+R58 -> 300 | S60: =S45+S58 -> 289 | T60: =T45+T58 -> 315 | U60: =U45+U58 -> 199 | V60: =V45+V58 -> 268 | ... AR60: =AR45+AR58 -> 217
B62: שינויים בסעיפי רכוש והתחייבויות תפעוליים
B63: שינוי במלאי | C63: -7 | D63: 465 | E63: -527 | F63: -267 | G63: 54 | H63: -72 | I63: -115 | J63: 57 | K63: 70 | L63: 25 | M63: -33 | O63: -6 | P63: 28 | Q63: =C63-R63-S63-T63 -> -102 | R63: -14 | S63: 58 | T63: 51 | U63: =D63-V63-W63-X63 -> 50 | V63: 251 | W63: 113 | X63: 51 | Y63: =E63-Z63-AA63-AB63 -> -72 | Z63: -160 | AA63: -208 | AB63: -87 | AC63: =F63-AD63-AE63-AF63 -> -155 | AD63: -139 | AE63: -3 | AF63: 30 | AG63: =G63-AH63-AI63-AJ63 -> 2 | AH63: -10 | AI63: 34 | AJ63: 28 | AK63: =H63-AL63-AM63-AN63 -> -72 | AL63: -26 | AM63: 13 | AN63: 13 | AP63: -17 | AQ63: 0 | AR63: -42
B64: שינוי בלקוחות | C64: 26 | D64: 252 | E64: -215 | F64: -426 | G64: -89 | H64: 199 | I64: -104 | J64: 21 | K64: 150 | L64: -86 | M64: -25 | O64: 119 | P64: -202 | Q64: =C64-R64-S64-T64 -> 68 | R64: 73 | S64: 26 | T64: -141 | U64: =D64-V64-W64-X64 -> 47 | V64: -28 | W64: 268 | X64: -35 | Y64: =E64-Z64-AA64-AB64 -> 149 | Z64: 84 | AA64: 21 | AB64: -469 | AC64: =F64-AD64-AE64-AF64 -> -218 | AD64: -34 | AE64: -27 | AF64: -147 | AG64: =G64-AH64-AI64-AJ64 -> -47 | AH64: 33 | AI64: 111 | AJ64: -186 | AK64: =H64-AL64-AM64-AN64 -> 185 | AL64: 70 | AM64: 1 | AN64: -57 | AP64: 67 | AQ64: -96 | AR64: -44
B65: שינוי בספקים | C65: 104 | D65: -101 | E65: -42 | F65: 274 | G65: 84 | H65: -58 | I65: -36 | J65: -45 | K65: -90 | L65: -106 | M65: 55 | O65: 28 | P65: 31 | Q65: =C65-R65-S65-T65 -> 87 | R65: 46 | S65: -55 | T65: 26 | U65: =D65-V65-W65-X65 -> 66 | V65: -59 | W65: -71 | X65: -37 | Y65: =E65-Z65-AA65-AB65 -> -100 | Z65: -41 | AA65: 105 | AB65: -6 | AC65: =F65-AD65-AE65-AF65 -> 166 | AD65: 33 | AE65: 36 | AF65: 39 | AG65: =G65-AH65-AI65-AJ65 -> 72 | AH65: -55 | AI65: -4 | AJ65: 71 | AK65: =H65-AL65-AM65-AN65 -> -8 | AL65: 27 | AM65: 44 | AN65: -121 | AP65: -66 | AQ65: 35 | AR65: -69
B66: שינוי בחייבים אחרים | C66: 39 | D66: 26 | E66: -46 | F66: 9 | G66: 5 | H66: 5 | I66: 0 | J66: 0 | K66: 0 | L66: 0 | M66: 0 | O66: -4 | P66: -15 | Q66: =C66-R66-S66-T66 -> 66 | R66: -31 | S66: -14 | T66: 18 | U66: =D66-V66-W66-X66 -> 37 | V66: -6 | W66: 1 | X66: -6 | Y66: =E66-Z66-AA66-AB66 -> 12 | Z66: 32 | AA66: -89 | AB66: -1 | AC66: =F66-AD66-AE66-AF66 -> 29 | AD66: 20 | AE66: -31 | AF66: -9 | AG66: =G66-AH66-AI66-AJ66 -> -9 | AH66: 28 | AI66: -8 | AJ66: -6 | AK66: =H66-AL66-AM66-AN66 -> 34 | AL66: -15 | AM66: -14 | AN66: 0 | AP66: -29 | AQ66: -14 | AR66: 0
B67: שינוי בזכאים אחרים | C67: 43 | D67: -210 | E67: 107 | F67: 107 | G67: 54 | H67: 4 | I67: -66 | J67: -4 | K67: 0 | L67: -90 | M67: 0 | O67: -80 | P67: 18 | Q67: =C67-R67-S67-T67 -> 39 | R67: 22 | S67: -28 | T67: 10 | U67: =D67-V67-W67-X67 -> 16 | V67: -19 | W67: -184 | X67: -23 | Y67: =E67-Z67-AA67-AB67 -> 48 | Z67: 68 | AA67: -52 | AB67: 43 | AC67: =F67-AD67-AE67-AF67 -> 81 | AD67: 55 | AE67: -17 | AF67: -12 | AG67: =G67-AH67-AI67-AJ67 -> 95 | AH67: 35 | AI67: -140 | AJ67: 64 | AK67: =H67-AL67-AM67-AN67 -> 147 | AL67: -19 | AM67: -124 | AN67: 0 | AP67: -39 | AQ67: 5 | AR67: 0
B68: שינוי בהפרשות לעובדים | C68: 0 | D68: 0 | E68: 0 | F68: 0 | G68: 0 | H68: 0 | I68: 0 | J68: 0 | K68: 98 | L68: 0 | M68: 66 | O68: 0 | P68: 0 | Q68: =C68-R68-S68-T68 -> 0 | R68: 0 | S68: 0 | T68: 0 | U68: =D68-V68-W68-X68 -> 0 | V68: 0 | W68: 0 | X68: 0 | Y68: =E68-Z68-AA68-AB68 -> 0 | Z68: 0 | AA68: 0 | AB68: 0 | AC68: =F68-AD68-AE68-AF68 -> 0 | AD68: 0 | AE68: 0 | AF68: 0 | AG68: =G68-AH68-AI68-AJ68 -> -125 | AH68: 38 | AI68: 112 | AJ68: -25 | AK68: =H68-AL68-AM68-AN68 -> -3 | AL68: 2 | AM68: 0 | AN68: 1 | AP68: -21 | AQ68: -25 | AR68: -26
B69: תנועה בצי כלי הרכב של החברה | C69: =SUM(C63:C68) -> 205 | D69: =SUM(D63:D68) -> 432 | E69: =SUM(E63:E68) -> -723 | F69: =SUM(F63:F68) -> -303 | G69: =SUM(G63:G68) -> 108 | H69: =SUM(H63:H68) -> 78 | I69: =SUM(I63:I68) -> -321 | J69: =SUM(J63:J68) -> 29 | ... M69: =SUM(M63:M68) -> 63 | O69: =SUM(O63:O68) -> 57 | P69: =SUM(P63:P68) -> -140 | Q69: =SUM(Q63:Q68) -> 158 | R69: =SUM(R63:R68) -> 96 | S69: =SUM(S63:S68) -> -13 | T69: =SUM(T63:T68) -> -36 | U69: =SUM(U63:U68) -> 216 | V69: =SUM(V63:V68) -> 139 | ... AR69: =SUM(AR63:AR68) -> -181
B71: תזרים מזומנים מפעילות שוטפת | C71: =C45+C58+C69 -> 1363 | D71: =D45+D58+D69 -> 1595 | E71: =E45+E58+E69 -> 2025 | F71: =F45+F58+F69 -> 1065 | G71: =G45+G58+G69 -> 804 | H71: =H45+H58+H69 -> 992 | I71: =I45+I58+I69 -> 620 | J71: =J45+J58+J69 -> 847 | ... M71: =M45+M58+M69 -> 893 | O71: =O45+O58+O69 -> 231 | P71: =P45+P58+P69 -> 152 | Q71: =Q45+Q58+Q69 -> 412 | R71: =R45+R58+R69 -> 396 | S71: =S45+S58+S69 -> 276 | T71: =T45+T58+T69 -> 279 | U71: =U45+U58+U69 -> 415 | V71: =V45+V58+V69 -> 407 | ... AR71: =AR45+AR58+AR69 -> 36
B73: השקעה בפקדונות נטו | C73: 56 | D73: -88 | E73: -36 | F73: 355 | G73: 34 | H73: -2 | I73: -3 | J73: -65 | K73: -198 | L73: 0 | M73: 0 | O73: 1 | P73: -4 | Q73: =C73-R73-S73-T73 -> -5 | R73: 0 | S73: 11 | T73: 50 | U73: =D73-V73-W73-X73 -> -10 | V73: 1 | W73: -35 | X73: -44 | Y73: =E73-Z73-AA73-AB73 -> 1 | Z73: 1 | AA73: -30 | AB73: -8 | AC73: =F73-AD73-AE73-AF73 -> 148 | AD73: 109 | AE73: 90 | AF73: 8 | AG73: =G73-AH73-AI73-AJ73 -> 33 | AH73: -1 | AI73: 17 | AJ73: =12-27 -> -15 | AK73: =H73-AL73-AM73-AN73 -> -6 | AL73: -7 | AM73: -3 | AN73: 14 | AP73: -3 | AQ73: 0 | AR73: 10
B74: צירופי עסקים | C74: -74 | D74: 0 | E74: -18 | F74: -365 | G74: -27 | O74: 0 | P74: -3 | Q74: =C74-R74-S74-T74 -> -2 | R74: -50 | S74: 0 | T74: -22 | U74: =D74-V74-W74-X74 -> 0 | V74: 0 | W74: 0 | X74: 0 | Y74: =E74-Z74-AA74-AB74 -> 0 | Z74: 0 | AA74: -18 | AB74: 0 | AC74: =F74-AD74-AE74-AF74 -> 2 | AD74: -303 | AE74: 0 | AF74: -64 | AG74: =G74-AH74-AI74-AJ74 -> -27
B75: רכישת רכוש קבוע ונכסים בלתי מוחשיים | C75: -713 | D75: -780 | E75: -747 | F75: -611 | G75: -626 | H75: -576 | I75: -572 | J75: -457 | K75: -632 | L75: -619 | M75: =-835 -> -835 | O75: -202 | P75: -190 | Q75: =C75-R75-S75-T75 -> -267 | R75: -159 | S75: -142 | T75: -145 | U75: =D75-V75-W75-X75 -> -255 | V75: -191 | W75: -170 | X75: -164 | Y75: =E75-Z75-AA75-AB75 -> -212 | Z75: -184 | AA75: -220 | AB75: -131 | AC75: =F75-AD75-AE75-AF75 -> -185 | AD75: -128 | AE75: -151 | AF75: -147 | AG75: =G75-AH75-AI75-AJ75 -> -487 | AH75: 0 | AI75: 0 | AJ75: -139 | AK75: =H75-AL75-AM75-AN75 -> -157 | AL75: -147 | AM75: -141 | AN75: -131 | AP75: -145 | AQ75: -121 | AR75: -127
B76: תמורה ממכירת עסקים נטו | C76: 19 | D76: 4 | E76: 33 | F76: 31 | G76: 26 | H76: 0 | I76: 902 | J76: 6 | K76: 17 | L76: -351 | M76: -143 | O76: 1 | P76: 2 | Q76: =C76-R76-S76-T76 -> 4 | R76: 0 | S76: 0 | T76: 15 | U76: =D76-V76-W76-X76 -> 0 | V76: 1 | W76: 0 | X76: 3 | Y76: =E76-Z76-AA76-AB76 -> 4 | Z76: 7 | AA76: 2 | AB76: 20 | AC76: =F76-AD76-AE76-AF76 -> 6 | AD76: 25 | AE76: 0 | AF76: 0 | AG76: =G76-AH76-AI76-AJ76 -> 330 | AH76: -143 | AI76: -161 | AJ76: 0 | AK76: =H76-AL76-AM76-AN76 -> 0 | AL76: 0 | AM76: 0 | AN76: 0 | AP76: -1 | AQ76: -24 | AR76: 931
B77: תמורה ממכירת השקעה בחברה מוחזקת לפי אקוויטי | C77: 0 | D77: 0 | E77: 14 | F77: 11 | G77: 10 | H77: 0 | I77: 0 | J77: 168 | K77: 0 | L77: 59 | M77: 0 | O77: 0 | P77: 0 | Q77: =C77-R77-S77-T77 -> 0 | R77: 0 | S77: 0 | T77: 0 | U77: =D77-V77-W77-X77 -> 0 | V77: 0 | W77: 0 | X77: 0 | Y77: =E77-Z77-AA77-AB77 -> 14 | Z77: 0 | AA77: 0 | AB77: 0 | AC77: =F77-AD77-AE77-AF77 -> 10 | AD77: 1 | AE77: 0 | AF77: 0 | AG77: =G77-AH77-AI77-AJ77 -> -7 | AH77: 0 | AI77: 17 | AJ77: 0 | AK77: =H77-AL77-AM77-AN77 -> 0 | AL77: 0 | AM77: 0 | AN77: 0 | AP77: 0 | AQ77: 0 | AR77: 0
B78: דיבידנדים שהתקבלו מחברות מוחזקות לפי אקוויטי | C78: 0 | D78: 0 | E78: 0 | F78: 0 | G78: 0 | H78: 3 | I78: 2 | J78: 3 | K78: 12 | L78: 0 | M78: 5 | O78: 0 | P78: 0 | Q78: =C78-R78-S78-T78 -> 0 | R78: 0 | S78: 0 | T78: 0 | U78: =D78-V78-W78-X78 -> 0 | V78: 0 | W78: 0 | X78: 0 | Y78: =E78-Z78-AA78-AB78 -> 0 | Z78: 0 | AA78: 0 | AB78: 0 | AC78: =F78-AD78-AE78-AF78 -> 0 | AD78: 0 | AE78: 0 | AF78: 0 | AG78: =G78-AH78-AI78-AJ78 -> -3 | AH78: 0 | AI78: 2 | AJ78: 1 | AK78: =H78-AL78-AM78-AN78 -> 2 | AL78: 0 | AM78: 1 | AN78: 0 | AP78: 0 | AQ78: 0 | AR78: 0
B79: תמורה ממכירת רכוש קבוע | C79: 1 | D79: 1 | E79: 0 | F79: 0 | G79: 0 | H79: 50 | I79: 2 | J79: 12 | K79: 1 | L79: 364 | M79: -23 | O79: -16 | P79: 0 | Q79: =C79-R79-S79-T79 -> -3 | R79: 1 | S79: 3 | T79: 0 | U79: =D79-V79-W79-X79 -> 0 | V79: 0 | W79: 0 | X79: 1 | Y79: =E79-Z79-AA79-AB79 -> -14 | Z79: 0 | AA79: 2 | AB79: 12 | AC79: =F79-AD79-AE79-AF79 -> -3 | AD79: 0 | AE79: 3 | AF79: 0 | AG79: =G79-AH79-AI79-AJ79 -> -2 | AH79: 0 | AI79: 2 | AJ79: 0 | AK79: =H79-AL79-AM79-AN79 -> 14 | AL79: 1 | AM79: 0 | AN79: 35 | AP79: 0 | AQ79: 2 | AR79: 0
B80: מזומנים נטו שנבעו מפעילות השקעה | C80: =SUM(C73:C79) -> -711 | D80: =SUM(D73:D79) -> -863 | E80: =SUM(E73:E79) -> -754 | F80: =SUM(F73:F79) -> -579 | G80: =SUM(G73:G79) -> -583 | H80: =SUM(H73:H79) -> -525 | I80: =SUM(I73:I79) -> 331 | J80: =SUM(J73:J79) -> -333 | ... M80: =SUM(M73:M79) -> -996 | O80: =SUM(O73:O79) -> -216 | P80: =SUM(P73:P79) -> -195 | Q80: =SUM(Q73:Q79) -> -273 | R80: =SUM(R73:R79) -> -208 | S80: =SUM(S73:S79) -> -128 | T80: =SUM(T73:T79) -> -102 | U80: =SUM(U73:U79) -> -265 | V80: =SUM(V73:V79) -> -189 | ... AR80: =SUM(AR73:AR79) -> 814
B82: דיבידנדים ששולמו לבעלי מניות החברה | C82: -251 | D82: -474 | E82: -1166 | F82: -276 | G82: -118 | H82: -273 | I82: -241 | J82: -237 | K82: -162 | L82: -348 | M82: -846 | O82: -55 | P82: -52 | Q82: =C82-R82-S82-T82 -> -68 | R82: -63 | S82: -59 | T82: -61 | U82: =D82-V82-W82-X82 -> -68 | V82: -82 | W82: -146 | X82: -178 | Y82: =E82-Z82-AA82-AB82 -> -314 | Z82: -376 | AA82: -307 | AB82: -169 | AC82: =F82-AD82-AE82-AF82 -> -107 | AD82: -68 | AE82: -67 | AF82: -34 | AG82: =G82-AH82-AI82-AJ82 -> -28 | AH82: =-35-2 -> -37 | AI82: -30 | AJ82: -23 | AK82: =H82-AL82-AM82-AN82 -> -64 | AL82: -73 | AM82: -75 | AN82: -61 | AP82: -56 | AQ82: -51 | AR82: -69
B83: קבלת הלוואות לז"א | C83: 889 | D83: 633 | E83: 1045 | F83: 1230 | G83: 1175 | H83: 657 | I83: 1746 | J83: 966 | K83: 0 | L83: 363 | M83: 916 | O83: 683 | P83: 361 | Q83: =C83-R83-S83-T83 -> 278 | R83: 273 | S83: 140 | T83: 198 | U83: =D83-V83-W83-X83 -> 149 | V83: 131 | W83: 95 | X83: 258 | Y83: =E83-Z83-AA83-AB83 -> 311 | Z83: 201 | AA83: 190 | AB83: 343 | AC83: =F83-AD83-AE83-AF83 -> 113 | AD83: 620 | AE83: 187 | AF83: 310 | AG83: =G83-AH83-AI83-AJ83 -> 116 | AH83: 182 | AI83: 355 | AJ83: 522 | AK83: =H83-AL83-AM83-AN83 -> 200 | AL83: 50 | AM83: 167 | AN83: 240 | AP83: 140 | AQ83: 918 | AR83: 418
B84: פירעון הלוואות לז"א | C84: -1302 | D84: -836 | E84: -1181 | F84: -1120 | G84: -1133 | H84: -689 | I84: -2115 | J84: -1387 | K84: -87 | L84: 0 | M84: 0 | O84: -138 | P84: -397 | Q84: =C84-R84-S84-T84 -> -383 | R84: -307 | S84: =-226 -> -226 | T84: -386 | U84: =D84-V84-W84-X84 -> -183 | V84: -255 | W84: -228 | X84: -170 | Y84: =E84-Z84-AA84-AB84 -> -383 | Z84: -183 | AA84: -259 | AB84: -356 | AC84: =F84-AD84-AE84-AF84 -> -207 | AD84: -458 | AE84: -144 | AF84: -311 | AG84: =G84-AH84-AI84-AJ84 -> -207 | AH84: -375 | AI84: -408 | AJ84: -143 | AK84: =H84-AL84-AM84-AN84 -> -139 | AL84: -138 | AM84: -142 | AN84: -270 | AP84: -241 | AQ84: -1498 | AR84: -250
B85: אשראי לז"ק מבנקים ואחרים, נטו | C85: -1 | D85: -25 | E85: -21 | F85: -58 | G85: -52 | H85: -183 | I85: -283 | J85: 147 | K85: 14 | L85: 0 | M85: 0 | O85: -206 | P85: 109 | Q85: =C85-R85-S85-T85 -> -8 | R85: 8 | S85: -18 | T85: 17 | U85: =D85-V85-W85-X85 -> 64 | V85: -72 | W85: -54 | X85: 37 | Y85: =E85-Z85-AA85-AB85 -> 30 | Z85: 21 | AA85: 25 | AB85: -97 | AC85: =F85-AD85-AE85-AF85 -> 50 | AD85: -92 | AE85: 25 | AF85: -41 | AG85: =G85-AH85-AI85-AJ85 -> -5 | AH85: 61 | AI85: -99 | AJ85: -9 | AK85: =H85-AL85-AM85-AN85 -> -63 | AL85: -90 | AM85: -12 | AN85: -18 | AP85: 64 | AQ85: -19 | AR85: -238
B86: אחר | C86: =-2-57 -> -59 | D86: =5-15 -> -10 | E86: 20 | F86: =-17-3 -> -20 | G86: =24-1 -> 23 | H86: -2 | I86: -1 | J86: 0 | K86: -4 | L86: 0 | M86: 0 | O86: =-2-42 -> -44 | P86: 0 | Q86: =C86-R86-S86-T86 -> -3 | R86: -2 | S86: -57 | T86: 3 | U86: =D86-V86-W86-X86 -> -1 | V86: 0 | W86: -15 | X86: 6 | Y86: =E86-Z86-AA86-AB86 -> 1 | Z86: 0 | AA86: 0 | AB86: 19 | AC86: =F86-AD86-AE86-AF86 -> -2 | AD86: 0 | AE86: -32 | AF86: 14 | AG86: =G86-AH86-AI86-AJ86 -> 25 | AH86: 0 | AI86: =14 -> 14 | AJ86: =-16 -> -16 | AK86: =H86-AL86-AM86-AN86 -> 0 | AL86: -2 | AM86: 0 | AN86: 0 | AP86: 0 | AQ86: 0 | AR86: 0
B87: מזומנים שנבעו מפעילות מימון לרבות דיבידנד | C87: =SUM(C82:C86) -> -724 | D87: =SUM(D82:D86) -> -712 | E87: =SUM(E82:E86) -> -1303 | F87: =SUM(F82:F86) -> -244 | G87: =SUM(G82:G86) -> -105 | H87: =SUM(H82:H86) -> -490 | I87: =SUM(I82:I86) -> -894 | J87: =SUM(J82:J86) -> -511 | ... M87: =SUM(M82:M86) -> 70 | O87: =SUM(O82:O86) -> 240 | P87: =SUM(P82:P86) -> 21 | Q87: =SUM(Q82:Q86) -> -184 | R87: =SUM(R82:R86) -> -91 | S87: =SUM(S82:S86) -> -220 | T87: =SUM(T82:T86) -> -229 | U87: =SUM(U82:U86) -> -39 | V87: =SUM(V82:V86) -> -278 | ... AR87: =SUM(AR82:AR86) -> -139
B89: מזומנים יתרת פתיחה | C89: =D95 -> 420 | D89: =E95 -> 417 | E89: =F95 -> 473 | F89: =G95 -> 214 | G89: 95 | H89: 121 | I89: 83 | J89: =191-104 -> 87 | K89: 161 | L89: 138 | M89: 188 | O89: =P95 -> 312 | P89: =Q95 -> 327 | Q89: =R95 -> 393 | R89: =S95 -> 287 | S89: =T95 -> 363 | T89: =U95 -> 420 | U89: =V95 -> 307 | V89: =W95 -> 372 | ... AI89: =AJ95 -> 434 | AJ89: 95 | AK89: =AL95 -> 96 | AL89: 137 | AM89: 103 | AN89: 121 | AO89: =AP95 -> 102 | AP89: 155 | AQ89: 798 | AR89: 88
B91: עליה (ירידה) ביתרות המזומנים | C91: =C71+C80+C87 -> -72 | D91: =D71+D80+D87 -> 20 | E91: =E71+E80+E87 -> -32 | F91: =F71+F80+F87 -> 242 | G91: =G71+G80+G87 -> 116 | H91: =H71+H80+H87 -> -23 | I91: =I71+I80+I87 -> 57 | J91: =J71+J80+J87 -> 3 | ... M91: =M71+M80+M87 -> -33 | O91: =O71+O80+O87 -> 255 | P91: =P71+P80+P87 -> -22 | Q91: =Q71+Q80+Q87 -> -45 | R91: =R71+R80+R87 -> 97 | S91: =S71+S80+S87 -> -72 | T91: =T71+T80+T87 -> -52 | U91: =U71+U80+U87 -> 111 | V91: =V71+V80+V87 -> -60 | ... AR91: =AR71+AR80+AR87 -> 711
B92: הפרשי שער | C92: -21 | D92: -17 | E92: -24 | F92: 17 | G92: 3 | H92: -3 | I92: -24 | J92: -2 | K92: -1 | L92: -18 | M92: -16 | O92: 15 | P92: 7 | Q92: =C92-R92-S92-T92 -> -21 | R92: 9 | S92: -4 | T92: -5 | U92: =D92-V92-W92-X92 -> 2 | V92: -5 | W92: -18 | X92: 4 | Y92: =E92-Z92-AA92-AB92 -> 14 | Z92: -21 | AA92: -25 | AB92: 8 | AC92: =F92-AD92-AE92-AF92 -> 3 | AD92: 4 | AE92: 8 | AF92: 2 | AG92: =G92-AH92-AI92-AJ92 -> 2 | AH92: 3 | AI92: 3 | AJ92: -5 | AK92: =H92-AL92-AM92-AN92 -> 0 | AL92: -3 | AM92: 0 | AN92: 0 | AP92: -7 | AQ92: -14 | AR92: -1
B93: מזומנים שנכללו במסגרת נכסים המוחזקים למכירה | C93: 0 | D93: 0 | E93: 0 | F93: 0 | G93: 0 | H93: 0 | I93: 5 | J93: -5 | K93: 0 | L93: 0 | M93: -8 | O93: 0 | P93: 0 | R93: 0 | S93: 0 | T93: 0 | V93: 0 | W93: 0 | X93: 0 | Z93: 0 | AA93: 0 | AB93: 0 | AD93: 0 | AE93: 0 | AF93: 0 | AH93: 0 | AI93: 0 | AJ93: 0
B95: מזומנים יתרת סגירה | C95: =C89+C91+C92+C93 -> 327 | D95: =D89+D91+D92+D93 -> 420 | E95: =E89+E91+E92+E93 -> 417 | F95: =F89+F91+F92+F93 -> 473 | G95: =G89+G91+G92+G93 -> 214 | H95: =H89+H91+H92+H93 -> 95 | I95: =I89+I91+I92+I93 -> 121 | J95: =J89+J91+J92+J93 -> 83 | ... M95: =M89+M91+M92+M93 -> 131 | O95: =O89+O91+O92+O93 -> 582 | P95: =P89+P91+P92+P93 -> 312 | Q95: =Q89+Q91+Q92+Q93 -> 327 | R95: =R89+R91+R92+R93 -> 393 | S95: =S89+S91+S92+S93 -> 287 | T95: =T89+T91+T92+T93 -> 363 | U95: =U89+U91+U92+U93 -> 420 | V95: =V89+V91+V92+V93 -> 307 | ... AR95: =AR89+AR91+AR92+AR93 -> 798
B96: בדיקה | C96: =C102-C95 -> 0 | D96: =D102-D95 -> 0 | E96: =E102-E95 -> 0 | F96: =F102-F95 -> 0 | G96: =G102-G95 -> 0 | H96: =H102-H95 -> 0 | I96: =I102-I95 -> 0 | J96: =J102-J95 -> 0 | ... M96: =M102-M95 -> 116 | O96: =O102-O95 -> 0 | P96: =P102-P95 -> 0 | Q96: =C96-R96-S96-T96 -> 0 | R96: =R102-R95 -> 0 | S96: =S102-S95 -> 0 | T96: =T102-T95 -> 0 | U96: =U102-U95 -> 0 | V96: =V102-V95 -> 0 | W96: =W102-W95 -> 0 | X96: =X102-X95 -> 0 | Y96: =Y102-Y95 -> 0 | ... AR96: =AR102-AR95 -> 0
B98: מידע נוסף:
B99: מיסי הכנסה ששולמו
A101: מאזן | C101: =C$2 -> FY 2024 | D101: =D$2 -> FY 2023 | E101: =E$2 -> FY 2022 | F101: =F$2 -> FY 2021 | G101: =G$2 -> FY 2020 | H101: =H$2 -> FY 2019 | I101: =I$2 -> FY 2018 | J101: =J$2 -> FY 2017 | ... M101: =M$2 -> FY 2014 | O101: =O$2 -> Q2 2025 | P101: =P$2 -> Q1 2025 | Q101: =Q$2 -> Q4 2024 | R101: =R$2 -> Q3 2024 | S101: =S$2 -> Q2 2024 | T101: =T$2 -> Q1 2024 | U101: =U$2 -> Q4 2023 | V101: =V$2 -> Q3 2023 | ... AR101: =AR$2 -> Q1 2018
B102: מזומנים ושווי מזומנים | C102: 327 | D102: 420 | E102: 417 | F102: 473 | G102: 214 | H102: 95 | I102: 121 | J102: 83 | K102: 87 | L102: 248 | M102: 247 | O102: 582 | P102: 312 | Q102: 327 | R102: 393 | S102: 287 | T102: 363 | U102: =D102 -> 420 | V102: 307 | W102: 372 | X102: 552 | Y102: =E102 -> 417 | Z102: 498 | AA102: 426 | AB102: 439 | AC102: =F102 -> 473 | AD102: 301 | AE102: 318 | AF102: 157 | AG102: =G102 -> 214 | AH102: 216 | AI102: 323 | AJ102: 434 | AK102: =H102 -> 95 | AL102: 96 | AM102: 137 | AN102: 103 | AO102: =I102 -> 121 | AP102: 102 | AQ102: 155 | AR102: 798
B103: השקעות ופקדונות לז"ק | C103: 115 | D103: 172 | E103: 91 | F103: 91 | G103: 100 | H103: 96 | I103: 92 | J103: 90 | K103: 29 | L103: 0 | M103: 0 | O103: 119 | P103: 121 | Q103: 115 | R103: 110 | S103: 109 | T103: 121 | U103: =D103 -> 172 | V103: 162 | W103: 166 | X103: 129 | Y103: =E103 -> 91 | Z103: 92 | AA103: 90 | AB103: 93 | AC103: =F103 -> 91 | AD103: 88 | AE103: 92 | AF103: 99 | AG103: =G103 -> 100 | AH103: 98 | AI103: 86 | AJ103: 90 | AK103: =H103 -> 96 | AL103: 91 | AM103: 82 | AN103: 80 | AO103: =I103 -> 92 | AP103: 85 | AQ103: 80 | AR103: 78
B104: לקוחות | C104: 1260 | D104: 1376 | E104: 1583 | F104: 1418 | G104: 883 | H104: 778 | I104: 990 | J104: 932 | K104: 966 | L104: 1082 | M104: 1039 | O104: 1431 | P104: 1497 | Q104: 1260 | R104: 1393 | S104: 1429 | T104: 1492 | U104: =D104 -> 1376 | V104: 1387 | W104: 1380 | X104: 1631 | Y104: =E104 -> 1583 | Z104: 1672 | AA104: 1812 | AB104: 1898 | AC104: =F104 -> 1418 | AD104: 1210 | AE104: 1097 | AF104: 1056 | AG104: =G104 -> 883 | AH104: 813 | AI104: 831 | AJ104: 939 | AK104: =H104 -> 778 | AL104: 979 | AM104: 1071 | AN104: 1071 | AO104: =I104 -> 990 | AP104: 1000 | AQ104: 1074 | AR104: 1014
B105: מלאי | C105: 1626 | D105: 1703 | E105: 2134 | F105: 1570 | G105: 1250 | H105: 1312 | I105: 1290 | J105: 1226 | K105: 1267 | L105: 1364 | M105: 1335 | O105: 1690 | P105: 1629 | Q105: 1626 | R105: 1591 | S105: 1544 | T105: 1630 | U105: =D105 -> 1703 | V105: 1722 | W105: 2006 | X105: 2116 | Y105: =E105 -> 2134 | Z105: 1982 | AA105: 1857 | AB105: 1673 | AC105: =F105 -> 1570 | AD105: 1409 | AE105: 1207 | AF105: 1195 | AG105: =G105 -> 1250 | AH105: 1233 | AI105: 1202 | AJ105: 1256 | AK105: =H105 -> 1312 | AL105: 1205 | AM105: 1245 | AN105: 1254 | AO105: =I105 -> 1290 | AP105: 1225 | AQ105: 1208 | AR105: 1255
B106: נכסים מוחזקים למכירה | C106: 0 | D106: 0 | E106: 0 | F106: 0 | G106: 0 | H106: 0 | I106: 0 | J106: 169 | K106: 0 | L106: 39 | M106: 225 | O106: 0 | P106: 0 | Q106: 0 | R106: 0 | S106: 0 | T106: 0 | U106: =D106 -> 0 | V106: 0 | W106: 0 | X106: 0 | Y106: =E106 -> 0 | Z106: 0 | AA106: 0 | AB106: 0 | AC106: =F106 -> 0 | AD106: 0 | AE106: 0 | AF106: 0 | AG106: =G106 -> 0 | AH106: 0 | AI106: 0 | AJ106: 0 | AK106: =H106 -> 0 | AL106: 0 | AM106: 0 | AN106: 0 | AO106: =I106 -> 0 | AP106: 0 | AQ106: 0 | AR106: 0
B107: חייבים אחרים | C107: 258 | D107: 363 | E107: 323 | F107: 357 | G107: 394 | H107: 403 | I107: 295 | J107: 225 | K107: 222 | L107: =45+207 -> 252 | M107: =139+155 -> 294 | O107: 413 | P107: 277 | Q107: 258 | R107: 337 | S107: 298 | T107: 301 | U107: =D107 -> 363 | V107: 362 | W107: 333 | X107: 316 | Y107: =E107 -> 323 | Z107: 361 | AA107: 572 | AB107: 355 | AC107: =F107 -> 357 | AD107: =350+103 -> 453 | AE107: =180+344 -> 524 | AF107: 481 | AG107: =G107 -> 394 | AH107: 388 | AI107: 422 | AJ107: 412 | AK107: =H107 -> 403 | AL107: 324 | AM107: 303 | AN107: 271 | AO107: =I107 -> 295 | AP107: 269 | AQ107: 276 | AR107: 296
B108: סה"כ נכסים שוטפים | C108: =SUM(C102:C107) -> 3586 | D108: =SUM(D102:D107) -> 4034 | E108: =SUM(E102:E107) -> 4548 | F108: =SUM(F102:F107) -> 3909 | G108: =SUM(G102:G107) -> 2841 | H108: =SUM(H102:H107) -> 2684 | I108: =SUM(I102:I107) -> 2788 | J108: =SUM(J102:J107) -> 2725 | ... M108: =SUM(M102:M107) -> 3140 | O108: =SUM(O102:O107) -> 4235 | P108: =SUM(P102:P107) -> 3836 | Q108: =SUM(Q102:Q107) -> 3586 | R108: =SUM(R102:R107) -> 3824 | S108: =SUM(S102:S107) -> 3667 | T108: =SUM(T102:T107) -> 3907 | U108: =SUM(U102:U107) -> 4034 | V108: =SUM(V102:V107) -> 3940 | ... AR108: =SUM(AR102:AR107) -> 3441
B109: השקעות הנמדדות בשווי הוגן דרך רווח כולל אחר | C109: 0 | D109: 0 | E109: 0 | F109: 0 | G109: 83 | H109: 111 | I109: 145 | J109: 29 | K109: 153 | L109: 159 | M109: 185 | O109: 0 | P109: 0 | Q109: 0 | R109: 0 | S109: 0 | T109: 0 | U109: =D109 -> 0 | V109: 0 | W109: 0 | X109: 0 | Y109: =E109 -> 0 | Z109: 0 | AA109: 0 | AB109: 0 | AC109: =F109 -> 0 | AD109: 0 | AE109: 0 | AF109: 0 | AG109: =G109 -> 83 | AH109: 73 | AI109: 76 | AJ109: 100 | AK109: =H109 -> 111 | AL109: 29 | AM109: 29 | AN109: 30 | AO109: =I109 -> 145 | AP109: 28 | AQ109: 29 | AR109: 30
B110: נכסים פיננסיים זמינים למכירה | C110: 0 | D110: 0 | E110: 0 | F110: 0 | G110: 0 | H110: 0 | I110: 0 | J110: 212 | K110: 253 | L110: 0 | M110: 0 | O110: 0 | P110: 0 | Q110: 0 | R110: 0 | S110: 0 | T110: 0 | U110: =D110 -> 0 | V110: 0 | W110: 0 | X110: 0 | Y110: =E110 -> 0 | Z110: 0 | AA110: 0 | AB110: 0 | AC110: =F110 -> 0 | AD110: 0 | AE110: 0 | AF110: 0 | AG110: =G110 -> 0 | AH110: 0 | AI110: 0 | AJ110: 0 | AK110: =H110 -> 0 | AL110: 144 | AM110: 173 | AN110: 201 | AO110: =I110 -> 0 | AP110: 149 | AQ110: 150 | AR110: 219
B111: נכסי מיסים נדחים | C111: 143 | D111: 152 | E111: 150 | F111: 147 | G111: 127 | H111: 109 | I111: 122 | J111: 132 | K111: 150 | L111: 0 | M111: 0 | O111: 172 | P111: 151 | Q111: 143 | R111: 149 | S111: 147 | T111: 155 | U111: =D111 -> 152 | V111: 141 | W111: 149 | X111: 155 | Y111: =E111 -> 150 | Z111: 152 | AA111: 132 | AB111: 142 | AC111: =F111 -> 147 | AD111: 157 | AE111: 143 | AF111: 136 | AG111: =G111 -> 127 | AH111: 121 | AI111: 116 | AJ111: 102 | AK111: =H111 -> 109 | AL111: 97 | AM111: 94 | AN111: 83 | AO111: =I111 -> 122 | AP111: 112 | AQ111: 114 | AR111: 123
B112: רכוש קבוע | C112: 6462 | D112: 6329 | E112: 5969 | F112: 5754 | G112: 5550 | H112: 5331 | I112: 4663 | J112: 4521 | K112: 4309 | L112: 4212 | M112: 3927 | O112: 6701 | P112: 6526 | Q112: 6462 | R112: 6414 | S112: 6285 | T112: 6285 | U112: =D112 -> 6329 | V112: 6125 | W112: 6097 | X112: 6066 | Y112: =E112 -> 5969 | Z112: 5764 | AA112: 5749 | AB112: 5797 | AC112: =F112 -> 5754 | AD112: 5632 | AE112: 5601 | AF112: 5531 | AG112: =G112 -> 5550 | AH112: 5368 | AI112: 5228 | AJ112: 5316 | AK112: =H112 -> 5331 | AL112: 5068 | AM112: 5045 | AN112: 4961 | AO112: =I112 -> 4663 | AP112: 4580 | AQ112: 4548 | AR112: 4577
B113: נכסים בלתי מוחשיים | C113: 869 | D113: 873 | E113: 852 | F113: 867 | G113: 670 | H113: 652 | I113: 671 | J113: 722 | K113: 824 | L113: 1185 | M113: 803 | O113: 941 | P113: 918 | Q113: 869 | R113: 916 | S113: 857 | T113: 897 | U113: =D113 -> 873 | V113: 851 | W113: 872 | X113: 867 | Y113: =E113 -> 852 | Z113: 825 | AA113: 867 | AB113: 889 | AC113: =F113 -> 867 | AD113: 927 | AE113: 725 | AF113: 709 | AG113: =G113 -> 670 | AH113: 645 | AI113: 634 | AJ113: 652 | AK113: =H113 -> 652 | AL113: 641 | AM113: 662 | AN113: 664 | AO113: =I113 -> 671 | AP113: 672 | AQ113: 688 | AR113: 732
B114: נכסים אחרים שאינם שוטפים | C114: 261 | D114: 239 | E114: 231 | F114: 403 | G114: 393 | H114: 286 | I114: 387 | J114: 373 | K114: 292 | L114: 536 | M114: 293 | O114: 326 | P114: 260 | Q114: 261 | R114: 255 | S114: 249 | T114: 242 | U114: =D114 -> 239 | V114: 217 | W114: 209 | X114: 213 | Y114: =E114 -> 231 | Z114: 252 | AA114: 273 | AB114: 378 | AC114: =F114 -> 403 | AD114: 395 | AE114: 373 | AF114: 356 | AG114: =G114 -> 393 | AH114: 311 | AI114: 308 | AJ114: 247 | AK114: =H114 -> 286 | AL114: 439 | AM114: 401 | AN114: 399 | AO114: =I114 -> 387 | AP114: 421 | AQ114: 409 | AR114: 448
B115: סה"כ נכסים לא שוטפים | C115: =SUM(C109:C114) -> 7735 | D115: =SUM(D109:D114) -> 7593 | E115: =SUM(E109:E114) -> 7202 | F115: =SUM(F109:F114) -> 7171 | G115: =SUM(G109:G114) -> 6823 | H115: =SUM(H109:H114) -> 6489 | I115: =SUM(I109:I114) -> 5988 | J115: =SUM(J109:J114) -> 5989 | ... M115: =SUM(M109:M114) -> 5208 | O115: =SUM(O109:O114) -> 8140 | P115: =SUM(P109:P114) -> 7855 | Q115: =SUM(Q109:Q114) -> 7735 | R115: =SUM(R109:R114) -> 7734 | S115: =SUM(S109:S114) -> 7538 | T115: =SUM(T109:T114) -> 7579 | U115: =SUM(U109:U114) -> 7593 | V115: =SUM(V109:V114) -> 7334 | ... AR115: =SUM(AR109:AR114) -> 6129
B116: סה"כ נכסים | C116: =C108+C115 -> 11321 | D116: =D108+D115 -> 11627 | E116: =E108+E115 -> 11750 | F116: =F108+F115 -> 11080 | G116: =G108+G115 -> 9664 | H116: =H108+H115 -> 9173 | I116: =I108+I115 -> 8776 | J116: =J108+J115 -> 8714 | ... M116: =M108+M115 -> 8348 | O116: =O108+O115 -> 12375 | P116: =P108+P115 -> 11691 | Q116: =Q108+Q115 -> 11321 | R116: =R108+R115 -> 11558 | S116: =S108+S115 -> 11205 | T116: =T108+T115 -> 11486 | U116: =U108+U115 -> 11627 | V116: =V108+V115 -> 11274 | ... AR116: =AR108+AR115 -> 9570
B117: אשראי מתאגידים בנקאיים וחלויות שוטפות של הלוואות לזמן ארוך | C117: 384 | D117: 858 | E117: 512 | F117: 577 | G117: 679 | H117: 420 | I117: 610 | J117: 822 | K117: 588 | L117: 673 | M117: 603 | O117: 365 | P117: 570 | Q117: 384 | R117: 606 | S117: 577 | T117: 623 | U117: =D117 -> 858 | V117: 592 | W117: 674 | X117: 704 | Y117: =E117 -> 512 | Z117: 481 | AA117: 466 | AB117: 506 | AC117: =F117 -> 577 | AD117: 597 | AE117: 630 | AF117: 617 | AG117: =G117 -> 679 | AH117: 614 | AI117: 544 | AJ117: 606 | AK117: =H117 -> 420 | AL117: 476 | AM117: 598 | AN117: 638 | AO117: =I117 -> 610 | AP117: 671 | AQ117: 616 | AR117: 642
...

Sheet Reported Rev.. Split
C3: FY 2024 | D3: FY 2023 | E3: FY 2022 | F3: FY 2021 | G3: FY 2020 | H3: FY 2019 | I3: FY 2018 | J3: FY 2017 | K3: FY 2016 | M3: Q22025 | N3: Q12025 | O3: Q42024 | P3: Q32024 | Q3: Q22024 | R3: Q12024 | S3: Q42023 | T3: Q32023 | U3: Q22023 | V3: Q12023 | W3: Q12022 | X3: Q42021 | Y3: Q32021 | Z3: Q22021 | AA3: Q12021 | AB3: Q42020 | AC3: Q32020 | AD3: Q2 2020 | AE3: Q1 2020 | AF3: Q4 2019 | AG3: Q3 2019 | AH3: Q2 2019 | AI3: Q1 2019 | AJ3: Q4 2018 | AK3: Q3 2018 | AL3: Q2 2018 | AM3: Q1 2018
B5: הכנסות מחצוניים לפי מגזרים
B6: אשלג | C6: =O6+P6+Q6+R6 -> 1462 | D6: 1973 | E6: 3031 | F6: 1768 | G6: 1183 | H6: 1330 | I6: 1481 | J6: 1258 | K6: 1213 | M6: 347 | N6: 358 | O6: 373 | P6: 341 | Q6: 381 | R6: 367 | S6: =D6-(V6+U6+T6) -> 461 | T6: 477 | U6: 505 | V6: 530 | W6: 728 | X6: =F6-(AA6+Z6+Y6) -> 660 | Y6: 392 | Z6: 370 | AA6: 346 | AB6: =G6-(AE6+AD6+AC6) -> 337 | AC6: 274 | AD6: 301 | AE6: 271 | AF6: =H6-AG6-AH6-AI6 -> 262 | AG6: 333 | AH6: 389 | AI6: 346 | AJ6: =I6-AK6-AL6-AM6 -> 472 | AK6: 368 | AL6: 316 | AM6: 325
B7: פתרונות פוספט | C7: =O7+P7+Q7+R7 -> 2049 | D7: 2141 | E7: 2851 | F7: 2334 | G7: 1871 | H7: 1901 | I7: 2001 | J7: 1938 | K7: 2082 | M7: 589 | N7: 536 | O7: 475 | P7: 529 | Q7: 528 | R7: 517 | S7: =D7-(V7+U7+T7) -> 370 | T7: 559 | U7: 553 | V7: 659 | W7: 748 | X7: =F7-(AA7+Z7+Y7) -> 580 | Y7: 630 | Z7: 599 | AA7: 525 | AB7: =G7-(AE7+AD7+AC7) -> 479 | AC7: 488 | AD7: 421 | AE7: 483 | AF7: =H7-AG7-AH7-AI7 -> 400 | AG7: 491 | AH7: 496 | AI7: 514 | AJ7: =I7-AK7-AL7-AM7 -> 471 | AK7: 513 | AL7: 509 | AM7: 508
B8: מוצרים תעשייתיים | C8: =O8+P8+Q8+R8 -> 1220 | D8: 1206 | E8: 1737 | F8: 1601 | G8: 1242 | H8: 1307 | I8: 1281 | J8: 1179 | K8: 1111 | M8: 315 | N8: 338 | O8: 275 | P8: 305 | Q8: 309 | R8: 331 | S8: =D8-(V8+U8+T8) -> 294 | T8: 264 | U8: 297 | V8: 351 | W8: 488 | X8: =F8-(AA8+Z8+Y8) -> 418 | Y8: 383 | Z8: 406 | AA8: 394 | AB8: =G8-(AE8+AD8+AC8) -> 333 | AC8: 267 | AD8: 281 | AE8: 361 | AF8: =H8-AG8-AH8-AI8 -> 290 | AG8: 337 | AH8: 333 | AI8: 347 | AJ8: =I8-AK8-AL8-AM8 -> 316 | AK8: 325 | AL8: 326 | AM8: 314
B9: פתרונות חדשניים לחקלאות | C9: =O9+P9+Q9+R9 -> 1932 | D9: 2047 | E9: 2376 | F9: 1226 | G9: 715 | H9: 699 | I9: 719 | J9: 671 | K9: 632 | M9: 534 | N9: 491 | O9: 435 | P9: 534 | Q9: 489 | R9: 474 | S9: =D9-(V9+U9+T9) -> 475 | T9: 546 | U9: 473 | V9: 553 | W9: 556 | X9: =F9-(AA9+Z9+Y9) -> 374 | Y9: 379 | Z9: 235 | AA9: 238 | AB9: =G9-(AE9+AD9+AC9) -> 158 | AC9: 168 | AD9: 193 | AE9: 196 | AF9: =H9-AG9-AH9-AI9 -> 145 | AG9: 156 | AH9: 199 | AI9: 199 | AJ9: =I9-AK9-AL9-AM9 -> 142 | AK9: 157 | AL9: 209 | AM9: 211
B10: פעילויות אחרות | C10: =O10+P10+Q10+R10 -> 178 | D10: 169 | E10: 20 | F10: 26 | G10: 32 | H10: 34 | I10: 74 | J10: 372 | K10: 325 | M10: 47 | N10: 44 | O10: 43 | P10: 44 | Q10: 45 | R10: 46 | S10: =D10-(V10+U10+T10) -> 142 | T10: 16 | U10: 6 | V10: 5 | W10: 5 | X10: =F10-(AA10+Z10+Y10) -> 6 | Y10: 6 | Z10: 7 | AA10: 7 | AB10: =G10-(AE10+AD10+AC10) -> 10 | AC10: 7 | AD10: 7 | AE10: 8 | AF10: =H10-AG10-AH10-AI10 -> 9 | AG10: 8 | AH10: 8 | AI10: 9 | AJ10: =I10-AK10-AL10-AM10 -> 9 | AK10: 8 | AL10: 11 | AM10: 46
B11: התאמות | C11: =O11+P11+Q11+R11 -> 0 | D11: 0 | E11: 0 | F11: 0 | G11: 0 | H11: 0 | I11: 0 | J11: 0 | K11: 0 | M11: 0 | N11: 0 | O11: 0 | P11: 0 | Q11: 0 | R11: 0 | S11: =D11-(V11+U11+T11) -> 0 | T11: 0 | U11: 0 | V11: 0 | W11: 0 | X11: =F11-(AA11+Z11+Y11) -> 0 | Y11: 0 | Z11: 0 | AA11: 0 | AB11: =G11-(AE11+AD11+AC11) -> 0 | AC11: 0 | AD11: 0 | AE11: 0 | AF11: =H11-AG11-AH11-AI11 -> 0 | AG11: 0 | AH11: 0 | AI11: 0 | AJ11: =I11-AK11-AL11-AM11 -> 0 | AK11: 0 | AL11: 0 | AM11: 0
B12: סה"כ | C12: =SUM(C6:C11) -> 6841 | D12: =SUM(D6:D11) -> 7536 | E12: =SUM(E6:E11) -> 10015 | F12: =SUM(F6:F11) -> 6955 | G12: =SUM(G6:G11) -> 5043 | H12: =SUM(H6:H11) -> 5271 | I12: =SUM(I6:I11) -> 5556 | J12: =SUM(J6:J11) -> 5418 | K12: =SUM(K6:K11) -> 5363 | M12: =SUM(M6:M11) -> 1832 | N12: =SUM(N6:N11) -> 1767 | O12: =SUM(O6:O11) -> 1601 | P12: =SUM(P6:P11) -> 1753 | Q12: =SUM(Q6:Q11) -> 1752 | R12: =SUM(R6:R11) -> 1735 | S12: =SUM(S6:S11) -> 1742 | T12: =SUM(T6:T11) -> 1862 | ... AM12: =SUM(AM6:AM11) -> 1404
B13: בדיקה | C13: ='IC&CF&BS'!C3-C12 -> 0 | D13: ='IC&CF&BS'!D3-D12 -> 0 | E13: ='IC&CF&BS'!E3-E12 -> 0 | F13: ='IC&CF&BS'!F3-F12 -> 0 | G13: ='IC&CF&BS'!G3-G12 -> 0 | H13: ='IC&CF&BS'!H3-H12 -> 0 | I13: ='IC&CF&BS'!I3-I12 -> 0 | J13: ='IC&CF&BS'!J3-J12 -> 0 | K13: ='IC&CF&BS'!K3-K12 -> 0 | M13: ='IC&CF&BS'!O3-M12 -> 0 | N13: ='IC&CF&BS'!P3-N12 -> 0 | O13: ='IC&CF&BS'!Q3-O12 -> 0 | P13: ='IC&CF&BS'!R3-P12 -> 0 | Q13: ='IC&CF&BS'!S3-Q12 -> 0 | R13: ='IC&CF&BS'!T3-R12 -> 0 | S13: ='IC&CF&BS'!U3-S12 -> 0 | T13: ='IC&CF&BS'!V3-T12 -> 0 | ... V13: ='IC&CF&BS'!X3-V12 -> 0 | W13: ='IC&CF&BS'!AB3-W12 -> 0 | X13: ='IC&CF&BS'!AC3-X12 -> 0 | Y13: ='IC&CF&BS'!AD3-Y12 -> 0 | Z13: ='IC&CF&BS'!AE3-Z12 -> 0 | AA13: ='IC&CF&BS'!AF3-AA12 -> 0 | AB13: ='IC&CF&BS'!AG3-AB12 -> 0 | AC13: ='IC&CF&BS'!AH3-AC12 -> 0 | AD13: ='IC&CF&BS'!AI3-AD12 -> 0 | ... AM13: ='IC&CF&BS'!AR3-AM12 -> 0
B15: שיעור מסך הכנסות
B16: אשלג | C16: =IFERROR(C6/C$12,"") -> 0.21371145 | D16: =IFERROR(D6/D$12,"") -> 0.26180998 | E16: =IFERROR(E6/E$12,"") -> 0.30264603 | F16: =IFERROR(F6/F$12,"") -> 0.25420561 | G16: =IFERROR(G6/G$12,"") -> 0.23458259 | H16: =IFERROR(H6/H$12,"") -> 0.25232404 | I16: =IFERROR(I6/I$12,"") -> 0.26655868 | J16: =IFERROR(J6/J$12,"") -> 0.232189 | K16: =IFERROR(K6/K$12,"") -> 0.22617938 | M16: =IFERROR(M6/M$12,"") -> 0.18941048 | N16: =IFERROR(N6/N$12,"") -> 0.20260328 | O16: =IFERROR(O6/O$12,"") -> 0.23297939 | P16: =IFERROR(P6/P$12,"") -> 0.19452367 | Q16: =IFERROR(Q6/Q$12,"") -> 0.21746575 | R16: =IFERROR(R6/R$12,"") -> 0.21152738 | S16: =IFERROR(S6/S$12,"") -> 0.26463835 | T16: =IFERROR(T6/T$12,"") -> 0.25617615 | ... AM16: =IFERROR(AM6/AM$12,"") -> 0.23148148
B17: פתרונות פוספט | C17: =IFERROR(C7/C$12,"") -> 0.29951761 | D17: =IFERROR(D7/D$12,"") -> 0.28410297 | E17: =IFERROR(E7/E$12,"") -> 0.28467299 | F17: =IFERROR(F7/F$12,"") -> 0.33558591 | G17: =IFERROR(G7/G$12,"") -> 0.37100932 | H17: =IFERROR(H7/H$12,"") -> 0.36065263 | I17: =IFERROR(I7/I$12,"") -> 0.36015119 | J17: =IFERROR(J7/J$12,"") -> 0.35769657 | K17: =IFERROR(K7/K$12,"") -> 0.38821555 | M17: =IFERROR(M7/M$12,"") -> 0.32150655 | N17: =IFERROR(N7/N$12,"") -> 0.30333899 | O17: =IFERROR(O7/O$12,"") -> 0.29668957 | P17: =IFERROR(P7/P$12,"") -> 0.3017684 | Q17: =IFERROR(Q7/Q$12,"") -> 0.30136986 | R17: =IFERROR(R7/R$12,"") -> 0.29798271 | S17: =IFERROR(S7/S$12,"") -> 0.21239954 | T17: =IFERROR(T7/T$12,"") -> 0.30021482 | ... AM17: =IFERROR(AM7/AM$12,"") -> 0.36182336
B18: מוצרים תעשייתיים | C18: =IFERROR(C8/C$12,"") -> 0.1783365 | D18: =IFERROR(D8/D$12,"") -> 0.16003185 | E18: =IFERROR(E8/E$12,"") -> 0.17343984 | F18: =IFERROR(F8/F$12,"") -> 0.2301941 | G18: =IFERROR(G8/G$12,"") -> 0.24628198 | H18: =IFERROR(H8/H$12,"") -> 0.24796054 | I18: =IFERROR(I8/I$12,"") -> 0.23056156 | J18: =IFERROR(J8/J$12,"") -> 0.21760797 | K18: =IFERROR(K8/K$12,"") -> 0.20716017 | M18: =IFERROR(M8/M$12,"") -> 0.17194323 | N18: =IFERROR(N8/N$12,"") -> 0.19128466 | O18: =IFERROR(O8/O$12,"") -> 0.17176765 | P18: =IFERROR(P8/P$12,"") -> 0.17398745 | Q18: =IFERROR(Q8/Q$12,"") -> 0.17636986 | R18: =IFERROR(R8/R$12,"") -> 0.1907781 | S18: =IFERROR(S8/S$12,"") -> 0.16877153 | T18: =IFERROR(T8/T$12,"") -> 0.14178303 | ... AM18: =IFERROR(AM8/AM$12,"") -> 0.22364672
B19: פתרונות חדשניים לחקלאות | C19: =IFERROR(C9/C$12,"") -> 0.28241485 | D19: =IFERROR(D9/D$12,"") -> 0.27162951 | E19: =IFERROR(E9/E$12,"") -> 0.23724413 | F19: =IFERROR(F9/F$12,"") -> 0.17627606 | G19: =IFERROR(G9/G$12,"") -> 0.14178069 | H19: =IFERROR(H9/H$12,"") -> 0.13261241 | I19: =IFERROR(I9/I$12,"") -> 0.12940965 | J19: =IFERROR(J9/J$12,"") -> 0.12384644 | K19: =IFERROR(K9/K$12,"") -> 0.11784449 | M19: =IFERROR(M9/M$12,"") -> 0.29148472 | N19: =IFERROR(N9/N$12,"") -> 0.2778721 | O19: =IFERROR(O9/O$12,"") -> 0.27170518 | P19: =IFERROR(P9/P$12,"") -> 0.30462065 | Q19: =IFERROR(Q9/Q$12,"") -> 0.27910959 | R19: =IFERROR(R9/R$12,"") -> 0.27319885 | S19: =IFERROR(S9/S$12,"") -> 0.27267509 | T19: =IFERROR(T9/T$12,"") -> 0.29323308 | ... AM19: =IFERROR(AM9/AM$12,"") -> 0.1502849
B20: פעילויות אחרות | C20: =IFERROR(C10/C$12,"") -> 0.026019588 | D20: =IFERROR(D10/D$12,"") -> 0.02242569 | E20: =IFERROR(E10/E$12,"") -> 0.0019970045 | F20: =IFERROR(F10/F$12,"") -> 0.0037383178 | G20: =IFERROR(G10/G$12,"") -> 0.0063454293 | H20: =IFERROR(H10/H$12,"") -> 0.0064503889 | I20: =IFERROR(I10/I$12,"") -> 0.013318934 | J20: =IFERROR(J10/J$12,"") -> 0.068660022 | K20: =IFERROR(K10/K$12,"") -> 0.06060041 | M20: =IFERROR(M10/M$12,"") -> 0.025655022 | N20: =IFERROR(N10/N$12,"") -> 0.024900962 | O20: =IFERROR(O10/O$12,"") -> 0.026858214 | P20: =IFERROR(P10/P$12,"") -> 0.025099829 | Q20: =IFERROR(Q10/Q$12,"") -> 0.025684932 | R20: =IFERROR(R10/R$12,"") -> 0.026512968 | S20: =IFERROR(S10/S$12,"") -> 0.081515499 | T20: =IFERROR(T10/T$12,"") -> 0.0085929108 | ... AM20: =IFERROR(AM10/AM$12,"") -> 0.032763533
B21: התאמות
B23: צמיחה שנתית
B24: אשלג | C24: =IFERROR(C6/D6-1,"") -> -0.25899645 | D24: =IFERROR(D6/E6-1,"") -> -0.34905972 | E24: =IFERROR(E6/F6-1,"") -> 0.71436652 | F24: =IFERROR(F6/G6-1,"") -> 0.49450549 | G24: =IFERROR(G6/H6-1,"") -> -0.11052632 | H24: =IFERROR(H6/I6-1,"") -> -0.10195814 | I24: =IFERROR(I6/J6-1,"") -> 0.1772655 | J24: =IFERROR(J6/K6-1,"") -> 0.037098104 | K24: =IFERROR(K6/#REF!-1,"") | M24: =IFERROR(M6/N6-1,"") -> -0.030726257 | N24: =IFERROR(N6/O6-1,"") -> -0.040214477 | O24: =IFERROR(O6/P6-1,"") -> 0.093841642 | P24: =IFERROR(P6/Q6-1,"") -> -0.10498688 | Q24: =IFERROR(Q6/R6-1,"") -> 0.038147139 | R24: =IFERROR(R6/S6-1,"") -> -0.20390456 | S24: =IFERROR(S6/T6-1,"") -> -0.033542977 | T24: =IFERROR(T6/U6-1,"") -> -0.055445545 | ... AM24: =IFERROR(AM6/AN6-1,"")
B25: פתרונות פוספט | C25: =IFERROR(C7/D7-1,"") -> -0.042970574 | D25: =IFERROR(D7/E7-1,"") -> -0.24903543 | E25: =IFERROR(E7/F7-1,"") -> 0.22150814 | F25: =IFERROR(F7/G7-1,"") -> 0.24746125 | G25: =IFERROR(G7/H7-1,"") -> -0.015781168 | H25: =IFERROR(H7/I7-1,"") -> -0.049975012 | I25: =IFERROR(I7/J7-1,"") -> 0.03250774 | J25: =IFERROR(J7/K7-1,"") -> -0.069164265 | K25: =IFERROR(K7/#REF!-1,"") | M25: =IFERROR(M7/N7-1,"") -> 0.098880597 | N25: =IFERROR(N7/O7-1,"") -> 0.12842105 | O25: =IFERROR(O7/P7-1,"") -> -0.1020794 | P25: =IFERROR(P7/Q7-1,"") -> 0.0018939394 | Q25: =IFERROR(Q7/R7-1,"") -> 0.021276596 | R25: =IFERROR(R7/S7-1,"") -> 0.3972973 | S25: =IFERROR(S7/T7-1,"") -> -0.33810376 | T25: =IFERROR(T7/U7-1,"") -> 0.01084991 | ... AM25: =IFERROR(AM7/AN7-1,"")
B26: מוצרים תעשייתיים | C26: =IFERROR(C8/D8-1,"") -> 0.011608624 | D26: =IFERROR(D8/E8-1,"") -> -0.30569948 | E26: =IFERROR(E8/F8-1,"") -> 0.084946908 | F26: =IFERROR(F8/G8-1,"") -> 0.28904992 | G26: =IFERROR(G8/H8-1,"") -> -0.049732211 | H26: =IFERROR(H8/I8-1,"") -> 0.020296643 | I26: =IFERROR(I8/J8-1,"") -> 0.086513995 | J26: =IFERROR(J8/K8-1,"") -> 0.061206121 | K26: =IFERROR(K8/#REF!-1,"") | M26: =IFERROR(M8/N8-1,"") -> -0.068047337 | N26: =IFERROR(N8/O8-1,"") -> 0.22909091 | O26: =IFERROR(O8/P8-1,"") -> -0.098360656 | P26: =IFERROR(P8/Q8-1,"") -> -0.012944984 | Q26: =IFERROR(Q8/R8-1,"") -> -0.066465257 | R26: =IFERROR(R8/S8-1,"") -> 0.12585034 | S26: =IFERROR(S8/T8-1,"") -> 0.11363636 | T26: =IFERROR(T8/U8-1,"") -> -0.11111111 | ... AM26: =IFERROR(AM8/AN8-1,"")
B27: פתרונות חדשניים לחקלאות | C27: =IFERROR(C9/D9-1,"") -> -0.056179775 | D27: =IFERROR(D9/E9-1,"") -> -0.13846801 | E27: =IFERROR(E9/F9-1,"") -> 0.93800979 | F27: =IFERROR(F9/G9-1,"") -> 0.71468531 | G27: =IFERROR(G9/H9-1,"") -> 0.022889843 | H27: =IFERROR(H9/I9-1,"") -> -0.027816412 | I27: =IFERROR(I9/J9-1,"") -> 0.071535022 | J27: =IFERROR(J9/K9-1,"") -> 0.061708861 | K27: =IFERROR(K9/#REF!-1,"") | M27: =IFERROR(M9/N9-1,"") -> 0.087576375 | N27: =IFERROR(N9/O9-1,"") -> 0.12873563 | O27: =IFERROR(O9/P9-1,"") -> -0.18539326 | P27: =IFERROR(P9/Q9-1,"") -> 0.09202454 | Q27: =IFERROR(Q9/R9-1,"") -> 0.03164557 | R27: =IFERROR(R9/S9-1,"") -> -0.0021052632 | S27: =IFERROR(S9/T9-1,"") -> -0.13003663 | T27: =IFERROR(T9/U9-1,"") -> 0.15433404 | ... AM27: =IFERROR(AM9/AN9-1,"")
B28: פעילויות אחרות | C28: =IFERROR(C10/D10-1,"") -> 0.053254438 | D28: =IFERROR(D10/E10-1,"") -> 7.45 | E28: =IFERROR(E10/F10-1,"") -> -0.23076923 | F28: =IFERROR(F10/G10-1,"") -> -0.1875 | G28: =IFERROR(G10/H10-1,"") -> -0.058823529 | H28: =IFERROR(H10/I10-1,"") -> -0.54054054 | I28: =IFERROR(I10/J10-1,"") -> -0.80107527 | J28: =IFERROR(J10/K10-1,"") -> 0.14461538 | K28: =IFERROR(K10/#REF!-1,"") | M28: =IFERROR(M10/N10-1,"") -> 0.068181818 | N28: =IFERROR(N10/O10-1,"") -> 0.023255814 | O28: =IFERROR(O10/P10-1,"") -> -0.022727273 | P28: =IFERROR(P10/Q10-1,"") -> -0.022222222 | Q28: =IFERROR(Q10/R10-1,"") -> -0.02173913 | R28: =IFERROR(R10/S10-1,"") -> -0.67605634 | S28: =IFERROR(S10/T10-1,"") -> 7.875 | T28: =IFERROR(T10/U10-1,"") -> 1.6666667 | ... AM28: =IFERROR(AM10/AN10-1,"")
B29: התאמות | C29: =IFERROR(C11/D11-1,"") | D29: =IFERROR(D11/E11-1,"") | E29: =IFERROR(E11/F11-1,"") | F29: =IFERROR(F11/G11-1,"") | G29: =IFERROR(G11/H11-1,"") | H29: =IFERROR(H11/I11-1,"") | I29: =IFERROR(I11/J11-1,"") | J29: =IFERROR(J11/K11-1,"") | K29: =IFERROR(K11/#REF!-1,"") | M29: =IFERROR(M11/N11-1,"") | N29: =IFERROR(N11/O11-1,"") | O29: =IFERROR(O11/P11-1,"") | P29: =IFERROR(P11/Q11-1,"") | Q29: =IFERROR(Q11/R11-1,"") | R29: =IFERROR(R11/S11-1,"") | S29: =IFERROR(S11/T11-1,"") | T29: =IFERROR(T11/U11-1,"") | ... AM29: =IFERROR(AM11/AN11-1,"")
B30: סה"כ | C30: =IFERROR(C12/D12-1,"") -> -0.092223992 | D30: =IFERROR(D12/E12-1,"") -> -0.24752871 | E30: =IFERROR(E12/F12-1,"") -> 0.43997124 | F30: =IFERROR(F12/G12-1,"") -> 0.3791394 | G30: =IFERROR(G12/H12-1,"") -> -0.043255549 | H30: =IFERROR(H12/I12-1,"") -> -0.051295896 | I30: =IFERROR(I12/J12-1,"") -> 0.025470653 | J30: =IFERROR(J12/K12-1,"") -> 0.010255454 | K30: =IFERROR(K12/#REF!-1,"") | M30: =IFERROR(M12/N12-1,"") -> 0.036785512 | N30: =IFERROR(N12/O12-1,"") -> 0.1036852 | O30: =IFERROR(O12/P12-1,"") -> -0.0867085 | P30: =IFERROR(P12/Q12-1,"") -> 0.00057077626 | Q30: =IFERROR(Q12/R12-1,"") -> 0.0097982709 | R30: =IFERROR(R12/S12-1,"") -> -0.0040183697 | S30: =IFERROR(S12/T12-1,"") -> -0.064446831 | T30: =IFERROR(T12/U12-1,"") -> 0.015267176 | ... AM30: =IFERROR(AM12/AN12-1,"")
B32: רווח (הפסד) מגזרי
B33: אשלג | C33: =O33+P33+Q33+R33 -> 250 | D33: 668 | E33: 1822 | F33: 399 | G33: 120 | H33: 289 | I33: 315 | J33: 198 | K33: 245 | M33: 52 | N33: 56 | O33: 69 | P33: 59 | Q33: 60 | R33: 62 | S33: =D33-(V33+U33+T33) -> 122 | T33: 125 | U33: 167 | V33: 254 | W33: 410 | X33: =F33-(AA33+Z33+Y33) -> 244 | Y33: 83 | Z33: 43 | AA33: 29 | AB33: =G33-(AE33+AD33+AC33) -> 40 | AC33: 28 | AD33: 38 | AE33: 14 | AF33: =H33-AG33-AH33-AI33 -> 22 | AG33: 83 | AH33: 105 | AI33: 79 | AJ33: =I33-AK33-AL33-AM33 -> 138 | AK33: 78 | AL33: 56 | AM33: 43 | AO33: =K33 -> 245 | AP33: =AO33/$AO$39 -> 0.41315346 | AQ33: =AP33*$AO$40 -> -132.62226 | AR33: =AO33+AQ33 -> 112.37774
B34: פתרונות פוספט | C34: =O34+P34+Q34+R34 -> 358 | D34: 350 | E34: 777 | F34: 307 | G34: 66 | H34: 100 | I34: 113 | J34: 53 | K34: 75 | M34: 90 | N34: 91 | O34: 81 | P34: 100 | Q34: 93 | R34: 84 | S34: =D34-(V34+U34+T34) -> 95 | T34: 69 | U34: 71 | V34: 115 | W34: 200 | X34: =F34-(AA34+Z34+Y34) -> 97 | Y34: 93 | Z34: 77 | AA34: 40 | AB34: =G34-(AE34+AD34+AC34) -> 21 | AC34: 28 | AD34: 8 | AE34: 9 | AF34: =H34-AG34-AH34-AI34 -> 1 | AG34: 32 | AH34: 32 | AI34: 35 | AJ34: =I34-AK34-AL34-AM34 -> 14 | AK34: 40 | AL34: 31 | AM34: 28 | AO34: =K34 -> 75 | AP34: =AO34/$AO$39 -> 0.12647555 | AQ34: =AP34*$AO$40 -> -40.598651 | AR34: =AO34+AQ34 -> 34.401349
B35: מוצרים תעשייתיים | C35: =O35+P35+Q35+R35 -> 224 | D35: 220 | E35: 628 | F35: 435 | G35: 303 | H35: 338 | I35: 300 | J35: 247 | K35: 241 | M35: 54 | N35: 62 | O35: 55 | P35: 50 | Q35: 60 | R35: 59 | S35: =D35-(V35+U35+T35) -> 39 | T35: 31 | U35: 60 | V35: 90 | W35: 188 | X35: =F35-(AA35+Z35+Y35) -> 111 | Y35: 105 | Z35: 114 | AA35: 105 | AB35: =G35-(AE35+AD35+AC35) -> 80 | AC35: 50 | AD35: 70 | AE35: 103 | AF35: =H35-AG35-AH35-AI35 -> 60 | AG35: 88 | AH35: 93 | AI35: 97 | AJ35: =I35-AK35-AL35-AM35 -> 70 | AK35: 83 | AL35: 81 | AM35: 66 | AO35: =K35 -> 241 | AP35: =AO35/$AO$39 -> 0.40640809 | AQ35: =AP35*$AO$40 -> -130.457 | AR35: =AO35+AQ35 -> 110.543
B36: פתרונות חדשניים לחקלאות | C36: =O36+P36+Q36+R36 -> 128 | D36: 51 | E36: 378 | F36: 121 | G36: 40 | H36: 21 | I36: 29 | J36: 29 | K36: 28 | M36: 35 | N36: 28 | O36: 31 | P36: 49 | Q36: 25 | R36: 23 | S36: =D36-(V36+U36+T36) -> -5 | T36: 20 | U36: 4 | V36: 32 | W36: 93 | X36: =F36-(AA36+Z36+Y36) -> 33 | Y36: 46 | Z36: 20 | AA36: 22 | AB36: =G36-(AE36+AD36+AC36) -> 5 | AC36: 6 | AD36: 15 | AE36: 14 | AF36: =H36-AG36-AH36-AI36 -> -2 | AG36: -2 | AH36: 12 | AI36: 13 | AJ36: =I36-AK36-AL36-AM36 -> -4 | AK36: -1 | AL36: 16 | AM36: 18 | AO36: =K36 -> 28 | AP36: =AO36/$AO$39 -> 0.047217538 | AQ36: =AP36*$AO$40 -> -15.15683 | AR36: =AO36+AQ36 -> 12.84317
B37: פעילויות אחרות | C37: =O37+P37+Q37+R37 -> -22 | D37: -34 | E37: -9 | F37: -8 | G37: -5 | H37: 19 | I37: 9 | J37: 127 | K37: 41 | M37: -2 | N37: -3 | O37: -8 | P37: -7 | Q37: -4 | R37: -3 | S37: =D37-(V37+U37+T37) -> -22 | T37: -7 | U37: -3 | V37: -2 | W37: -3 | X37: =F37-(AA37+Z37+Y37) -> -1 | Y37: -3 | Z37: -2 | AA37: -2 | AB37: =G37-(AE37+AD37+AC37) -> -2 | AC37: -1 | AD37: -2 | AE37: 0 | AF37: =H37-AG37-AH37-AI37 -> 2 | AG37: 5 | AH37: -1 | AI37: 13 | AJ37: =I37-AK37-AL37-AM37 -> 0 | AK37: 1 | AL37: 2 | AM37: 6 | AO37: =K37 -> 41 | AP37: =AO37/$AO$39 -> 0.069139966 | AQ37: =AP37*$AO$40 -> -22.193929 | AR37: =AO37+AQ37 -> 18.806071
B38: התאמות | C38: =O38+P38+Q38+R38 -> -65 | D38: -37 | E38: -87 | F38: -60 | G38: -15 | H38: -7 | I38: -13 | J38: -2 | K38: -37 | M38: -28 | N38: -26 | O38: -38 | P38: -8 | Q38: -9 | R38: -10 | S38: =D38-(V38+U38+T38) -> -18 | T38: -11 | U38: 1 | V38: -9 | W38: -8 | X38: =F38-(AA38+Z38+Y38) -> -26 | Y38: -9 | Z38: -16 | AA38: -9 | AB38: =G38-(AE38+AD38+AC38) -> -1 | AC38: -5 | AD38: -1 | AE38: -8 | AF38: =H38-AG38-AH38-AI38 -> 5 | AG38: -5 | AH38: -11 | AI38: 4 | AJ38: =I38-AK38-AL38-AM38 -> -4 | AK38: -1 | AL38: 2 | AM38: -10 | AO38: =K38 -> -37 | AP38: =AO38/$AO$39 -> -0.062394604 | AQ38: =AP38*$AO$40 -> 20.028668 | AR38: =AO38+AQ38 -> -16.971332
B39: סה"כ רווח מגזרי כולל חלק החברה ברווח של שותפויות בשליטה משותפת | C39: =SUM(C33:C38) -> 873 | D39: =SUM(D33:D38) -> 1218 | E39: =SUM(E33:E38) -> 3509 | F39: =SUM(F33:F38) -> 1194 | G39: =SUM(G33:G38) -> 509 | H39: =SUM(H33:H38) -> 760 | I39: =SUM(I33:I38) -> 753 | J39: =SUM(J33:J38) -> 652 | K39: =SUM(K33:K38) -> 593 | M39: =SUM(M33:M38) -> 201 | N39: =SUM(N33:N38) -> 208 | O39: =SUM(O33:O38) -> 190 | P39: =SUM(P33:P38) -> 243 | Q39: =SUM(Q33:Q38) -> 225 | R39: =SUM(R33:R38) -> 215 | S39: =SUM(S33:S38) -> 211 | T39: =SUM(T33:T38) -> 227 | ... AM39: =SUM(AM33:AM38) -> 151 | AO39: =SUM(AO33:AO38) -> 593 | AP39: =AO39/$AO$39 -> 1 | AQ39: =AP39*$AO$40 -> -321 | AR39: =SUM(AR33:AR38) -> 272
B40: הוצאות לא משוייכות | C40: =O40+P40+Q40+R40 -> -98 | D40: -77 | E40: 7 | F40: 16 | G40: -307 | H40: -4 | I40: 766 | J40: -23 | K40: -323 | M40: -20 | N40: -23 | O40: -43 | P40: -29 | Q40: -14 | R40: -12 | S40: =D40-(V40+U40+T40) -> -62 | T40: 0 | U40: 0 | V40: -15 | W40: 22 | X40: =F40-(AA40+Z40+Y40) -> 3 | Y40: 6 | Z40: 7 | AA40: 0 | AB40: =G40-(AE40+AD40+AC40) -> -4 | AC40: -6 | AD40: -297 | AE40: 0 | AF40: 0 | AG40: 0 | AH40: 10 | AI40: -14 | AJ40: =I40-AK40-AL40-AM40 -> -48 | AK40: -4 | AL40: -16 | AM40: 834 | AO40: -321
B41: רווח תפעולי לפני אחרות | C41: =SUM(C39:C40) -> 775 | D41: =SUM(D39:D40) -> 1141 | E41: =SUM(E39:E40) -> 3516 | F41: =SUM(F39:F40) -> 1210 | G41: =SUM(G39:G40) -> 202 | H41: =SUM(H39:H40) -> 756 | I41: =SUM(I39:I40) -> 1519 | J41: =SUM(J39:J40) -> 629 | K41: =SUM(K39:K40) -> 270 | M41: =SUM(M39:M40) -> 181 | N41: =SUM(N39:N40) -> 185 | O41: =SUM(O39:O40) -> 147 | P41: =SUM(P39:P40) -> 214 | Q41: =SUM(Q39:Q40) -> 211 | R41: =SUM(R39:R40) -> 203 | S41: =SUM(S39:S40) -> 149 | T41: =SUM(T39:T40) -> 227 | ... AM41: =SUM(AM39:AM40) -> 985
C42: ='IC&CF&BS'!C9+'IC&CF&BS'!C10-C41 -> 0 | D42: ='IC&CF&BS'!D9+'IC&CF&BS'!D10-D41 -> 0 | E42: ='IC&CF&BS'!E9+'IC&CF&BS'!E10-E41 -> 0 | F42: ='IC&CF&BS'!F9+'IC&CF&BS'!F10-F41 -> 0 | G42: ='IC&CF&BS'!G9+'IC&CF&BS'!G10-G41 -> 0 | H42: ='IC&CF&BS'!H9+'IC&CF&BS'!H10-H41 -> 0 | I42: ='IC&CF&BS'!I9+'IC&CF&BS'!I10-I41 -> 0 | J42: ='IC&CF&BS'!J9+'IC&CF&BS'!J10-J41 -> 0 | K42: ='IC&CF&BS'!K9+'IC&CF&BS'!K10 -> -3 | M42: ='IC&CF&BS'!O9+'IC&CF&BS'!O10-M41 -> 0 | N42: ='IC&CF&BS'!P9+'IC&CF&BS'!P10-N41 -> 0 | O42: ='IC&CF&BS'!Q9+'IC&CF&BS'!Q10-O41 -> 0 | P42: ='IC&CF&BS'!R9+'IC&CF&BS'!R10-P41 -> 0 | Q42: ='IC&CF&BS'!S9+'IC&CF&BS'!S10-Q41 -> 0 | R42: ='IC&CF&BS'!T9+'IC&CF&BS'!T10-R41 -> 0 | S42: ='IC&CF&BS'!U9+'IC&CF&BS'!U10-S41 -> 0 | T42: ='IC&CF&BS'!V9+'IC&CF&BS'!V10-T41 -> 0 | ... V42: ='IC&CF&BS'!X9+'IC&CF&BS'!X10-V41 -> 0 | W42: ='IC&CF&BS'!AB9+'IC&CF&BS'!AB10-W41 -> 0 | X42: ='IC&CF&BS'!AC9+'IC&CF&BS'!AC10-X41 -> 0 | Y42: ='IC&CF&BS'!AD9+'IC&CF&BS'!AD10-Y41 -> 0 | Z42: ='IC&CF&BS'!AE9+'IC&CF&BS'!AE10-Z41 -> 0 | AA42: ='IC&CF&BS'!AF9+'IC&CF&BS'!AF10-AA41 -> 0 | AB42: ='IC&CF&BS'!AG9+'IC&CF&BS'!AG10-AB41 -> 0 | AC42: ='IC&CF&BS'!AH9+'IC&CF&BS'!AH10-AC41 -> 0 | AD42: ='IC&CF&BS'!AI9+'IC&CF&BS'!AI10-AD41 -> 0 | ... AM42: ='IC&CF&BS'!AR9+'IC&CF&BS'!AR10-AM41 -> 0
B43: שיעור הרווח התפעולי (מגזרי)
B44: אשלג | C44: =IFERROR(C33/C6,"") -> 0.17099863 | D44: =IFERROR(D33/D6,"") -> 0.3385707 | E44: =IFERROR(E33/E6,"") -> 0.60112174 | F44: =IFERROR(F33/F6,"") -> 0.22567873 | G44: =IFERROR(G33/G6,"") -> 0.10143702 | H44: =IFERROR(H33/H6,"") -> 0.21729323 | I44: =IFERROR(I33/I6,"") -> 0.21269413 | J44: =IFERROR(J33/J6,"") -> 0.15739269 | K44: =IFERROR(K33/K6,"") -> 0.20197857 | M44: =IFERROR(M33/M6,"") -> 0.14985591 | N44: =IFERROR(N33/N6,"") -> 0.15642458 | O44: =IFERROR(O33/O6,"") -> 0.1849866 | P44: =IFERROR(P33/P6,"") -> 0.17302053 | Q44: =IFERROR(Q33/Q6,"") -> 0.15748031 | R44: =IFERROR(R33/R6,"") -> 0.16893733 | S44: =IFERROR(S33/S6,"") -> 0.26464208 | T44: =IFERROR(T33/T6,"") -> 0.26205451 | ... AM44: =IFERROR(AM33/AM6,"") -> 0.13230769
B45: פתרונות פוספט | C45: =IFERROR(C34/C7,"") -> 0.17471938 | D45: =IFERROR(D34/D7,"") -> 0.16347501 | E45: =IFERROR(E34/E7,"") -> 0.27253595 | F45: =IFERROR(F34/F7,"") -> 0.13153385 | G45: =IFERROR(G34/G7,"") -> 0.035275254 | H45: =IFERROR(H34/H7,"") -> 0.052603893 | I45: =IFERROR(I34/I7,"") -> 0.056471764 | J45: =IFERROR(J34/J7,"") -> 0.027347781 | K45: =IFERROR(K34/K7,"") -> 0.036023055 | M45: =IFERROR(M34/M7,"") -> 0.15280136 | N45: =IFERROR(N34/N7,"") -> 0.16977612 | O45: =IFERROR(O34/O7,"") -> 0.17052632 | P45: =IFERROR(P34/P7,"") -> 0.18903592 | Q45: =IFERROR(Q34/Q7,"") -> 0.17613636 | R45: =IFERROR(R34/R7,"") -> 0.16247582 | S45: =IFERROR(S34/S7,"") -> 0.25675676 | T45: =IFERROR(T34/T7,"") -> 0.1234347 | ... AM45: =IFERROR(AM34/AM7,"") -> 0.05511811
B46: מוצרים תעשייתיים | C46: =IFERROR(C35/C8,"") -> 0.18360656 | D46: =IFERROR(D35/D8,"") -> 0.18242123 | E46: =IFERROR(E35/E8,"") -> 0.36154289 | F46: =IFERROR(F35/F8,"") -> 0.27170518 | G46: =IFERROR(G35/G8,"") -> 0.24396135 | H46: =IFERROR(H35/H8,"") -> 0.2586075 | I46: =IFERROR(I35/I8,"") -> 0.23419204 | J46: =IFERROR(J35/J8,"") -> 0.20949958 | K46: =IFERROR(K35/K8,"") -> 0.21692169 | M46: =IFERROR(M35/M8,"") -> 0.17142857 | N46: =IFERROR(N35/N8,"") -> 0.18343195 | O46: =IFERROR(O35/O8,"") -> 0.2 | P46: =IFERROR(P35/P8,"") -> 0.16393443 | Q46: =IFERROR(Q35/Q8,"") -> 0.19417476 | R46: =IFERROR(R35/R8,"") -> 0.17824773 | S46: =IFERROR(S35/S8,"") -> 0.13265306 | T46: =IFERROR(T35/T8,"") -> 0.11742424 | ... AM46: =IFERROR(AM35/AM8,"") -> 0.21019108
B47: פתרונות חדשניים לחקלאות | C47: =IFERROR(C36/C9,"") -> 0.066252588 | D47: =IFERROR(D36/D9,"") -> 0.024914509 | E47: =IFERROR(E36/E9,"") -> 0.15909091 | F47: =IFERROR(F36/F9,"") -> 0.098694943 | G47: =IFERROR(G36/G9,"") -> 0.055944056 | H47: =IFERROR(H36/H9,"") -> 0.030042918 | I47: =IFERROR(I36/I9,"") -> 0.040333797 | J47: =IFERROR(J36/J9,"") -> 0.043219076 | K47: =IFERROR(K36/K9,"") -> 0.044303797 | M47: =IFERROR(M36/M9,"") -> 0.065543071 | N47: =IFERROR(N36/N9,"") -> 0.057026477 | O47: =IFERROR(O36/O9,"") -> 0.071264368 | P47: =IFERROR(P36/P9,"") -> 0.0917603 | Q47: =IFERROR(Q36/Q9,"") -> 0.051124744 | R47: =IFERROR(R36/R9,"") -> 0.048523207 | S47: =IFERROR(S36/S9,"") -> -0.010526316 | T47: =IFERROR(T36/T9,"") -> 0.036630037 | ... AM47: =IFERROR(AM36/AM9,"") -> 0.085308057
B48: פעילויות אחרות | C48: =IFERROR(C37/C10,"") -> -0.12359551 | D48: =IFERROR(D37/D10,"") -> -0.20118343 | E48: =IFERROR(E37/E10,"") -> -0.45 | F48: =IFERROR(F37/F10,"") -> -0.30769231 | G48: =IFERROR(G37/G10,"") -> -0.15625 | H48: =IFERROR(H37/H10,"") -> 0.55882353 | I48: =IFERROR(I37/I10,"") -> 0.12162162 | J48: =IFERROR(J37/J10,"") -> 0.34139785 | K48: =IFERROR(K37/K10,"") -> 0.12615385 | M48: =IFERROR(M37/M10,"") -> -0.042553191 | N48: =IFERROR(N37/N10,"") -> -0.068181818 | O48: =IFERROR(O37/O10,"") -> -0.18604651 | P48: =IFERROR(P37/P10,"") -> -0.15909091 | Q48: =IFERROR(Q37/Q10,"") -> -0.088888889 | R48: =IFERROR(R37/R10,"") -> -0.065217391 | S48: =IFERROR(S37/S10,"") -> -0.15492958 | T48: =IFERROR(T37/T10,"") -> -0.4375 | ... AM48: =IFERROR(AM37/AM10,"") -> 0.13043478
B49: סה"כ רווח מגזרי כולל חלק החברה ברווח של שותפויות בשליטה משותפת | C49: =IFERROR(C39/C12,"") -> 0.12761292 | D49: =IFERROR(D39/D12,"") -> 0.1616242 | E49: =IFERROR(E39/E12,"") -> 0.35037444 | F49: =IFERROR(F39/F12,"") -> 0.17167505 | G49: =IFERROR(G39/G12,"") -> 0.10093198 | H49: =IFERROR(H39/H12,"") -> 0.14418516 | I49: =IFERROR(I39/I12,"") -> 0.13552916 | J49: =IFERROR(J39/J12,"") -> 0.12033961 | K49: =IFERROR(K39/K12,"") -> 0.11057244 | M49: =IFERROR(M39/M12,"") -> 0.10971616 | N49: =IFERROR(N39/N12,"") -> 0.11771364 | O49: =IFERROR(O39/O12,"") -> 0.11867583 | P49: =IFERROR(P39/P12,"") -> 0.13861951 | Q49: =IFERROR(Q39/Q12,"") -> 0.12842466 | R49: =IFERROR(R39/R12,"") -> 0.12391931 | S49: =IFERROR(S39/S12,"") -> 0.12112514 | T49: =IFERROR(T39/T12,"") -> 0.12191192 | ... AM49: =IFERROR(AM39/AM12,"") -> 0.10754986
B51: Capex
B52: אשלג | C52: =W52+V52+U52+T52 -> 348 | D52: 384 | E52: 346 | F52: 298 | G52: 296 | H52: 383 | I52: =356 -> 356 | J52: 270 | K52: 311 | T52: 116 | U52: 87 | V52: 79 | W52: 66
B53: פתרונות פוספט | C53: =W53+V53+U53+T53 -> 328 | D53: 270 | E53: 259 | F53: 238 | G53: 275 | H53: 213 | I53: 180 | J53: 154 | K53: 237 | T53: 147 | U53: 70 | V53: 59 | W53: 52
B54: מוצרים תעשייתיים | C54: =W54+V54+U54+T54 -> 94 | D54: 91 | E54: 90 | F54: 74 | G54: 84 | H54: 66 | I54: 50 | J54: 49 | K54: 38 | T54: 38 | U54: 21 | V54: 19 | W54: 16 | AC54: שיעור מגזרי מהרווח התפעולי Q1-22 | AH54: שיעור מגזרי מהרווח התפעולי 2021 | AN54: שיעור מגזרי מהרווח התפעולי 2019 | AR54: שיעור מגזרי מהרווח התפעולי 2013
B55: פתרונות חדשניים לחקלאות | C55: =W55+V55+U55+T55 -> 93 | D55: 92 | E55: 101 | F55: 36 | G55: 20 | H55: 21 | I55: 15 | J55: 12 | K55: 7 | T55: 44 | U55: 20 | V55: 14 | W55: 15 | AC55: =AH55 -> אשלג | AD55: =AE55/$AE$61 -> 0.46590909 | AE55: =W33 -> 410 | AH55: =AN55 -> אשלג | AI55: =AJ55/$AJ$61 -> 0.33417085 | AJ55: =F33 -> 399 | AN55: =B33 -> אשלג | AO55: =AP55/$AP$61 -> 0.3767927 | AP55: =H33 -> 289 | AR55: =K33 -> 245 | AS55: =AT55/$AT$61 -> 0.631012 | AT55: 996.491
B56: פעילויות אחרות | C56: =W56+V56+U56+T56 -> 8 | D56: 13 | E56: 9 | F56: 6 | G56: 6 | H56: 4 | I56: 1 | J56: 19 | K56: 1 | T56: 3 | U56: 2 | V56: 2 | W56: 1 | AC56: =AH56 -> פתרונות פוספט | AD56: =AE56/$AE$61 -> 0.22727273 | AE56: =W34 -> 200 | AH56: =AN56 -> פתרונות פוספט | AI56: =AJ56/$AJ$61 -> 0.25711893 | AJ56: =F34 -> 307 | AN56: =B34 -> פתרונות פוספט | AO56: =AP56/$AP$61 -> 0.1303781 | AP56: =H34 -> 100 | AR56: =K34 -> 75 | AS56: =AT56/$AT$61 -> 0.1028999 | AT56: 162.499
B57: התאמות | C57: =W57+V57+U57+T57 -> 28 | D57: 23 | E57: 17 | F57: 17 | G57: 15 | H57: 6 | I57: 3 | J57: 3 | K57: 58 | T57: 12 | U57: 7 | V57: 4 | W57: 5 | AC57: =AH57 -> מוצרים תעשייתיים | AD57: =AE57/$AE$61 -> 0.21363636 | AE57: =W35 -> 188 | AH57: =AN57 -> מוצרים תעשייתיים | AI57: =AJ57/$AJ$61 -> 0.36432161 | AJ57: =F35 -> 435 | AN57: =B35 -> מוצרים תעשייתיים | AO57: =AP57/$AP$61 -> 0.44067797 | AP57: =H35 -> 338 | AR57: =K35 -> 241 | AS57: =AT57/$AT$61 -> 0.14609215 | AT57: 230.708
B58: סה"כ | C58: =SUM(C52:C57) -> 899 | D58: =SUM(D52:D57) -> 873 | E58: =SUM(E52:E57) -> 822 | F58: =SUM(F52:F57) -> 669 | G58: =SUM(G52:G57) -> 696 | H58: =SUM(H52:H57) -> 693 | I58: =SUM(I52:I57) -> 605 | J58: =SUM(J52:J57) -> 507 | K58: =SUM(K52:K57) -> 652 | T58: =SUM(T52:T57) -> 360 | U58: =SUM(U52:U57) -> 207 | V58: =SUM(V52:V57) -> 177 | W58: =SUM(W52:W57) -> 155 | AC58: =AH58 -> פתרונות חדשניים לחקלאות | AD58: =AE58/$AE$61 -> 0.10568182 | AE58: =W36 -> 93 | AH58: =AN58 -> פתרונות חדשניים לחקלאות | AI58: =AJ58/$AJ$61 -> 0.10134003 | AJ58: =F36 -> 121 | AN58: =B36 -> פתרונות חדשניים לחקלאות | AO58: =AP58/$AP$61 -> 0.0273794 | AP58: =H36 -> 21 | AR58: =K36 -> 28 | AS58: =AT58/$AT$61 -> 0.1139283 | AT58: 179.915
B59: השקעה הונית כתוצאה מצירוף עסקיןם | C59: =U59+T59 -> 92 | F59: 377 | T59: 4 | U59: 88 | AC59: =AH59 -> 0 | AE59: =W37 -> -3 | AH59: =AN59 -> 0 | AJ59: =F37 -> -8
B60: פער מול תזרים | C60: =-'IC&CF&BS'!C75-C58 -> -186 | D60: =-'IC&CF&BS'!D75-D58 -> -93 | E60: =-'IC&CF&BS'!E75-E58 -> -75 | F60: =-'IC&CF&BS'!F75-F58 -> -58 | G60: =-'IC&CF&BS'!G75-G58 -> -70 | H60: =-'IC&CF&BS'!H75-H58 -> -117 | I60: =-'IC&CF&BS'!I75-I58 -> -33 | J60: =-'IC&CF&BS'!J75-J58 -> -50 | K60: =-'IC&CF&BS'!K75-K58 -> -20 | T60: =-'IC&CF&BS'!T75-T58 -> -215 | U60: =-'IC&CF&BS'!U75-U58 -> 48 | V60: =-'IC&CF&BS'!V75-V58 -> 14 | W60: =-'IC&CF&BS'!W75-W58 -> 15 | AC60: =AH60 -> פעילויות אחרות | AD60: =AE60/$AE$61 -> -0.0090909091 | AE60: =W38 -> -8 | AH60: =AN60 -> פעילויות אחרות | AI60: =AJ60/$AJ$61 -> -0.050251256 | AJ60: =F38 -> -60 | AN60: =B37 -> פעילויות אחרות | AO60: =AP60/$AP$61 -> 0.024771838 | AP60: =H37 -> 19 | AR60: =K37 -> 41 | AS60: =AT60/$AT$61 -> 0.0060676484 | AT60: 9.582
AC61: =AH61 -> 0 | AD61: =AE61/$AE$61 -> 1 | AE61: =SUM(AE55:AE60) -> 880 | AH61: =AN61 -> 0 | AI61: =AJ61/$AJ$61 -> 1 | AJ61: =SUM(AJ55:AJ60) -> 1194 | AO61: =AP61/$AP$61 -> 1 | AP61: =SUM(AP55:AP60) -> 767 | AS61: =AT61/$AT$61 -> 1 | AT61: =SUM(AT55:AT60) -> 1579.195
B62: פחת והפחתות
B63: אשלג | C63: =W63+V63+U63+T63 -> 230 | D63: 175 | E63: 166 | F63: 165 | G63: 166 | H63: 149 | I63: =141 -> 141 | J63: 128 | K63: 127 | T63: 61 | U63: 61 | V63: 46 | W63: 62
B64: פתרונות פוספט | C64: =W64+V64+U64+T64 -> 194 | D64: 207 | E64: 189 | F64: 215 | G64: 210 | H64: 177 | I64: 172 | J64: 172 | K64: 203 | T64: 51 | U64: 40 | V64: 56 | W64: 47
B65: מוצרים תעשייתיים | C65: =W65+V65+U65+T65 -> 57 | D65: 57 | E65: 61 | F65: 65 | G65: 77 | H65: 67 | I65: 63 | J65: 61 | K65: 52 | T65: 15 | U65: 15 | V65: 14 | W65: 13
B66: פתרונות חדשניים לחקלאות | C66: =W66+V66+U66+T66 -> 72 | D66: 68 | E66: 70 | F66: 38 | G66: 25 | H66: 21 | I66: 19 | J66: 19 | K66: 17 | T66: 20 | U66: 15 | V66: 18 | W66: 19
B67: פעילויות אחרות | C67: =W67+V67+U67+T67 -> 14 | D67: 17 | E67: 3 | F67: 2 | G67: 3 | H67: 22 | I67: 4 | J67: 8 | K67: 3 | T67: 4 | U67: 3 | V67: 3 | W67: 4
B68: התאמות | C68: =W68+V68+U68+T68 -> 32 | D68: 12 | E68: 9 | F68: -1 | G68: 98 | H68: -3 | I68: 21 | J68: 3 | K68: 4 | T68: 13 | U68: 13 | V68: 4 | W68: 2
B69: סה"כ | C69: =SUM(C63:C68) -> 599 | D69: =SUM(D63:D68) -> 536 | E69: =SUM(E63:E68) -> 498 | F69: =SUM(F63:F68) -> 484 | G69: =SUM(G63:G68) -> 579 | H69: =SUM(H63:H68) -> 433 | I69: =SUM(I63:I68) -> 420 | J69: =SUM(J63:J68) -> 391 | K69: =SUM(K63:K68) -> 406 | T69: =SUM(T63:T68) -> 164 | U69: =SUM(U63:U68) -> 147 | V69: =SUM(V63:V68) -> 141 | W69: =SUM(W63:W68) -> 147
B70: פער מול תזרים | C70: ='IC&CF&BS'!C46+'IC&CF&BS'!C47-C69 -> 11 | D70: ='IC&CF&BS'!D46+'IC&CF&BS'!D47-D69 -> 0 | E70: ='IC&CF&BS'!E46+'IC&CF&BS'!E47-E69 -> 0 | F70: ='IC&CF&BS'!F46+'IC&CF&BS'!F47-F69 -> 0 | G70: ='IC&CF&BS'!G46+'IC&CF&BS'!G47-G69 -> 0 | H70: ='IC&CF&BS'!H46+'IC&CF&BS'!H47-H69 -> 0 | I70: ='IC&CF&BS'!I46+'IC&CF&BS'!I47-I69 -> 0 | J70: ='IC&CF&BS'!J46+'IC&CF&BS'!J47-J69 -> 27 | K70: ='IC&CF&BS'!K46+'IC&CF&BS'!K47-K69 -> 0

Sheet DCF 1.6.2025
A2: הערכת שווי איי.סי.אל
A3: שנה סעיף | B3: 1999A | C3: 2000A | D3: 2001A | E3: 2002A | F3: 2003A | G3: 2004A | H3: 2006A | I3: 2005A | J3: 2006A | K3: 2007A | L3: 2008A | M3: 2009A | N3: Q1-10A | O3: Q2-10A | P3: Q3-10A | Q3: Q4-10A | R3: 2010A | S3: Q1-11A | T3: Q2-11A | U3: Q3-11A | V3: Q4-11A | W3: 2011A | X3: Q1-12A | Y3: Q2-12A | Z3: Q3-12A | AA3: Q4-12A | AB3: 2012A | AC3: Q1-13A | AD3: Q2-13A | AE3: Q3-13A | AF3: Q4-13A | AG3: 2013A | AH3: 2016A | AI3: 2017A | AJ3: 2018A | AK3: 2019A | AL3: 2020A | AM3: 2021A | AN3: Q1-22A | AO3: 2022A | AP3: Q1-23A | AQ3: Q2-23A | AR3: Q3-23A | AS3: Q4-23E | AT3: 2023A | AU3: Q1-24A | AV3: Q2-24A | AW3: Q3-24A | AX3: Q4-24A | AY3: 2024A | AZ3: Q1-25A | BA3: Q2-25A | BB3: H2-25E | BC3: 2025E | BD3: 2026E | BE3: 2027E | BG3: ביחס ל- 2023
AE4: מ' $
A5: הכנסות:
A6: מכירות חצוניים אשלג (א' טון) | I6: =#REF!*1000 -> #REF! | J6: =#REF!*1000 -> #REF! | K6: =#REF!*1000 -> #REF! | L6: =#REF!*1000 -> #REF! | M6: =#REF!*1000 -> #REF! | N6: =#REF!*1000 -> #REF! | O6: =#REF!*1000 -> #REF! | P6: =#REF!*1000 -> #REF! | ... AG6: =#REF!*1000 -> #REF! | AH6: ='Final Potash Pricing Q1.25'!AI16*1000 -> 4818 | AI6: ='Final Potash Pricing Q1.25'!AN16*1000 -> 4738 | AJ6: ='Final Potash Pricing Q1.25'!AS16*1000 -> 4610 | AK6: ='Final Potash Pricing Q1.25'!AX16*1000 -> 3780 | AL6: ='Final Potash Pricing Q1.25'!BC16*1000 -> 4100.9495 | AM6: ='Final Potash Pricing Q1.25'!BH16*1000 -> 4059.7162 | AN6: ='Final Potash Pricing Q1.25'!BI16*1000 -> 1053.0818 | AO6: ='Final Potash Pricing Q1.25'!BJ16*1000 -> 4125 | AP6: ='Final Potash Pricing Q1.25'!BK16*1000 -> 869.5 | AQ6: ='Final Potash Pricing Q1.25'!BL16*1000 -> 1164 | AR6: ='Final Potash Pricing Q1.25'!BM16*1000 -> 1182 | AS6: =AT6-AP6-AQ6-AR6 -> 1093.5 | AT6: ='Final Potash Pricing Q1.25'!BO16*1000 -> 4309 | AU6: ='Final Potash Pricing Q1.25'!BP16*1000 -> 989 | AV6: ='Final Potash Pricing Q1.25'!BQ16*1000 -> 1060 | AW6: ='Final Potash Pricing Q1.25'!BR16*1000 -> 980 | AX6: ='Final Potash Pricing Q1.25'!BS16*1000 -> 1160 | AY6: =AU6+AV6+AW6+AX6 -> 4189 | AZ6: ='Final Potash Pricing Q1.25'!BU16*1000 -> 1005 | BA6: ='Final Potash Pricing Q1.25'!BV16*1000 -> 876 | BB6: =BC6-BA6-AZ6 -> 2119 | BC6: 4000 | BD6: 4170 | BE6: 4350
A7: מחיר לטון אשלג | I7: =#REF! -> #REF! | J7: =#REF! -> #REF! | K7: =#REF! -> #REF! | L7: =#REF! -> #REF! | M7: =#REF! -> #REF! | N7: =#REF! -> #REF! | O7: =#REF! -> #REF! | P7: =#REF! -> #REF! | ... AG7: =#REF! -> #REF! | AH7: ='Final Potash Pricing Q1.25'!AI31 -> 259.05 | AI7: ='Final Potash Pricing Q1.25'!AN31 -> 236.2 | AJ7: ='Final Potash Pricing Q1.25'!AS31 -> 277.6 | AK7: ='Final Potash Pricing Q1.25'!AX31 -> 286 | AL7: ='Final Potash Pricing Q1.25'!BC31 -> 230 | AM7: ='Final Potash Pricing Q1.25'!BH31 -> 337 | AN7: ='Final Potash Pricing Q1.25'!BI31 -> 601 | AO7: 682 | AP7: ='Final Potash Pricing Q1.25'!BK37 -> 541 | AQ7: ='Final Potash Pricing Q1.25'!BL37 -> 403 | AR7: ='Final Potash Pricing Q1.25'!BM37 -> 342 | AS7: 330 | AT7: ='Final Potash Pricing Q1.25'!BO31 -> 393 | AU7: ='Final Potash Pricing Q1.25'!BP31 -> 324 | AV7: ='Final Potash Pricing Q1.25'!BQ31 -> 300 | AW7: ='Final Potash Pricing Q1.25'!BR31 -> 297 | AX7: ='Final Potash Pricing Q1.25'!BS31 -> 285 | AY7: ='Final Potash Pricing Q1.25'!BT31 -> 302 | AZ7: ='Final Potash Pricing Q1.25'!BU31 -> 300 | BA7: ='Final Potash Pricing Q1.25'!BV31 -> 333 | BB7: ='Final Potash Pricing Q1.25'!AX58 -> 359.69565 | BC7: 320 | BD7: ='Final Potash Pricing Q1.25'!AX65 -> 339.96377 | BE7: 310
A8: מכירות אשלג (מ' $) | H8: =#REF! -> #REF! | I8: =#REF! -> #REF! | J8: =#REF! -> #REF! | K8: =#REF! -> #REF! | L8: =#REF! -> #REF! | M8: =#REF! -> #REF! | N8: =#REF! -> #REF! | O8: =#REF! -> #REF! | ... AG8: =#REF! -> #REF! | AH8: ='Final Potash Pricing Q1.25'!AI33 -> 1213 | AI8: ='Final Potash Pricing Q1.25'!AN33 -> 1258 | AJ8: ='Final Potash Pricing Q1.25'!AS33 -> 1481 | AK8: ='Final Potash Pricing Q1.25'!AX33 -> 1330 | AL8: ='Final Potash Pricing Q1.25'!BC33 -> 1183 | AM8: ='Final Potash Pricing Q1.25'!BH33 -> 1768 | AN8: ='Final Potash Pricing Q1.25'!BI33 -> 728 | AO8: ='Reported Rev.. Split'!E6 -> 3031 | AP8: ='Reported Rev.. Split'!V6 -> 530 | AQ8: ='Reported Rev.. Split'!U6 -> 505 | AR8: ='Reported Rev.. Split'!T6 -> 477 | AS8: =AT8-AP8-AQ8-AR8 -> 461 | AT8: ='Reported Rev.. Split'!D6 -> 1973 | AU8: ='Reported Rev.. Split'!R6 -> 367 | AV8: ='Reported Rev.. Split'!Q6 -> 381 | AW8: ='Reported Rev.. Split'!P6 -> 341 | AX8: ='Reported Rev.. Split'!O6 -> 373 | AY8: =AU8+AV8+AW8+AX8 -> 1462 | AZ8: ='Reported Rev.. Split'!N6 -> 358 | BA8: ='Reported Rev.. Split'!M6 -> 347 | BB8: =BB6*BB7/1000+58*2 -> 878.19509 | BC8: =BB8+BA8+AZ8 -> 1583.1951 | BD8: =BD6*BD7/1000+200 -> 1617.6489 | BE8: =BE6*BE7/1000+200 -> 1548.5
A9: פוספט | I9: =#REF! -> #REF! | J9: =#REF! -> #REF! | K9: =#REF! -> #REF! | L9: =#REF! -> #REF! | M9: =#REF! -> #REF! | N9: =#REF! -> #REF! | O9: =#REF! -> #REF! | P9: =#REF! -> #REF! | Q9: =R9-(N9+O9+P9) -> #REF! | R9: =#REF! -> #REF! | S9: =#REF! -> #REF! | T9: =#REF! -> #REF! | U9: =#REF! -> #REF! | V9: =W9-(S9+T9+U9) -> #REF! | W9: =#REF! -> #REF! | X9: =#REF! -> #REF! | Y9: =#REF! -> #REF! | Z9: =#REF! -> #REF! | AA9: =AB9-(X9+Y9+Z9) -> #REF! | AB9: =#REF! -> #REF! | AC9: =#REF! -> #REF! | AD9: =#REF! -> #REF! | AE9: =#REF! -> #REF! | AF9: =AG9-(AC9+AD9+AE9) -> #REF! | AG9: =#REF! -> #REF! | AH9: ='Reported Rev.. Split'!K7 -> 2082 | AI9: ='Reported Rev.. Split'!J7 -> 1938 | AJ9: ='Reported Rev.. Split'!I7 -> 2001 | AK9: ='Reported Rev.. Split'!H7 -> 1901 | AL9: ='Reported Rev.. Split'!G7 -> 1871 | AM9: ='Reported Rev.. Split'!F7 -> 2334 | AN9: ='Reported Rev.. Split'!W7 -> 748 | AO9: ='Reported Rev.. Split'!E7 -> 2851 | AP9: ='Reported Rev.. Split'!V7 -> 659 | AQ9: ='Reported Rev.. Split'!U7 -> 553 | AR9: ='Reported Rev.. Split'!T7 -> 559 | AS9: 580 | AT9: ='Reported Rev.. Split'!D7 -> 2141 | AU9: ='Reported Rev.. Split'!R7 -> 517 | AV9: ='Reported Rev.. Split'!Q7 -> 528 | AW9: ='Reported Rev.. Split'!P7 -> 529 | AX9: ='Reported Rev.. Split'!O7 -> 475 | AY9: =AU9+AV9+AW9+AX9 -> 2049 | AZ9: ='Reported Rev.. Split'!N7 -> 536 | BA9: ='Reported Rev.. Split'!M7 -> 589 | BB9: =(AW9+AX9)*1.03 -> 1034.12 | BC9: =SUM(AZ9:BB9) -> 2159.12 | BD9: =BC9*(1+0.02) -> 2202.3024 | BE9: =BD9*(1+0.02) -> 2246.3484
A10: מוצרים תעשייתיים | I10: =#REF! -> #REF! | J10: =#REF! -> #REF! | K10: =#REF! -> #REF! | L10: =#REF! -> #REF! | M10: =#REF! -> #REF! | N10: =#REF! -> #REF! | O10: =#REF! -> #REF! | P10: =#REF! -> #REF! | Q10: =R10-(N10+O10+P10) -> #REF! | R10: =M10*(1+#REF!) -> #REF! | S10: =#REF! -> #REF! | T10: =#REF! -> #REF! | U10: =#REF! -> #REF! | V10: =W10-(S10+T10+U10) -> #REF! | W10: =#REF! -> #REF! | X10: =#REF! -> #REF! | Y10: =#REF! -> #REF! | Z10: =#REF! -> #REF! | AA10: =#REF! -> #REF! | AB10: =#REF! -> #REF! | AC10: =#REF! -> #REF! | AD10: =#REF! -> #REF! | ... AG10: =#REF! -> #REF! | AH10: ='Reported Rev.. Split'!K8 -> 1111 | AI10: ='Reported Rev.. Split'!J8 -> 1179 | AJ10: ='Reported Rev.. Split'!I8 -> 1281 | AK10: ='Reported Rev.. Split'!H8 -> 1307 | AL10: ='Reported Rev.. Split'!G8 -> 1242 | AM10: ='Reported Rev.. Split'!F8 -> 1601 | AN10: ='Reported Rev.. Split'!W8 -> 488 | AO10: ='Reported Rev.. Split'!E8 -> 1737 | AP10: ='Reported Rev.. Split'!V8 -> 351 | AQ10: ='Reported Rev.. Split'!U8 -> 297 | AR10: ='Reported Rev.. Split'!T8 -> 264 | AS10: =240 -> 240 | AT10: ='Reported Rev.. Split'!D8 -> 1206 | AU10: ='Reported Rev.. Split'!R8 -> 331 | AV10: ='Reported Rev.. Split'!Q8 -> 309 | AW10: ='Reported Rev.. Split'!P8 -> 305 | AX10: ='Reported Rev.. Split'!O8 -> 275 | AY10: =AU10+AV10+AW10+AX10 -> 1220 | AZ10: ='Reported Rev.. Split'!N8 -> 338 | BA10: ='Reported Rev.. Split'!M8 -> 315 | BB10: =(AW10+AX10)*1.08 -> 626.4 | BC10: =SUM(AZ10:BB10) -> 1279.4 | BD10: =BC10*(1+0.03) -> 1317.782 | BE10: =BD10*(1+0.05) -> 1383.6711
A11: פתרונות לחקלאות | I11: =#REF! -> #REF! | J11: =#REF! -> #REF! | K11: =#REF! -> #REF! | L11: =#REF! -> #REF! | M11: =#REF! -> #REF! | N11: =#REF! -> #REF! | O11: =#REF! -> #REF! | P11: =#REF! -> #REF! | Q11: =R11-(N11+O11+P11) -> #REF! | R11: =M11*(1+#REF!) -> #REF! | S11: =#REF! -> #REF! | T11: =#REF! -> #REF! | U11: =#REF! -> #REF! | V11: =W11-(S11+T11+U11) -> #REF! | W11: =#REF! -> #REF! | X11: =#REF! -> #REF! | Y11: =#REF! -> #REF! | Z11: =#REF! -> #REF! | AA11: =AB11-(X11+Y11+Z11) -> #REF! | AB11: =#REF! -> #REF! | AC11: =#REF! -> #REF! | AD11: =#REF! -> #REF! | AE11: =#REF! -> #REF! | AF11: =#REF! -> #REF! | AG11: =#REF! -> #REF! | AH11: ='Reported Rev.. Split'!K9 -> 632 | AI11: ='Reported Rev.. Split'!J9 -> 671 | AJ11: ='Reported Rev.. Split'!I9 -> 719 | AK11: ='Reported Rev.. Split'!H9 -> 699 | AL11: ='Reported Rev.. Split'!G9 -> 715 | AM11: ='Reported Rev.. Split'!F9 -> 1226 | AN11: ='Reported Rev.. Split'!W9 -> 556 | AO11: ='Reported Rev.. Split'!E9 -> 2376 | AP11: ='Reported Rev.. Split'!V9 -> 553 | AQ11: ='Reported Rev.. Split'!U9 -> 473 | AR11: ='Reported Rev.. Split'!T9 -> 546 | AS11: =530 -> 530 | AT11: ='Reported Rev.. Split'!D9 -> 2047 | AU11: ='Reported Rev.. Split'!R9 -> 474 | AV11: ='Reported Rev.. Split'!Q9 -> 489 | AW11: ='Reported Rev.. Split'!P9 -> 534 | AX11: ='Reported Rev.. Split'!O9 -> 435 | AY11: =AU11+AV11+AW11+AX11 -> 1932 | AZ11: ='Reported Rev.. Split'!N9 -> 491 | BA11: ='Reported Rev.. Split'!M9 -> 534 | BB11: =(AW11+AX11)*1.04 -> 1007.76 | BC11: =AZ11+BA11+BB11 -> 2032.76 | BD11: =BC11*(1+0.04) -> 2114.0704 | BE11: =BD11*(1+0.04) -> 2198.6332
A12: אחרים והתאמות | I12: =#REF!+#REF! -> #REF! | J12: =#REF!+#REF! -> #REF! | K12: =#REF!+#REF! -> #REF! | L12: =#REF!+#REF! -> #REF! | M12: =#REF!+#REF! -> #REF! | N12: =#REF!+#REF! -> #REF! | O12: =#REF!+#REF! -> #REF! | P12: =#REF!+#REF! -> #REF! | Q12: =R12-(N12+O12+P12) -> #REF! | R12: 215 | S12: =#REF!+#REF! -> #REF! | T12: =#REF!+#REF! -> #REF! | U12: =#REF!+#REF! -> #REF! | V12: =W12-(S12+T12+U12) -> #REF! | W12: =#REF! -> #REF! | X12: =#REF!+#REF! -> #REF! | Y12: =#REF!+#REF! -> #REF! | Z12: =#REF!+#REF! -> #REF! | AA12: =AB12-(X12+Y12+Z12) -> #REF! | AB12: =#REF!+#REF! -> #REF! | AC12: =#REF!+#REF! -> #REF! | AD12: =#REF!+#REF! -> #REF! | AE12: =#REF!+#REF! -> #REF! | AF12: =#REF!+#REF! -> #REF! | AG12: =#REF!+#REF! -> #REF! | AH12: ='Reported Rev.. Split'!K10+'Reported Rev.. Split'!K11 -> 325 | AI12: ='Reported Rev.. Split'!J10+'Reported Rev.. Split'!J11 -> 372 | AJ12: ='Reported Rev.. Split'!I10+'Reported Rev.. Split'!I11 -> 74 | AK12: ='Reported Rev.. Split'!H10+'Reported Rev.. Split'!H11 -> 34 | AL12: ='Reported Rev.. Split'!G10+'Reported Rev.. Split'!G11 -> 32 | AM12: ='Reported Rev.. Split'!F10+'Reported Rev.. Split'!F11 -> 26 | AN12: ='Reported Rev.. Split'!W10+'Reported Rev.. Split'!W11 -> 5 | AO12: ='Reported Rev.. Split'!E10 -> 20 | AP12: ='Reported Rev.. Split'!V10 -> 5 | AQ12: ='Reported Rev.. Split'!U10 -> 6 | AR12: ='Reported Rev.. Split'!T10 -> 16 | AS12: =15 -> 15 | AT12: ='Reported Rev.. Split'!D10 -> 169 | AU12: ='Reported Rev.. Split'!R10 -> 46 | AV12: ='Reported Rev.. Split'!Q10 -> 45 | AW12: ='Reported Rev.. Split'!P10 -> 44 | AX12: ='Reported Rev.. Split'!O10 -> 43 | AY12: =AU12+AV12+AW12+AX12 -> 178 | AZ12: ='Reported Rev.. Split'!N10 -> 44 | BA12: ='Reported Rev.. Split'!M10 -> 47 | BB12: =(AW12+AX12)*1.04 -> 90.48 | BC12: =AZ12+BA12+BB12 -> 181.48 | BD12: =BC12 -> 181.48 | BE12: =BD12 -> 181.48
A13: מכירות | B13: =#REF!+B6+#REF!+B8+B16 -> #REF! | C13: =#REF!+C6+#REF!+C8+C16 -> #REF! | D13: =#REF!+D6+#REF!+D8+D16 -> #REF! | E13: =#REF!+E6+#REF!+E8+E16 -> #REF! | F13: =#REF!+F6+#REF!+F8+F16 -> #REF! | G13: =#REF!+G6+#REF!+G8+G16 -> #REF! | H13: =#REF!+H6+#REF!+H8+H16 -> #REF! | I13: =I8+I9+I10+I11+I12 -> #REF! | J13: =J8+J9+J10+J11+J12 -> #REF! | K13: =K8+K9+K10+K11+K12 -> #REF! | L13: =L8+L9+L10+L11+L12 -> #REF! | M13: =M8+M9+M10+M11+M12 -> #REF! | N13: =N8+N9+N10+N11+N12 -> #REF! | O13: =O8+O9+O10+O11+O12 -> #REF! | P13: =P8+P9+P10+P11+P12 -> #REF! | ... BE13: =BE8+BE9+BE10+BE11+BE12 -> 7558.6328
A14: YOY | C14: =C13/B13-1 -> #REF! | D14: =D13/C13-1 -> #REF! | E14: =E13/D13-1 -> #REF! | F14: =F13/E13-1 -> #REF! | G14: =G13/F13-1 -> #REF! | H14: =H13/#REF!-1 -> #REF! | I14: =I13/#REF!-1 -> #REF! | J14: =J13/I13-1 -> #REF! | K14: =K13/J13-1 -> #REF! | L14: =L13/K13-1 -> #REF! | M14: =M13/L13-1 -> #REF! | N14: =N13/#REF!-1 -> #REF! | O14: =O13/#REF!-1 -> #REF! | P14: =P13/#REF!-1 -> #REF! | Q14: =Q13/#REF!-1 -> #REF! | R14: =R13/M13-1 -> #REF! | S14: =S13/#REF!-1 -> #REF! | T14: =T13/#REF!-1 -> #REF! | U14: =U13/#REF!-1 -> #REF! | V14: =V13/#REF!-1 -> #REF! | W14: =W13/R13-1 -> #REF! | X14: =X13/S13-1 -> #REF! | Y14: =Y13/#REF!-1 -> #REF! | Z14: =Z13/#REF!-1 -> #REF! | AA14: =AA13/#REF!-1 -> #REF! | AB14: =AB13/W13-1 -> #REF! | AC14: =AC13/X13-1 -> #REF! | AD14: =AD13/#REF!-1 -> #REF! | AE14: =AE13/#REF!-1 -> #REF! | AF14: =AF13/#REF!-1 -> #REF! | AG14: =AG13/AB13-1 -> #REF!
A15: רווח תפעולי:
A16: אשלג | I16: =#REF! -> #REF! | J16: =#REF! -> #REF! | K16: =#REF! -> #REF! | L16: =#REF! -> #REF! | M16: =#REF! -> #REF! | N16: =#REF! -> #REF! | O16: =#REF! -> #REF! | P16: =#REF! -> #REF! | ... AG16: =#REF! -> #REF! | AH16: ='Reported Rev.. Split'!K33 -> 245 | AI16: ='Reported Rev.. Split'!J33 -> 198 | AJ16: ='Reported Rev.. Split'!I33 -> 315 | AK16: ='Reported Rev.. Split'!H33 -> 289 | AL16: ='Reported Rev.. Split'!G33 -> 120 | AM16: ='Reported Rev.. Split'!F33 -> 399 | AN16: ='Reported Rev.. Split'!W33 -> 410 | AO16: ='Reported Rev.. Split'!E33 -> 1822 | AP16: ='Reported Rev.. Split'!V33 -> 254 | AQ16: ='Reported Rev.. Split'!U33 -> 167 | AR16: ='Reported Rev.. Split'!T33 -> 125 | AS16: =AS8*AS17 -> 115.25 | AT16: ='Reported Rev.. Split'!D33 -> 668 | AU16: ='Reported Rev.. Split'!R33 -> 62 | AV16: ='Reported Rev.. Split'!Q33 -> 60 | AW16: ='Reported Rev.. Split'!P33 -> 59 | AX16: ='Reported Rev.. Split'!O33 -> 69 | AY16: =AU16+AV16+AW16+AX16 -> 250 | AZ16: ='Reported Rev.. Split'!N33 -> 56 | BA16: ='Reported Rev.. Split'!M33 -> 52 | BB16: =BB17*BB8 -> 247.3789 | BC16: =SUM(AZ16:BB16) -> 355.3789 | BD16: =BD8*BD17 -> 451.86591 | BE16: =BE8*BE17 -> 362.92969 | BG16: =BC16-AT16 -> -312.6211
A17: מרווח תפעולי אשלג | AH17: =AH16/AH8 -> 0.20197857 | AI17: =AI16/AI8 -> 0.15739269 | AJ17: =AJ16/AJ8 -> 0.21269413 | AK17: =AK16/AK8 -> 0.21729323 | AL17: =AL16/AL8 -> 0.10143702 | AM17: =AM16/AM8 -> 0.22567873 | AN17: =AN16/AN8 -> 0.56318681 | AO17: =AO16/AO8 -> 0.60112174 | ... AR17: =AR16/AR8 -> 0.26205451 | AS17: 0.25 | AT17: =AT16/AT8 -> 0.3385707 | AU17: =AU16/AU8 -> 0.16893733 | AV17: =AV16/AV8 -> 0.15748031 | AW17: =AW16/AW8 -> 0.17302053 | AX17: =AX16/AX8 -> 0.1849866 | AY17: =AY16/AY8 -> 0.17099863 | AZ17: =AZ16/AZ8 -> 0.15642458 | BA17: =BA16/BA8 -> 0.14985591 | BB17: ='Final Potash Pricing Q1.25'!BZ42 -> 0.28169014 | BC17: =BC16/BC8 -> 0.22446943 | BD17: ='Final Potash Pricing Q1.25'!CA42 -> 0.27933497 | BE17: ='Final Potash Pricing Q1.25'!CB42 -> 0.234375
A18: פוספט | I18: =#REF! -> #REF! | J18: =#REF! -> #REF! | K18: =#REF! -> #REF! | L18: =#REF! -> #REF! | M18: =#REF! -> #REF! | N18: =#REF! -> #REF! | O18: =#REF! -> #REF! | P18: =#REF! -> #REF! | Q18: =R18-(N18+O18+P18) -> #REF! | R18: =R9*#REF! -> #REF! | S18: =#REF! -> #REF! | T18: =#REF! -> #REF! | U18: =#REF! -> #REF! | V18: =W18-(S18+T18+U18) -> #REF! | W18: =W9*#REF! -> #REF! | X18: =#REF! -> #REF! | Y18: =#REF! -> #REF! | Z18: =#REF! -> #REF! | AA18: =AB18-(X18+Y18+Z18) -> #REF! | AB18: =#REF!+33 -> #REF! | AC18: =#REF! -> #REF! | AD18: =#REF! -> #REF! | AE18: =#REF! -> #REF! | AF18: =AG18-(AC18+AD18+AE18) -> #REF! | AG18: =#REF!+60 -> #REF! | AH18: ='Reported Rev.. Split'!K34 -> 75 | AI18: ='Reported Rev.. Split'!J34 -> 53 | AJ18: ='Reported Rev.. Split'!I34 -> 113 | AK18: ='Reported Rev.. Split'!H34 -> 100 | AL18: ='Reported Rev.. Split'!G34 -> 66 | AM18: ='Reported Rev.. Split'!F34 -> 307 | AN18: ='Reported Rev.. Split'!W34 -> 200 | AO18: ='Reported Rev.. Split'!E34 -> 777 | AP18: ='Reported Rev.. Split'!V34 -> 115 | AQ18: ='Reported Rev.. Split'!U34 -> 71 | AR18: ='Reported Rev.. Split'!T34 -> 69 | AS18: =AS9*AS19 -> 78.3 | AT18: ='Reported Rev.. Split'!D34 -> 350 | AU18: ='Reported Rev.. Split'!R34 -> 84 | AV18: ='Reported Rev.. Split'!Q34 -> 93 | AW18: ='Reported Rev.. Split'!P34 -> 100 | AX18: ='Reported Rev.. Split'!O34 -> 81 | AY18: =AU18+AV18+AW18+AX18 -> 358 | AZ18: ='Reported Rev.. Split'!N34 -> 91 | BA18: ='Reported Rev.. Split'!M34 -> 90 | BB18: 195 | BC18: =AZ18+BA18+BB18 -> 376 | BD18: =BD9*BD19 -> 374.39141 | BE18: =BE9*BE19 -> 381.87924 | BG18: =BC18-AT18 -> 26
A19: מרווח תפעולי פוספט | AH19: =AH18/AH9 -> 0.036023055 | AI19: =AI18/AI9 -> 0.027347781 | AJ19: =AJ18/AJ9 -> 0.056471764 | AK19: =AK18/AK9 -> 0.052603893 | AL19: =AL18/AL9 -> 0.035275254 | AM19: =AM18/AM9 -> 0.13153385 | AN19: =AN18/AN9 -> 0.26737968 | AO19: =AO18/AO9 -> 0.27253595 | ... AR19: =AR18/AR9 -> 0.1234347 | AS19: 0.135 | AT19: =AT18/AT9 -> 0.16347501 | AU19: =AU18/AU9 -> 0.16247582 | AV19: =AV18/AV9 -> 0.17613636 | AW19: =AW18/AW9 -> 0.18903592 | AX19: =AX18/AX9 -> 0.17052632 | AY19: =AY18/AY9 -> 0.17471938 | AZ19: =AZ18/AZ9 -> 0.16977612 | BA19: =BA18/BA9 -> 0.15280136 | BB19: =BB18/BB9 -> 0.18856612 | BC19: 0.175 | BD19: 0.17 | BE19: 0.17
A20: מוצרים תעשייתיים | I20: =#REF! -> #REF! | J20: =#REF! -> #REF! | K20: =#REF! -> #REF! | L20: =#REF! -> #REF! | M20: =#REF! -> #REF! | N20: =#REF! -> #REF! | O20: =#REF! -> #REF! | P20: =#REF! -> #REF! | Q20: =R20-(N20+O20+P20) -> #REF! | R20: =#REF! -> #REF! | S20: =#REF! -> #REF! | T20: =#REF! -> #REF! | U20: =#REF! -> #REF! | V20: =W20-(S20+T20+U20) -> #REF! | W20: =#REF! -> #REF! | X20: =#REF! -> #REF! | Y20: =#REF! -> #REF! | Z20: =#REF! -> #REF! | AA20: =AB20-(X20+Y20+Z20) -> #REF! | AB20: =#REF! -> #REF! | AC20: =#REF! -> #REF! | AD20: =#REF! -> #REF! | AE20: =#REF! -> #REF! | AF20: =AG20-(AC20+AD20+AE20) -> #REF! | AG20: =#REF! -> #REF! | AH20: ='Reported Rev.. Split'!K35 -> 241 | AI20: ='Reported Rev.. Split'!J35 -> 247 | AJ20: ='Reported Rev.. Split'!I35 -> 300 | AK20: ='Reported Rev.. Split'!H35 -> 338 | AL20: ='Reported Rev.. Split'!G35 -> 303 | AM20: ='Reported Rev.. Split'!F35 -> 435 | AN20: ='Reported Rev.. Split'!W35 -> 188 | AO20: ='Reported Rev.. Split'!E35 -> 628 | AP20: ='Reported Rev.. Split'!V35 -> 90 | AQ20: ='Reported Rev.. Split'!U35 -> 60 | AR20: ='Reported Rev.. Split'!T35 -> 31 | AS20: =AS10*AS21 -> 25.2 | AT20: ='Reported Rev.. Split'!D35 -> 220 | AU20: ='Reported Rev.. Split'!R35 -> 59 | AV20: ='Reported Rev.. Split'!Q35 -> 60 | AW20: ='Reported Rev.. Split'!P35 -> 50 | AX20: ='Reported Rev.. Split'!O35 -> 55 | AY20: =AU20+AV20+AW20+AX20 -> 224 | AZ20: ='Reported Rev.. Split'!N35 -> 62 | BA20: ='Reported Rev.. Split'!M35 -> 54 | BB20: 120 | BC20: =AZ20+BA20+BB20 -> 236 | BD20: =BD10*BD21 -> 256.96749 | BE20: =BE10*BE21 -> 290.57093 | BG20: =BC20-AT20 -> 16
A21: מרווח תפעולי מוצרים תעשייתיים | AH21: =AH20/AH10 -> 0.21692169 | AI21: =AI20/AI10 -> 0.20949958 | AJ21: =AJ20/AJ10 -> 0.23419204 | AK21: =AK20/AK10 -> 0.2586075 | AL21: =AL20/AL10 -> 0.24396135 | AM21: =AM20/AM10 -> 0.27170518 | AN21: =AN20/AN10 -> 0.3852459 | AO21: =AO20/AO10 -> 0.36154289 | ... AR21: =AR20/AR10 -> 0.11742424 | AS21: 0.105 | AT21: =AT20/AT10 -> 0.18242123 | AU21: =AU20/AU10 -> 0.17824773 | AV21: =AV20/AV10 -> 0.19417476 | AW21: =AW20/AW10 -> 0.16393443 | AX21: =AX20/AX10 -> 0.2 | AY21: =AY20/AY10 -> 0.18360656 | AZ21: =AZ20/AZ10 -> 0.18343195 | BA21: =BA20/BA10 -> 0.17142857 | ... BC21: =BC20/BC10 -> 0.18446147 | BD21: 0.195 | BE21: 0.21
A22: פתרונות לחקלאות | I22: =#REF! -> #REF! | J22: =#REF! -> #REF! | K22: =#REF! -> #REF! | L22: =#REF! -> #REF! | M22: =#REF! -> #REF! | N22: =#REF! -> #REF! | O22: =#REF! -> #REF! | P22: =#REF! -> #REF! | Q22: =R22-(N22+O22+P22) -> #REF! | R22: =R11*#REF! -> #REF! | S22: =#REF! -> #REF! | T22: =#REF! -> #REF! | U22: =#REF! -> #REF! | V22: =W22-(S22+T22+U22) -> #REF! | W22: =W11*#REF! -> #REF! | X22: =#REF! -> #REF! | Y22: =#REF! -> #REF! | Z22: =#REF! -> #REF! | AA22: =AB22-(X22+Y22+Z22) -> #REF! | AB22: =#REF!-11 -> #REF! | AC22: =#REF! -> #REF! | AD22: =#REF! -> #REF! | AE22: =#REF! -> #REF! | AF22: =#REF! -> #REF! | AG22: =#REF! -> #REF! | AH22: ='Reported Rev.. Split'!K36 -> 28 | AI22: ='Reported Rev.. Split'!J36 -> 29 | AJ22: ='Reported Rev.. Split'!I36 -> 29 | AK22: ='Reported Rev.. Split'!H36 -> 21 | AL22: ='Reported Rev.. Split'!G36 -> 40 | AM22: ='Reported Rev.. Split'!F36 -> 121 | AN22: ='Reported Rev.. Split'!W36 -> 93 | AO22: ='Reported Rev.. Split'!E36 -> 378 | AP22: ='Reported Rev.. Split'!V36 -> 32 | AQ22: ='Reported Rev.. Split'!U36 -> 4 | AR22: ='Reported Rev.. Split'!T36 -> 20 | AS22: =AS11*AS23 -> 18.55 | AT22: ='Reported Rev.. Split'!D36 -> 51 | AU22: ='Reported Rev.. Split'!R36 -> 23 | AV22: ='Reported Rev.. Split'!Q36 -> 25 | AW22: ='Reported Rev.. Split'!P36 -> 49 | AX22: ='Reported Rev.. Split'!O36 -> 31 | AY22: =AU22+AV22+AW22+AX22 -> 128 | AZ22: ='Reported Rev.. Split'!N36 -> 28 | BA22: ='Reported Rev.. Split'!M36 -> 35 | BB22: 67 | BC22: =AZ22+BA22+BB22 -> 130 | BD22: =BD11*BD23 -> 158.55528 | BE22: =BE11*BE23 -> 186.88382 | BG22: =BC22-AT22 -> 79
A23: מרווח תפעולי פתרונות לחקלאות | AH23: =AH22/AH11 -> 0.044303797 | AI23: =AI22/AI11 -> 0.043219076 | AJ23: =AJ22/AJ11 -> 0.040333797 | AK23: =AK22/AK11 -> 0.030042918 | AL23: =AL22/AL11 -> 0.055944056 | AM23: =AM22/AM11 -> 0.098694943 | AN23: =AN22/AN11 -> 0.16726619 | AO23: =AO22/AO11 -> 0.15909091 | ... AR23: =AR22/AR11 -> 0.036630037 | AS23: 0.035 | AT23: =AT22/AT11 -> 0.024914509 | AU23: =AU22/AU11 -> 0.048523207 | AV23: =AV22/AV11 -> 0.051124744 | AW23: =AW22/AW11 -> 0.0917603 | AX23: =AX22/AX11 -> 0.071264368 | AY23: =AY22/AY11 -> 0.066252588 | AZ23: =AZ22/AZ11 -> 0.057026477 | BA23: =BA22/BA11 -> 0.065543071 | ... BC23: =BC22/BC11 -> 0.063952459 | BD23: 0.075 | BE23: 0.085
A24: אחרים | I24: =#REF!+#REF! -> #REF! | J24: =#REF!+#REF! -> #REF! | K24: =#REF!+#REF! -> #REF! | L24: =#REF!+#REF! -> #REF! | M24: =#REF!+#REF! -> #REF! | N24: =#REF!+#REF! -> #REF! | O24: =#REF!+#REF! -> #REF! | P24: =#REF!+#REF! -> #REF! | ... V24: =#REF!+#REF! -> #REF! | W24: =W12*#REF! -> #REF! | X24: =#REF!+#REF! -> #REF! | Y24: =#REF!+#REF! -> #REF! | Z24: =#REF!+#REF! -> #REF! | AA24: =AB24-(X24+Y24+Z24) -> #REF! | AB24: =#REF!+#REF! -> #REF! | AC24: =#REF!+#REF! -> #REF! | AD24: =#REF!+#REF! -> #REF! | AE24: =#REF!+#REF! -> #REF! | AF24: =#REF!+#REF! -> #REF! | AG24: =#REF!+#REF! -> #REF! | AH24: ='Reported Rev.. Split'!K37 -> 41 | AI24: ='Reported Rev.. Split'!J37 -> 127 | AJ24: ='Reported Rev.. Split'!I37 -> 9 | AK24: ='Reported Rev.. Split'!H37 -> 19 | AL24: ='Reported Rev.. Split'!G37 -> -5 | AM24: ='Reported Rev.. Split'!F37 -> -8 | AN24: ='Reported Rev.. Split'!W37+'Reported Rev.. Split'!W38 -> -11 | AO24: ='Reported Rev.. Split'!E37 -> -9 | AP24: ='Reported Rev.. Split'!V37 -> -2 | AQ24: ='Reported Rev.. Split'!U37 -> -3 | AR24: ='Reported Rev.. Split'!T37 -> -7 | AS24: =-5 -> -5 | AT24: ='Reported Rev.. Split'!D37 -> -34 | AU24: ='Reported Rev.. Split'!R37 -> -3 | AV24: ='Reported Rev.. Split'!Q37 -> -4 | AW24: ='Reported Rev.. Split'!P37 -> -7 | AX24: ='Reported Rev.. Split'!O37 -> -8 | AY24: =AU24+AV24+AW24+AX24 -> -22 | AZ24: ='Reported Rev.. Split'!N37 -> -3 | BA24: ='Reported Rev.. Split'!M37 -> -2 | BB24: =BA24*2 -> -4 | BC24: =AZ24+BA24+BB24 -> -9 | BD24: =BC24 -> -9 | BE24: =BD24 -> -9 | BG24: =BC24-AT24 -> 25
A25: התאמות והוצאות לא משויכות | I25: =#REF!+#REF! -> #REF! | J25: =#REF!+#REF! -> #REF! | K25: =#REF!+#REF! -> #REF! | L25: =#REF!+#REF! -> #REF! | M25: =#REF!+#REF! -> #REF! | N25: =#REF!+#REF! -> #REF! | O25: =#REF!+#REF! -> #REF! | P25: =#REF!+#REF! -> #REF! | ... V25: =#REF!+#REF! -> #REF! | W25: =W13*#REF! -> #REF! | X25: =#REF!+#REF! -> #REF! | Y25: =#REF!+#REF! -> #REF! | Z25: =#REF!+#REF! -> #REF! | AA25: =AB25-(X25+Y25+Z25) -> #REF! | AB25: =#REF!+#REF! -> #REF! | AC25: =#REF!+#REF! -> #REF! | AD25: =#REF!+#REF! -> #REF! | AE25: =#REF!+#REF! -> #REF! | AF25: =#REF!+#REF! -> #REF! | AG25: =#REF!+#REF! -> #REF! | AH25: ='Reported Rev.. Split'!K38+'Reported Rev.. Split'!K40 -> -360 | AI25: ='Reported Rev.. Split'!J38+'Reported Rev.. Split'!J40 -> -25 | AJ25: ='Reported Rev.. Split'!I38+'Reported Rev.. Split'!I40 -> 753 | AK25: ='Reported Rev.. Split'!H38+'Reported Rev.. Split'!H40 -> -11 | AL25: ='Reported Rev.. Split'!G38+'Reported Rev.. Split'!G40 -> -322 | AM25: ='Reported Rev.. Split'!F38+'Reported Rev.. Split'!F40 -> -44 | AO25: ='Reported Rev.. Split'!E38+'Reported Rev.. Split'!E40 -> -80 | AP25: ='Reported Rev.. Split'!V38+'Reported Rev.. Split'!V40 -> -24 | AQ25: ='Reported Rev.. Split'!U38+'Reported Rev.. Split'!U40 -> 1 | AR25: ='Reported Rev.. Split'!T38+'Reported Rev.. Split'!T40 -> -11 | AS25: -5 | AT25: ='Reported Rev.. Split'!D38+'Reported Rev.. Split'!D40 -> -114 | AU25: ='Reported Rev.. Split'!R38+'Reported Rev.. Split'!R40 -> -22 | AV25: ='Reported Rev.. Split'!Q38+'Reported Rev.. Split'!Q40 -> -23 | AW25: ='Reported Rev.. Split'!P38+'Reported Rev.. Split'!P40 -> -37 | AX25: ='Reported Rev.. Split'!O38+'Reported Rev.. Split'!O40 -> -81 | AY25: =AU25+AV25+AW25+AX25 -> -163 | AZ25: ='Reported Rev.. Split'!N38+'Reported Rev.. Split'!N40 -> -49 | BA25: ='Reported Rev.. Split'!M38+'Reported Rev.. Split'!M40 -> -48 | BB25: =BA25*2 -> -96 | BC25: =AZ25+BA25+BB25 -> -193 | BD25: =BC25 -> -193 | BE25: =BD25 -> -193 | BG25: =BC25-AT25 -> -79
A26: רווח תפעולי | I26: =I16+I18+I20+I22+I24 -> #REF! | J26: =J16+J18+J20+J22+J24 -> #REF! | K26: =K16+K18+K20+K22+K24 -> #REF! | L26: =L16+L18+L20+L22+L24 -> #REF! | M26: =M16+M18+M20+M22+M24 -> #REF! | N26: =#REF! -> #REF! | O26: =#REF! -> #REF! | P26: =#REF! -> #REF! | Q26: =Q16+Q18+Q20+Q22 -> #REF! | R26: =R16+R18+R20+R22+R24 -> #REF! | S26: =#REF! -> #REF! | T26: =#REF! -> #REF! | U26: =#REF! -> #REF! | V26: =V16+V18+V20+V22 -> #REF! | W26: =W16+W18+W20+W22+W24 -> #REF! | X26: =#REF! -> #REF! | Y26: =#REF! -> #REF! | Z26: =#REF! -> #REF! | AA26: =AA16+AA18+AA20+AA22 -> #REF! | AB26: =AB16+AB18+AB20+AB22+AB24 -> #REF! | AC26: =#REF! -> #REF! | AD26: =#REF! -> #REF! | AE26: =#REF! -> #REF! | AF26: =AF16+AF18+AF20+AF22 -> #REF! | AG26: =AG16+AG18+AG20+AG22+AG24 -> #REF! | AH26: =AH16+AH18+AH20+AH22+AH24+AH25 -> 270 | AI26: =AI16+AI18+AI20+AI22+AI24+AI25 -> 629 | AJ26: =AJ16+AJ18+AJ20+AJ22+AJ24+AJ25 -> 1519 | AK26: =AK16+AK18+AK20+AK22+AK24+AK25 -> 756 | AL26: =AL16+AL18+AL20+AL22+AL24+AL25 -> 202 | AM26: =AM16+AM18+AM20+AM22+AM24+AM25 -> 1210 | AN26: =AN16+AN18+AN20+AN22+AN24 -> 880 | AO26: =AO16+AO18+AO20+AO22+AO24+AO25 -> 3516 | AP26: =AP16+AP18+AP20+AP22+AP24+AP25 -> 465 | AQ26: =AQ16+AQ18+AQ20+AQ22+AQ24+AQ25 -> 300 | AR26: =AR16+AR18+AR20+AR22+AR24+AR25 -> 227 | AS26: =AS16+AS18+AS20+AS22+AS24+AS25 -> 227.3 | AT26: =AT16+AT18+AT20+AT22+AT24+AT25 -> 1141 | AU26: =AU16+AU18+AU20+AU22+AU24+AU25 -> 203 | AV26: =AV16+AV18+AV20+AV22+AV24+AV25 -> 211 | ... BB26: =BB16+BB18+BB20+BB22+BB24+BB25 -> 529.3789 | BC26: =AZ26+BA26+BB26 -> 895.3789 | BD26: =BD16+BD18+BD20+BD22+BD24+BD25 -> 1039.7801 | BE26: =BE16+BE18+BE20+BE22+BE24+BE25 -> 1020.2637 | BG26: =BC26-AT26 -> -245.6211
A27: פחת | I27: =#REF! -> #REF! | J27: =#REF! -> #REF! | K27: =#REF! -> #REF! | L27: =#REF! -> #REF! | M27: =#REF! -> #REF! | N27: ='השקעה ברכוש קבוע'!AH14 -> 52.112 | O27: ='השקעה ברכוש קבוע'!AI14 -> 52.31 | P27: ='השקעה ברכוש קבוע'!AJ14 -> 53.899 | Q27: =R27-(N27+O27+P27) -> 59.074 | R27: ='השקעה ברכוש קבוע'!AL14 -> 217.395 | S27: ='השקעה ברכוש קבוע'!AM14 -> 54.893 | T27: ='השקעה ברכוש קבוע'!AN14 -> 67.621 | U27: ='השקעה ברכוש קבוע'!AO14 -> 75.097 | V27: =W27-(S27+T27+U27) -> 69.829 | W27: ='השקעה ברכוש קבוע'!AQ14 -> 267.44 | X27: ='השקעה ברכוש קבוע'!AR14 -> 72.582 | Y27: ='השקעה ברכוש קבוע'!AS14 -> 65.244 | Z27: ='השקעה ברכוש קבוע'!AT14 -> 72.469 | AA27: =AB27-(X27+Y27+Z27) -> 76.768 | AB27: ='השקעה ברכוש קבוע'!AV14 -> 287.063 | AC27: ='השקעה ברכוש קבוע'!AW14 -> 82.5 | AD27: ='השקעה ברכוש קבוע'!AX14 -> 81.428 | AE27: ='השקעה ברכוש קבוע'!AY14 -> 81.727 | AF27: ='השקעה ברכוש קבוע'!AZ14 -> 102.086 | AG27: ='השקעה ברכוש קבוע'!BA14 -> 347.741 | AH27: ='Reported Rev.. Split'!K69 -> 406 | AI27: ='Reported Rev.. Split'!J69 -> 391 | AJ27: ='Reported Rev.. Split'!I69 -> 420 | AK27: ='Reported Rev.. Split'!H69 -> 433 | AL27: ='Reported Rev.. Split'!G69 -> 579 | AM27: ='Reported Rev.. Split'!F69 -> 484 | AN27: ='IC&CF&BS'!AB46 -> 122 | AO27: ='IC&CF&BS'!E46 -> 498 | AP27: ='IC&CF&BS'!X46 -> 130 | AQ27: ='IC&CF&BS'!W46 -> 141 | AR27: ='IC&CF&BS'!V46 -> 119 | AS27: 120 | AT27: ='IC&CF&BS'!D46 -> 536 | AU27: ='IC&CF&BS'!T46 -> 147 | AV27: ='IC&CF&BS'!S46 -> 152 | AW27: ='IC&CF&BS'!R46 -> 140 | AX27: ='IC&CF&BS'!Q46 -> 157 | AY27: =AU27+AV27+AW27+AX27 -> 596 | AZ27: ='IC&CF&BS'!P46 -> 151 | BA27: ='IC&CF&BS'!O46 -> 150 | BB27: =BA27*2 -> 300 | BC27: =AZ27+BA27+BB27 -> 601 | BD27: 620 | BE27: 600
A28: EBITDA | I28: =I26+I27 -> #REF! | J28: =J26+J27 -> #REF! | K28: =K26+K27 -> #REF! | L28: =L26+L27 -> #REF! | M28: =M26+M27 -> #REF! | N28: =N26+N27 -> #REF! | O28: =O26+O27 -> #REF! | P28: =P26+P27 -> #REF! | Q28: =R28-(N28+O28+P28) -> #REF! | R28: =R26+R27 -> #REF! | S28: =S26+S27 -> #REF! | T28: =T26+T27 -> #REF! | U28: =U26+U27 -> #REF! | V28: =W28-(S28+T28+U28) -> #REF! | W28: =W26+W27 -> #REF! | X28: =X26+X27 -> #REF! | Y28: =Y26+Y27 -> #REF! | Z28: =Z26+Z27 -> #REF! | AA28: =AB28-(X28+Y28+Z28) -> #REF! | AB28: =AB26+AB27 -> #REF! | AC28: =AC26+AC27 -> #REF! | AD28: =AD26+AD27 -> #REF! | AE28: =AE26+AE27 -> #REF! | AF28: =AG28-(AC28+AD28+AE28) -> #REF! | AG28: =AG26+AG27 -> #REF! | AH28: =AH26+AH27 -> 676 | AI28: =AI26+AI27 -> 1020 | AJ28: =AJ26+AJ27 -> 1939 | AK28: =AK26+AK27 -> 1189 | AL28: =AL26+AL27 -> 781 | AM28: =AM26+AM27 -> 1694 | AN28: =AN26+AN27 -> 1002 | ... BE28: =BE26+BE27 -> 1620.2637
A29: התאמות תזרימיות ל- EBITDA | AG29: 0 | AH29: =AH30-AH28 -> 274 | AI29: =AI30-AI28 -> 8 | AJ29: =AJ30-AJ28 -> -775 | AK29: =AK30-AK28 -> -10 | AL29: =AL30-AL28 -> 236 | AM29: =AM30-AM28 -> -6 | AN29: =AN30-AN28 -> -1 | AO29: =AO30-AO28 -> -24 | AT29: =AT30-AT28 -> 106 | AU29: =AU30-AU28 -> 0 | AV29: =AV30-AV28 -> -1 | AW29: =AW30-AW28 -> 27 | AX29: =AX30-AX28 -> 27 | AY29: =AY30-AY28 -> 53 | AZ29: =AZ30-AZ28 -> 12 | BA29: 8 | BC29: =AZ29+BA29+BB29 -> 20 | BD29: 0 | BE29: 0
A30: תזרים תפעולי | AG30: =AG28+AG29 -> #REF! | AH30: ='IC&CF&BS'!K235 -> 950 | AI30: ='IC&CF&BS'!J235 -> 1028 | AJ30: ='IC&CF&BS'!I235 -> 1164 | AK30: ='IC&CF&BS'!H235 -> 1179 | AL30: ='IC&CF&BS'!G235 -> 1017 | AM30: ='IC&CF&BS'!F235 -> 1688 | AN30: ='IC&CF&BS'!AB235 -> 1001 | AO30: ='IC&CF&BS'!E235 -> 3990 | AP30: ='IC&CF&BS'!X235 -> 608 | AQ30: ='IC&CF&BS'!W235 -> 433 | AR30: ='IC&CF&BS'!V235 -> 358 | AS30: =AS28 -> 347.3 | AT30: ='IC&CF&BS'!D235 -> 1783 | AU30: ='IC&CF&BS'!T235 -> 350 | AV30: ='IC&CF&BS'!S235 -> 362 | AW30: ='IC&CF&BS'!R235 -> 381 | AX30: ='IC&CF&BS'!Q235 -> 331 | AY30: =AU30+AV30+AW30+AX30 -> 1424 | AZ30: ='IC&CF&BS'!P235 -> 348 | BA30: =BA28+BA29 -> 339 | BB30: =BB28+BB29 -> 829.3789 | BC30: =AZ30+BA30+BB30 -> 1516.3789 | BD30: =BD28+BD29 -> 1659.7801 | BE30: =BE28+BE29 -> 1620.2637
A31: הוצאות אחרות | AG31: 0 | AH31: ='IC&CF&BS'!K239 -> -23 | AI31: ='IC&CF&BS'!J239 -> 118 | AJ31: ='IC&CF&BS'!I239 -> -12 | AK31: ='IC&CF&BS'!H239 -> 97 | AL31: ='IC&CF&BS'!G239 -> -30 | AM31: ='IC&CF&BS'!F239 -> 80 | AN31: ='IC&CF&BS'!AB239 -> 26 | AO31: ='IC&CF&BS'!E239 -> 83 | AP31: ='IC&CF&BS'!X239 -> -6 | AQ31: ='IC&CF&BS'!W239 -> 27 | AR31: ='IC&CF&BS'!V239 -> 3 | AS31: 0 | AT31: ='IC&CF&BS'!D235+'IC&CF&BS'!D239-AT30 -> -85 | AU31: ='IC&CF&BS'!T239 -> 19 | AV31: ='IC&CF&BS'!S239 -> 29 | AW31: ='IC&CF&BS'!R239 -> -9 | AX31: ='IC&CF&BS'!Q239 -> 37 | AY31: =AU31+AV31+AW31+AX31 -> 76 | AZ31: ='IC&CF&BS'!P239 -> 30 | BA31: ='IC&CF&BS'!O239 -> -77 | BB31: 0 | BC31: =AZ31+BA31+BB31 -> -47 | BD31: 0 | BE31: 0
A32: הוצאות מימון נטו | I32: =#REF! -> #REF! | J32: =#REF! -> #REF! | K32: =#REF! -> #REF! | L32: =#REF! -> #REF! | M32: =#REF! -> #REF! | N32: =#REF! -> #REF! | O32: =#REF! -> #REF! | P32: =#REF! -> #REF! | Q32: =R32-(N32+O32+P32) -> #REF! | R32: =#REF! -> #REF! | S32: =#REF! -> #REF! | T32: =#REF! -> #REF! | U32: =#REF! -> #REF! | V32: =W32-(S32+T32+U32) -> #REF! | W32: =#REF! -> #REF! | X32: =#REF! -> #REF! | Y32: =#REF! -> #REF! | Z32: =#REF! -> #REF! | AA32: =AB32-(X32+Y32+Z32) -> #REF! | AB32: =#REF! -> #REF! | AC32: =#REF! -> #REF! | AD32: =#REF! -> #REF! | AE32: =#REF! -> #REF! | AF32: =#REF! -> #REF! | AG32: =-221 -> -221 | AH32: ='IC&CF&BS'!K243 -> -132 | AI32: ='IC&CF&BS'!J243 -> -124 | AJ32: ='IC&CF&BS'!I243 -> -158 | AK32: ='IC&CF&BS'!H243 -> -243 | AL32: ='IC&CF&BS'!G243 -> -265 | AM32: ='IC&CF&BS'!F243 -> -211 | AN32: ='IC&CF&BS'!AB243 -> -50 | AO32: ='IC&CF&BS'!E243 -> -219 | AP32: ='IC&CF&BS'!X243 -> -61 | AQ32: ='IC&CF&BS'!W243 -> -91 | AR32: ='IC&CF&BS'!V243 -> -61 | AS32: -70 | AT32: ='IC&CF&BS'!D243 -> -283 | AU32: ='IC&CF&BS'!T243 -> -48 | AV32: ='IC&CF&BS'!S243 -> -73 | AW32: ='IC&CF&BS'!R243 -> -51 | AX32: ='IC&CF&BS'!Q243 -> -73 | AY32: =AU32+AV32+AW32+AX32 -> -245 | AZ32: ='IC&CF&BS'!P243 -> -50 | BA32: ='IC&CF&BS'!O243 -> -51 | BB32: =AZ32+BA32 -> -101 | BC32: =AZ32+BA32+BB32 -> -202 | BD32: =-245 -> -245 | BE32: -245
A33: חלק ברווחי כלולות | I33: =#REF! -> #REF! | J33: =#REF! -> #REF! | K33: =#REF! -> #REF! | L33: =#REF! -> #REF! | M33: =#REF! -> #REF! | N33: =#REF! -> #REF! | O33: =#REF! -> #REF! | P33: =#REF! -> #REF! | Q33: =R33-(N33+O33+P33) -> #REF! | R33: =#REF! -> #REF! | S33: =#REF! -> #REF! | T33: =#REF! -> #REF! | U33: =#REF! -> #REF! | V33: =W33-(S33+T33+U33) -> #REF! | W33: =#REF! -> #REF! | X33: =#REF! -> #REF! | Y33: =#REF! -> #REF! | Z33: =#REF! -> #REF! | AA33: =AB33-(X33+Y33+Z33) -> #REF! | AB33: =#REF! -> #REF! | AC33: =#REF! -> #REF! | AD33: =#REF! -> #REF! | AE33: =#REF! -> #REF! | AF33: =#REF! -> #REF! | AG33: =#REF! -> #REF! | AH33: ='IC&CF&BS'!K14 -> 18 | AI33: ='IC&CF&BS'!J14 -> 0 | AJ33: ='IC&CF&BS'!I14 -> 3 | AK33: ='IC&CF&BS'!H14 -> 1 | AL33: ='IC&CF&BS'!I14 -> 3 | AM33: ='IC&CF&BS'!J14 -> 0 | AN33: ='IC&CF&BS'!K14 -> 18 | AO33: =#REF! -> #REF! | AT33: =AO33 -> #REF! | AY33: =AT33 -> #REF! | BC33: =AT33 -> #REF! | BD33: =AY33 -> #REF! | BE33: =BC33 -> #REF!
A34: רווח לפני מס | I34: =#REF! -> #REF! | J34: =#REF! -> #REF! | K34: =#REF! -> #REF! | L34: =#REF! -> #REF! | M34: =#REF! -> #REF! | N34: =#REF! -> #REF! | O34: =#REF! -> #REF! | P34: =#REF! -> #REF! | Q34: =R34-(N34+O34+P34) -> #REF! | R34: =R26+R32 -> #REF! | S34: =#REF! -> #REF! | T34: =#REF! -> #REF! | U34: =#REF! -> #REF! | V34: =W34-(S34+T34+U34) -> #REF! | W34: =W26+W32 -> #REF! | X34: =#REF! -> #REF! | Y34: =#REF! -> #REF! | Z34: =#REF! -> #REF! | AA34: =AB34-(X34+Y34+Z34) -> #REF! | AB34: =AB26+AB32 -> #REF! | AC34: =#REF! -> #REF! | AD34: =#REF! -> #REF! | AE34: =#REF! -> #REF! | AF34: =AG34-(AC34+AD34+AE34) -> #REF! | AG34: =AG26+AG32 -> #REF! | AH34: =AH26+AH32+AH33 -> 156 | AI34: =AI26+AI32+AI33 -> 505 | AJ34: =AJ26+AJ32+AJ33 -> 1364 | AK34: =AK26+AK32+AK33 -> 514 | AL34: =AL26+AL32+AL33 -> -60 | AM34: =AM26+AM32+AM33 -> 999 | AN34: =AN26+AN32+AN33 -> 848 | AO34: =AO26+AO32 -> 3297 | AT34: =AT26+AT32 -> 858 | AY34: =AY26+AY32 -> 530 | BC34: =BC26+BC32 -> 693.3789 | BD34: =BD26+BD32 -> 794.78008 | BE34: =BE26+BE32 -> 775.26368
A35: מס תזרימי | I35: =#REF! -> #REF! | J35: =#REF! -> #REF! | K35: =#REF! -> #REF! | L35: =#REF! -> #REF! | M35: =#REF! -> #REF! | N35: =#REF! -> #REF! | O35: =#REF! -> #REF! | P35: =#REF! -> #REF! | Q35: =R35-(N35+O35+P35) -> #REF! | R35: =#REF! -> #REF! | S35: =#REF! -> #REF! | T35: =#REF! -> #REF! | U35: =#REF! -> #REF! | V35: =W35-(S35+T35+U35) -> #REF! | W35: =#REF! -> #REF! | X35: =#REF! -> #REF! | Y35: =#REF! -> #REF! | Z35: =#REF! -> #REF! | AA35: =AB35-(X35+Y35+Z35) -> #REF! | AB35: =#REF! -> #REF! | AC35: =#REF! -> #REF! | AD35: =#REF! -> #REF! | AE35: =#REF! -> #REF! | AF35: =#REF! -> #REF! | AG35: =#REF! -> #REF! | AH35: ='IC&CF&BS'!K247 -> -57 | AI35: ='IC&CF&BS'!J247 -> -204 | AJ35: ='IC&CF&BS'!I247 -> -53 | AK35: ='IC&CF&BS'!H247 -> -120 | AL35: ='IC&CF&BS'!G247 -> -31 | AM35: ='IC&CF&BS'!F247 -> -193 | AN35: ='IC&CF&BS'!AB247 -> -132 | AO35: ='IC&CF&BS'!E245 -> -1185 | AP35: ='IC&CF&BS'!X247 -> -109 | AQ35: ='IC&CF&BS'!W247 -> -105 | AR35: ='IC&CF&BS'!V247 -> -32 | AS35: -55 | AT35: ='IC&CF&BS'!D247 -> -253 | AU35: ='IC&CF&BS'!T247 -> -6 | AV35: ='IC&CF&BS'!S247 -> -29 | AW35: ='IC&CF&BS'!R247 -> -22 | AX35: ='IC&CF&BS'!Q247 -> -41 | AY35: =AU35+AV35+AW35+AX35 -> -98 | AZ35: ='IC&CF&BS'!P247 -> -36 | BA35: ='IC&CF&BS'!O247 -> -37 | BB35: =BA35*2 -> -74 | BC35: =-(BC26+BC32)*15% -> -104.00683 | BD35: =-(BD26+BD32)*17% -> -135.11261 | BE35: =-(BE26+BE32)*19% -> -147.3001
A36: % מס | C36: =C34/B34-1 -> #DIV/0! | D36: =D34/C34-1 -> #DIV/0! | E36: =E34/D34-1 -> #DIV/0! | F36: =F34/E34-1 -> #DIV/0! | G36: =G34/F34-1 -> #DIV/0! | H36: =H34/#REF!-1 -> #REF! | I36: =-I35/I34 -> #REF! | J36: =-J35/J34 -> #REF! | K36: =-K35/K34 -> #REF! | L36: =-L35/L34 -> #REF! | M36: =-M35/M34 -> #REF! | N36: =-N35/N34 -> #REF! | O36: =-O35/O34 -> #REF! | P36: =-P35/P34 -> #REF! | ... AG36: =-AG35/AG34 -> #REF! | AH36: =AH35/AH34 -> -0.36538462 | AI36: =AI35/AI34 -> -0.4039604 | AJ36: =AJ35/AJ34 -> -0.038856305 | AK36: =AK35/AK34 -> -0.23346304 | AL36: =AL35/AL34 -> 0.51666667 | AM36: =AM35/AM34 -> -0.19319319 | AN36: =AN35/AN34 -> -0.15566038 | AO36: =#REF! -> #REF! | AT36: =AO36 -> #REF! | AY36: =AT36 -> #REF! | BC36: =AT36 -> #REF! | BD36: =AY36 -> #REF! | BE36: =BC36 -> #REF!
A37: חלק המיעוט | C37: =C35/B35-1 -> #DIV/0! | D37: =D35/C35-1 -> #DIV/0! | E37: =E35/D35-1 -> #DIV/0! | F37: =F35/E35-1 -> #DIV/0! | G37: =G35/F35-1 -> #DIV/0! | H37: =H35/#REF!-1 -> #REF! | I37: =#REF! -> #REF! | J37: =#REF! -> #REF! | K37: =#REF! -> #REF! | L37: =#REF! -> #REF! | M37: =#REF! -> #REF! | N37: =#REF! -> #REF! | O37: =#REF! -> #REF! | P37: =#REF! -> #REF! | Q37: =R37-(N37+O37+P37) -> #REF! | R37: -4 | S37: =#REF! -> #REF! | T37: =#REF! -> #REF! | U37: =#REF! -> #REF! | V37: =W37-(S37+T37+U37) -> #REF! | W37: =#REF! -> #REF! | X37: =#REF! -> #REF! | Y37: =#REF! -> #REF! | Z37: =#REF! -> #REF! | AA37: =#REF! -> #REF! | AB37: =#REF! -> #REF! | AC37: =#REF! -> #REF! | AD37: =#REF! -> #REF! | ... AG37: =#REF! -> #REF!
A38: תקבולים מבנות | AG38: =0 -> 0 | AH38: ='IC&CF&BS'!K251 -> 0 | AI38: ='IC&CF&BS'!J251 -> 0 | AJ38: ='IC&CF&BS'!I251 -> 0 | AK38: ='IC&CF&BS'!H251 -> 1 | AL38: ='IC&CF&BS'!G251 -> 5 | AM38: ='IC&CF&BS'!F251 -> 4 | AN38: ='IC&CF&BS'!AB251 -> 0 | AO38: ='IC&CF&BS'!E251 -> 1 | AP38: ='IC&CF&BS'!X251 -> 0 | AQ38: ='IC&CF&BS'!W251 -> 0 | AR38: ='IC&CF&BS'!V251 -> 0 | AS38: ='IC&CF&BS'!W251 -> 0 | AT38: ='IC&CF&BS'!D251 -> 1 | AU38: ='IC&CF&BS'!T251 -> 0 | AV38: ='IC&CF&BS'!S251 -> 0 | AW38: ='IC&CF&BS'!R251 -> 1 | AX38: ='IC&CF&BS'!Q251 -> 0 | AY38: =AU38+AV38+AW38+AX38 -> 1 | AZ38: ='IC&CF&BS'!P251 -> 0 | BA38: ='IC&CF&BS'!O251 -> 0 | BB38: 0 | BC38: =0 -> 0 | BD38: =0 -> 0 | BE38: =0 -> 0
A39: FFO | C39: =C36/B36-1 -> #DIV/0! | D39: =D36/C36-1 -> #DIV/0! | E39: =E36/D36-1 -> #DIV/0! | F39: =F36/E36-1 -> #DIV/0! | G39: =G36/F36-1 -> #DIV/0! | H39: =H36/#REF!-1 -> #REF! | I39: =I34+I35+I37-2 -> #REF! | J39: =J34+J35+J37 -> #REF! | K39: =K34+K35+K37 -> #REF! | L39: =L34+L35+L37 -> #REF! | M39: =M34+M35+M37 -> #REF! | N39: =N34+N35+N37 -> #REF! | O39: =O34+O35+O37 -> #REF! | P39: =P34+P35+P37 -> #REF! | Q39: =Q34+Q35+Q37 -> #REF! | ... AG39: =AG34+AG35+AG37 -> #REF! | AH39: =AH30+AH31+AH32+AH35+AH38 -> 738 | AI39: =AI30+AI31+AI32+AI35+AI38 -> 818 | AJ39: =AJ30+AJ31+AJ32+AJ35+AJ38 -> 941 | AK39: =AK30+AK31+AK32+AK35+AK38 -> 914 | AL39: =AL30+AL31+AL32+AL35+AL38 -> 696 | AM39: =AM30+AM31+AM32+AM35+AM38 -> 1368 | AN39: =AN30+AN31+AN32+AN35+AN38 -> 845 | AO39: =AO30+AO31+AO32+AO35+AO38 -> 2670 | ... BE39: =BE30+BE31+BE32+BE35+BE38 -> 1227.9636
A40: Capex | I40: ='השקעה ברכוש קבוע'!N8 -> 143.203 | J40: ='השקעה ברכוש קבוע'!R8 -> 125.826 | K40: ='השקעה ברכוש קבוע'!W8 -> 188.104 | L40: ='השקעה ברכוש קבוע'!AB8 -> 318.614 | M40: ='השקעה ברכוש קבוע'!AG8 -> 361.688 | N40: ='השקעה ברכוש קבוע'!AH8 -> 87.915 | O40: ='השקעה ברכוש קבוע'!AI8 -> 75.629 | P40: ='השקעה ברכוש קבוע'!AJ8 -> 79.501 | Q40: =R40-(N40+O40+P40) -> 100.336 | R40: ='השקעה ברכוש קבוע'!AL8 -> 343.381 | S40: ='השקעה ברכוש קבוע'!AM8 -> 85.563 | T40: ='השקעה ברכוש קבוע'!AN8 -> 125.292 | U40: ='השקעה ברכוש קבוע'!AO8 -> 160.385 | V40: ='השקעה ברכוש קבוע'!AP8 -> 149.565 | W40: ='השקעה ברכוש קבוע'!AQ8 -> 520.805 | X40: ='השקעה ברכוש קבוע'!AR8 -> 130.801 | Y40: ='השקעה ברכוש קבוע'!AS8 -> 204.388 | ... AG40: ='השקעה ברכוש קבוע'!BA8 -> 851.985 | AH40: ='IC&CF&BS'!K75 -> -632 | AI40: ='IC&CF&BS'!J75 -> -457 | AJ40: ='IC&CF&BS'!I75 -> -572 | AK40: ='IC&CF&BS'!H75 -> -576 | AL40: ='IC&CF&BS'!G75 -> -626 | AM40: ='IC&CF&BS'!F75 -> -611 | AN40: ='IC&CF&BS'!AB75 -> -131 | AO40: ='IC&CF&BS'!E75 -> -747 | AP40: ='IC&CF&BS'!X75 -> -164 | AQ40: ='IC&CF&BS'!W75 -> -170 | AR40: ='IC&CF&BS'!V75 -> -191 | AS40: ='IC&CF&BS'!W75 -> -170 | AT40: ='IC&CF&BS'!D75 -> -780 | AU40: ='IC&CF&BS'!T75 -> -145 | AV40: ='IC&CF&BS'!S75 -> -142 | AW40: ='IC&CF&BS'!R75 -> -159 | AX40: ='IC&CF&BS'!Q75 -> -267 | AY40: =AU40+AV40+AW40+AX40 -> -713 | AZ40: ='IC&CF&BS'!P75 -> -190 | BA40: ='IC&CF&BS'!O75 -> -202 | BB40: ='IC&CF&BS'!Y75 -> -212 | BC40: -710 | BD40: -670 | BE40: -600
A41: הון חוזר | I41: =' מאזן ויחסי יעילות תפעולית'!H54 -> 867.195 | J41: =' מאזן ויחסי יעילות תפעולית'!I54 -> 953.631 | K41: =' מאזן ויחסי יעילות תפעולית'!J54 -> 1506.498 | L41: =' מאזן ויחסי יעילות תפעולית'!K54 -> 1884.237 | M41: =' מאזן ויחסי יעילות תפעולית'!O54 -> 1733.072 | N41: =' מאזן ויחסי יעילות תפעולית'!P54 -> 1786.198 | O41: =' מאזן ויחסי יעילות תפעולית'!Q54 -> 1546.139 | P41: =' מאזן ויחסי יעילות תפעולית'!R54 -> 1521.016 | Q41: =' מאזן ויחסי יעילות תפעולית'!S54 -> 1542.568 | R41: =' מאזן ויחסי יעילות תפעולית'!T54 -> 1542.568 | S41: =' מאזן ויחסי יעילות תפעולית'!U54 -> 1764.265 | T41: =' מאזן ויחסי יעילות תפעולית'!V54 -> 1922.612 | ... V41: =' מאזן ויחסי יעילות תפעולית'!X54 -> 2073.415 | W41: =V41 -> 2073.415 | X41: =' מאזן ויחסי יעילות תפעולית'!Y54 -> 2133.56 | Y41: =' מאזן ויחסי יעילות תפעולית'!Z54 -> 2135.323 | Z41: =' מאזן ויחסי יעילות תפעולית'!AA54 -> 1990.988 | AA41: =' מאזן ויחסי יעילות תפעולית'!AB54 -> 1900.494 | AB41: =AA41 -> 1900.494 | AC41: =' מאזן ויחסי יעילות תפעולית'!AC54 -> 2004.021 | AD41: =' מאזן ויחסי יעילות תפעולית'!AD54 -> 1899.916 | AE41: =' מאזן ויחסי יעילות תפעולית'!AE54 -> 1748.033 | AF41: =' מאזן ויחסי יעילות תפעולית'!AF54 -> 1796.223 | AG41: =AF41 -> 1796.223 | AH41: ='IC&CF&BS'!K104+'IC&CF&BS'!K105-'IC&CF&BS'!K118 -> 1589 | AI41: ='IC&CF&BS'!J104+'IC&CF&BS'!J105-'IC&CF&BS'!J118 -> 1368 | AJ41: ='IC&CF&BS'!I104+'IC&CF&BS'!I105-'IC&CF&BS'!I118 -> 1565 | AK41: ='IC&CF&BS'!H104+'IC&CF&BS'!H105-'IC&CF&BS'!H118 -> 1378 | AL41: ='IC&CF&BS'!I104+'IC&CF&BS'!I105-'IC&CF&BS'!I118 -> 1565 | AM41: ='IC&CF&BS'!J104+'IC&CF&BS'!J105-'IC&CF&BS'!J118 -> 1368 | AN41: ='IC&CF&BS'!K104+'IC&CF&BS'!K105-'IC&CF&BS'!K118 -> 1589 | AO41: =AO13*AO42 -> 2744.11 | AT41: =AT13*AT42 -> 2049.792 | AY41: =AY13*AY42 -> 1860.752 | BC41: =BC13*BC42 -> 1946.4719 | BD41: =BD13*BD42 -> 1999.5533 | BE41: =BE13*BE42 -> 2033.2722
A42: הון חוזר ממכירות | C42: =C41/B41-1 -> #DIV/0! | D42: =D41/C41-1 -> #DIV/0! | E42: =E41/D41-1 -> #DIV/0! | F42: =F41/E41-1 -> #DIV/0! | G42: =G41/F41-1 -> #DIV/0! | H42: =H41/#REF!-1 -> #REF! | I42: =I41/I13 -> #REF! | J42: =J41/J13 -> #REF! | K42: =K41/K13 -> #REF! | L42: =L41/L13 -> #REF! | M42: =M41/M13 -> #REF! | N42: =N41/N13/4 -> #REF! | O42: =O41/O13/4 -> #REF! | P42: =P41/P13/4 -> #REF! | Q42: =Q41/Q13/4 -> #REF! | R42: 0.265 | S42: =S41/S13/4 -> #REF! | T42: =T41/T13/4 -> #REF! | U42: =U41/U13/4 -> #REF! | V42: =V41/V13/4 -> #REF! | W42: =W41/W13 -> #REF! | X42: =X41/X13/4 -> #REF! | Y42: =Y41/Y13/4 -> #REF! | Z42: =Z41/Z13/4 -> #REF! | AA42: =AA41/AA13/4 -> #REF! | AB42: =AB41/AB13 -> #REF! | AC42: =AC41/AC13/4 -> #REF! | AD42: =AD41/AD13/4 -> #REF! | AE42: =AE41/AE13/4 -> #REF! | AF42: =AF41/AF13/4 -> #REF! | AG42: =AG41/AG13 -> #REF! | AH42: =AH41/AH13 -> 0.29628939 | AI42: =AI41/AI13 -> 0.25249169 | AJ42: =AJ41/AJ13 -> 0.28167747 | AK42: =AK41/AK13 -> 0.26143047 | AL42: =AL41/AL13 -> 0.31033115 | AM42: =AM41/AM13 -> 0.19669303 | AN42: =AN41/AN13 -> 0.62930693 | AO42: 0.274 | AT42: 0.272 | AY42: 0.272 | BC42: 0.269 | BD42: 0.269 | BE42: 0.269
A43: תזרים תפעולי נקי | AH43: =AH39+AH40 -> 106 | AI43: =AI39+AI40 -> 361 | AJ43: =AJ39+AJ40 -> 369 | AK43: =AK39+AK40 -> 338 | AL43: =AL39+AL40 -> 70 | AM43: =AM39+AM40 -> 757 | AN43: =AN39+AN40 -> 714 | AO43: =AO39+AO40 -> 1923 | ... BE43: =BE39+BE40 -> 627.96358
A44: תקופה | AS44: 0.125 | BC44: 0.25 | BD44: 1 | BE44: =1+BD44 -> 2
A45: תזרים מהוון | AN45: =AN43 -> 714 | AS45: =AS43/(1+$AH$55)^AS44 -> 51.710046 | BC45: =BC43/(1+$AH$55)^BC44 -> 443.2015 | BD45: =BD43/(1+$AH$55)^BD44 -> 556.77395 | BE45: =BE43/(AH55-AH56)/(1+$AH$55)^(BE44-0.5) -> 7307.2172
A46: מכפילים:
AO47: 2022E | AT47: 2023E | AY47: 2023E | BC47: 2024E | BD47: 2024E | BE47: 2024E
A48: שוק EV/EBITDA | C48: 7.5929 | D48: 7.884 | E48: 6.9166 | F48: 7.3616 | G48: 6.5222 | AO48: =AM56/AO28 -> 2.8373155 | AT48: =$AK$57/AT28 -> #VALUE! | AY48: =$AK$57/AY28 -> #VALUE! | BC48: =$AK$57/BC28 -> #VALUE! | BD48: =$AK$57/BD28 -> #VALUE! | BE48: =$AK$57/BE28 -> #VALUE!
A49: כלכלי EV/EBITDA | C49: 7.5929 | D49: 7.884 | E49: 6.9166 | F49: 7.3616 | G49: 6.5222 | AO49: =(#REF!+$AH$57)/AO28 -> #REF! | AT49: =(#REF!+$AH$57)/AT28 -> #REF! | AY49: =(#REF!+$AH$57)/AY28 -> #REF! | BC49: =(#REF!+$AH$57)/BC28 -> #REF! | BD49: =(#REF!+$AH$57)/BD28 -> #REF! | BE49: =(#REF!+$AH$57)/BE28 -> #REF!
A50: P/E שוק | C50: 14.8521 | D50: 15.75 | E50: 13.3214 | F50: 16.9 | G50: 11.5533 | AO50: =$AH$62/AO39 -> 2.944064 | AT50: =$AH$62/AT39 -> 6.7589431 | AY50: =$AH$62/AY39 -> 6.7881268 | BC50: =$AH$62/BC39 -> 6.7567815 | BD50: =$AH$62/BD39 -> 6.1427293 | BE50: =$AH$62/BE39 -> 6.4013713
A51: P/E כלכלי | C51: 14.8521 | D51: 15.75 | E51: 13.3214 | F51: 16.9 | G51: 11.5533 | AO51: =$AH$61/AO39 -> 3.1842168 | AT51: =$AH$61/AT39 -> 7.3102828 | AY51: =$AH$61/AY39 -> 7.3418471 | BC51: =$AH$61/BC39 -> 7.3079449 | BD51: =$AH$61/BD39 -> 6.6438033 | BE51: =$AH$61/BE39 -> 6.9235432
A54: סיכום הערכת שווי: | AH54: פרמטר | AI54: הערות
A55: שיעור היוון | AH55: 0.095 | AK55: חוב פיננסי ברוטו | AM55: ='IC&CF&BS'!P145 -> 3852
A56: שיעור צמיחה | AH56: 0.02 | AK56: שוק EV | AM56: =AH62-AH59-AH58+AM55 -> 11388.985 | BC56: =AM56/BC28 -> 7.6110299 | BD56: =AM56/BD28 -> 6.8617431 | BE56: =AM56/BE28 -> 7.0290933
A57: שווי תפעולי | AH57: =SUM(BC45:BE45)-AZ43-BA43 -> 8233.1926 | AK57: כלכלי EV | AM57: =AH57+AM55-AH58-AH59-AH60 -> 11816.526 | BC57: =AM57/BC28 -> 7.8967475 | BD57: =AM57/BD28 -> 7.1193325 | BE57: =AM57/BE28 -> 7.292965
A58: נכסים עודפים | AH58: =-('IC&CF&BS'!O146+'IC&CF&BS'!O147) -> 701
A59: חלק המיעוט | AH59: =-'IC&CF&BS'!O130/'IC&CF&BS'!O129*(AH57+AH58) -> -377.33371 | BE59: ניתוח רגישות לשיעור היוון ולשיעור צמיחה פרמננטית
A60: דיב' אחרי תאריך המאזן | AH60: -55 | AI60: יום אקס 5/6/2025 | AZ60: =BC28-BC27+BC31+BC32+BC35 -> 542.37206 | BA60: =BD28-BD27+BD31+BD32+BD35 -> 659.66747 | BE60: =AH68 -> 22.71301 | BF60: 0.085 | BG60: 0.0875 | BH60: 0.09 | BI60: 0.0925 | BJ60: 0.095 | BK60: 0.0975 | BL60: 0.1 | BM60: 0.1025 | BN60: 0.105
A61: שווי כלכלי חברה | AH61: =SUM(AH57:AH60) -> 8501.8589 | AI61: מיל' $ | AZ61: =AH62/AZ60 -> 14.493097 | BA61: =AH62/BA60 -> 11.916081 | BE61: 0.01 | BF61: 22.987822 | BG61: 22.309156 | BH61: 21.673027 | BI61: 21.075567 | BJ61: 20.513363 | BK61: 19.983391 | BL61: 19.482965 | BM61: 19.009687 | BN61: 18.561414
A62: שווי שוק חברה | AH62: =AH65*AH69/AH71 -> 7860.6508 | BE62: 0.0125 | BF62: 23.64148 | BG62: 22.918535 | BH62: 22.242356 | BI62: 21.608556 | BJ62: 21.013283 | BK62: 20.453134 | BL62: 19.9251 | BM62: 19.426501 | BN62: 18.954951
A63: שווי כלכלי חברה | AH63: =AH61*AH71 -> 29314.409 | AI63: מיל' ₪ | AZ63: =BA30+BB30+445 -> 1613.3789 | BE63: 0.015 | BF63: 24.341828 | BG63: 23.56994 | BH63: 22.849639 | BI63: 22.175931 | BJ63: 21.544447 | BK63: 20.951347 | BL63: 20.393242 | BM63: 19.867133 | BN63: 19.370351
A64: שווי שוק חברה | AH64: =AH62*AH71 -> 27103.524 | AZ64: =AM56/AZ63 -> 7.0590886 | BE64: 0.0175 | BF64: 25.094053 | BG64: 24.267874 | BH64: 23.498805 | BI64: 22.781132 | BJ64: 22.109881 | BK64: 21.480698 | BL64: 20.889757 | BM64: 20.333684 | BN64: 19.809488
A65: כמות מניות בדילול מלא | AH65: =1290.644 -> 1290.644 | BE65: 0.02 | BF65: 25.904141 | BG65: 25.017507 | BH65: 24.194339 | BI65: 23.42807 | BJ65: 22.71301 | BK65: 22.0442 | BL65: 21.417305 | BM65: 20.828511 | BN65: 20.274457
A66: שווי כלכלי למניה | AH66: =AH61/AH65 -> 6.5872997 | AI66: $ | BE66: 0.0225 | BF66: 26.779037 | BG66: 25.824804 | BH66: 24.941394 | BI66: 24.121218 | BJ66: 23.357734 | BK66: 22.645269 | BL66: 21.978887 | BM66: 21.354265 | BN66: 20.767606
A67: שווי שוק למניה | AH67: =AH69/AH71 -> 6.0904872 | BE67: 0.025 | BF67: 27.726841 | BG67: 26.696684 | BH67: 25.745915 | BI67: 24.865711 | BJ67: 24.048509 | BK67: 23.287792 | BL67: 22.577909 | BM67: 21.913939 | BN67: 21.291577
A68: שווי כלכלי למניה | AH68: =AH66*AH71 -> 22.71301 | AI68: ש"ח | BE68: 0.0275 | BF68: 28.757063 | BG68: 27.641222 | BH68: 26.614798 | BI68: 25.667472 | BJ68: 24.790454 | BK68: 23.976209 | BL68: 23.218242 | BM68: 22.510924 | BN68: 21.849352
A69: שווי שוק | AH69: 21 | BE69: 0.03 | BF69: 29.880941 | BG69: 28.667893 | BH69: 27.556088 | BI69: 26.533374 | BJ69: 25.589471 | BK69: 24.715619 | BL69: 23.904313 | BM69: 23.14908 | BN69: 22.444312
A70: דיסקאונט | AH70: =AH68/AH69-1 -> 0.081571883
A71: שער ה- $ | AH71: 3.448
BE72: ניתוח רגישות מחיר יעד למחיר אשלג מייצג
A73: סימול איי.סי.אל | J73: EBITDA H2-14 | K73: EBITDA H1-15 | L73: EBITDA 12ME | M73: EV שוק | R73: EV/ EBITDA שוק | W73: EV/ EBITDA רצוי | AB73: EV נגזר | AC73: שווי שוק נגזר | AD73: שווי מנייה נגזר | AH73: 281014 | BE73: מחיר אשלג | BF73: 300 | BG73: 310 | BH73: 320 | BI73: 330 | BJ73: 340
A74: סימול $ | J74: =#REF! -> #REF! | K74: =#REF!/2 -> #REF! | L74: =J74+K74 -> #REF! | M74: =AK57 -> כלכלי EV | R74: =AK57/L74 -> #VALUE! | W74: 7 | AB74: =L74*W74 -> #REF! | AC74: =AH62-(M74-AB74) -> #VALUE! | AD74: =AC74/AH65*I72 -> #VALUE! | AH74: 9999806 | BE74: מחיר יעד | BF74: 21.8 | BG74: 22.8 | BH74: 23.8 | BI74: 24.6 | BJ74: 25.5
I102: 195 | J102: 40344 | R102: 0.05 | W102: 0.05 | AB102: 0.05 | AC102: 0.05 | AG102: 0.05
I103: 170 | J103: 40296
I104: 170 | J104: 40540
I105: 177 | J105: 40428
I106: 668 | J106: 40344
I107: 155 | J107: 40281
I108: =SUM(I104:I107) -> 1170
I109: =I108/AH62 -> 0.14884264 | J109: תשואת דיב' ב- 2010
I110: =(I102+I103)*2/AH62 -> 0.092867629 | J110: תשואת דיב' ב- 2011 לפי קצב חלוקות דיב' נוכחי (730 מ' $ בשנת 2010)
I111: (*) מדיניות חלוקת דיבידנד של עד 70% מהרווח הנקי
I113: ניתוח רגישות שווי כלכלי למניה - שיעור היוון וצמיחה פרמננטית
I114: =$AH$68 -> 22.71301 | J114: 0.0825 | K114: 0.085 | L114: 0.0875 | M114: 0.09 | N114: 0.0925 | O114: 0.095 | P114: 0.0975 | Q114: 0.1 | R114: 0.1025 | S114: 0.11
I115: 0.01 | J115: 22.71301 | K115: 22.71301 | L115: 22.71301 | M115: 22.71301 | N115: 22.71301 | O115: 22.71301 | P115: 22.71301 | Q115: 22.71301 | R115: 22.71301 | S115: 22.71301
I116: 0.0125 | J116: 22.71301 | K116: 22.71301 | L116: 22.71301 | M116: 22.71301 | N116: 22.71301 | O116: 22.71301 | P116: 22.71301 | Q116: 22.71301 | R116: 22.71301 | S116: 22.71301
I117: 0.015 | J117: 22.71301 | K117: 22.71301 | L117: 22.71301 | M117: 22.71301 | N117: 22.71301 | O117: 22.71301 | P117: 22.71301 | Q117: 22.71301 | R117: 22.71301 | S117: 22.71301
I118: 0.0175 | J118: 22.71301 | K118: 22.71301 | L118: 22.71301 | M118: 22.71301 | N118: 22.71301 | O118: 22.71301 | P118: 22.71301 | Q118: 22.71301 | R118: 22.71301 | S118: 22.71301
I119: 0.02 | J119: 22.71301 | K119: 22.71301 | L119: 22.71301 | M119: 22.71301 | N119: 22.71301 | O119: 22.71301 | P119: 22.71301 | Q119: 22.71301 | R119: 22.71301 | S119: 22.71301
I120: 0.0225 | J120: 22.71301 | K120: 22.71301 | L120: 22.71301 | M120: 22.71301 | N120: 22.71301 | O120: 22.71301 | P120: 22.71301 | Q120: 22.71301 | R120: 22.71301 | S120: 22.71301
I121: 0.025 | J121: 22.71301 | K121: 22.71301 | L121: 22.71301 | M121: 22.71301 | N121: 22.71301 | O121: 22.71301 | P121: 22.71301 | Q121: 22.71301 | R121: 22.71301 | S121: 22.71301
I122: 0.0275 | J122: 22.71301 | K122: 22.71301 | L122: 22.71301 | M122: 22.71301 | N122: 22.71301 | O122: 22.71301 | P122: 22.71301 | Q122: 22.71301 | R122: 22.71301 | S122: 22.71301
I123: 0.03 | J123: 22.71301 | K123: 22.71301 | L123: 22.71301 | M123: 22.71301 | N123: 22.71301 | O123: 22.71301 | P123: 22.71301 | Q123: 22.71301 | R123: 22.71301 | S123: 22.71301
I126: שיעור היוון | J126: 0.0925
I127: צמיחה פרמ' | J127: 0.0175
I129: ניתוח רגישות שווי כלכלי למניה - מחיר אשלג
I130: =$AH$68 -> 22.71301 | J130: 400 | K130: 425 | L130: 450 | M130: 475 | N130: 500 | O130: 525 | P130: 550 | Q130: 575 | R130: 600
I131: שווי למניה | J131: 47.4 | K131: 49.4 | L131: 51.3 | M131: 53.3 | N131: =AH68 -> 22.71301 | O131: 57.3 | P131: 59.2 | Q131: 61.2 | R131: 63.2
I132: שוש"כ | J132: =$AH$69/J131 -> 0.44303797 | K132: =$AH$69/K131 -> 0.42510121 | L132: =$AH$69/L131 -> 0.40935673 | M132: =$AH$69/M131 -> 0.39399625 | N132: =$AH$69/N131 -> 0.92458025 | O132: =$AH$69/O131 -> 0.36649215 | P132: =$AH$69/P131 -> 0.35472973 | Q132: =$AH$69/Q131 -> 0.34313725 | R132: =$AH$69/R131 -> 0.33227848
I133: מרווח תפעולי אשלג | J133: 0.438 | K133: 0.471 | L133: 0.5 | M133: 0.526 | N133: 0.55 | O133: 0.571 | P133: 0.591 | Q133: 0.609 | R133: 0.625
I135: מחיר אשלג בשנה המייצגת | L135: =#REF! -> #REF!

Sheet Q2.25F
H6: תחזית תוצאות איי.סי.אל
H7: סעיף | I7: Q2-25A | J7: Q2-25E | K7: Q1-25A | L7: Q2-24A
H8: אשלג
H9: מכירות אשלג חיצוניים (א' טון) | I9: ='DCF 1.6.2025'!BA6 -> 876 | J9: 1080 | K9: 1005 | L9: 1060
H10: מחיר לטון אשלג | I10: ='DCF 1.6.2025'!BA7 -> 333 | J10: 326.9058 | K10: 300 | L10: 300
H11: מכירות אשלג חיצוניים (מ' $) | I11: ='DCF 1.6.2025'!BA8 -> 347 | J11: 409.05826 | K11: 358 | L11: 381
H12: רווח מגזרי | I12: ='DCF 1.6.2025'!BA16 -> 52 | J12: 108.7455 | K12: 56 | L12: 60
H13: מרווח מגזרי אשלג | I13: ='DCF 1.6.2025'!BA17 -> 0.14985591 | J13: 0.26584355 | K13: 0.15642458 | L13: 0.15748031
H14: פוספט
H15: מכירות פוספט חיצוניים (מ' $) | I15: ='DCF 1.6.2025'!BA9 -> 589 | J15: 543.84 | K15: 536 | L15: 528
H16: רווח מגזרי | I16: ='DCF 1.6.2025'!BA18 -> 90 | J16: 97 | K16: 91 | L16: 93
H17: מרווח מגזרי פוספט | I17: ='DCF 1.6.2025'!BA19 -> 0.15280136 | J17: 0.17836128 | K17: 0.16977612 | L17: 0.17613636
H18: מוצרים תעשייתיים
H19: מכירות מוצרים תעשייתיים חיצוניים (מ' $) | I19: ='DCF 1.6.2025'!BA10 -> 315 | J19: 327 | K19: 338 | L19: 309
H20: רווח מגזרי | I20: ='DCF 1.6.2025'!BA20 -> 54 | J20: 61 | K20: 62 | L20: 60
H21: מרווח מגזרי מוצרים תעשייתיים | I21: ='DCF 1.6.2025'!BA21 -> 0.17142857 | J21: 0.18654434 | K21: 0.18343195 | L21: 0.19417476
H22: פתרונות חדשניים לחקלאות
H23: מכירות פתרונות חדשניים חיצוניים (מ' $) | I23: ='DCF 1.6.2025'!BA11 -> 534 | J23: 508.56 | K23: 491 | L23: 489
H24: רווח מגזרי | I24: ='DCF 1.6.2025'!BA22 -> 35 | J24: 32 | K24: 28 | L24: 25
H25: מרווח מגזרי מוצרים תעשייתיים | I25: ='DCF 1.6.2025'!BA23 -> 0.065543071 | J25: 0.062922762 | K25: 0.057026477 | L25: 0.051124744
H26: סך הכנסות | I26: ='DCF 1.6.2025'!BA13 -> 1832 | J26: 1833.4583 | K26: 1767 | L26: 1752
H27: רווח תפעולי (כולל אחרים והוצ' לא משויכות) | I27: ='DCF 1.6.2025'!BA26 -> 181 | J27: 265.7455 | K27: 185 | L27: 211
H28: EBITDA | I28: ='DCF 1.6.2025'!BA28 -> 331 | J28: 415.7455 | K28: 336 | L28: 363
H29: FFO | I29: ='DCF 1.6.2025'!BA39 -> 174 | J29: 311.23267 | K29: 292 | L29: 289

Sheet Final Potash Pricing Q1.25
A2: מגזר האשלג - נתונים השוואתיים
A3: שנה סעיף | B3: 2003A | C3: 2004A | D3: 2005A | E3: 2006A | F3: Q1-07A | G3: Q2-07A | H3: Q3-07A | I3: Q4-07A | J3: 2007A | K3: Q1-08A | L3: Q2-08A | M3: Q3-08A | N3: Q4-08A | O3: 2012A | P3: Q1-09A | Q3: Q2-09A | R3: Q3-09A | S3: Q4-09A | T3: 2013A | U3: Q1-10A | V3: Q2-10A | W3: Q3-10A | X3: Q4-10A | Y3: 2014A | Z3: Q1-11A | AA3: Q2-11A | AB3: Q3-11A | AC3: Q4-11A | AD3: 2015A | AE3: Q1-12A | AF3: Q2-12A | AG3: Q3-12A | AH3: Q4-12A | AI3: 2016A | AJ3: Q1-13A | AK3: Q2-13A | AL3: Q3-13A | AM3: Q4-13A | AN3: 2017A | AO3: Q1-14A | AP3: Q2-14A | AQ3: Q3-14A | AR3: Q4-14A | AS3: 2018A | AT3: Q1-15A | AU3: Q2-15A | AV3: Q3-15A | AW3: Q4-15A | AX3: 2019A | AY3: Q1-20A | AZ3: Q2-20A | BA3: Q3-20A | BB3: Q4-20A | BC3: 2020A | BD3: Q1-21A | BE3: Q2-21A | BF3: Q3-21A | BG3: Q4-21A | BH3: 2021A | BI3: Q1-22A | BJ3: 2022A | BK3: Q1-23A | BL3: Q2-23A | BM3: Q3-23A | BN3: Q4-23A | BO3: 2023A | BP3: Q1-24A | BQ3: Q2-24A | BR3: Q3-24A | BS3: Q4-24A | BT3: 2024A | BU3: Q1-25A | BV3: Q2-25A | BW3: מייצג | BY3: Q2-25E | BZ3: H2-25E | CA3: 2026E | CB3: מייצג
A5: כמויות מכירה (מ' טון):
A6: מערב אירופה | J6: 1.8 | O6: 1.1 | T6: =O6*(1+T7) -> 0.11 | Y6: 1.246 | AD6: 1 | AI6: =0.91127-0.05 -> 0.86127 | AN6: 0.746 | AS6: 0.746 | AX6: 0.746 | BC6: 0.746 | BH6: 0.746 | BJ6: 0.746 | BO6: 0.746 | BT6: 0.746
A7: YOY | O7: =O6/J6-1 -> -0.38888889 | T7: -0.9 | Y7: =Y6/T6-1 -> 10.327273 | AD7: =AD6/Y6-1 -> -0.19743178 | AI7: =AI6/AD6-1 -> -0.13873 | AN7: =AN6/AI6-1 -> -0.13383724 | AS7: =AS6/AN6-1 -> 0 | AX7: =AX6/AS6-1 -> 0 | BC7: =BC6/AX6-1 -> 0 | BH7: =BH6/BC6-1 -> 0 | BJ7: =BJ6/BE6-1 -> #DIV/0! | BO7: =BO6/BI6-1 -> #DIV/0! | BT7: =BT6/BN6-1 -> #DIV/0!
A8: מזרח אסיה/ שאר העולם | J8: 0.85 | O8: 0.85 | T8: =O8*(1+T9) -> 0.3825 | Y8: 0.85 | AD8: =1+0.15 -> 1.15 | AI8: =1.28+0.05 -> 1.33 | AN8: 1.25 | AS8: 1.25 | AX8: 1.25 | BC8: 1.25 | BH8: 1.25 | BJ8: 1.25 | BO8: 1.25 | BT8: 1.25
A9: YOY | O9: =O8/J8-1 -> 0 | T9: -0.55 | Y9: =Y8/T8-1 -> 1.2222222 | AD9: =AD8/Y8-1 -> 0.35294118 | AI9: =AI8/AD8-1 -> 0.15652174 | AN9: =AN8/AI8-1 -> -0.060150376 | AS9: =AS8/AN8-1 -> 0 | AX9: =AX8/AS8-1 -> 0 | BC9: =BC8/AX8-1 -> 0 | BH9: =BH8/BC8-1 -> 0 | BJ9: =BJ8/BE8-1 -> #DIV/0! | BO9: =BO8/BI8-1 -> #DIV/0! | BT9: =BT8/BN8-1 -> #DIV/0!
A10: דרום אמריקה | J10: 0.95 | O10: 1 | T10: =O10*(1+T11) -> 1 | Y10: 1.02 | AD10: 0.654 | AI10: =7.35*13.8% -> 1.0143 | AN10: =7.6*15% -> 1.14 | AS10: =7.6*15% -> 1.14 | AX10: =7.6*15% -> 1.14 | BC10: =7.6*15% -> 1.14 | BH10: =7.6*15% -> 1.14 | BJ10: =7.6*15% -> 1.14 | BO10: =7.6*15% -> 1.14 | BT10: =7.6*15% -> 1.14
A11: YOY | O11: =O10/J10-1 -> 0.052631579 | T11: 0 | Y11: =Y10/T10-1 -> 0.02 | AD11: =AD10/Y10-1 -> -0.35882353 | AI11: =AI10/AD10-1 -> 0.55091743 | AN11: =AN10/AI10-1 -> 0.12392783 | AS11: =AS10/AN10-1 -> 0 | AX11: =AX10/AS10-1 -> 0 | BC11: =BC10/AX10-1 -> 0 | BH11: =BH10/BC10-1 -> 0 | BJ11: =BJ10/BE10-1 -> #DIV/0! | BO11: =BO10/BI10-1 -> #DIV/0! | BT11: =BT10/BN10-1 -> #DIV/0!
A12: הודו | J12: 1 | O12: 1.05 | T12: =O12*(1+T13) -> 0.9975 | Y12: 1.43 | AD12: 0.86 | AI12: =3.4*21.6% -> 0.7344 | AN12: 0.81 | AS12: 0.81 | AX12: 0.81 | BC12: 0.81 | BH12: 0.81 | BJ12: 0.81 | BO12: 0.81 | BT12: 0.81
A13: YOY | O13: =O12/J12-1 -> 0.05 | T13: -0.05 | Y13: =Y12/T12-1 -> 0.43358396 | AD13: =AD12/Y12-1 -> -0.3986014 | AI13: =AI12/AD12-1 -> -0.14604651 | AN13: =AN12/AI12-1 -> 0.10294118 | AS13: =AS12/AN12-1 -> 0 | AX13: =AX12/AS12-1 -> 0 | BC13: =BC12/AX12-1 -> 0 | BH13: =BH12/BC12-1 -> 0 | BJ13: =BJ12/BE12-1 -> #DIV/0! | BO13: =BO12/BI12-1 -> #DIV/0! | BT13: =BT12/BN12-1 -> #DIV/0!
A14: סין | J14: 0.6 | O14: 0.483 | T14: =T16-T6-T8-T10-T12 -> 2.222 | Y14: 0.72 | AD14: =1.24 -> 1.24 | AI14: =3.07*12.9% -> 0.39603 | AN14: =6.03*12.7% -> 0.76581 | AS14: =6.03*12.7% -> 0.76581 | AX14: =6.03*12.7% -> 0.76581 | BC14: =6.03*12.7% -> 0.76581 | BH14: =6.03*12.7% -> 0.76581 | BJ14: =6.03*12.7% -> 0.76581 | BO14: =6.03*12.7% -> 0.76581 | BT14: =6.03*12.7% -> 0.76581
A15: YOY | O15: =O14/J14-1 -> -0.195 | T15: -0.85 | Y15: =Y14/T14-1 -> -0.6759676 | AD15: =AD14/Y14-1 -> 0.72222222 | AI15: =AI14/AD14-1 -> -0.68062097 | AN15: =AN14/AI14-1 -> 0.93371714 | AS15: =AS14/AN14-1 -> 0 | AX15: =AX14/AS14-1 -> 0 | BC15: =BC14/AX14-1 -> 0 | BH15: =BH14/BC14-1 -> 0 | BJ15: =BJ14/BE14-1 -> #DIV/0! | BO15: =BO14/BI14-1 -> #DIV/0! | BT15: =BT14/BN14-1 -> #DIV/0!
A16: מכירות (כמות) | B16: 5.2 | C16: 5.1 | D16: 4.7 | E16: 3.9 | F16: =F21 -> 1.173 | G16: =G21 -> 1.239 | H16: =H21 -> 1.349 | I16: =J16-(F16+G16+H16) -> 1.439 | J16: =J6+J8+J10+J12+J14 -> 5.2 | K16: =K21 -> 1.39 | L16: =L21 -> 1.413 | M16: =M21 -> 1.179 | N16: =O16-(K16+L16+M16) -> 0.354 | O16: =O21 -> 4.336 | P16: =P21 -> 0.299 | Q16: =Q21 -> 0.347 | R16: =R21 -> 0.939 | S16: =T16-(P16+Q16+R16) -> 3.127 | T16: =T21 -> 4.712 | U16: =U21 -> 1.273 | V16: =V21 -> 1.455 | W16: =W21 -> 1.212 | X16: =X21 -> 1.094 | Y16: =Y21 -> 5.034 | Z16: =Z21 -> 0.987 | AA16: =AA21 -> 1.274 | AB16: =AB21 -> 1.316 | AC16: =AD16-(Z16+AA16+AB16) -> 0.682 | AD16: =AD21 -> 4.259 | AE16: =AE21 -> 0.85 | AF16: =AF21 -> 1.443 | AG16: =AG21 -> 1.315 | AH16: =AI16-(AE16+AF16+AG16) -> 1.21 | AI16: =AI21 -> 4.818 | AJ16: =AJ21 -> 1.251 | AK16: =AK21 -> 1.298 | AL16: =AL21 -> 0.918 | AM16: =AN16-(AJ16+AK16+AL16) -> 1.271 | AN16: =AN21 -> 4.738 | AO16: =AO21 -> 1.401 | AP16: =AP21 -> 1.249 | AQ16: 1.234 | AR16: =AS16-(AO16+AP16+AQ16) -> 0.726 | AS16: =AS21 -> 4.61 | AT16: =AT21 -> 1.067 | AU16: =AU21 -> 0.65 | AV16: =AV21 -> 1.126 | AW16: =AW21 -> 0.937 | AX16: =AX21 -> 3.78 | AY16: =AY21 -> 0.8596051 | AZ16: =AZ21 -> 1.0853706 | BA16: =BA21 -> 0.97256869 | BB16: =BC16-(AY16+AZ16+BA16) -> 1.1834051 | BC16: =BC21 -> 4.1009495 | BD16: =BD21 -> 0.9661039 | BE16: =BE21 -> 1.0309709 | BF16: =BF21 -> 0.95662385 | BG16: =BH16-(BD16+BE16+BF16) -> 1.1060176 | BH16: =BH21 -> 4.0597162 | BI16: =BI21 -> 1.0530818 | BJ16: =BJ21 -> 4.125 | BK16: =BK21 -> 0.8695 | BL16: =BL21 -> 1.164 | BM16: =BM21 -> 1.182 | BN16: =BO16-BK16-BL16-BM16 -> 1.0935 | BO16: =BO21 -> 4.309 | BP16: =BP21 -> 0.989 | BQ16: =BQ21 -> 1.06 | BR16: =BR21 -> 0.98 | BS16: =BS21 -> 1.16 | BT16: =BT21 -> 4.189 | BU16: =BU21 -> 1.005 | BV16: =BV21 -> 0.876 | BW16: 4.6
A17: YOY | C17: =C16/B16-1 -> -0.019230769 | D17: =D16/C16-1 -> -0.078431373 | E17: =E16/D16-1 -> -0.17021277 | J17: =J16/E16-1 -> 0.33333333 | O17: =O16/J16-1 -> -0.16615385 | T17: =T16/O16-1 -> 0.086715867 | U17: =U16/P16-1 -> 3.2575251 | V17: =V16/Q16-1 -> 3.1930836 | W17: =W16/R16-1 -> 0.29073482 | X17: =X16/S16-1 -> -0.65014391 | Y17: =Y16/T16-1 -> 0.068336163 | Z17: =Z16/V16-1 -> -0.32164948 | AA17: =AA16/V16-1 -> -0.12439863 | AB17: =AB16/W16-1 -> 0.085808581 | AC17: =AC16/X16-1 -> -0.37659963 | AD17: =AD16/Y16-1 -> -0.15395312 | AE17: =AE16/Z16-1 -> -0.13880446 | AF17: =AF16/AA16-1 -> 0.13265306 | AG17: =AG16/AB16-1 -> -0.00075987842 | AH17: =AH16/AC16-1 -> 0.77419355 | ... AX17: =AX16/AS16-1 -> -0.18004338 | AY17: =AY16/AS16-1 -> -0.81353469 | AZ17: =AZ16/AT16-1 -> 0.017217046 | BA17: =BA16/AV16-1 -> -0.13626226 | BB17: =BB16/AW16-1 -> 0.26297237 | BC17: =BC16/AX16-1 -> 0.08490727 | BD17: =BD16/AX16-1 -> -0.74441696 | BE17: =BE16/AY16-1 -> 0.19935407 | BF17: =BF16/BA16-1 -> -0.016394561 | BG17: =BG16/BB16-1 -> -0.065393938 | BH17: =BH16/BC16-1 -> -0.010054567 | BI17: =BI16/BC16-1 -> -0.74321026 | BJ17: =BJ16/BE16-1 -> 3.001083 | BK17: =BK16/BE16-1 -> -0.15662021 | BL17: =BL16/BF16-1 -> 0.21677919 | BM17: =BM16/BG16-1 -> 0.068699101 | BO17: =BO16/BJ16-1 -> 0.044606061 | BP17: =BP16/BI16-1 -> -0.060851648 | BT17: =BT16/BO16-1 -> -0.027848689 | BU17: =BU16/BN16-1 -> -0.080932785 | BV17: =BV16/BO16-1 -> -0.79670457
A18: כושר ייצור אפקטיבי | B18: =C18-0.45 -> 5.55 | C18: 6 | D18: 6 | E18: 6 | J18: 6 | O18: 6 | T18: 6 | U18: 6 | V18: 6 | W18: 6 | X18: 6 | Y18: 6 | Z18: =Y18 -> 6 | AA18: =Z18 -> 6 | AB18: =AA18 -> 6 | AC18: =AB18 -> 6 | AD18: 6 | AE18: =AD18 -> 6 | AF18: =AE18 -> 6 | AG18: =AF18 -> 6 | AH18: =AG18 -> 6 | AI18: 6 | AJ18: =AI18 -> 6 | AK18: =AJ18 -> 6 | AL18: =AK18 -> 6 | AM18: =AL18 -> 6 | AN18: 5.688 | AO18: =AN18 -> 5.688 | AP18: =AO18 -> 5.688 | AQ18: =AP18 -> 5.688 | AR18: =AQ18 -> 5.688 | AS18: 5.363 | AT18: =AS18 -> 5.363 | AU18: =AT18 -> 5.363 | AV18: =AU18 -> 5.363 | AW18: =AV18 -> 5.363 | AX18: 5.23 | AY18: 5.23 | AZ18: 5.23 | BA18: 5.23 | BB18: =BC18 -> 5.23 | BC18: 5.23 | BD18: 5.23 | BE18: 5.23 | BF18: 5.23 | BG18: =BH18 -> 5.23 | BH18: 5.23 | BI18: 5.23 | BJ18: 5.23 | BK18: 5.5 | BL18: 5.5 | BM18: 5.5 | BN18: 5.5 | BO18: 5.23 | BP18: 5.5 | BQ18: 5.5 | BR18: 5.5 | BS18: 5.5 | BT18: 5.5 | BU18: 5.5 | BV18: 5.5 | BW18: 5.5
A19: שיעור ניצולת | B19: =B20/B18 -> 0.92594595 | C19: =C20/C18 -> 0.89783333 | D19: =D20/D18 -> 0.87716667 | E19: =E20/E18 -> 0.84766667 | J19: =J20/J18 -> 0.84633333 | O19: =O20/O18 -> 0.82266667 | T19: =T21/T18 -> 0.78533333 | U19: =U20*4/U18 -> 0.664 | V19: =V20*4/V18 -> 0.70466667 | W19: =W20*4/W18 -> 0.67533333 | X19: =X20*4/X18 -> 1.3846667 | Y19: =Y21/Y18 -> 0.839 | Z19: =Z20*4/Z18 -> 0.49866667 | AA19: =AA20*4/AA18 -> 0.8 | AB19: =AB20*4/AB18 -> 0.74866667 | AC19: =AC20*4/AC18 -> 0.74933333 | AD19: =AD21/AD18 -> 0.70983333 | AE19: =AE20*4/AE18 -> 0.808 | AF19: =AF20*4/AF18 -> 0.86866667 | AG19: =AG20*4/AG18 -> 0.776 | AH19: =AH20*4/AH18 -> 1.0666667 | AI19: =AI21/AI18 -> 0.803 | AJ19: =AJ20*4/AJ18 -> 0.86866667 | AK19: =AK20*4/AK18 -> 0.82 | AL19: =AL20*4/AL18 -> 0.848 | AM19: =AM20*4/AM18 -> 0.64533333 | AN19: =AN21/AN18 -> 0.83298172 | AO19: =AO20*4/AO18 -> 0.8931083 | AP19: =AP20*4/AP18 -> 0.87834037 | AQ19: =AQ20*4/AQ18 -> 0.91772152 | AR19: =AR20*4/AR18 -> 0.74261603 | AS19: =AS21/AS18 -> 0.85959351 | AT19: =AT20*4/AT18 -> 0.6220399 | AU19: =AU20*4/AU18 -> 0.43483125 | AV19: =AV20*4/AV18 -> 0.98303189 | AW19: =AW20*4/AW18 -> 1.0620921 | AX19: =AX21/AX18 -> 0.72275335 | AY19: =AY21*4/AY18 -> 0.65744176 | AZ19: =AZ21*4/AZ18 -> 0.83011135 | BA19: =BA21*4/BA18 -> 0.74383839 | BB19: =BB21*4/BB18 -> 0.90508995 | BC19: =BC21/BC18 -> 0.78412036 | BD19: =BD21*4/BD18 -> 0.73889399 | BE19: =BE21*4/BE18 -> 0.78850545 | BF19: =BF21*4/BF18 -> 0.73164348 | BG19: =BG21*4/BG18 -> 0.84590255 | BH19: =BH21/BH18 -> 0.77623637 | BI19: =BI21*4/BI18 -> 0.80541626 | BJ19: =BJ21/BJ18 -> 0.78871893 | BK19: =BK21*4/BK18 -> 0.63236364 | BL19: =BL21*4/BL18 -> 0.84654545 | BM19: =BM21*4/BM18 -> 0.85963636 | BN19: =BN21*4/BN18 -> 0.79527273 | BO19: =BO21/BO18 -> 0.82390057 | BP19: =BP21*4/BP18 -> 0.71927273 | BQ19: =BQ21*4/BQ18 -> 0.77090909 | BR19: =BR21*4/BR18 -> 0.71272727 | BS19: =BS21*4/BS18 -> 0.84363636 | BT19: =BT21/BT18 -> 0.76163636 | BU19: =BU21*4/BU18 -> 0.73090909 | BV19: =BV21*4/BV18 -> 0.63709091 | BW19: =BW21/BW18 -> 0.82727273
A20: ייצור אשלג (מ' טון) | B20: 5.139 | C20: 5.387 | D20: 5.263 | E20: 5.086 | F20: 1.226 | G20: 1.167 | H20: 1.264 | I20: =J20-(F20+G20+H20) -> 1.421 | J20: 5.078 | K20: 1.288 | L20: 1.283 | M20: 1.192 | N20: =O20-(K20+L20+M20) -> 1.173 | O20: 4.936 | P20: 0.997 | Q20: =2.069-P20 -> 1.072 | R20: 1.009 | S20: =T20-(P20+Q20+R20) -> 2.077 | T20: 5.155 | U20: 0.996 | V20: 1.057 | W20: 1.013 | X20: =Y20-(U20+V20+W20) -> 2.077 | Y20: 5.143 | Z20: 0.748 | AA20: 1.2 | AB20: 1.123 | AC20: =AD20-(Z20+AA20+AB20) -> 1.124 | AD20: 4.195 | AE20: 1.212 | AF20: 1.303 | AG20: 1.164 | AH20: =AI20-(AE20+AF20+AG20) -> 1.6 | AI20: 5.279 | AJ20: 1.303 | AK20: 1.23 | AL20: 1.272 | AM20: =AN20-(AJ20+AK20+AL20) -> 0.968 | AN20: 4.773 | AO20: 1.27 | AP20: 1.249 | AQ20: 1.305 | AR20: =AS20-(AO20+AP20+AQ20) -> 1.056 | AS20: 4.88 | AT20: 0.834 | AU20: 0.583 | AV20: 1.318 | AW20: =AX20-(AT20+AU20+AV20) -> 1.424 | AX20: 4.159 | AY20: 1.145 | AZ20: 1.11 | BA20: 1.064 | BB20: =BC20-(AY20+AZ20+BA20) -> 1.208 | BC20: 4.527 | BD20: 1.152 | BE20: 1.022 | BF20: 1.152 | BG20: =BH20-(BD20+BE20+BF20) -> 1.188 | BH20: 4.514 | BI20: 1.093 | BJ20: 4.691 | BK20: 1.07 | BL20: 1.11 | BM20: 1.101 | BN20: =BO20-BK20-BL20-BM20 -> 1.139 | BO20: 4.42 | BP20: 1.131 | BQ20: 1.108 | BR20: 1.085 | BS20: =BT20-BP20-BQ20-BR20 -> 1.178 | BT20: 4.502 | BU20: 1.062 | BV20: 0.957 | BW20: 4.9
A21: מכירות ללקוחות חיצוניים (מ' טון) | B21: 5.198 | C21: 5.137 | D21: 4.721 | E21: 3.912 | F21: 1.173 | G21: 1.239 | H21: 1.349 | I21: =J21-(F21+G21+H21) -> 1.43 | J21: 5.191 | K21: 1.39 | L21: 1.413 | M21: 1.179 | N21: =O21-(K21+L21+M21) -> 0.354 | O21: 4.336 | P21: 0.299 | Q21: =0.646-P21 -> 0.347 | R21: 0.939 | S21: =T21-(P21+Q21+R21) -> 3.127 | T21: 4.712 | U21: 1.273 | V21: 1.455 | W21: 1.212 | X21: =Y21-(U21+V21+W21) -> 1.094 | Y21: 5.034 | Z21: 0.987 | AA21: 1.274 | AB21: 1.316 | AC21: =AD21-(Z21+AA21+AB21) -> 0.682 | AD21: 4.259 | AE21: 0.85 | AF21: 1.443 | AG21: 1.315 | AH21: =AI21-(AE21+AF21+AG21) -> 1.21 | AI21: 4.818 | AJ21: 1.251 | AK21: 1.298 | AL21: 0.918 | AM21: =AN21-(AJ21+AK21+AL21) -> 1.271 | AN21: =4.738 -> 4.738 | AO21: 1.401 | AP21: 1.249 | AQ21: 1.234 | AR21: =AS21-(AO21+AP21+AQ21) -> 0.726 | AS21: =4.61 -> 4.61 | AT21: 1.067 | AU21: 0.65 | AV21: 1.126 | AW21: =AX21-(AT21+AU21+AV21) -> 0.937 | AX21: 3.78 | AY21: =0.996-AY22 -> 0.8596051 | AZ21: =1.226-AZ22 -> 1.0853706 | BA21: =1.111-BA22 -> 0.97256869 | BB21: =BC21-(AY21+AZ21+BA21) -> 1.1834051 | BC21: =4.666-BC22 -> 4.1009495 | BD21: =1.075-BD22 -> 0.9661039 | BE21: =1.148-BE22 -> 1.0309709 | BF21: =1.064-BF22 -> 0.95662385 | BG21: =BH21-(BD21+BE21+BF21) -> 1.1060176 | BH21: =4.434-BH22 -> 4.0597162 | BI21: =1.15-BI22 -> 1.0530818 | BJ21: =4.499-BJ22 -> 4.125 | BK21: =0.963-BK22 -> 0.8695 | BL21: =1.261-BL22 -> 1.164 | BM21: =1.28-BM22 -> 1.182 | BN21: =BO21-BK21-BL21-BM21 -> 1.0935 | BO21: =4.683-BO22 -> 4.309 | BP21: =1.084-BP22 -> 0.989 | BQ21: =1.153-BQ22 -> 1.06 | BR21: =1.06-BR22 -> 0.98 | BS21: =BT21-BP21-BQ21-BR21 -> 1.16 | BT21: =4.556-BT22 -> 4.189 | BU21: =1.103-BU22 -> 1.005 | BV21: =0.971-BV22 -> 0.876 | BW21: 4.55
A22: מכירות פנימיות (מ' טון) | B22: 0.245 | C22: 0.28 | D22: 0.252 | E22: 0.236 | F22: 0.05 | G22: 0.072 | H22: 0.077 | I22: =J22-(F22+G22+H22) -> 0.065 | J22: 0.264 | K22: 0.068 | L22: 0.088 | M22: 0.07 | N22: =O22-(K22+L22+M22) -> 0.067 | O22: 0.293 | P22: 0.031 | Q22: =0.053-P22 -> 0.022 | R22: 0.04 | S22: =T22-(P22+Q22+R22) -> 0.23 | T22: 0.323 | U22: 0.056 | V22: 0.072 | W22: 0.074 | X22: =Y22-(U22+V22+W22) -> 0.119 | Y22: 0.321 | Z22: 0.059 | AA22: 0.078 | AB22: 0.079 | AC22: =AD22-(Z22+AA22+AB22) -> 0.082 | AD22: 0.298 | AE22: 0.069 | AF22: 0.069 | AG22: 0.075 | AH22: =AI22-(AE22+AF22+AG22) -> 0.134 | AI22: 0.347 | AJ22: 0.058 | AK22: 0.083 | AL22: 0.097 | AM22: =AN22-(AJ22+AK22+AL22) -> 0.063 | AN22: =0.301 -> 0.301 | AO22: 0.066 | AP22: 0.102 | AQ22: 0.084 | AR22: =AS22-(AO22+AP22+AQ22) -> 0.033 | AS22: =0.285 -> 0.285 | AT22: 0.074 | AU22: 0.069 | AV22: 0.076 | AW22: =AX22-(AT22+AU22+AV22) -> 0.131 | AX22: 0.35 | AY22: =0.996*(AY34-AY33)/AY34 -> 0.1363949 | AZ22: =1.226*(AZ34-AZ33)/AZ34 -> 0.14062941 | BA22: =1.111*(BA34-BA33)/BA34 -> 0.13843131 | BB22: =BC22-(AY22+AZ22+BA22) -> 0.14959489 | BC22: =4.666*(BC34-BC33)/BC34 -> 0.56505052 | BD22: =1.075*(BD34-BD33)/BD34 -> 0.1088961 | BE22: =1.148*(BE34-BE33)/BE34 -> 0.11702913 | BF22: =1.064*(BF34-BF33)/BF34 -> 0.10737615 | BG22: =BH22-(BD22+BE22+BF22) -> 0.040982414 | BH22: =4.434*(BH34-BH33)/BH34 -> 0.37428379 | BI22: =1.15*(BI34-BI33)/BI34 -> 0.096918239 | BJ22: 0.374 | BK22: =BJ22*0.25 -> 0.0935 | BL22: 0.097 | BM22: 0.098 | BN22: =BO22-BK22-BL22-BM22 -> 0.0855 | BO22: 0.374 | BP22: 0.095 | BQ22: 0.093 | BR22: 0.08 | BS22: 0.099 | BT22: =BP22+BQ22+BR22+BS22 -> 0.367 | BU22: 0.098 | BV22: 0.095 | BW22: 0.365
A23: ייצור למלאי (מכירות מהמלאי) | B23: =B20-B21-B22 -> -0.304 | C23: =C20-C21-C22 -> -0.03 | D23: =D20-D21-D22 -> 0.29 | E23: =E20-E21-E22 -> 0.938 | F23: =F20-F21-F22 -> 0.003 | G23: =G20-G21-G22 -> -0.144 | H23: =H20-H21-H22 -> -0.162 | I23: =I20-I21-I22 -> -0.074 | ... W23: =W20-W21-W22 -> -0.273 | X23: =X24-W24 -> 0.864 | Y23: =Y20-Y21-Y22 -> -0.212 | Z23: =Z20-Z21-Z22 -> -0.298 | AA23: =AA20-AA21-AA22 -> -0.152 | AB23: =AB20-AB21-AB22 -> -0.272 | AC23: =AC20-AC21-AC22 -> 0.36 | AD23: =AD20-AD21-AD22 -> -0.362 | AE23: =AE20-AE21-AE22 -> 0.293 | AF23: =AF20-AF21-AF22 -> -0.209 | AG23: =AG20-AG21-AG22 -> -0.226 | AH23: =AI23-(AE23+AF23+AG23) -> 0.256 | AI23: =AI20-AI21-AI22 -> 0.114 | AJ23: =AJ20-AJ21-AJ22 -> -0.006 | AK23: =AK20-AK21-AK22 -> -0.151 | AL23: =AL20-AL21-AL22 -> 0.257 | AM23: =AM20-AM21-AM22 -> -0.366 | AN23: =AN20-AN21-AN22 -> -0.266 | AO23: =AO20-AO21-AO22 -> -0.197 | AP23: =AP20-AP21-AP22 -> -0.102 | ... BM23: =BM20-BM21-BM22 -> -0.179 | BN23: =BO23-BK23-BL23-BM23 -> -0.04 | BO23: =BO20-BO21-BO22 -> -0.263 | BP23: =BP20-BP21-BP22 -> 0.047 | BQ23: =BQ20-BQ21-BQ22 -> -0.045 | BR23: =BR20-BR21-BR22 -> 0.025 | BS23: =BS20-BS21-BS22 -> -0.081 | BT23: =BT20-BT21-BT22 -> -0.054 | BU23: =BU20-BU21-BU22 -> -0.041 | BV23: =BV20-BV21-BV22 -> -0.014 | BW23: =BW20-BW21-BW22 -> -0.015
A24: מלאי סגירה | B24: 0.464 | C24: 0.434 | D24: 0.724 | E24: 1.662 | F24: =E24+F23 -> 1.665 | G24: =F24+G23 -> 1.521 | H24: =G24+H23 -> 1.359 | I24: =H24+I23 -> 1.285 | J24: 1.285 | K24: =J24+K23 -> 1.115 | L24: =K24+L23 -> 0.897 | M24: =L24+M23 -> 0.84 | N24: =M24+N23 -> 1.592 | O24: 1.006 | P24: =O24+P23 -> 1.673 | Q24: =P24+Q23 -> 2.376 | R24: =Q24+R23 -> 2.406 | S24: =R24+S23 -> 1.126 | T24: =O24+T23 -> 1.126 | U24: =T24+U23 -> 0.793 | V24: =U24+V23 -> 0.323 | W24: =V24+W23 -> 0.05 | X24: =Y24 -> 0.914 | Y24: =T24+Y23 -> 0.914 | Z24: =Y24+Z23 -> 0.616 | AA24: =Z24+AA23 -> 0.464 | AB24: =AA24+AB23 -> 0.192 | AC24: =AB24+AC23 -> 0.552 | AD24: =Y24+AD23 -> 0.552 | AE24: =AD24+AE23 -> 0.845 | AF24: =AE24+AF23 -> 0.636 | AG24: =AF24+AG23 -> 0.41 | AH24: =AG24+AH23 -> 0.666 | AI24: =AD24+AI23 -> 0.666 | AJ24: =AI24+AJ23 -> 0.66 | AK24: =AJ24+AK23 -> 0.509 | AL24: =AK24+AL23 -> 0.766 | AM24: =AL24+AM23 -> 0.4 | AN24: =AI24+AN23 -> 0.4 | AO24: =AN24+AO23 -> 0.203 | AP24: =AO24+AP23 -> 0.101 | AQ24: =AP24+AQ23 -> 0.088 | AR24: =AQ24+AR23 -> 0.385 | AS24: =AN24+AS23 -> 0.385 | AT24: =AS24+AT23 -> 0.078 | AU24: =AT24+AU23 -> -0.058 | AV24: =AU24+AV23 -> 0.058 | AW24: =AV24+AW23 -> 0.414 | AX24: =AS24+AX23 -> 0.414 | AY24: 0.563 | AZ24: 0.448 | BA24: 0.401 | BB24: =BC24 -> 0.275 | BC24: =AX24+BC23 -> 0.275 | BD24: 0.353 | BE24: 0.226 | BF24: 0.314 | BG24: =BH24 -> 0.355 | BH24: =BC24+BH23 -> 0.355 | BI24: 0.298 | BJ24: 0.547 | BK24: =BJ24+BK23 -> 0.654 | BL24: =BK24+BL23 -> 0.503 | BM24: =BL24+BM23 -> 0.324 | BN24: =BM24+BN23 -> 0.284 | BO24: 0.284 | BP24: =BK24+BP23 -> 0.701 | BQ24: =BL24+BQ23 -> 0.458 | BR24: =BM24+BR23 -> 0.349 | BS24: =BN24+BS23 -> 0.203 | BT24: 0.229 | BU24: =BT24+BU23 -> 0.188 | BV24: =BU24+BV23 -> 0.174 | BW24: 0.3
A25: הנחות מחיר:
A26: מערב אירופה | J26: 225 | O26: 550 | T26: 550 | Y26: 370.4 | AD26: 477 | AI26: 422 | AN26: 395 | AS26: 395 | AX26: 395 | BC26: 395 | BH26: 395 | BJ26: 395 | BO26: 395 | BT26: 395
A27: מזרח אסיה/ שאר העולם | J27: 270 | O27: 580 | T27: 550 | Y27: 370.4 | AD27: 497 | AI27: 430 | AN27: 360 | AS27: 360 | AX27: 360 | BC27: 360 | BH27: 360 | BJ27: 360 | BO27: 360 | BT27: 360
A28: דרום אמריקה | J28: 260 | O28: 580 | T28: 500 | Y28: 370.4 | AD28: 490 | AI28: 460 | AN28: 385 | AS28: 385 | AX28: 385 | BC28: 385 | BH28: 385 | BJ28: 385 | BO28: 385 | BT28: 385
A29: הודו | J29: 240 | O29: 500 | T29: 460 | Y29: 385 | AD29: =350*3/8+490*5/8 -> 437.5 | AI29: 490 | AN29: 386 | AS29: 386 | AX29: 386 | BC29: 386 | BH29: 386 | BJ29: 386 | BO29: 386 | BT29: 386
A30: סין | J30: 175 | O30: 476 | T30: 500 | Y30: 350 | AD30: =400*0.5+470*0.5 -> 435 | AI30: 470 | AN30: 389 | AS30: 389 | AX30: 389 | BC30: 389 | BH30: 389 | BJ30: 389 | BO30: 389 | BT30: 389
A31: מחיר ממוצע | B31: =#REF!/(B16+B22) -> #REF! | C31: =#REF!/(C16+C22) -> #REF! | D31: =#REF!/(D16+D22) -> #REF! | E31: =#REF!/(E16+E22) -> #REF! | F31: =#REF!/(F16+F22) -> #REF! | G31: =#REF!/(G16+G22) -> #REF! | H31: =#REF!/(H16+H22) -> #REF! | I31: =#REF!/(I16+I22) -> #REF! | ... S31: =#REF!/(S16+S22) -> #REF! | T31: =T37 -> 381.36672 | U31: =#REF!/(U16+U22) -> #REF! | V31: =#REF!/(V16+V22) -> #REF! | W31: =#REF!/(W16+W22) -> #REF! | X31: =#REF!/(X16+X22) -> #REF! | Y31: =Y37 -> 321.81168 | Z31: =#REF!/(Z16+Z22) -> #REF! | AA31: =#REF!/(AA16+AA22) -> #REF! | AB31: =#REF!/(AB16+AB22) -> #REF! | AC31: =#REF!/(AC16+AC22) -> #REF! | AD31: =AD37 -> 303.3576 | AE31: =#REF!/(AE16+AE22) -> #REF! | AF31: =#REF!/(AF16+AF22) -> #REF! | AG31: =#REF!/(AG16+AG22) -> #REF! | AH31: =#REF!/(AH16+AH22) -> #REF! | AI31: 259.05 | AJ31: =#REF!/(AJ16+AJ22) -> #REF! | AK31: =#REF!/(AK16+AK22) -> #REF! | AL31: =#REF!/(AL16+AL22) -> #REF! | AM31: =#REF!/(AM16+AM22) -> #REF! | AN31: 236.2 | AO31: =#REF!/(AO16+AO22) -> #REF! | AP31: =#REF!/(AP16+AP22) -> #REF! | AQ31: =#REF!/(AQ16+AQ22) -> #REF! | AR31: =#REF!/(AR16+AR22) -> #REF! | AS31: =277.6 -> 277.6 | AT31: =#REF!/(AT16+AT22) -> #REF! | AU31: =#REF!/(AU16+AU22) -> #REF! | AV31: =#REF!/(AV16+AV22) -> #REF! | AW31: =#REF!/(AW16+AW22) -> #REF! | AX31: 286 | AY31: =AY37 -> 250 | AZ31: =AZ37 -> 226 | BA31: =BA37 -> 220 | BB31: =BC31 -> 230 | BC31: =BC37 -> 230 | BD31: =BD37 -> 257 | BE31: =BE37 -> 281 | BF31: =BF37 -> 317 | BG31: =BG37 -> 337 | BH31: =BH37 -> 337 | BI31: =BI37 -> 601 | BJ31: 682 | BK31: =BK37 -> 541 | BL31: =BL37 -> 403 | BM31: =BM37 -> 342 | BN31: =BN37 -> 343 | BO31: 393 | BP31: =BP37 -> 324 | BQ31: =BQ37 -> 300 | BR31: =BR37 -> 297 | BS31: =BS37 -> 285 | BT31: 302 | BU31: =BU37 -> 300 | BV31: =BV37 -> 333 | BW31: 320
A32: בדיקה | B32: =B31 -> #REF! | C32: =C31 -> #REF! | D32: =D31 -> #REF! | E32: =E31 -> #REF! | F32: =F31 -> #REF! | G32: =G31 -> #REF! | H32: =H31 -> #REF! | I32: =I31 -> #REF! | ... AM32: =AM31 -> #REF! | AN32: =(AN6*AN26+AN8*AN27+AN10*AN28+AN12*AN29+AN14*AN30)/AN16 -> 378.66823 | AO32: =AO31 -> #REF! | AP32: =AP31 -> #REF! | AQ32: =AQ31 -> #REF! | AR32: =AR31 -> #REF! | AS32: =AS31 -> 277.6 | AT32: =AT31 -> #REF! | AU32: =AU31 -> #REF! | AV32: =AV31 -> #REF! | ... BA32: =BA31 -> 220 | BC32: =BC31 -> 230 | BD32: =BD31 -> 257 | BE32: =BE31 -> 281 | BF32: =BF31 -> 317 | BH32: =BH31 -> 337 | BI32: =BI31 -> 601 | BJ32: =BJ31 -> 682 | BK32: =BK31 -> 541 | BL32: =BL31 -> 403 | BM32: =BM31 -> 342 | BO32: =BO31 -> 393 | BP32: =BP31 -> 324 | BQ32: =BQ31 -> 300 | BR32: =BR31 -> 297 | BS32: =BS31 -> 285 | BT32: =BT31 -> 302 | BU32: =BU31 -> 300 | BV32: =BV31 -> 333 | BW32: =BW31 -> 320
A33: סך מכירות חיצוניים | B33: =#REF! -> #REF! | C33: =#REF! -> #REF! | D33: =#REF! -> #REF! | E33: =#REF! -> #REF! | F33: 246.168 | G33: 265.71 | H33: =317.726 -> 317.726 | I33: =J33-(F33+G33+H33) -> #REF! | J33: =#REF! -> #REF! | K33: 523.129 | L33: 770.92 | M33: 835.08 | N33: =O33-(K33+L33+M33) -> -164.388 | O33: =1964.741 -> 1964.741 | P33: =#REF! -> #REF! | Q33: =#REF! -> #REF! | R33: =#REF! -> #REF! | S33: =#REF! -> #REF! | T33: 1797 | U33: =#REF! -> #REF! | V33: =#REF! -> #REF! | W33: =#REF! -> #REF! | X33: =#REF! -> #REF! | Y33: 1620 | Z33: =#REF! -> #REF! | AA33: =#REF! -> #REF! | AB33: =#REF! -> #REF! | AC33: =#REF! -> #REF! | AD33: 1292 | AE33: =#REF! -> #REF! | AF33: =#REF! -> #REF! | AG33: =#REF! -> #REF! | AH33: =#REF! -> #REF! | AI33: ='Reported Rev.. Split'!K6 -> 1213 | AJ33: =#REF! -> #REF! | AK33: =#REF! -> #REF! | AL33: =#REF! -> #REF! | AM33: =AN33-(AJ33+AK33+AL33) -> #REF! | AN33: ='Reported Rev.. Split'!J6 -> 1258 | AO33: =#REF! -> #REF! | AP33: =#REF! -> #REF! | AQ33: =#REF! -> #REF! | AR33: =AS33-(AO33+AP33+AQ33) -> #REF! | AS33: ='Reported Rev.. Split'!I6 -> 1481 | AT33: =#REF! -> #REF! | AU33: =#REF! -> #REF! | AV33: =#REF! -> #REF! | AW33: =AX33-(AT33+AU33+AV33) -> #REF! | AX33: ='Reported Rev.. Split'!H6 -> 1330 | AY33: ='Reported Rev.. Split'!AE6 -> 271 | AZ33: ='Reported Rev.. Split'!AD6 -> 301 | BA33: ='Reported Rev.. Split'!AC6 -> 274 | BB33: =BC33-(AY33+AZ33+BA33) -> 337 | BC33: ='Reported Rev.. Split'!G6 -> 1183 | BD33: ='Reported Rev.. Split'!AA6 -> 346 | BE33: ='Reported Rev.. Split'!Z6 -> 370 | BF33: ='Reported Rev.. Split'!Y6 -> 392 | BG33: =BH33-(BD33+BE33+BF33) -> 660 | BH33: ='Reported Rev.. Split'!F6 -> 1768 | BI33: ='Reported Rev.. Split'!W6 -> 728 | BJ33: ='Reported Rev.. Split'!E6 -> 3031 | BK33: ='Reported Rev.. Split'!V6 -> 530 | BL33: ='Reported Rev.. Split'!U6 -> 505 | BM33: ='Reported Rev.. Split'!T6 -> 477 | BN33: ='Reported Rev.. Split'!S6 -> 461 | BO33: ='Reported Rev.. Split'!D6 -> 1973 | BP33: ='Reported Rev.. Split'!R6 -> 367 | BQ33: ='Reported Rev.. Split'!Q6 -> 381 | BR33: ='Reported Rev.. Split'!P6 -> 341 | BS33: ='Reported Rev.. Split'!O6 -> 373 | BT33: =BP33+BQ33+BR33+BS33 -> 1462 | BU33: ='Reported Rev.. Split'!N6 -> 358 | BV33: ='Reported Rev.. Split'!M6 -> 347 | BW33: =BW31*BW16 -> 1472
A34: סך מכירות פנימי+חיצוני | B34: =B33+85.837 -> #REF! | C34: =C33+103.063 -> #REF! | D34: =D33+136.273 -> #REF! | E34: =E33+133.722 -> #REF! | F34: =F33+29.68 -> 275.848 | G34: =G33+38.102 -> 303.812 | H34: =H33+40.02 -> 357.746 | I34: =J34-(F34+G34+H34) -> #REF! | J34: =J33+158.183 -> #REF! | K34: =K33+58.309 -> 581.438 | L34: =L33+83.313 -> 854.233 | M34: =M33+102.555 -> 937.635 | N34: =O34-(K34+L34+M34) -> -174.978 | O34: =2198.328 -> 2198.328 | P34: =P33+40.747 -> #REF! | Q34: 240.5 | R34: =477.6 -> 477.6 | S34: =T34-(P34+Q34+R34) -> #REF! | T34: 2027 | U34: 538.8 | V34: 563.7 | W34: =W33+47.709 -> #REF! | X34: =X33+47.709 -> #REF! | Y34: 1816 | Z34: =Z33+46.019 -> #REF! | AA34: =AA33+61.6 -> #REF! | AB34: =AB33+62.827 -> #REF! | AC34: =AC33+62.827 -> #REF! | AD34: 1450 | AE34: =AE33+46.019 -> #REF! | AF34: =AF33+69 -> #REF! | AG34: =AG33+62.827 -> #REF! | AH34: =AI34-(AE34+AF34+AG34) -> #REF! | AI34: =AI33+135 -> 1348 | AJ34: =AJ33+54.439 -> #REF! | AK34: =AK33+67 -> #REF! | AL34: =AL33+59 -> #REF! | AM34: =AN34-(AJ34+AK34+AL34) -> #REF! | AN34: =AN33+125 -> 1383 | AO34: =AO33+45.647 -> #REF! | AP34: =AP33+57.359 -> #REF! | AQ34: 450.028 | AR34: =AS34-(AO34+AP34+AQ34) -> #REF! | AS34: =AS33+142 -> 1623 | AT34: =AT33+34.819 -> #REF! | AU34: =AU33+37 -> #REF! | AV34: =AV33+43 -> #REF! | AW34: =AX34-(AT34+AU34+AV34) -> #REF! | AX34: =AX33+164 -> 1494 | AY34: =AY33+43 -> 314 | AZ34: =AZ33+39 -> 340 | BA34: =BA33+39 -> 313 | BB34: =BC34-(AY34+AZ34+BA34) -> 379 | BC34: =1346 -> 1346 | BD34: 385 | BE34: =412 -> 412 | BF34: =436 -> 436 | BG34: =BH34-(BD34+BE34+BF34) -> 698 | BH34: 1931 | BI34: 795 | BJ34: =BJ33+282 -> 3313 | BK34: =BK33+53 -> 583 | BL34: 546 | BM34: 526 | BN34: =BO34-BK34-BL34-BM34 -> 447 | BO34: =BO33+129 -> 2102 | BP34: =BP33+31 -> 398 | BQ34: =BQ33+41 -> 422 | BR34: =BR33+48 -> 389 | BS34: =BS33+49 -> 422 | BT34: =BP34+BQ34+BR34+BS34 -> 1631 | BU34: =BU33+47 -> 405 | BV34: =BV33+36 -> 383
A35: הנחות עלות:
A36: מכירות לחיצונים (מ' $) | B36: =#REF! -> #REF! | C36: =#REF! -> #REF! | D36: =#REF! -> #REF! | E36: =#REF! -> #REF! | F36: =F33 -> 246.168 | G36: =G33 -> 265.71 | H36: =H33 -> 317.726 | I36: =I33 -> #REF! | J36: =#REF! -> #REF! | K36: =K33 -> 523.129 | L36: =L33 -> 770.92 | M36: =M33 -> 835.08 | N36: =N33 -> -164.388 | O36: =O33 -> 1964.741 | P36: =#REF! -> #REF! | Q36: =#REF! -> #REF! | R36: =#REF! -> #REF! | S36: =#REF! -> #REF! | T36: =T33 -> 1797 | U36: =#REF! -> #REF! | V36: =#REF! -> #REF! | W36: =#REF! -> #REF! | X36: =#REF! -> #REF! | Y36: =Y33 -> 1620 | Z36: =#REF! -> #REF! | AA36: =#REF! -> #REF! | AB36: =#REF! -> #REF! | AC36: =#REF! -> #REF! | AD36: =AD33 -> 1292 | AE36: =#REF! -> #REF! | AF36: =#REF! -> #REF! | AG36: =#REF! -> #REF! | AH36: =AI36-(AE36+AF36+AG36) -> #REF! | AI36: =AI33 -> 1213 | AJ36: =#REF! -> #REF! | AK36: =#REF! -> #REF! | AL36: =#REF! -> #REF! | AM36: =AN36-(AJ36+AK36+AL36) -> #REF! | AN36: =AN33 -> 1258 | AO36: =#REF! -> #REF! | AP36: =#REF! -> #REF! | AQ36: =#REF! -> #REF! | AR36: =AS36-(AO36+AP36+AQ36) -> #REF! | AS36: =AS33 -> 1481 | AT36: =#REF! -> #REF! | AU36: =#REF! -> #REF! | AV36: =#REF! -> #REF! | AW36: =AX36-(AT36+AU36+AV36) -> #REF! | AX36: =AX33 -> 1330 | AY36: =AY33 -> 271 | AZ36: =AZ33 -> 301 | BA36: =BA33 -> 274 | BB36: =BC36-(AY36+AZ36+BA36) -> 337 | BC36: =BC33 -> 1183 | BD36: =BD33 -> 346 | BE36: =BE33 -> 370 | BF36: =BF33 -> 392 | BG36: =BH36-(BD36+BE36+BF36) -> 660 | BH36: =BH33 -> 1768 | BI36: =BI33 -> 728 | BJ36: =BJ33 -> 3031 | BK36: =BK33 -> 530 | BL36: =BL33 -> 505 | BM36: =BM33 -> 477 | BN36: =BN33 -> 461 | BO36: =BO33 -> 1973 | ... BW36: =BW33 -> 1472
A37: מחיר לטון לחיצוניים | B37: =B36/B16 -> #REF! | C37: =C36/C16 -> #REF! | D37: =D36/D16 -> #REF! | E37: =E36/E16 -> #REF! | F37: =F36/F16 -> 209.86189 | G37: =G36/G16 -> 214.45521 | H37: =H36/H16 -> 235.52706 | I37: =I36/I16 -> #REF! | ... AH37: =AH36/AH16 -> #REF! | AI37: =AI31 -> 259.05 | AJ37: =AJ36/AJ16 -> #REF! | AK37: =AK36/AK16 -> #REF! | AL37: =AL36/AL16 -> #REF! | AM37: =AM36/AM16 -> #REF! | AN37: =AN31 -> 236.2 | AO37: =AO36/AO16 -> #REF! | AP37: =AP36/AP16 -> #REF! | AQ37: =AQ36/AQ16 -> #REF! | AR37: =AR36/AR16 -> #REF! | AS37: 277.6 | AT37: =AT36/AT16 -> #REF! | AU37: =AU36/AU16 -> #REF! | AV37: =AV36/AV16 -> #REF! | AW37: =AW36/AW16 -> #REF! | AX37: 286 | AY37: 250 | AZ37: 226 | BA37: 220 | BB37: =BC37 -> 230 | BC37: 230 | BD37: 257 | BE37: 281 | BF37: 317 | BG37: =BH37 -> 337 | BH37: 337 | BI37: 601 | BJ37: =BJ31 -> 682 | BK37: 541 | BL37: 403 | BM37: 342 | BN37: 343 | BO37: =BO31 -> 393 | BP37: 324 | BQ37: 300 | BR37: =BM37-45 -> 297 | BS37: 285 | BT37: =BT31 -> 302 | BU37: 300 | BV37: 333 | BW37: 320 | BY37: ='DCF 1.6.2025'!BA7 -> 333 | BZ37: 355 | CA37: =AX65 -> 339.96377 | CB37: =BW37 -> 320
A38: עלות מכר+ עלות תפעולית | B38: =B36-B40 -> #REF! | C38: =C36-C40 -> #REF! | D38: =D36-D40 -> #REF! | E38: =E36-E40 -> #REF! | F38: =F36-F40 -> 183.952 | G38: =G36-G40 -> 184.351 | H38: =H36-H40 -> 201.884 | I38: =I36-I40 -> #REF! | ... AG38: =AG36-AG40 -> #REF! | AH38: =AI38-(AE38+AF38+AG38) -> #REF! | AI38: =AI36-AI40 -> 968 | AJ38: =AJ36-AJ40 -> #REF! | AK38: =AK36-AK40 -> #REF! | AL38: =AL36-AL40 -> #REF! | AM38: =AN38-(AJ38+AK38+AL38) -> #REF! | AN38: =AN36-AN40 -> 1060 | AO38: =AO36-AO40 -> #REF! | AP38: =AP36-AP40 -> #REF! | AQ38: =AQ36-AQ40 -> #REF! | AR38: =AS38-(AO38+AP38+AQ38) -> #REF! | AS38: =AS36-AS40 -> 1166 | AT38: =AT36-AT40 -> #REF! | AU38: =AU36-AU40 -> #REF! | AV38: =AV36-AV40 -> #REF! | AW38: =AX38-(AT38+AU38+AV38) -> #REF! | AX38: =AX36-AX40 -> 1041 | AY38: =AY36-AY40 -> 257 | AZ38: =AZ36-AZ40 -> 263 | BA38: =BA36-BA40 -> 246 | BB38: =BB36-BB40 -> 297 | BC38: =BC36-BC40 -> 1063 | BD38: =BD36-BD40 -> 317 | BE38: =BE36-BE40 -> 327 | ... BM38: =BM36-BM40 -> 352 | BN38: =BO38-BK38-BL38-BM38 -> 339 | BO38: =BO36-BO40 -> 1305 | BP38: =BP36-BP40 -> 305 | BQ38: =BQ36-BQ40 -> 321 | BR38: =BR36-BR40 -> 282 | BS38: =BS36-BS40 -> 304 | BT38: =BT36-BT40 -> 1212 | BU38: =BU36-BU40 -> 302 | BV38: =BV36-BV40 -> 295 | BW38: =BW36-BW40 -> 1127
A39: עלות מכר+עלות תפעולית לטון | B39: =B38/B16 -> #REF! | C39: =C38/C16 -> #REF! | D39: =D38/D16 -> #REF! | E39: =E38/E16 -> #REF! | F39: =F38/F16 -> 156.82182 | G39: =G38/G16 -> 148.79015 | H39: =H38/H16 -> 149.65456 | I39: =I38/I16 -> #REF! | ... N39: =N38/N16 -> 576.12994 | O39: =O37-O41 -> 223.30489 | P39: =P38/P16 -> #REF! | Q39: =Q38/Q16 -> #REF! | R39: =R38/R16 -> #REF! | S39: =S38/S16 -> #REF! | T39: =T37-T41 -> 224.32088 | U39: =U38/U16 -> #REF! | V39: =V38/V16 -> #REF! | W39: =W38/W16 -> #REF! | X39: =X38/X16 -> #REF! | Y39: =Y37-Y41 -> 215.33572 | Z39: =Z38/Z16 -> #REF! | AA39: =AA38/AA16 -> #REF! | AB39: =AB38/AB16 -> #REF! | AC39: =AC38/AC16 -> #REF! | AD39: =AD37-AD41 -> 215.30876 | AE39: =AE38/AE16 -> #REF! | AF39: =AF38/AF16 -> #REF! | AG39: =AG38/AG16 -> #REF! | AH39: =AH38/AH16 -> #REF! | AI39: =AI37-AI41 -> 208.19902 | AJ39: =AJ38/AJ16 -> #REF! | AK39: =AK38/AK16 -> #REF! | AL39: =AL38/AL16 -> #REF! | AM39: =AM38/AM16 -> #REF! | AN39: =AN37-AN41 -> 194.41022 | AO39: =AO38/AO16 -> #REF! | AP39: =AP38/AP16 -> #REF! | AQ39: =AQ38/AQ16 -> #REF! | AR39: =AR38/AR16 -> #REF! | AS39: =AS37-AS41 -> 209.27028 | AT39: =AT38/AT16 -> #REF! | AU39: =AU38/AU16 -> #REF! | AV39: =AV38/AV16 -> #REF! | AW39: =AW38/AW21 -> #REF! | AX39: =AX37-AX41 -> 209.54497 | AY39: =AY37-AY41 -> 233.71345 | AZ39: =AZ37-AZ41 -> 190.98892 | BA39: =BA37-BA41 -> 191.21026 | BB39: =BB37-BB41 -> 196.19923 | BC39: =BC37-BC41 -> 200.73848 | BD39: =BD37-BD41 -> 226.98252 | BE39: =BE37-BE41 -> 239.29174 | ... BV39: =BV37-BV41 -> 273.63927 | BW39: 245 | BY39: 240 | BZ39: 255 | CA39: 245 | CB39: 245
A40: רווח תפעולי מתואם | B40: =#REF! -> #REF! | C40: =#REF! -> #REF! | D40: =#REF! -> #REF! | E40: =#REF! -> #REF! | F40: 62.216 | G40: 81.359 | H40: 115.842 | I40: =J40-(F40+G40+H40) -> #REF! | J40: =#REF! -> #REF! | K40: 280.532 | L40: 487.462 | M40: 596.835 | N40: =O40-(K40+L40+M40) -> -368.338 | O40: 996.491 | P40: =#REF! -> #REF! | Q40: =#REF! -> #REF! | R40: =#REF! -> #REF! | S40: =#REF! -> #REF! | T40: 740 | U40: =#REF! -> #REF! | V40: =#REF! -> #REF! | W40: =#REF! -> #REF! | X40: =#REF! -> #REF! | Y40: 536 | Z40: =#REF! -> #REF! | AA40: =#REF! -> #REF! | AB40: =#REF! -> #REF! | AC40: =#REF! -> #REF! | AD40: 375 | AE40: =#REF! -> #REF! | AF40: =#REF! -> #REF! | AG40: =#REF! -> #REF! | AH40: =AI40-(AE40+AF40+AG40) -> #REF! | AI40: ='Reported Rev.. Split'!K33 -> 245 | AJ40: =#REF! -> #REF! | AK40: =#REF! -> #REF! | AL40: =#REF! -> #REF! | AM40: =AN40-(AJ40+AK40+AL40) -> #REF! | AN40: ='Reported Rev.. Split'!J33 -> 198 | AO40: =#REF! -> #REF! | AP40: 139 | AQ40: =#REF! -> #REF! | AR40: =AS40-(AO40+AP40+AQ40) -> #REF! | AS40: ='Reported Rev.. Split'!I33 -> 315 | AT40: 177 | AU40: 104 | AV40: 135 | AW40: =AX40-(AT40+AU40+AV40) -> -127 | AX40: ='Reported Rev.. Split'!H33 -> 289 | AY40: ='Reported Rev.. Split'!AE33 -> 14 | AZ40: ='Reported Rev.. Split'!AD33 -> 38 | BA40: ='Reported Rev.. Split'!AC33 -> 28 | BB40: ='Reported Rev.. Split'!AB33 -> 40 | BC40: ='Reported Rev.. Split'!G33 -> 120 | BD40: ='Reported Rev.. Split'!AA33 -> 29 | BE40: ='Reported Rev.. Split'!Z33 -> 43 | BF40: ='Reported Rev.. Split'!Y33 -> 83 | BG40: ='Reported Rev.. Split'!X33 -> 244 | BH40: ='Reported Rev.. Split'!F33 -> 399 | BI40: ='Reported Rev.. Split'!W33 -> 410 | BJ40: ='Reported Rev.. Split'!E33 -> 1822 | BK40: ='Reported Rev.. Split'!V33 -> 254 | BL40: ='Reported Rev.. Split'!U33 -> 167 | BM40: ='Reported Rev.. Split'!T33 -> 125 | BN40: ='Reported Rev.. Split'!S33 -> 122 | BO40: ='Reported Rev.. Split'!D33 -> 668 | BP40: ='Reported Rev.. Split'!R33 -> 62 | BQ40: ='Reported Rev.. Split'!Q33 -> 60 | BR40: ='Reported Rev.. Split'!P33 -> 59 | BS40: ='Reported Rev.. Split'!O33 -> 69 | BT40: =BP40+BQ40+BR40+BS40 -> 250 | BU40: ='Reported Rev.. Split'!N33 -> 56 | BV40: ='Reported Rev.. Split'!M33 -> 52 | BW40: =BW41*BW16 -> 345
A41: רווח תפעולי לטון | B41: =B40/B16 -> #REF! | C41: =C40/C16 -> #REF! | D41: =D40/D16 -> #REF! | E41: =E40/E16 -> #REF! | F41: =F40/F16 -> 53.040068 | G41: =G40/G16 -> 65.665052 | H41: =H40/H16 -> 85.872498 | I41: =I40/I16 -> #REF! | ... BV41: =BV40/BV16 -> 59.360731 | BW41: =BW37-BW39 -> 75 | BY41: =BY37-BY39 -> 93 | BZ41: =BZ37-BZ39 -> 100 | CA41: =CA37-CA39 -> 94.963768 | CB41: =CB37-CB39 -> 75
A42: שיעור רווח תפעולי אשלג | B42: =B40/B34 -> #REF! | C42: =C40/C34 -> #REF! | D42: =D40/D34 -> #REF! | E42: =E40/E34 -> #REF! | F42: =F40/F33 -> 0.25273797 | G42: =G40/G33 -> 0.30619472 | H42: =H40/H33 -> 0.36459717 | I42: =I40/I33 -> #REF! | J42: =J40/J34 -> #REF! | K42: =K40/K33 -> 0.53625779 | L42: =L40/L33 -> 0.63231204 | M42: =M40/M33 -> 0.71470398 | N42: =N40/N33 -> 2.2406623 | O42: =O40/O34 -> 0.45329496 | P42: =P40/P33 -> #REF! | Q42: =Q40/Q33 -> #REF! | R42: =R40/R33 -> #REF! | S42: =S40/S33 -> #REF! | T42: =T40/T36 -> 0.41179744 | U42: =U40/U33 -> #REF! | V42: =V40/V33 -> #REF! | W42: =W40/W33 -> #REF! | X42: =X40/X33 -> #REF! | Y42: =Y40/Y36 -> 0.3308642 | Z42: =Z40/Z33 -> #REF! | AA42: =AA40/AA33 -> #REF! | AB42: =AB40/AB33 -> #REF! | AC42: =AC40/AC33 -> #REF! | AD42: =AD40/AD36 -> 0.29024768 | AE42: =AE40/AE33 -> #REF! | AF42: =AF40/AF33 -> #REF! | AG42: =AG40/AG33 -> #REF! | AH42: =AH40/AH33 -> #REF! | AI42: =AI40/AI36 -> 0.20197857 | AJ42: =AJ40/AJ33 -> #REF! | AK42: =AK40/AK33 -> #REF! | AL42: =AL40/AL33 -> #REF! | AM42: =AM40/AM33 -> #REF! | AN42: =AN40/AN36 -> 0.15739269 | AO42: =AO40/AO33 -> #REF! | AP42: =AP40/AP33 -> #REF! | AQ42: =AQ40/AQ33 -> #REF! | AR42: =AR40/AR33 -> #REF! | AS42: =AS40/AS36 -> 0.21269413 | AT42: =AT40/AT34 -> #REF! | AU42: =AU40/AU34 -> #REF! | AV42: =AV40/AV34 -> #REF! | AW42: =AW40/AW34 -> #REF! | AX42: =AX40/AX36 -> 0.21729323 | AY42: =AY40/AY36 -> 0.051660517 | AZ42: =AZ40/AZ36 -> 0.12624585 | BA42: =BA40/BA36 -> 0.10218978 | BB42: =BB40/BB36 -> 0.11869436 | BC42: =BC40/BC36 -> 0.10143702 | BD42: =BD40/BD36 -> 0.083815029 | BE42: =BE40/BE36 -> 0.11621622 | ... BW42: =BW40/BW36 -> 0.234375 | BY42: =BY41/BY37 -> 0.27927928 | BZ42: =BZ41/BZ37 -> 0.28169014 | CA42: =CA41/CA37 -> 0.27933497 | CB42: =CB41/CB37 -> 0.234375
B44: הממוצעת בתקופה זו.
B45: כמות גשמים נמוכה בעונת המונסונים עלולה לפגוע בצריכת הדשנים של החקלאים.
A46: מחיר אשלג Q2-25
AD47: נתח | AI47: מחיר עד 15/6 | AN47: מחיר 15/6-30/6 | AS47: מחיר ממוצע | AX47: מחיר משוקלל
A48: סין | AD48: =1000/4600 -> 0.2173913 | AI48: 273 | AN48: 355 | AS48: =AI48*5/6+AN48*1/6 -> 286.66667 | AX48: =AD48*AS48 -> 62.318841
A49: הודו | AD49: =900/4600 -> 0.19565217 | AI49: 284 | AN49: 349 | AS49: =AI49*5/6+AN49*1/6 -> 294.83333 | AX49: =AD49*AS49 -> 57.684783
A50: שאר העולם | AD50: =1-AD48-AD49 -> 0.58695652 | AI50: 350 | AN50: 365 | AS50: =AI50*5/6+AN50*1/6 -> 352.5 | AX50: =AD50*AS50 -> 206.90217
AX51: =SUM(AX48:AX50) -> 326.9058
A53: מחיר אשלג H2-25
AD54: נתח | AI54: מחיר עד 15/6 | AN54: מחיר 15/6-30/6 | AS54: מחיר ממוצע | AX54: מחיר משוקלל
A55: סין | AD55: =1000/4600 -> 0.2173913 | AS55: =355 -> 355 | AX55: =AD55*AS55 -> 77.173913
A56: הודו | AD56: =900/4600 -> 0.19565217 | AS56: 349 | AX56: =AD56*AS56 -> 68.282609
A57: שאר העולם | AD57: =1-AD55-AD56 -> 0.58695652 | AS57: 365 | AX57: =AD57*AS57 -> 214.23913
AX58: =SUM(AX55:AX57) -> 359.69565
A60: מחיר אשלג 2026E
AD61: נתח | AI61: מחיר עד 3/26 | AN61: מחיר 4-12/26 | AS61: מחיר ממוצע | AX61: מחיר משוקלל
A62: סין | AD62: =1000/4600 -> 0.2173913 | AI62: =AS55 -> 355 | AN62: 300 | AS62: =AI62*5/6+AN62*1/6 -> 345.83333 | AX62: =AD62*AS62 -> 75.181159
A63: הודו | AD63: =900/4600 -> 0.19565217 | AI63: =AS56 -> 349 | AN63: 300 | AS63: =AI63*5/6+AN63*1/6 -> 340.83333 | AX63: =AD63*AS63 -> 66.684783
A64: שאר העולם | AD64: =1-AD62-AD63 -> 0.58695652 | AI64: =340 -> 340 | AN64: 325 | AS64: =AI64*5/6+AN64*1/6 -> 337.5 | AX64: =AD64*AS64 -> 198.09783
AX65: =SUM(AX62:AX64) -> 339.96377
A68: תמחור ביחס למתחרות
A94: כמויות מכירה - אשלג כיל:
A96: שנה | B96: =B3 -> 2003A | C96: =C3 -> 2004A | D96: =D3 -> 2005A | E96: =E3 -> 2006A | J96: =J3 -> 2007A | O96: =O3 -> 2012A | T96: =T3 -> 2013A | Y96: =Y3 -> 2014A | AD96: =AD3 -> 2015A | AI96: =AI3 -> 2016A | AJ96: =AN3 -> 2017A | AK96: =AO3 -> Q1-14A | AL96: =AP3 -> Q2-14A | AM96: 2014E | AN96: 2015E | AO96: 2016E | AP96: 2017E | AQ96: =#REF! -> #REF! | AR96: 2014E | AS96: 2015E | AT96: 2016E | AU96: 2017E | AV96: =BZ3 -> H2-25E | AW96: 2014E | AX96: 2015E | AY96: 2016E | AZ96: 2016E | BA96: 2016E | BC96: 2015E | BD96: 2016E | BE96: 2016E | BF96: 2016E | BH96: 2015E | BI96: 2016E | BJ96: 2015E | BK96: 2016E | BL96: 2016E | BM96: 2016E | BO96: 2015E | BP96: 2016E | BQ96: 2016E | BR96: 2016E | BS96: 2016E | BT96: 2015E | BU96: 2016E | BV96: 2016E | BW96: 2016E
A97: כמויות אשלג נמכרות כיל (מ' טון) | B97: =B16 -> 5.2 | C97: =C16 -> 5.1 | D97: =D16 -> 4.7 | E97: =E16 -> 3.9 | J97: =J16 -> 5.2 | O97: =O16 -> 4.336 | T97: =T16 -> 4.712 | Y97: =Y16 -> 5.034 | AD97: =AD16 -> 4.259 | AI97: =AI16 -> 4.818 | AJ97: =AN16 -> 4.738 | AK97: =AO16 -> 1.401 | AL97: =AP16 -> 1.249 | AM97: 5.15 | AN97: =AM97*(1+$D$101) -> 5.2015 | AO97: =AN97*(1+$D$101) -> 5.253515 | AP97: =AO97*(1+$D$101) -> 5.3060501 | AQ97: =#REF! -> #REF! | AR97: 5.15 | AS97: =AR97*(1+$D$101) -> 5.2015 | AT97: =AS97*(1+$D$101) -> 5.253515 | AU97: =AT97*(1+$D$101) -> 5.3060501 | AV97: =BZ16 -> 0 | AW97: 5.15 | AX97: =AW97*(1+$D$101) -> 5.2015 | AY97: =AW97*(1+$D$101) -> 5.2015 | AZ97: =AX97*(1+$D$101) -> 5.253515 | BA97: =AZ97*(1+$D$101) -> 5.3060501 | BC97: =BB97*(1+$D$101) -> 0 | BD97: =BB97*(1+$D$101) -> 0 | BE97: =BC97*(1+$D$101) -> 0 | BF97: =BE97*(1+$D$101) -> 0 | BH97: =BG97*(1+$D$101) -> 0 | BI97: =BG97*(1+$D$101) -> 0 | BJ97: =BI97*(1+$D$101) -> 0 | BK97: =BI97*(1+$D$101) -> 0 | BL97: =BJ97*(1+$D$101) -> 0 | BM97: =BK97*(1+$D$101) -> 0 | BO97: =BM97*(1+$D$101) -> 0 | BP97: =BM97*(1+$D$101) -> 0 | BQ97: =BM97*(1+$D$101) -> 0 | BR97: =BO97*(1+$D$101) -> 0 | BS97: =BP97*(1+$D$101) -> 0 | BT97: =BR97*(1+$D$101) -> 0 | BU97: =BR97*(1+$D$101) -> 0 | BV97: =BS97*(1+$D$101) -> 0 | BW97: =AY97*(1+$D$101) -> 5.253515
A98: משלוחי אשלג בעולם (מ' טון) | B98: 45.5 | C98: 51 | D98: 50 | E98: 48 | J98: 55 | O98: 50 | T98: 30 | Y98: 53 | AD98: 56 | AI98: 51 | AJ98: 54 | AM98: 57.5 | AN98: =AM98*(1+$D$99) -> 58.9375 | AO98: =AN98*(1+$D$99) -> 60.410937 | AP98: =AO98*(1+$D$99) -> 61.921211 | AR98: 57.5 | AS98: =AR98*(1+$D$99) -> 58.9375 | AT98: =AS98*(1+$D$99) -> 60.410937 | AU98: =AT98*(1+$D$99) -> 61.921211 | AW98: 57.5 | AX98: =AW98*(1+$D$99) -> 58.9375 | AY98: =AW98*(1+$D$99) -> 58.9375 | AZ98: =AX98*(1+$D$99) -> 60.410937 | BA98: =AZ98*(1+$D$99) -> 61.921211 | BC98: =BB98*(1+$D$99) -> 0 | BD98: =BB98*(1+$D$99) -> 0 | BE98: =BC98*(1+$D$99) -> 0 | BF98: =BE98*(1+$D$99) -> 0 | BH98: =BG98*(1+$D$99) -> 0 | BI98: =BG98*(1+$D$99) -> 0 | BJ98: =BI98*(1+$D$99) -> 0 | BK98: =BI98*(1+$D$99) -> 0 | BL98: =BJ98*(1+$D$99) -> 0 | BM98: =BK98*(1+$D$99) -> 0 | BO98: =BM98*(1+$D$99) -> 0 | BP98: =BM98*(1+$D$99) -> 0 | BQ98: =BM98*(1+$D$99) -> 0 | BR98: =BO98*(1+$D$99) -> 0 | BS98: =BP98*(1+$D$99) -> 0 | BT98: =BR98*(1+$D$99) -> 0 | BU98: =BR98*(1+$D$99) -> 0 | BV98: =BS98*(1+$D$99) -> 0 | BW98: =AY98*(1+$D$99) -> 60.410937
A99: הנחת קצב גידול עולמי בביקוש | D99: 0.025
A100: שיעור צמיחה שנתי במכירות כיל 2003-2014 | D100: =(AM98/B98)^(1/12)-1 -> 0.019697538
A101: שיעור צמיחה שנתי צפוי במכירו כמויות כיל מ- 2014. | D101: 0.01
A103: על מה מתבססת הנחת קצב גידול?
A104: א. שיעור גידול שנתי ממוצע בין השנים 1998-2014 (לפי הגרף של Fertecon)
A105: ב. הגידול הטבעי באוכלוסייה, ותהליך העיור, הגורמים לצמצום בקרקע ראויה לעיבוד חקלאי לנפש, צפויים לגרום לגידול בביקוש לדשנים לאורך זמן
A106: ככל שהשטח החקלאי הזמין לעיבוד הולך וקטן, ואוכלוסיית העולם גדלה, יש צורך בייצור כמות גדולה יותר של מזון על שטח קטן יותר.
A107: ג. השינוי בהרכב צריכת המזון: הואיל וצריכת הדשנים ליחידת תזונה של בשר גבוהה יותר מזו של יחידת תזונה מן הצומח, גדלה צריכת הדשנים לאורך זמן
A108: ד. מחירי האנרגיה הגבוהים והשפעות אקולוגיות של שימוש בדלקים מסוימים, מגבירים כיום את השימוש בדלקים המיוצרים מגידולים חקלאיים.
A109: מאידך, בעקבות החלטת הסוכנות להגנת הסביבה האמריקאית שלא להעלות את אחוז האתנול בבנזין מ- 10% ל- 15% אין צפי לצמיחה בביקוש לתירס מצד תעשיות האתנול
A130: מנגד,
A131: א. שנת 2014 מהווה שנת בסיס טובה יחסית (קצב משלוחים של 57-58 מ' טון) והצמיחה משנה זו עשויה להיות נמוכה יותר.
A132: ב. מחירי הסחורות ירדו בחדות בחודשים האחרונים וברמות מחיר אלה התמריץ לחקלאים לרכוש דשנים הולך ויורד.
A133: ג. הטווח הקצר נראה בכל מקרה טוב בשווקי היעד המרגזיים של החברה (סין, ברזיל, הודו).
A134: ד. ממוצע המכירות של החברה בשנים האחרונות (2003-2013) עמד על 4.58 מיל' טון.
... A138: מחיר מכירה - אשלג כיל
A140: שנה | B140: =B96 -> 2003A | C140: =C96 -> 2004A | D140: =D96 -> 2005A | E140: =E96 -> 2006A | J140: =J96 -> 2007A | O140: =O96 -> 2012A | T140: =T96 -> 2013A | Y140: =Y96 -> 2014A | AD140: =AD96 -> 2015A | AI140: =AI96 -> 2016A | AJ140: =AJ96 -> 2017A | AK140: =AK96 -> Q1-14A | AL140: =AL96 -> Q2-14A | AM140: Q3-14E | AN140: Q4-14E | AO140: =AM96 -> 2014E | AP140: =AN96 -> 2015E | AQ140: =AQ96 -> #REF! | AR140: Q3-14E | AS140: Q4-14E | AT140: =AR96 -> 2014E | AU140: =AS96 -> 2015E | AV140: =AV96 -> H2-25E | AW140: Q3-14E | AX140: Q4-14E | AY140: =AV96 -> H2-25E | AZ140: =AW96 -> 2014E | BA140: =AY96 -> 2016E | BC140: Q4-14E | BD140: =BA96 -> 2016E | BE140: =BB96 -> 0 | BF140: =BD96 -> 2016E | BH140: Q4-14E | BI140: =BF96 -> 2016E | BJ140: Q4-14E | BK140: =BH96 -> 2015E | BL140: =BI96 -> 2016E | BM140: =BJ96 -> 2015E | BO140: Q4-14E | BP140: =BL96 -> 2016E | BQ140: =BL96 -> 2016E | BR140: =BM96 -> 2016E | BS140: =BO96 -> 2015E | BT140: Q4-14E | BU140: =BQ96 -> 2016E | BV140: =BR96 -> 2016E | BW140: =AX96 -> 2015E
A141: מחיר מכירה ממוצע שנתי | B141: =B31 -> #REF! | C141: =C31 -> #REF! | D141: =D31 -> #REF! | E141: =E31 -> #REF! | J141: =J31 -> #REF! | O141: =O31 -> #REF! | T141: =T31 -> 381.36672 | Y141: =Y31 -> 321.81168 | AD141: =AD31 -> 303.3576 | AI141: =AI31 -> 259.05 | AJ141: =AN31 -> 236.2 | AK141: =AO31 -> #REF! | AL141: =AP31 -> #REF! | AM141: =325 -> 325 | AN141: 333 | AO141: =#REF! -> #REF! | AP141: 345 | AQ141: =#REF! -> #REF! | AR141: =325 -> 325 | AS141: 333 | AT141: =#REF! -> #REF! | AU141: 345 | AV141: =BZ31 -> 0 | AW141: =325 -> 325 | AX141: 333 | AY141: =#REF! -> #REF! | AZ141: =CC31 -> 0 | BA141: =CE31 -> 0 | BC141: 333 | BD141: =#REF! -> #REF! | BE141: =CH31 -> 0 | BF141: =CJ31 -> 0 | BH141: 333 | BI141: =#REF! -> #REF! | BJ141: 333 | BK141: =#REF! -> #REF! | BL141: =#REF! -> #REF! | BM141: =#REF! -> #REF! | BO141: 333 | BP141: =#REF! -> #REF! | BQ141: =#REF! -> #REF! | BR141: =#REF! -> #REF! | BS141: =#REF! -> #REF! | BT141: 333 | BU141: =#REF! -> #REF! | BV141: =#REF! -> #REF! | BW141: =CD31 -> 0
A142: מערב אירופה | AM142: 350 | AN142: 360 | AP142: 360 | AR142: 350 | AS142: 360 | AU142: 360 | AW142: 350 | AX142: 360 | BC142: 360 | BH142: 360 | BJ142: 360 | BO142: 360 | BT142: 360
A143: מזרח אסיה/ שאר העולם | AM143: 305 | AN143: 330 | AP143: 330 | AR143: 305 | AS143: 330 | AU143: 330 | AW143: 305 | AX143: 330 | BC143: 330 | BH143: 330 | BJ143: 330 | BO143: 330 | BT143: 330
A144: דרום אמריקה | AM144: 350 | AN144: 380 | AP144: 380 | AR144: 350 | AS144: 380 | AU144: 380 | AW144: 350 | AX144: 380 | BC144: 380 | BH144: 380 | BJ144: 380 | BO144: 380 | BT144: 380
A145: הודו | AM145: 322 | AN145: =AM145 -> 322 | AP145: 338 | AR145: 322 | AS145: =AR145 -> 322 | AU145: 338 | AW145: 322 | AX145: =AW145 -> 322 | BC145: =BB145 -> 0 | BH145: =BG145 -> 0 | BJ145: =BI145 -> 0 | BO145: =BM145 -> 0 | BT145: =BR145 -> 0
