Workbook

Sheet Monthly_Board_Pack
B2: PROJECT PATRY
B4: MONTHLY BOARD PACK
B6: =TEXT(DATE(YEAR(TODAY()),MONTH(TODAY()),1),"mmmm yyyy") -> January 2026
B8: Prepared for: Board of Directors
B10: ="Generated: "&TEXT(NOW(),"mmmm d, yyyy")&" at "&TEXT(NOW(),"h:mm AM/PM") -> Generated: January 12, 2026 at 9:41 AM
B14: 1. EXECUTIVE SUMMARY
B16: Total Revenue | D16: Net Operating Income | F16: NOI Margin | H16: Portfolio Occupancy | J16: FFO | L16: Debt Service Coverage
B17: {=CAP_21_Investor_Quarterly!B5} -> 13350000 | D17: {=FIN_01_Investor_Pack!E21} -> 7715000 | F17: {=CAP_21_Investor_Quarterly!B7} -> 0.614 | H17: {=OPS_11_Occupancy_Mix!D12} -> 0.95219124 | J17: {=CAP_21_Investor_Quarterly!B10} -> 7050000 | L17: {=FIN_07_Debt_Covenant!D5} -> 1.52
B18: {=CAP_21_Investor_Quarterly!D5} -> 0.019083969 | D18: vs Q3: +2.1% | F18: vs Plan: +0.4% | H18: vs Plan: +1.2% | J18: {=CAP_21_Investor_Quarterly!D10} -> 0.02173913 | L18: ✓ All Pass
B20: 2. PORTFOLIO PERFORMANCE
B22: FINANCIAL METRICS | I22: OPERATIONS METRICS
B23: Metric | C23: YTD Actual | E23: YTD Plan | F23: Variance | G23: Status | I23: Metric | J23: YTD Actual | L23: Plan | M23: Variance | N23: Status
B24: Total Revenue | C24: {=Portfolio_Summary!B6} -> 0 | E24: {=Portfolio_Summary!C6} -> 52500000 | F24: {=Portfolio_Summary!E6} -> -1 | G24: {=Portfolio_Summary!F6} -> ✗ | I24: Occupancy % | J24: {=Portfolio_Summary!B15} -> 0.95219124 | L24: {=Portfolio_Summary!C15} -> 0.94 | M24: {=Portfolio_Summary!E15} -> 0.012969399 | N24: {=Portfolio_Summary!F15} -> ✓
B25: Net Operating Income | C25: {=Portfolio_Summary!B7} -> 7715000 | E25: {=Portfolio_Summary!C7} -> 32000000 | F25: {=Portfolio_Summary!E7} -> -0.75890625 | G25: {=Portfolio_Summary!F7} -> ✗ | I25: Avg NER | J25: {=Portfolio_Summary!B16} -> 1814.3724 | L25: {=Portfolio_Summary!C16} -> 1780 | M25: {=Portfolio_Summary!E16} -> 0.019310329 | N25: {=Portfolio_Summary!F16} -> ✓
B26: NOI Margin % | C26: {=Portfolio_Summary!B8} -> 0 | E26: {=Portfolio_Summary!C8} -> 0.61 | F26: {=Portfolio_Summary!E8} -> -1 | G26: {=Portfolio_Summary!F8} -> ✗ | I26: Lead→Lease Conv | J26: {=Portfolio_Summary!B17} -> 0.090356212 | L26: {=Portfolio_Summary!C17} -> 0.08 | M26: {=Portfolio_Summary!E17} -> 0.12945265 | N26: {=Portfolio_Summary!F17} -> ✓
B27: FFO | C27: {=Portfolio_Summary!B9} -> 100000 | E27: {=Portfolio_Summary!C9} -> 28000000 | F27: {=Portfolio_Summary!E9} -> -0.99642857 | G27: {=Portfolio_Summary!F9} -> ✗ | I27: Renewal Rate | J27: {=Portfolio_Summary!B18} -> 0.72727273 | L27: {=Portfolio_Summary!C18} -> 0.7 | M27: {=Portfolio_Summary!E18} -> 0.038961039 | N27: {=Portfolio_Summary!F18} -> ✓
B28: Same-Store Growth | C28: {=Portfolio_Summary!B10} -> 0.035689774 | E28: {=Portfolio_Summary!C10} -> 0.025 | F28: {=Portfolio_Summary!E10} -> 0.42759094 | G28: {=Portfolio_Summary!F10} -> ✓ | I28: Retention Rate | J28: {=Portfolio_Summary!B19} -> 0.69583333 | L28: {=Portfolio_Summary!C19} -> 0.68 | M28: {=Portfolio_Summary!E19} -> 0.023284314 | N28: {=Portfolio_Summary!F19} -> ✓
B29: DSCR | C29: {=Portfolio_Summary!B11} -> 2.85 | E29: {=Portfolio_Summary!C11} -> 1.4 | F29: {=Portfolio_Summary!E11} -> 1.0357143 | G29: {=Portfolio_Summary!F11} -> ✓ | I29: WO Completion (hrs) | J29: {=Portfolio_Summary!B20} -> 19.392509 | L29: {=Portfolio_Summary!C20} -> 24 | M29: {=Portfolio_Summary!E20} -> 0.19197878 | N29: {=Portfolio_Summary!F20} -> ✓
B32: 3. KEY PERFORMANCE CHARTS
B34: 12-Month Net Cash Flow Trend | I34: Occupancy by Floorplan
B35: Month | C35: Cash Flow ($M) | I35: Floorplan | J35: Occupancy
B36: Jan | C36: =FIN_05_Cash_Flow!B27/1000000 -> 2.09425 | I36: Studio | J36: {=OPS_11_Occupancy_Mix!D5} -> 0.95833333
B37: Feb | C37: =FIN_05_Cash_Flow!C27/1000000 -> 2.20855 | I37: 1BR | J37: {=OPS_11_Occupancy_Mix!D6} -> 0.95588235
B38: Mar | C38: =FIN_05_Cash_Flow!D27/1000000 -> 2.31585 | I38: 1BR+Den | J38: {=OPS_11_Occupancy_Mix!D7} -> 0.9375
B39: Apr | C39: =FIN_05_Cash_Flow!E27/1000000 -> 2.4332 | I39: 2BR | J39: {=OPS_11_Occupancy_Mix!D8} -> 0.93333333
B40: May | C40: =FIN_05_Cash_Flow!F27/1000000 -> 2.5406 | I40: 2BR+Den | J40: {=OPS_11_Occupancy_Mix!D9} -> 0.96428571
B41: Jun | C41: =FIN_05_Cash_Flow!G27/1000000 -> 2.647 | I41: 3BR | J41: {=OPS_11_Occupancy_Mix!D10} -> 0.94444444
B42: Jul | C42: =FIN_05_Cash_Flow!H27/1000000 -> 2.74345 | I42: Penthouse | J42: {=OPS_11_Occupancy_Mix!D11} -> 1
B43: Aug | C43: =FIN_05_Cash_Flow!I27/1000000 -> 2.85595
B44: Sep | C44: =FIN_05_Cash_Flow!J27/1000000 -> 2.97445
B45: Oct | C45: =FIN_05_Cash_Flow!K27/1000000 -> 3.106
B46: Nov | C46: =FIN_05_Cash_Flow!L27/1000000 -> 3.2286
B47: Dec | C47: =FIN_05_Cash_Flow!M27/1000000 -> 3.3522
B50: can y | I50: Marketing Channel Attribution
B51: Stage | C51: Count | I51: Channel | J51: Revenue
B52: Leads | C52: {=MKT_16_Marketing_CPA!C6} -> 1151 | I52: ILS | J52: {=MKT_17_Attribution!E5} -> 425000
B53: Tours | C53: {=MKT_16_Marketing_CPA!E6} -> 401 | I53: Social | J53: {=MKT_17_Attribution!E6} -> 320000
B54: Applications | C54: {=MKT_16_Marketing_CPA!F6} -> 59.850374 | I54: PPC | J54: {=MKT_17_Attribution!E7} -> 285000
B55: Leases | C55: {=MKT_16_Marketing_CPA!G6} -> 104 | I55: Organic | J55: {=MKT_17_Attribution!E8} -> 195000
I56: Referral | J56: {=MKT_17_Attribution!E9} -> 625000
B60: 4. QUARTERLY VARIANCE ANALYSIS
B61: Q4 2025 Actual vs Plan Performance with Management Commentary
B63: FINANCIAL VARIANCES | I63: OPERATIONS VARIANCES
B64: Metric | C64: Q4 Actual | D64: Q4 Plan | E64: Variance $ | F64: Variance % | G64: Status | I64: Metric | J64: Actual | K64: Plan | L64: Var % | M64: Status
B65: Total Revenue | C65: {=CAP_21_Investor_Quarterly!B5} -> 13350000 | D65: 13500000 | E65: =C65-D65 -> -150000 | F65: =IF(D65=0,0,(C65-D65)/D65) -> -0.011111111 | G65: =IF(F65>=0,"✓ Fav","✗ Unfav") -> ✗ Unfav | I65: Occupancy | J65: {=OPS_11_Occupancy_Mix!D12} -> 0.95219124 | K65: 0.94 | L65: =IF(K65=0,0,(J65-K65)/K65) -> 0.012969399 | M65: =IF(L65>=0,"✓","✗") -> ✓
B66: Net Operating Income | C66: {=CAP_21_Investor_Quarterly!B6} -> 8200000 | D66: 8100000 | E66: =C66-D66 -> 100000 | F66: =IF(D66=0,0,(C66-D66)/D66) -> 0.012345679 | G66: =IF(F66>=0,"✓ Fav","✗ Unfav") -> ✓ Fav | I66: Avg NER | J66: {=OPS_11_Occupancy_Mix!G12} -> 1814.3724 | K66: 1780 | L66: =IF(K66=0,0,(J66-K66)/K66) -> 0.019310329 | M66: =IF(L66>=0,"✓","✗") -> ✓
B67: NOI Margin | C67: {=CAP_21_Investor_Quarterly!B7} -> 0.614 | D67: 0.6 | E67: =C67-D67 -> 0.014 | F67: =IF(D67=0,0,(C67-D67)/D67) -> 0.023333333 | G67: =IF(F67>=0,"✓ Fav","✗ Unfav") -> ✓ Fav | I67: Renewal Rate | J67: {=OPS_12_Renewal_Retention!D10} -> 0.72727273 | K67: 0.7 | L67: =IF(K67=0,0,(J67-K67)/K67) -> 0.038961039 | M67: =IF(L67>=0,"✓","✗") -> ✓
B68: FFO | C68: {=CAP_21_Investor_Quarterly!B10} -> 7050000 | D68: 6800000 | E68: =C68-D68 -> 250000 | F68: =IF(D68=0,0,(C68-D68)/D68) -> 0.036764706 | G68: =IF(F68>=0,"✓ Fav","✗ Unfav") -> ✓ Fav | I68: Retention Rate | J68: {=OPS_12_Renewal_Retention!H13} -> 0.69583333 | K68: 0.68 | L68: =IF(K68=0,0,(J68-K68)/K68) -> 0.023284314 | M68: =IF(L68>=0,"✓","✗") -> ✓
B69: FFO per Share | C69: {=CAP_21_Investor_Quarterly!B11} -> 0.14 | D69: 0.136 | E69: =C69-D69 -> 0.004 | F69: =IF(D69=0,0,(C69-D69)/D69) -> 0.029411765 | G69: =IF(F69>=0,"✓ Fav","✗ Unfav") -> ✓ Fav | I69: WO Completion (hrs) | J69: {=OPS_14_Maintenance_WO!E11} -> 19.392509 | K69: 24 | L69: =IF(K69=0,0,(K69-J69)/K69) -> 0.19197878 | M69: =IF(L69>=0,"✓","✗") -> ✓
B70: DSCR | C70: {=CAP_21_Investor_Quarterly!B12} -> 1.52 | D70: 1.45 | E70: =C70-D70 -> 0.07 | F70: =IF(D70=0,0,(C70-D70)/D70) -> 0.048275862 | G70: =IF(F70>=0,"✓ Fav","✗ Unfav") -> ✓ Fav | I70: Emergency SLA | J70: {=OPS_14_Maintenance_WO!E15} -> 0.95238095 | K70: 0.95 | L70: =IF(K70=0,0,(J70-K70)/K70) -> 0.0025062657 | M70: =IF(L70>=0,"✓","✗") -> ✓
B72: MANAGEMENT COMMENTARY
B73: Category | D73: Commentary
B74: Revenue | C74: ⚠ | D74: Revenue slightly below plan (-1.1%) due to delayed lease-ups at Parkside Phase II. Expect to recover in Q1 as 15 pending applications convert.
B75: NOI Performance | C75: ✓ | D75: NOI exceeded plan by +1.2% driven by lower-than-expected utility costs and successful renegotiation of landscaping contract.
B76: Occupancy | C76: ✓ | D76: Portfolio occupancy at 95.2% vs 94.0% plan (+1.3%). Strong performance across all unit types, with Penthouse achieving 100%.
B77: FFO Growth | C77: ✓ | D77: FFO beat plan by +3.7% ($250K). Lower interest expense from recent refinancing contributed $150K; remainder from operating efficiencies.
B78: Operational Excellence | C78: ✓ | D78: WO completion improved 19% vs plan (19.4 hrs vs 24 hrs target). New maintenance dispatch system driving efficiency gains.
B79: Key Risk | C79: ⚠ | D79: AR delinquency at 39.5% requires attention. Collections team implementing new payment plan program to address aged receivables.
B80: VARIANCE SUMMARY: | D80: Financial: 5/6 Favorable | G80: Operations: 6/6 Favorable | J80: Overall: AHEAD OF PLAN
B82: 5. APPENDIX: COMPLIANCE & RISK
B84: DEBT COVENANT COMPLIANCE | I84: RISK SUMMARY
B85: Covenant | C85: Type | D85: Threshold | E85: Current | F85: Cushion | G85: Status | I85: Risk Category | J85: Status | L85: Notes
B86: {=FIN_07_Debt_Covenant!A5} -> Debt Service Coverage Ratio | C86: {=FIN_07_Debt_Covenant!B5} -> Minimum | D86: {=FIN_07_Debt_Covenant!C5} -> 1.25 | E86: {=FIN_07_Debt_Covenant!D5} -> 1.52 | F86: {=FIN_07_Debt_Covenant!E5} -> 0.27 | G86: {=FIN_07_Debt_Covenant!F5} -> ✓ PASS | I86: Covenant Compliance | J86: ✓ ALL PASS | L86: All 7 covenants in compliance
B87: {=FIN_07_Debt_Covenant!A6} -> Loan-to-Value | C87: {=FIN_07_Debt_Covenant!B6} -> Maximum | D87: {=FIN_07_Debt_Covenant!C6} -> 0.75 | E87: {=FIN_07_Debt_Covenant!D6} -> 0.58 | F87: {=FIN_07_Debt_Covenant!E6} -> 0.17 | G87: {=FIN_07_Debt_Covenant!F6} -> ✓ PASS | I87: AR Delinquency | J87: ⚠ 39.5% | L87: Above 30% threshold - action needed
B88: {=FIN_07_Debt_Covenant!A7} -> Debt Yield | C88: {=FIN_07_Debt_Covenant!B7} -> Minimum | D88: {=FIN_07_Debt_Covenant!C7} -> 0.08 | E88: {=FIN_07_Debt_Covenant!D7} -> 0.092 | F88: {=FIN_07_Debt_Covenant!E7} -> 0.012 | G88: {=FIN_07_Debt_Covenant!F7} -> ✓ PASS | I88: Development Permits | J88: ⚠ 1 High Risk | L88: Downtown permit pending 35 days
B89: {=FIN_07_Debt_Covenant!A8} -> Interest Coverage Ratio | C89: {=FIN_07_Debt_Covenant!B8} -> Minimum | D89: {=FIN_07_Debt_Covenant!C8} -> 1.5 | E89: {=FIN_07_Debt_Covenant!D8} -> 1.85 | F89: {=FIN_07_Debt_Covenant!E8} -> 0.35 | G89: {=FIN_07_Debt_Covenant!F8} -> ✓ PASS | I89: ESG Targets | J89: ⚠ 8/8 Behind | L89: All sustainability metrics behind target
B90: {=FIN_07_Debt_Covenant!A9} -> Net Worth Minimum | C90: {=FIN_07_Debt_Covenant!B9} -> Minimum | D90: {=FIN_07_Debt_Covenant!C9} -> 15000000 | E90: {=FIN_07_Debt_Covenant!D9} -> 22500000 | F90: {=FIN_07_Debt_Covenant!E9} -> 7500000 | G90: {=FIN_07_Debt_Covenant!F9} -> ✓ PASS | I90: Cash Position | J90: ✓ 14.8 mo runway | L90: Above 12-month minimum
B91: {=FIN_07_Debt_Covenant!A10} -> Liquidity Requirement | C91: {=FIN_07_Debt_Covenant!B10} -> Minimum | D91: {=FIN_07_Debt_Covenant!C10} -> 2000000 | E91: {=FIN_07_Debt_Covenant!D10} -> 3852200 | F91: {=FIN_07_Debt_Covenant!E10} -> 1852200 | G91: {=FIN_07_Debt_Covenant!F10} -> ✓ PASS | I91: Market Conditions | J91: ✓ Stable | L91: No material changes to market
B92: {=FIN_07_Debt_Covenant!A11} -> Occupancy Minimum | C92: {=FIN_07_Debt_Covenant!B11} -> Minimum | D92: {=FIN_07_Debt_Covenant!C11} -> 0.9 | E92: {=FIN_07_Debt_Covenant!D11} -> 0.952 | F92: {=FIN_07_Debt_Covenant!E11} -> 0.052 | G92: {=FIN_07_Debt_Covenant!F11} -> ✓ PASS
B96: CONFIDENTIAL - FOR BOARD USE ONLY
B97: ="Prepared: "&TEXT(NOW(),"mmmm d, yyyy")&" at "&TEXT(NOW(),"h:mm AM/PM") -> Prepared: January 12, 2026 at 9:41 AM | I97: Questions: investor-relations@projectpatry.com

Sheet _Executive_Dashboard
B1: PROJECT PATRY - EXECUTIVE DASHBOARD
B2: =TEXT(TODAY(),"mmmm d, yyyy") -> January 12, 2026
B4: FINANCIAL
B6: FFO | D6: NOI | F6: Total Revenue | H6: Cash Position | J6: DSCR | L6: AR Balance
B7: =_xlfn.IFERROR(FIN_01_Investor_Pack!L7,"—") -> 0.0071428571 | D7: =_xlfn.IFERROR(FIN_01_Investor_Pack!L10,"—") -> 0.02117061 | F7: =_xlfn.IFERROR(CAP_21_Investor_Quarterly!B5,"—") -> 13350000 | H7: =_xlfn.IFERROR(FIN_05_Cash_Flow!Q8,"—") -> 3852200 | J7: =_xlfn.IFERROR(FIN_07_Debt_Covenant!D5,"—") -> 1.52 | L7: =_xlfn.IFERROR(FIN_08_AR_Bad_Debt!I4,"—") -> 206500
B10: OPERATIONS
B12: Occupancy | D12: Avg NER | F12: Renewal Rate | H12: Avg Turnover Days | J12: Open Work Orders | L12: Resident NPS
B13: =_xlfn.IFERROR(OPS_11_Occupancy_Mix!D12,"—") -> 0.95219124 | D13: =_xlfn.IFERROR(OPS_11_Occupancy_Mix!G12,"—") -> 1814.3724 | F13: =_xlfn.IFERROR(OPS_12_Renewal_Retention!H13,"—") -> 0.69583333 | H13: =_xlfn.IFERROR(OPS_13_Turnover_MakeReady!K5,"—") -> 0.075697211 | J13: =_xlfn.IFERROR(OPS_14_Maintenance_WO!J4,"—") -> 64 | L13: =_xlfn.IFERROR(OPS_15_Resident_NPS!I4,"—") -> 0.4789916
B16: MARKETING
B18: Total Spend | D18: Total Leads | F18: Avg CPA | H18: New Leases | J18: Attributed Revenue | L18: Avg ROAS
B19: =_xlfn.IFERROR(MKT_16_Marketing_CPA!B16,"—") -> 800 | D19: =_xlfn.IFERROR(MKT_16_Marketing_CPA!C16,"—") -> 42 | F19: =_xlfn.IFERROR(MKT_16_Marketing_CPA!H16,"—") -> 266.66667 | H19: =_xlfn.IFERROR(MKT_16_Marketing_CPA!G16,"—") -> 3 | J19: =_xlfn.IFERROR(MKT_17_Attribution!E12,"—") -> 2060000 | L19: =_xlfn.IFERROR(MKT_17_Attribution!F12,"—") -> 85.833333
B22: DEVELOPMENT
B24: Total Budget | D24: Spent to Date | F24: Est. to Complete | H24: Total Dev Units | J24: Total EV | L24: Active Permits
B25: =_xlfn.IFERROR(DEV_19_Cost_Complete!B10,"—") -> 159000000 | D25: =_xlfn.IFERROR(DEV_19_Cost_Complete!C10,"—") -> 109100000 | F25: =_xlfn.IFERROR(DEV_19_Cost_Complete!E10,"—") -> 25800000 | H25: =_xlfn.IFERROR(DEV_18_Project_EV!B8,"—") -> 550 | J25: =_xlfn.IFERROR(DEV_18_Project_EV!F8,"—") -> 1.9620914e+08 | L25: =_xlfn.IFERROR(COUNTIF(DEV_20_Entitlement_Risk!C5:C10,"<>Approved"),"—") -> 3
B28: CAPITAL MARKETS | H28: ESG & SUSTAINABILITY
B30: Revenue QoQ | D30: NOI Margin | F30: FFO/Share | H30: Energy (kWh/sqft) | J30: Waste Diversion | L30: ENERGY STAR
B31: =_xlfn.IFERROR(CAP_21_Investor_Quarterly!D5,"—") -> 0.019083969 | D31: =_xlfn.IFERROR(CAP_21_Investor_Quarterly!B7,"—") -> 0.614 | F31: =_xlfn.IFERROR(CAP_21_Investor_Quarterly!B11,"—") -> 0.14 | H31: =_xlfn.IFERROR(ESG_22_Sustainability!B5,"—") -> 12.8 | J31: =_xlfn.IFERROR(ESG_22_Sustainability!B7,"—") -> 0.42 | L31: =_xlfn.IFERROR(ESG_22_Sustainability!B9,"—") -> 72
B34: TREND INDICATORS (12-MONTH)
B36: Net Cash Flow | E36: Retention Rate | H36: Occupancy Trend | K36: Revenue Trend
B39: Generated: | C39: =TEXT(NOW(),"mmm d, yyyy h:mm AM/PM") -> Jan 12, 2026 9:41 AM | K39: Project Patry Enterprise Reporting System
B41: ALERTS & STATUS
B43: Covenant Status: | D43: =_xlfn.IFERROR(IF(COUNTIF(FIN_07_Debt_Covenant!F5:F11,"✓ PASS")=7,"✓ ALL COVENANTS PASS","⚠ COVENANT BREACH"),"—") -> ✓ ALL COVENANTS PASS | H43: AR Delinquency: | J43: =_xlfn.IFERROR(FIN_08_AR_Bad_Debt!I7,"—") -> 0.39467312 | L43: High Risk Permits: | M43: =_xlfn.IFERROR(COUNTIF(DEV_20_Entitlement_Risk!G5:G10,"High"),"—") -> 1
B44: Cash Runway: | D44: =_xlfn.IFERROR(FIN_05_Cash_Flow!Q11&" months","—") -> 14.801657785672 months | H44: ESG Behind Target: | J44: =_xlfn.IFERROR(COUNTIF(ESG_22_Sustainability!F5:F12,"⚠ Behind")&"/8","—") -> 8/8

Sheet Variance_Summary
B1: VARIANCE SUMMARY - ALL REPORTS
B2: =TEXT(TODAY(),"As of mmmm d, yyyy")&" | Favorable/Unfavorable Analysis with Executive Commentary" -> A0 o0 January 12, 2026 | Favorable/Unfavorable Analysis with Executive Commentary
B4: Report | C4: Key Metric | D4: Actual | E4: Plan/Target | F4: Variance | G4: Var % | H4: Status | I4: Executive Commentary
B6: FINANCIAL REPORTS
B7: FIN_01_Investor_Pack | C7: FFO (Q4) | D7: =_xlfn.IFERROR(FIN_01_Investor_Pack!E34,"") -> 100000 | F7: =_xlfn.IFERROR(D7-E7,0) -> 100000 | G7: =_xlfn.IFERROR(IF(E7=0,0,(D7-E7)/E7),0) -> 0 | H7: =_xlfn.IFERROR(IF(G7>=0,"✓ Fav","✗ Unfav"),"—") -> ✓ Fav | I7: [Commentary: Enter FFO performance drivers and outlook]
B8: FIN_02_NOI_Pack | C8: Portfolio NOI | D8: =_xlfn.IFERROR(FIN_01_Investor_Pack!E21,"") -> 7715000 | F8: =_xlfn.IFERROR(D8-E8,0) -> 7715000 | G8: =_xlfn.IFERROR(IF(E8=0,0,(D8-E8)/E8),0) -> 0 | H8: =_xlfn.IFERROR(IF(G8>=0,"✓ Fav","✗ Unfav"),"—") -> ✓ Fav | I8: [Commentary: Enter NOI margin drivers and cost control measures]
B9: FIN_03_Rent_Roll | C9: Total Units | D9: =_xlfn.IFERROR(FIN_03_Rent_Roll!G6,"") -> 251 | F9: =_xlfn.IFERROR(D9-E9,0) -> 251 | G9: =_xlfn.IFERROR(IF(E9=0,0,(D9-E9)/E9),0) -> 0 | H9: =_xlfn.IFERROR(IF(G9>=0,"✓ Fav","✗ Unfav"),"—") -> ✓ Fav | I9: [Commentary: Enter rent roll changes and lease expiration status]
B10: FIN_04_Budget_Variance | C10: Total Variance | F10: =_xlfn.IFERROR(D10-E10,0) -> 0 | I10: [Commentary: GL-level variance analysis pending data population]
B11: FIN_05_Cash_Flow | C11: Cash Position | D11: =_xlfn.IFERROR(FIN_05_Cash_Flow!Q8,"") -> 3852200 | F11: =_xlfn.IFERROR(D11-E11,0) -> 3852200 | G11: =_xlfn.IFERROR(IF(E11=0,0,(D11-E11)/E11),0) -> 0 | H11: =_xlfn.IFERROR(IF(G11>=0,"✓ Fav","✗ Unfav"),"—") -> ✓ Fav | I11: [Commentary: Enter liquidity position and runway analysis]
B12: FIN_06_Capex | C12: % Budget Spent | D12: =_xlfn.IFERROR(FIN_06_Capex!I22,"") -> 395000 | F12: =_xlfn.IFERROR(D12-E12,0) -> 395000 | G12: =_xlfn.IFERROR(IF(E12=0,0,(E12-D12)/E12),0) -> 0 | H12: =_xlfn.IFERROR(IF(G12>=0,"✓ Fav","✗ Unfav"),"—") -> ✓ Fav | I12: [Commentary: Enter capex project status and timing]
B13: FIN_07_Debt_Covenant | C13: DSCR | D13: =_xlfn.IFERROR(FIN_07_Debt_Covenant!D5,"") -> 1.52 | E13: =_xlfn.IFERROR(FIN_07_Debt_Covenant!C5,"") -> 1.25 | F13: =_xlfn.IFERROR(D13-E13,0) -> 0.27 | G13: =_xlfn.IFERROR(IF(E13=0,0,(D13-E13)/E13),0) -> 0.216 | H13: =_xlfn.IFERROR(IF(D13>=E13,"✓ Pass","✗ Breach"),"—") -> ✓ Pass | I13: [Commentary: Enter covenant headroom and debt strategy]
B14: FIN_08_AR_Bad_Debt | C14: Delinquency Rate | D14: =_xlfn.IFERROR(FIN_08_AR_Bad_Debt!I7,"") -> 0.39467312 | F14: =_xlfn.IFERROR(D14-E14,0) -> 0.39467312 | G14: =_xlfn.IFERROR(IF(E14=0,0,(E14-D14)/E14),0) -> 0 | H14: =_xlfn.IFERROR(IF(D14<=E14,"✓ Fav","⚠ Alert"),"—") -> ⚠ Alert | I14: [Commentary: Enter collections strategy and aged AR actions]
B16: OPERATIONS REPORTS
B17: OPS_09_Leasing_OnePager | C17: MTD Leases | D17: =_xlfn.IFERROR(OPS_09_Leasing_OnePager!D10,0) -> 0 | F17: =_xlfn.IFERROR(D17-E17,0) -> 0 | G17: =_xlfn.IFERROR(IF(E17=0,0,(D17-E17)/E17),0) -> 0 | H17: =_xlfn.IFERROR(IF(G17>=0,"✓ Fav","✗ Unfav"),"—") -> ✓ Fav | I17: [Commentary: Enter leasing velocity and pipeline status]
B18: OPS_10_Leasing_Funnel | C18: Lead→Lease Conv | D18: =_xlfn.IFERROR(OPS_10_Leasing_Funnel!I12,0) -> 0.090356212 | F18: =_xlfn.IFERROR(D18-E18,0) -> 0.090356212 | G18: =_xlfn.IFERROR(IF(E18=0,0,(D18-E18)/E18),0) -> 0 | H18: =_xlfn.IFERROR(IF(G18>=0,"✓ Fav","✗ Unfav"),"—") -> ✓ Fav | I18: [Commentary: Enter conversion bottlenecks and improvements]
B19: OPS_11_Occupancy_Mix | C19: Portfolio Occupancy | D19: =_xlfn.IFERROR(OPS_11_Occupancy_Mix!D12,0) -> 0.95219124 | F19: =_xlfn.IFERROR(D19-E19,0) -> 0.95219124 | G19: =_xlfn.IFERROR(IF(E19=0,0,(D19-E19)/E19),0) -> 0 | H19: =_xlfn.IFERROR(IF(G19>=0,"✓ Fav","✗ Unfav"),"—") -> ✓ Fav | I19: [Commentary: Enter unit type performance and absorption]
B20: OPS_12_Renewal_Retention | C20: Renewal Rate | D20: =_xlfn.IFERROR(OPS_12_Renewal_Retention!D10,0) -> 0.72727273 | F20: =_xlfn.IFERROR(D20-E20,0) -> 0.72727273 | G20: =_xlfn.IFERROR(IF(E20=0,0,(D20-E20)/E20),0) -> 0 | H20: =_xlfn.IFERROR(IF(G20>=0,"✓ Fav","✗ Unfav"),"—") -> ✓ Fav | I20: [Commentary: Enter renewal trends and concession strategy]
B21: OPS_13_Turnover_MakeReady | C21: Avg Turnover Days | D21: =_xlfn.IFERROR(OPS_13_Turnover_MakeReady!K5,0) -> 0.075697211 | F21: =_xlfn.IFERROR(D21-E21,0) -> 0.075697211 | G21: =_xlfn.IFERROR(IF(E21=0,0,(E21-D21)/E21),0) -> 0 | H21: =_xlfn.IFERROR(IF(D21<=E21,"✓ Fav","✗ Unfav"),"—") -> ✗ Unfav | I21: [Commentary: Enter make-ready efficiency and cost drivers]
B22: OPS_14_Maintenance_WO | C22: Avg WO Completion (hrs) | D22: =_xlfn.IFERROR(OPS_14_Maintenance_WO!E11,0) -> 19.392509 | F22: =_xlfn.IFERROR(D22-E22,0) -> 19.392509 | G22: =_xlfn.IFERROR(IF(E22=0,0,(E22-D22)/E22),0) -> 0 | H22: =_xlfn.IFERROR(IF(D22<=E22,"✓ Fav","✗ Unfav"),"—") -> ✗ Unfav | I22: [Commentary: Enter maintenance staffing and SLA performance]
B23: OPS_15_Resident_NPS | C23: Overall NPS | D23: =_xlfn.IFERROR(OPS_15_Resident_NPS!I4,0) -> 0.4789916 | F23: =_xlfn.IFERROR(D23-E23,0) -> 0.4789916 | G23: =_xlfn.IFERROR(IF(E23=0,0,(D23-E23)/E23),0) -> 0 | H23: =_xlfn.IFERROR(IF(D23>=E23,"✓ Fav","✗ Unfav"),"—") -> ✓ Fav | I23: [Commentary: Enter resident satisfaction drivers and detractors]
B25: MARKETING REPORTS
B26: MKT_16_Marketing_CPA | C26: Blended CPA | D26: =_xlfn.IFERROR(MKT_16_Marketing_CPA!H6,0) -> 230.76923 | F26: =_xlfn.IFERROR(D26-E26,0) -> 230.76923 | G26: =_xlfn.IFERROR(IF(E26=0,0,(E26-D26)/E26),0) -> 0 | H26: =_xlfn.IFERROR(IF(D26<=E26,"✓ Fav","✗ Unfav"),"—") -> ✗ Unfav | I26: [Commentary: Enter channel efficiency and spend optimization]
B27: MKT_17_Attribution | C27: Avg ROAS | D27: =_xlfn.IFERROR(MKT_17_Attribution!F12,0) -> 85.833333 | F27: =_xlfn.IFERROR(D27-E27,0) -> 85.833333 | G27: =_xlfn.IFERROR(IF(E27=0,0,(D27-E27)/E27),0) -> 0 | H27: =_xlfn.IFERROR(IF(D27>=E27,"✓ Fav","✗ Unfav"),"—") -> ✓ Fav | I27: [Commentary: Enter attribution model insights and channel mix]
B29: DEVELOPMENT REPORTS
B30: DEV_18_Project_EV | C30: Portfolio EV | D30: =_xlfn.IFERROR(DEV_18_Project_EV!F8,0) -> 1.9620914e+08 | F30: =_xlfn.IFERROR(D30-E30,0) -> 1.9620914e+08 | G30: =_xlfn.IFERROR(IF(E30=0,0,(D30-E30)/E30),0) -> 0 | H30: =_xlfn.IFERROR(IF(G30>=0,"✓ Fav","✗ Unfav"),"—") -> ✓ Fav | I30: [Commentary: Enter valuation drivers and cap rate assumptions]
B31: DEV_19_Cost_Complete | C31: Budget Variance | D31: =_xlfn.IFERROR(DEV_19_Cost_Complete!G10,0) -> 0 | F31: =_xlfn.IFERROR(D31-E31,0) -> 0 | H31: =_xlfn.IFERROR(IF(D31>=0,"✓ On Track","⚠ Over"),"—") -> ✓ On Track | I31: [Commentary: Enter cost drivers and contingency status]
B32: DEV_20_Entitlement_Risk | C32: High Risk Permits | D32: =_xlfn.IFERROR(COUNTIF(DEV_20_Entitlement_Risk!G5:G10,"High"),0) -> 1 | F32: =_xlfn.IFERROR(D32-E32,0) -> 1 | H32: =_xlfn.IFERROR(IF(D32=0,"✓ Clear","⚠ Risk"),"—") -> ⚠ Risk | I32: [Commentary: Enter permit status and mitigation actions]
B34: CAPITAL MARKETS REPORTS
B35: CAP_21_Investor_Quarterly | C35: FFO Growth YoY | D35: =_xlfn.IFERROR(CAP_21_Investor_Quarterly!F10,0) -> 0.060150376 | F35: =_xlfn.IFERROR(D35-E35,0) -> 0.060150376 | G35: =_xlfn.IFERROR(IF(E35=0,0,(D35-E35)/E35),0) -> 0 | H35: =_xlfn.IFERROR(IF(D35>=E35,"✓ Fav","✗ Unfav"),"—") -> ✓ Fav | I35: [Commentary: Enter investor messaging and distribution guidance]
B37: ESG REPORTS
B38: ESG_22_Sustainability | C38: Metrics On Track | D38: =_xlfn.IFERROR(COUNTIF(ESG_22_Sustainability!F5:F12,"✓ On Track"),0) -> 0 | F38: =_xlfn.IFERROR(D38-E38,0) -> 0 | G38: =_xlfn.IFERROR(IF(E38=0,0,(D38-E38)/E38),0) -> 0 | H38: =_xlfn.IFERROR(IF(D38>=6,"✓ Fav","⚠ Behind"),"—") -> ⚠ Behind | I38: [Commentary: Enter sustainability initiatives and progress]
B40: VARIANCE SUMMARY DASHBOARD
B42: Total Reports: | E42: =_xlfn.IFERROR(COUNTIF(H7:H14,"✓*")+COUNTIF(H17:H23,"✓*")+COUNTIF(H26:H27,"✓*")+COUNTIF(H30:H32,"✓*")+COUNTIF(H35,"✓*")+COUNTIF(H38,"✓*"),"—") -> 15 | G42: =_xlfn.IFERROR(COUNTIF(H7:H14,"✗*")+COUNTIF(H17:H23,"✗*")+COUNTIF(H26:H27,"✗*")+COUNTIF(H30:H32,"✗*")+COUNTIF(H35,"✗*")+COUNTIF(H38,"✗*"),"—") -> 3 | I42: =_xlfn.IFERROR(COUNTIF(H7:H38,"⚠*"),"—") -> 3
B44: OVERALL STATUS: | C44: =_xlfn.IFERROR(IF(G42<=3,"✓ ON TRACK",IF(G42<=5,"⚠ WATCH","✗ ACTION NEEDED")),"—") -> ✓ ON TRACK
B46: COMMENTARY GUIDELINES
B47: • Favorable variances: Explain drivers, sustainability, and outlook
B48: • Unfavorable variances: Root cause, corrective actions, timeline to resolution
B49: • Alerts/Risks: Mitigation strategy, escalation status, resource requirements
B50: • Use specific numbers and dates; avoid vague language
B51: • Reference related reports for cross-functional impacts
B53: Last Updated: | C53: =TEXT(NOW(),"mmmm d, yyyy h:mm AM/PM") -> January 12, 2026 9:41 AM | G53: Prepared by: | H53: [Enter Name]

Sheet Forecast_Reconciliation
A1: FORECAST RECONCILIATION & BRIDGE ANALYSIS
A2: Tracking Budget → Reforecast → Actual with Variance Explanations | Period: January 2026
A4: FORECAST BRIDGE SUMMARY
A6: Original Budget | B6: 585000 | C6: RF1 Adjustment | D6: 15000 | E6: RF2 Adjustment | F6: 8000 | G6: Current Forecast | H6: =B6+D6+F6 -> 608000 | I6: Actual | J6: 621000 | K6: Variance | L6: =J6-H6 -> 13000
A9: RECONCILIATION BY COST CENTER
A10: Cost Center | B10: Orig Budget | C10: RF1 (Q1) | D10: RF1 Δ | E10: RF2 (Q2) | F10: RF2 Δ | G10: Curr Fcst | H10: Actual | I10: Var to CF | J10: Var % | K10: Status | L10: Variance Explanation
A11: REVENUE
A12: 4100 Rental Revenue | B12: 1100000 | C12: 1115000 | D12: =C12-B12 -> 15000 | E12: 1120000 | F12: =E12-C12 -> 5000 | G12: {=E12} -> 1120000 | H12: 1125000 | I12: =H12-G12 -> 5000 | J12: =IF(G12=0,0,(H12-G12)/ABS(G12)) -> 0.0044642857 | K12: =IF(ABS(J12)<=0.03,"✓",IF(ABS(J12)<=0.07,"⚠","✗")) -> ✓ | L12: Occupancy 95.2% vs 94% plan; faster lease-up at Parkside
A13: 4200 Other Income | B13: 50000 | C13: 48000 | D13: =C13-B13 -> -2000 | E13: 46000 | F13: =E13-C13 -> -2000 | G13: {=E13} -> 46000 | H13: 45000 | I13: =H13-G13 -> -1000 | J13: =IF(G13=0,0,(H13-G13)/ABS(G13)) -> -0.02173913 | K13: =IF(ABS(J13)<=0.03,"✓",IF(ABS(J13)<=0.07,"⚠","✗")) -> ✓ | L13: Parking revenue below target; pet fees on track
A14: 4300 Concessions | B14: -35000 | C14: -32000 | D14: =C14-B14 -> 3000 | E14: -30000 | F14: =E14-C14 -> 2000 | G14: {=E14} -> -30000 | H14: -28000 | I14: =H14-G14 -> 2000 | J14: =IF(G14=0,0,(H14-G14)/ABS(G14)) -> 0.066666667 | K14: =IF(ABS(J14)<=0.03,"✓",IF(ABS(J14)<=0.07,"⚠","✗")) -> ⚠ | L14: Strong demand reduced need for concessions
A15: Revenue Subtotal | B15: =SUM(B12:B14) -> 1115000 | C15: =SUM(C12:C14) -> 1131000 | D15: =C15-B15 -> 16000 | E15: =SUM(E12:E14) -> 1136000 | F15: =E15-C15 -> 5000 | G15: =SUM(G12:G14) -> 1136000 | H15: =SUM(H12:H14) -> 1142000 | I15: =H15-G15 -> 6000 | J15: =IF(G15=0,0,(H15-G15)/ABS(G15)) -> 0.0052816901 | K15: 0 | L15: 0
A17: EXPENSES
A18: 5100 Payroll & Benefits | B18: -180000 | C18: -182000 | D18: =C18-B18 -> -2000 | E18: -184000 | F18: =E18-C18 -> -2000 | G18: {=E18} -> -184000 | H18: -185000 | I18: =H18-G18 -> -1000 | J18: =IF(G18=0,0,(H18-G18)/ABS(G18)) -> -0.0054347826 | K18: =IF(ABS(J18)<=0.03,"✓",IF(ABS(J18)<=0.07,"⚠","✗")) -> ✓ | L18: OT for maint backlog; hiring tech Feb to normalize
A19: 5200 Repairs & Maint | B19: -70000 | C19: -68000 | D19: =C19-B19 -> 2000 | E19: -65000 | F19: =E19-C19 -> 3000 | G19: {=E19} -> -65000 | H19: -62000 | I19: =H19-G19 -> 3000 | J19: =IF(G19=0,0,(H19-G19)/ABS(G19)) -> 0.046153846 | K19: =IF(ABS(J19)<=0.03,"✓",IF(ABS(J19)<=0.07,"⚠","✗")) -> ⚠ | L19: Preventive program reducing reactive repairs
A20: 5300 Utilities | B20: -55000 | C20: -52000 | D20: =C20-B20 -> 3000 | E20: -50000 | F20: =E20-C20 -> 2000 | G20: {=E20} -> -50000 | H20: -48000 | I20: =H20-G20 -> 2000 | J20: =IF(G20=0,0,(H20-G20)/ABS(G20)) -> 0.04 | K20: =IF(ABS(J20)<=0.03,"✓",IF(ABS(J20)<=0.07,"⚠","✗")) -> ⚠ | L20: LED retrofit savings; mild weather
A21: 5400 Insurance | B21: -30000 | C21: -31000 | D21: =C21-B21 -> -1000 | E21: -32000 | F21: =E21-C21 -> -1000 | G21: {=E21} -> -32000 | H21: -32000 | I21: =H21-G21 -> 0 | J21: =IF(G21=0,0,(H21-G21)/ABS(G21)) -> 0 | K21: =IF(ABS(J21)<=0.03,"✓",IF(ABS(J21)<=0.07,"⚠","✗")) -> ✓ | L21: Premium increase at renewal; shopping alternatives
A22: 5500 Property Taxes | B22: -85000 | C22: -85000 | D22: =C22-B22 -> 0 | E22: -85000 | F22: =E22-C22 -> 0 | G22: {=E22} -> -85000 | H22: -85000 | I22: =H22-G22 -> 0 | J22: =IF(G22=0,0,(H22-G22)/ABS(G22)) -> 0 | K22: =IF(ABS(J22)<=0.03,"✓",IF(ABS(J22)<=0.07,"⚠","✗")) -> ✓ | L22: On budget; appeal filed for 2027
A23: 5600 Marketing | B23: -28000 | C23: -26000 | D23: =C23-B23 -> 2000 | E23: -25000 | F23: =E23-C23 -> 1000 | G23: {=E23} -> -25000 | H23: -24000 | I23: =H23-G23 -> 1000 | J23: =IF(G23=0,0,(H23-G23)/ABS(G23)) -> 0.04 | K23: =IF(ABS(J23)<=0.03,"✓",IF(ABS(J23)<=0.07,"⚠","✗")) -> ⚠ | L23: Shifted to digital; higher ROI channels
A24: 5700 Professional Fees | B24: -15000 | C24: -16000 | D24: =C24-B24 -> -1000 | E24: -17000 | F24: =E24-C24 -> -1000 | G24: {=E24} -> -17000 | H24: -18000 | I24: =H24-G24 -> -1000 | J24: =IF(G24=0,0,(H24-G24)/ABS(G24)) -> -0.058823529 | K24: =IF(ABS(J24)<=0.03,"✓",IF(ABS(J24)<=0.07,"⚠","✗")) -> ⚠ | L24: Legal fees for lease dispute (one-time)
A25: 5800 Admin & General | B25: -25000 | C25: -24000 | D25: =C25-B25 -> 1000 | E25: -23000 | F25: =E25-C25 -> 1000 | G25: {=E25} -> -23000 | H25: -22000 | I25: =H25-G25 -> 1000 | J25: =IF(G25=0,0,(H25-G25)/ABS(G25)) -> 0.043478261 | K25: =IF(ABS(J25)<=0.03,"✓",IF(ABS(J25)<=0.07,"⚠","✗")) -> ⚠ | L25: Cost control initiatives effective
A26: 5900 Contract Services | B26: -42000 | C26: -43000 | D26: =C26-B26 -> -1000 | E26: -44000 | F26: =E26-C26 -> -1000 | G26: {=E26} -> -44000 | H26: -45000 | I26: =H26-G26 -> -1000 | J26: =IF(G26=0,0,(H26-G26)/ABS(G26)) -> -0.022727273 | K26: =IF(ABS(J26)<=0.03,"✓",IF(ABS(J26)<=0.07,"⚠","✗")) -> ✓ | L26: Landscaping scope expansion; renegotiating Q2
A27: Expense Subtotal | B27: =SUM(B18:B26) -> -530000 | C27: =SUM(C18:C26) -> -527000 | D27: =C27-B27 -> 3000 | E27: =SUM(E18:E26) -> -525000 | F27: =E27-C27 -> 2000 | G27: =SUM(G18:G26) -> -525000 | H27: =SUM(H18:H26) -> -521000 | I27: =H27-G27 -> 4000 | J27: =IF(G27=0,0,(H27-G27)/ABS(G27)) -> 0.0076190476
A29: NET OPERATING INCOME | B29: =B15+B27 -> 585000 | C29: =C15+C27 -> 604000 | D29: =C29-B29 -> 19000 | E29: =E15+E27 -> 611000 | F29: =E29-C29 -> 7000 | G29: =G15+G27 -> 611000 | H29: =H15+H27 -> 621000 | I29: =H29-G29 -> 10000 | J29: =IF(G29=0,0,(H29-G29)/ABS(G29)) -> 0.016366612 | K29: =IF(J29>=0,"✓",IF(J29>=-0.05,"⚠","✗")) -> ✓
A31: MONTHLY FORECAST HISTORY
A32: Period | B32: Orig Budget | C32: RF1 | D32: RF1 Chg | E32: RF2 | F32: RF2 Chg | G32: Curr Fcst | H32: Actual | I32: Variance | J32: Var % | K32: Fcst Acc | L32: Commentary
A33: Jan-26 | B33: 585000 | C33: 600000 | D33: =C33-B33 -> 15000 | E33: 608000 | F33: =E33-C33 -> 8000 | G33: {=E33} -> 608000 | H33: 621000 | I33: =H33-G33 -> 13000 | J33: =IF(G33=0,0,(H33-G33)/G33) -> 0.021381579 | K33: =1-ABS(J33) -> 0.97861842 | L33: Strong start; beat all forecasts
A34: Feb-26 | B34: 590000 | C34: 605000 | D34: =C34-B34 -> 15000 | E34: 612000 | F34: =E34-C34 -> 7000 | G34: {=E34} -> 612000 | H34: — | I34: — | J34: — | K34: — | L34: [Pending]
A35: Mar-26 | B35: 605000 | C35: 618000 | D35: =C35-B35 -> 13000 | E35: 625000 | F35: =E35-C35 -> 7000 | G35: {=E35} -> 625000 | H35: — | I35: — | J35: — | K35: — | L35: [Pending]
A36: Q1 Total | B36: 1780000 | C36: 1823000 | D36: =C36-B36 -> 43000 | E36: 1845000 | F36: =E36-C36 -> 22000 | G36: {=E36} -> 1845000 | H36: — | I36: — | J36: — | K36: — | L36: Q1 forecast tracking ahead
A38: REFORECAST CHANGE LOG
A39: RF # | B39: Date | C39: Impact | D39: Category | F39: Description of Change | K39: Approved By | L39: Status
A40: RF1 | B40: 2026-01-15 | C40: 23000 | D40: Revenue | F40: Increased rental revenue forecast based on Jan occupancy trends (+$15K) and reduced concessions (+$8K) | K40: CFO | L40: ✓ Approved
A41: RF1 | B41: 2026-01-15 | C41: -8000 | D41: Expense | F41: Added payroll for OT (-$2K), increased insurance reserve (-$1K), added legal contingency (-$5K) | K41: CFO | L41: ✓ Approved
A42: RF2 | B42: 2026-02-01 | C42: 14000 | D42: Revenue | F42: Further rental income increase based on Feb pipeline (+$5K), parking adjustment (-$2K), concessions (+$2K) | K42: CFO | L42: ✓ Approved
A43: RF2 | B43: 2026-02-01 | C43: -6000 | D43: Expense | F43: Payroll adjustment (-$2K), insurance finalized (-$1K), legal update (-$1K), contracts (-$1K), offset by savings (+$-1K) | K43: CFO | L43: ✓ Approved
A44: RF3 | B44: 2026-02-15 | C44: 0 | D44: TBD | F44: [Next reforecast scheduled for Feb 15 - will incorporate Jan actuals] | K44: Pending | L44: ⏳ Scheduled
A46: Forecast Accuracy Target: 97% | Current: 97.9% | F46: Last Updated: | G46: =TEXT(NOW(),"mmmm d, yyyy") -> January 12, 2026 | J46: Next RF: | K46: Feb 15, 2026

Sheet Variance_Root_Cause
B1: VARIANCE ROOT CAUSE ANALYSIS
B2: Drill-Down Analysis: Monthly Totals → Cost Centers → Transactions | January 2026
B4: LEVEL 1: TOTAL VARIANCE SUMMARY
B6: Total Variance: | C6: 36000 | E6: Favorable: | F6: 57000 | G6: Unfavorable: | H6: -21000 | I6: Net: | J6: =_xlfn.IFERROR(F6+H6,0) -> 36000
B10: LEVEL 2: CATEGORY BREAKDOWN
B11: Category | C11: Actual | D11: Budget | E11: Variance | F11: Var % | G11: % of Total | H11: Driver | I11: Status | J11: Root Cause Summary
B12: ▼ REVENUE | C12: 425000 | D12: 400000 | E12: =_xlfn.IFERROR(C12-D12,0) -> 25000 | F12: =_xlfn.IFERROR(E12/D12,0) -> 0.0625 | G12: =_xlfn.IFERROR(E12/$E$7,0) -> 0 | H12: Multiple | I12: ✓ | J12: Strong rental income; parking outperformance
B13: Rental Income | C13: 380000 | D13: 365000 | E13: =_xlfn.IFERROR(C13-D13,0) -> 15000 | F13: =_xlfn.IFERROR(E13/D13,0) -> 0.04109589 | G13: =_xlfn.IFERROR(E13/$E$7,0) -> 0 | H13: Rate | I13: ✓ | J13: Higher achieved rents vs budget
B14: Parking Revenue | C14: 28000 | D14: 22000 | E14: =_xlfn.IFERROR(C14-D14,0) -> 6000 | F14: =_xlfn.IFERROR(E14/D14,0) -> 0.27272727 | G14: =_xlfn.IFERROR(E14/$E$7,0) -> 0 | H14: Volume | I14: ✓ | J14: New parking tier pricing effective
B15: Other Income | C15: 17000 | D15: 13000 | E15: =_xlfn.IFERROR(C15-D15,0) -> 4000 | F15: =_xlfn.IFERROR(E15/D15,0) -> 0.30769231 | G15: =_xlfn.IFERROR(E15/$E$7,0) -> 0 | H15: Mix | I15: ✓ | J15: Pet fees and storage rentals up
B16: ▼ EXPENSES | C16: 196000 | D16: 215000 | E16: =_xlfn.IFERROR(C16-D16,0) -> -19000 | F16: =_xlfn.IFERROR(E16/D16,0) -> -0.088372093 | G16: =_xlfn.IFERROR(E16/$E$7,0) -> 0 | H16: Multiple | I16: ✓ | J16: Cost controls effective
B17: Payroll & Benefits | C17: 85000 | D17: 92000 | E17: =_xlfn.IFERROR(C17-D17,0) -> -7000 | F17: =_xlfn.IFERROR(E17/D17,0) -> -0.076086957 | G17: =_xlfn.IFERROR(E17/$E$7,0) -> 0 | H17: Volume | I17: ✓ | J17: Delayed hiring; lower overtime
B18: Repairs & Maintenance | C18: 32000 | D18: 28000 | E18: =_xlfn.IFERROR(C18-D18,0) -> 4000 | F18: =_xlfn.IFERROR(E18/D18,0) -> 0.14285714 | G18: =_xlfn.IFERROR(E18/$E$7,0) -> 0 | H18: Volume | I18: ⚠ | J18: HVAC emergency repairs in Bldg C
B19: Utilities | C19: 24000 | D19: 26000 | E19: =_xlfn.IFERROR(C19-D19,0) -> -2000 | F19: =_xlfn.IFERROR(E19/D19,0) -> -0.076923077 | G19: =_xlfn.IFERROR(E19/$E$7,0) -> 0 | H19: Rate | I19: ✓ | J19: Energy efficiency improvements
B20: Marketing | C20: 18000 | D20: 25000 | E20: =_xlfn.IFERROR(C20-D20,0) -> -7000 | F20: =_xlfn.IFERROR(E20/D20,0) -> -0.28 | G20: =_xlfn.IFERROR(E20/$E$7,0) -> 0 | H20: Timing | I20: ✓ | J20: Campaign shifted to Q2
B21: Admin & G&A | C21: 22000 | D21: 24000 | E21: =_xlfn.IFERROR(C21-D21,0) -> -2000 | F21: =_xlfn.IFERROR(E21/D21,0) -> -0.083333333 | G21: =_xlfn.IFERROR(E21/$E$7,0) -> 0 | H21: Rate | I21: ✓ | J21: Contract renegotiations
B22: Insurance | C22: 15000 | D22: 20000 | E22: =_xlfn.IFERROR(C22-D22,0) -> -5000 | F22: =_xlfn.IFERROR(E22/D22,0) -> -0.25 | G22: =_xlfn.IFERROR(E22/$E$7,0) -> 0 | H22: One-Time | I22: ✓ | J22: Multi-year policy discount
B25: LEVEL 3: COST CENTER DRILL-DOWN (Repairs & Maintenance)
B26: Cost Center | C26: Actual | D26: Budget | H26: Owner | I26: Status | J26: Action Required
B27: Building A - Exterior | C27: 6500 | D27: 7000 | E27: =_xlfn.IFERROR(C27-D27,0) -> -500 | F27: =_xlfn.IFERROR(E27/D27,0) -> -0.071428571 | H27: J. Martinez | I27: ✓ | J27: On track
B28: Building B - Interiors | C28: 5200 | D28: 5500 | E28: =C28-D28 -> -300 | F28: =E28/D28 -> -0.054545455 | G28: Volume | H28: J. Martinez | I28: ✓ | J28: Under budget
B29: Building C - HVAC | C29: 12800 | D29: 6000 | E29: =C29-D29 -> 6800 | F29: =E29/D29 -> 1.1333333 | G29: One-Time | H29: T. Williams | I29: ✗ | J29: Emergency compressor replacement
B30: Building D - Plumbing | C30: 3500 | D30: 4000 | E30: =C30-D30 -> -500 | F30: =E30/D30 -> -0.125 | G30: Rate | H30: J. Martinez | I30: ✓ | J30: Preventive maintenance
B31: Common Areas | C31: 2800 | D31: 3500 | E31: =C31-D31 -> -700 | F31: =E31/D31 -> -0.2 | G31: Volume | H31: S. Chen | I31: ✓ | J31: Deferred to Q2
B32: Landscaping | C32: 1200 | D32: 2000 | E32: =C32-D32 -> -800 | F32: =E32/D32 -> -0.4 | G32: Timing | H32: S. Chen | I32: ✓ | J32: Seasonal savings
B33: TOTAL R&M | C33: =SUM(C27:C32) -> 32000 | D33: =SUM(D27:D32) -> 28000 | E33: =C33-D33 -> 4000 | F33: =E33/D33 -> 0.14285714 | G33: — | H33: — | I33: ⚠ | J33: Net unfavorable due to HVAC
B36: LEVEL 4: TRANSACTION DETAIL (Building C - HVAC Variance: +$6,800)
B37: Date | C37: Vendor | D37: Description | E37: Amount | F37: PO # | G37: GL Code | H37: Approved By | I37: Type | J37: Notes
B38: 01/05/26 | C38: HVAC Solutions Inc | D38: Emergency compressor diagnostic | E38: 850 | F38: PO-2601 | G38: 6200-301 | H38: T. Williams | I38: Service | J38: After-hours call
B39: 01/08/26 | C39: HVAC Solutions Inc | D39: Compressor replacement - parts | E39: 6200 | F39: PO-2605 | G39: 6200-301 | H39: VP Ops | I39: Capital | J39: RTU-C3 unit failure
B40: 01/09/26 | C40: HVAC Solutions Inc | D40: Compressor replacement - labor | E40: 2800 | F40: PO-2605 | G40: 6200-301 | H40: VP Ops | I40: Service | J40: 8-hour install
B41: 01/12/26 | C41: TempControl Services | D41: Temporary cooling rental | E41: 1500 | F41: PO-2608 | G41: 6200-302 | H41: T. Williams | I41: Rental | J41: 3-day rental
B42: 01/15/26 | C42: HVAC Solutions Inc | D42: System testing & calibration | E42: 950 | F42: PO-2612 | G42: 6200-301 | H42: T. Williams | I42: Service | J42: Final commissioning
B43: 01/20/26 | C43: Building Systems Co | D43: Preventive maintenance - other units | E43: 500 | F43: PO-2615 | G43: 6200-301 | H43: J. Martinez | I43: Service | J43: Scheduled PM
D44: TOTAL HVAC SPEND (Jan) | E44: =_xlfn.IFERROR(SUM(E38:E43),0) -> 12800 | J44: Budget: $6,000
B47: DRIVER TYPE LEGEND | F47: ROOT CAUSE ANALYSIS SUMMARY
B48: Volume | C48: Quantity-driven variance (more/fewer units, hours, etc.) | F48: Primary Driver: | G48: One-Time (HVAC failure = 67% of unfavorable)
B49: Rate | C49: Price-driven variance (higher/lower unit cost) | F49: Secondary: | G49: Volume variances in labor & maintenance
B50: Mix | C50: Product/service mix shift affecting margins | F50: Offsetting: | G50: Rate savings from contract renegotiations
B51: Timing | C51: Planned spend shifted to different period | F51: Recommendation: | G51: Increase PM budget for aging equipment
B52: One-Time | C52: Non-recurring item (emergency, settlement, etc.) | F52: Risk: | G52: Building A HVAC showing similar wear patterns
B55: ACTION ITEMS FROM ROOT CAUSE ANALYSIS
B56: # | C56: Action | D56: Owner | E56: Due Date | F56: Status | G56: Impact | H56: 0 | I56: 0 | J56: 0
B57: 1 | C57: Submit capital request for Bldg A HVAC replacement | D57: T. Williams | E57: 02/15/26 | F57: In Progress | G57: $45K preventive
B58: 2 | C58: Review vendor contracts for emergency service rates | D58: J. Martinez | E58: 01/31/26 | F58: Open | G58: Est. 15% savings
B59: 3 | C59: Update preventive maintenance schedule | D59: S. Chen | E59: 01/25/26 | F59: Complete | G59: Risk mitigation
B60: 4 | C60: Implement real-time equipment monitoring | D60: VP Ops | E60: Q2 2026 | F60: Planning | G60: $20K investment

Sheet Daily_Leasing_Flash
A1: DAILY LEASING FLASH
A2: Executive Morning Briefing | Updated: 1/11/2026
A4: HEADLINE METRICS
A5: Occupancy | C5: NER | E5: MTD Leases | G5: Lead→Lease
A6: {=OPS_11_Occupancy_Mix!D12} -> 0.95219124 | C6: {=OPS_11_Occupancy_Mix!G12} -> 1814.3724 | E6: {=OPS_10_Leasing_Funnel!E12} -> 104 | G6: {=OPS_10_Leasing_Funnel!I12} -> 0.090356212
A8: LEASING FUNNEL (MTD) | F8: MARKETING PERFORMANCE
A9: Stage | B9: Count | C9: Conversion | D9: vs Target | F9: Metric | G9: Value | H9: Status
A10: Leads | B10: {=OPS_10_Leasing_Funnel!B12} -> 1151 | C10: — | D10: — | F10: Total Spend (MTD) | G10: {=MKT_16_Marketing_CPA!B6} -> 24000 | H10: —
A11: Tours | B11: {=OPS_10_Leasing_Funnel!C12} -> 401 | C11: {=OPS_10_Leasing_Funnel!F12} -> 0.3483927 | D11: =C11-0.35 -> -0.001607298 | F11: Cost Per Lead | G11: {=MKT_16_Marketing_CPA!D6} -> 20.851434 | H11: =IF(G11<=25,"✓ On Track","⚠ High") -> ✓ On Track
A12: Applications | B12: {=OPS_10_Leasing_Funnel!D12} -> 231 | C12: {=OPS_10_Leasing_Funnel!G12} -> 0.57605985 | D12: =C12-0.55 -> 0.02605985 | F12: Cost Per Acquisition | G12: {=MKT_16_Marketing_CPA!H6} -> 230.76923 | H12: =IF(G12<=300,"✓ On Track","⚠ High") -> ✓ On Track
A13: Leases | B13: {=OPS_10_Leasing_Funnel!E12} -> 104 | C13: {=OPS_10_Leasing_Funnel!H12} -> 0.45021645 | D13: =C13-0.45 -> 0.00021645022 | F13: LTV:CAC Ratio | G13: {=MKT_16_Marketing_CPA!B28} -> 311.31353 | H13: =IF(G13>=3,"✓ Healthy","⚠ Low") -> ✓ Healthy
A15: ⚠ ACTION REQUIRED
A16: Priority | B16: Alert | C16: Metric | D16: Value | E16: Threshold | F16: Owner | G16: Due
A17: 🔴 HIGH | B17: Lead Response SLA | C17: Contacts <1hr | D17: 78% | E17: >90% | F17: Leasing Mgr | G17: Today
A18: 🟡 MED | B18: Stale Leads | C18: No contact 48hrs | D18: 23 | E18: <15 | F18: Leasing Team | G18: Tomorrow
A19: 🟡 MED | B19: Expiring Leases | C19: No renewal offer | D19: 12 | E19: 0 | F19: Renewals Coord | G19: This Week
A21: TODAY'S ACTIVITY SNAPSHOT | F21: TOP CHANNELS BY LEASES
A22: Metric | B22: Today | C22: WTD | D22: MTD | F22: Channel | G22: Leases | H22: CPA
A23: New Leads | B23: 18 | C23: 85 | D23: 1151 | F23: Direct/Organic | G23: {=OPS_10_Leasing_Funnel!E9} -> 32 | H23: {=MKT_16_Marketing_CPA!H14} -> 0
A24: Tours Completed | B24: 6 | C24: 32 | D24: 401 | F24: Referral | G24: {=OPS_10_Leasing_Funnel!E10} -> 19 | H24: {=MKT_16_Marketing_CPA!H15} -> 26.315789
A25: Apps Submitted | B25: 3 | C25: 18 | D25: 231 | F25: ILS (Apartments.com) | G25: {=OPS_10_Leasing_Funnel!E5} -> 18 | H25: {=MKT_16_Marketing_CPA!H10} -> 472.22222
A26: Leases Signed | B26: 2 | C26: 8 | D26: 104
A27: Move-Ins | B27: 1 | C27: 5 | D27: 19
A28: Move-Outs | B28: 0 | C28: 3 | D28: 12
A30: Data Sources: OPS_09, OPS_10, OPS_11, MKT_16 | Auto-refreshes daily at 6:00 AM

Sheet Portfolio_Summary
A1: PORTFOLIO SUMMARY DASHBOARD
A2: YTD Performance vs Plan | As of January 2026
A4: FINANCIAL PERFORMANCE | I4: EXECUTIVE SUMMARY
A5: Metric | B5: YTD Actual | C5: YTD Plan | D5: Variance $ | E5: Variance % | F5: Status | G5: Source | I5: Portfolio Occupancy | J5: {=B15} -> 0.95219124
A6: Total Revenue | B6: {=FIN_01_Investor_Pack!E7} -> 0 | C6: 52500000 | D6: =B6-C6 -> -52500000 | E6: =IF(C6=0,0,(B6-C6)/C6) -> -1 | F6: =IF(E6>=0,"✓","✗") -> ✗ | G6: FIN_01 | I6: Avg NER | J6: {=B16} -> 1814.3724
A7: Net Operating Income | B7: {=FIN_01_Investor_Pack!E21} -> 7715000 | C7: 32000000 | D7: =B7-C7 -> -24285000 | E7: =IF(C7=0,0,(B7-C7)/C7) -> -0.75890625 | F7: =IF(E7>=0,"✓","✗") -> ✗ | G7: FIN_01 | I7: NOI Margin | J7: {=B8} -> 0
A8: NOI Margin % | B8: =IF(B6=0,0,B7/B6) -> 0 | C8: 0.61 | D8: =B8-C8 -> -0.61 | E8: =IF(C8=0,0,(B8-C8)/C8) -> -1 | F8: =IF(E8>=0,"✓","✗") -> ✗ | G8: Calculated | I8: Same-Store Growth | J8: {=B10} -> 0.035689774
A9: FFO | B9: {=FIN_01_Investor_Pack!E34} -> 100000 | C9: 28000000 | D9: =B9-C9 -> -27900000 | E9: =IF(C9=0,0,(B9-C9)/C9) -> -0.99642857 | F9: =IF(E9>=0,"✓","✗") -> ✗ | G9: FIN_01 | I9: DSCR | J9: {=B11} -> 2.85
A10: Same-Store NOI Growth | B10: {=FIN_01_Investor_Pack!E58} -> 0.035689774 | C10: 0.025 | D10: =B10-C10 -> 0.010689774 | E10: =IF(C10=0,0,(B10-C10)/C10) -> 0.42759094 | F10: =IF(E10>=0,"✓","✗") -> ✓ | G10: FIN_01 | I10: Blended CPA | J10: {=B27} -> 230.76923
A11: Debt Service Coverage | B11: {=FIN_01_Investor_Pack!C63} -> 2.85 | C11: 1.4 | D11: =(B11-C11) -> 1.45 | E11: =IF(C11=0,0,(B11-C11)/C11) -> 1.0357143 | F11: =IF(E11>=0,"✓","✗") -> ✓ | G11: FIN_01 | I11: Renewal Rate | J11: {=B18} -> 0.72727273
I12: WO Avg Time | J12: {=B20} -> 19.392509
A13: OPERATIONS PERFORMANCE
A14: Metric | B14: YTD Actual | C14: YTD Plan | D14: Variance | E14: Variance % | F14: Status | G14: Source
A15: Occupancy % | B15: {=OPS_11_Occupancy_Mix!D12} -> 0.95219124 | C15: 0.94 | D15: =B15-C15 -> 0.012191235 | E15: =IF(C15=0,0,(B15-C15)/C15) -> 0.012969399 | F15: =IF(E15>=0,"✓","✗") -> ✓ | G15: OPS_11
A16: Avg NER | B16: {=OPS_11_Occupancy_Mix!G12} -> 1814.3724 | C16: 1780 | D16: =B16-C16 -> 34.372385 | E16: =IF(C16=0,0,(B16-C16)/C16) -> 0.019310329 | F16: =IF(E16>=0,"✓","✗") -> ✓ | G16: OPS_11
A17: Lead→Lease Conversion | B17: {=OPS_10_Leasing_Funnel!I12} -> 0.090356212 | C17: 0.08 | D17: =B17-C17 -> 0.010356212 | E17: =IF(C17=0,0,(B17-C17)/C17) -> 0.12945265 | F17: =IF(E17>=0,"✓","✗") -> ✓ | G17: OPS_10
A18: Renewal Rate | B18: {=OPS_12_Renewal_Retention!D10} -> 0.72727273 | C18: 0.7 | D18: =B18-C18 -> 0.027272727 | E18: =IF(C18=0,0,(B18-C18)/C18) -> 0.038961039 | F18: =IF(E18>=0,"✓","✗") -> ✓ | G18: OPS_12
A19: TTM Retention Rate | B19: {=OPS_12_Renewal_Retention!H13} -> 0.69583333 | C19: 0.68 | D19: =B19-C19 -> 0.015833333 | E19: =IF(C19=0,0,(B19-C19)/C19) -> 0.023284314 | F19: =IF(E19>=0,"✓","✗") -> ✓ | G19: OPS_12
A20: Avg WO Completion (hrs) | B20: {=OPS_14_Maintenance_WO!E11} -> 19.392509 | C20: 24 | D20: =B20-C20 -> -4.6074906 | E20: =IF(C20=0,0,(C20-B20)/C20) -> 0.19197878 | F20: =IF(E20>=0,"✓","✗") -> ✓ | G20: OPS_14
A21: Emergency SLA % | B21: {=OPS_14_Maintenance_WO!E15} -> 0.95238095 | C21: 0.95 | D21: =B21-C21 -> 0.0023809524 | E21: =IF(C21=0,0,(B21-C21)/C21) -> 0.0025062657 | F21: =IF(E21>=0,"✓","✗") -> ✓ | G21: OPS_14
A23: MARKETING PERFORMANCE
A24: Metric | B24: YTD Actual | C24: YTD Plan | D24: Variance | E24: Variance % | F24: Status | G24: Source
A25: Total Marketing Spend | B25: {=MKT_16_Marketing_CPA!B6} -> 24000 | C25: 28000 | D25: =B25-C25 -> -4000 | E25: =IF(C25=0,0,(C25-B25)/C25) -> 0.14285714 | F25: =IF(E25>=0,"✓","✗") -> ✓ | G25: MKT_16
A26: Cost Per Lead (CPL) | B26: {=MKT_16_Marketing_CPA!D6} -> 20.851434 | C26: 25 | D26: =B26-C26 -> -4.1485665 | E26: =IF(C26=0,0,(C26-B26)/C26) -> 0.16594266 | F26: =IF(E26>=0,"✓","✗") -> ✓ | G26: MKT_16
A27: Cost Per Acquisition (CPA) | B27: {=MKT_16_Marketing_CPA!H6} -> 230.76923 | C27: 300 | D27: =B27-C27 -> -69.230769 | E27: =IF(C27=0,0,(C27-B27)/C27) -> 0.23076923 | F27: =IF(E27>=0,"✓","✗") -> ✓ | G27: MKT_16
A28: Total Leads | B28: {=MKT_16_Marketing_CPA!C6} -> 1151 | C28: 1200 | D28: =B28-C28 -> -49 | E28: =IF(C28=0,0,(B28-C28)/C28) -> -0.040833333 | F28: =IF(E28>=0,"✓","✗") -> ✗ | G28: MKT_16
A29: Total Leases | B29: {=MKT_16_Marketing_CPA!G6} -> 104 | C29: 95 | D29: =B29-C29 -> 9 | E29: =IF(C29=0,0,(B29-C29)/C29) -> 0.094736842 | F29: =IF(E29>=0,"✓","✗") -> ✓ | G29: MKT_16
A30: LTV:CAC Ratio | B30: {=MKT_16_Marketing_CPA!B28} -> 311.31353 | C30: 3 | D30: =B30-C30 -> 308.31353 | E30: =IF(C30=0,0,(B30-C30)/C30) -> 102.77118 | F30: =IF(E30>=0,"✓","✗") -> ✓ | G30: MKT_16

Sheet Data_Validation
A1: DATA VALIDATION & UPLOAD MONITORING
A2: Daily CSV upload status, field mapping validation, and error tracking
A4: DAILY UPLOAD STATUS | J4: VALIDATION SUMMARY
A5: Template | B5: File Pattern | C5: Expected Frequency | D5: Last Upload | E5: Records | F5: Status | G5: Errors | H5: Action | J5: Templates Active | K5: 5
A6: RentRoll.csv | B6: *_RentRoll.csv | C6: Daily 6AM | D6: 2026-01-11 06:02 | E6: 251 | F6: ✓ OK | G6: 0 | H6: =_xlfn.IFERROR(IF(G6>0,"Review Errors",IF(F6="⚠ STALE","Check Source","—")),"—") -> — | J6: Total Fields Tracked | K6: =_xlfn.IFERROR(SUM(B14:B18),"—") -> 60
A7: LeasingActivity.csv | B7: *_Leasing.csv | C7: Daily 6PM | D7: 2026-01-10 18:15 | E7: 1 | F7: ⚠ STALE | G7: 0 | H7: =_xlfn.IFERROR(IF(G7>0,"Review Errors",IF(F7="⚠ STALE","Check Source","—")),"—") -> Check Source | J7: Fields Mapped | K7: =_xlfn.IFERROR(SUM(C14:C18),"—") -> 59
A8: Marketing.csv | B8: *_Marketing.csv | C8: Weekly Mon | D8: 2026-01-06 09:00 | E8: 7 | F8: ✓ OK | G8: 2 | H8: =_xlfn.IFERROR(IF(G8>0,"Review Errors",IF(F8="⚠ STALE","Check Source","—")),"—") -> Review Errors | J8: Overall Mapping % | K8: =_xlfn.IFERROR(IF(K6=0,0,K7/K6),"—") -> 0.98333333
A9: Maintenance.csv | B9: *_Maintenance.csv | C9: Daily 7AM | D9: 2026-01-11 07:05 | E9: 95 | F9: ✓ OK | G9: 1 | H9: =_xlfn.IFERROR(IF(G9>0,"Review Errors",IF(F9="⚠ STALE","Check Source","—")),"—") -> Review Errors | J9: Open Errors | K9: =_xlfn.IFERROR(SUM(G6:G10),"—") -> 3
A10: Financials.csv | B10: *_Financials.csv | C10: Monthly 5th | D10: 2026-01-05 08:30 | E10: 48 | F10: ✓ OK | G10: 0 | H10: =_xlfn.IFERROR(IF(G10>0,"Review Errors",IF(F10="⚠ STALE","Check Source","—")),"—") -> — | J10: Stale Uploads | K10: =_xlfn.IFERROR(COUNTIF(F6:F10,"⚠ STALE"),"—") -> 1
J11: Overall Quality Score | K11: =_xlfn.IFERROR(AVERAGE(C30:C34),"—") -> 0.9516
A12: FIELD MAPPING VALIDATION
A13: Template | B13: Required Fields | C13: Fields Mapped | D13: Missing | E13: Mapping % | F13: Status
A14: RentRoll.csv | B14: 16 | C14: 16 | D14: =_xlfn.IFERROR(B14-C14,"—") -> 0 | E14: =_xlfn.IFERROR(IF(B14=0,0,C14/B14),"—") -> 1 | F14: =_xlfn.IFERROR(IF(E14=1,"✓ Complete",IF(E14>=0.9,"⚠ Partial","✗ Missing")),"—") -> ✓ Complete
A15: LeasingActivity.csv | B15: 12 | C15: 12 | D15: =_xlfn.IFERROR(B15-C15,"—") -> 0 | E15: =_xlfn.IFERROR(IF(B15=0,0,C15/B15),"—") -> 1 | F15: =_xlfn.IFERROR(IF(E15=1,"✓ Complete",IF(E15>=0.9,"⚠ Partial","✗ Missing")),"—") -> ✓ Complete
A16: Marketing.csv | B16: 10 | C16: 10 | D16: =_xlfn.IFERROR(B16-C16,"—") -> 0 | E16: =_xlfn.IFERROR(IF(B16=0,0,C16/B16),"—") -> 1 | F16: =_xlfn.IFERROR(IF(E16=1,"✓ Complete",IF(E16>=0.9,"⚠ Partial","✗ Missing")),"—") -> ✓ Complete
A17: Maintenance.csv | B17: 8 | C17: 8 | D17: =_xlfn.IFERROR(B17-C17,"—") -> 0 | E17: =_xlfn.IFERROR(IF(B17=0,0,C17/B17),"—") -> 1 | F17: =_xlfn.IFERROR(IF(E17=1,"✓ Complete",IF(E17>=0.9,"⚠ Partial","✗ Missing")),"—") -> ✓ Complete
A18: Financials.csv | B18: 14 | C18: 13 | D18: =_xlfn.IFERROR(B18-C18,"—") -> 1 | E18: =_xlfn.IFERROR(IF(B18=0,0,C18/B18),"—") -> 0.92857143 | F18: =_xlfn.IFERROR(IF(E18=1,"✓ Complete",IF(E18>=0.9,"⚠ Partial","✗ Missing")),"—") -> ⚠ Partial
A20: ERROR LOG (LAST 7 DAYS)
A21: Date | B21: Template | C21: Error Type | D21: Field | E21: Count | F21: Severity | G21: Status | H21: Resolution
A22: 2026-01-11 | B22: Maintenance.csv | C22: Missing Value | D22: priority | E22: 1 | F22: Medium | G22: Open | H22: —
A23: 2026-01-10 | B23: Marketing.csv | C23: Invalid Format | D23: spend_amount | E23: 2 | F23: Low | G23: Resolved | H23: Corrected source
A24: 2026-01-09 | B24: RentRoll.csv | C24: Duplicate Key | D24: unit_id | E24: 3 | F24: High | G24: Resolved | H24: Deduped
A25: 2026-01-08 | B25: Financials.csv | C25: Out of Range | D25: revenue | E25: 1 | F25: Critical | G25: Resolved | H25: Data corrected
A26: 2026-01-07 | B26: LeasingActivity.csv | C26: Type Mismatch | D26: tours_completed | E26: 2 | F26: Medium | G26: Resolved | H26: Cast to INT
A28: DATA QUALITY SCORECARD
A29: Metric | B29: Target | C29: Actual | D29: Status | E29: Trend (7d)
A30: Completeness (all required fields) | B30: 1 | C30: 0.987 | D30: =_xlfn.IFERROR(IF(C30>=B30,"✓ PASS",IF(C30>=B30*0.95,"⚠ WARN","✗ FAIL")),"—") -> ⚠ WARN | E30: ↑ +0.2%
A31: Timeliness (on-time uploads) | B31: 1 | C31: 0.8 | D31: =_xlfn.IFERROR(IF(C31>=B31,"✓ PASS",IF(C31>=B31*0.95,"⚠ WARN","✗ FAIL")),"—") -> ✗ FAIL | E31: ↓ -20%
A32: Accuracy (no errors) | B32: 0.99 | C32: 0.978 | D32: =_xlfn.IFERROR(IF(C32>=B32,"✓ PASS",IF(C32>=B32*0.95,"⚠ WARN","✗ FAIL")),"—") -> ⚠ WARN | E32: ↑ +0.5%
A33: Consistency (format compliance) | B33: 1 | C33: 0.995 | D33: =_xlfn.IFERROR(IF(C33>=B33,"✓ PASS",IF(C33>=B33*0.95,"⚠ WARN","✗ FAIL")),"—") -> ⚠ WARN | E33: → 0%
A34: Uniqueness (no duplicates) | B34: 1 | C34: 0.998 | D34: =_xlfn.IFERROR(IF(C34>=B34,"✓ PASS",IF(C34>=B34*0.95,"⚠ WARN","✗ FAIL")),"—") -> ⚠ WARN | E34: ↑ +0.1%

Sheet Dashboard
A1: PATRY ENTERPRISE DASHBOARD
A2: Reports by Division | Click sheet tabs to navigate
A4: FINANCE & PORTFOLIO
A5: # | B5: Report | C5: Cadence | D5: Owner
A6: 1 | B6: Consolidated Financial Statements / Investor Pack | C6: Quarterly | D6: CFO
A7: 2 | B7: Monthly Portfolio NOI Pack | C7: Monthly | D7: Asset Mgr
A8: 3 | B8: Rent Roll & Lease Expirations | C8: Monthly+Daily | D8: Ops
A9: 4 | B9: Budget vs Actual / Variance Analysis | C9: Monthly | D9: Finance
A10: 5 | B10: 12-Month Cash Flow Forecast & Liquidity | C10: Monthly | D10: CFO
A11: 6 | B11: Capex Pipeline & Spend vs Budget | C11: Monthly | D11: Asset Mgr
A12: 7 | B12: Debt / Covenant Compliance | C12: Monthly | D12: CFO
A13: 8 | B13: Accounts Receivable & Bad Debt Rollup | C13: Monthly | D13: Finance
A15: LEASING / OPS / MARKETING
A16: # | B16: Report | C16: Cadence | D16: Owner
A17: 9 | B17: Property Leasing One-Pager | C17: Daily | D17: Ops Mgr
A18: 10 | B18: Leasing Funnel & Conversion Dashboard | C18: Daily | D18: Leasing Dir
A19: 11 | B19: Occupancy & Unit Mix / Floorplan Performance | C19: Monthly | D19: Asset Mgr
A20: 12 | B20: Renewal & Retention Report | C20: Monthly | D20: Ops Dir
A21: 13 | B21: Turnover & Make-Ready Cost Report | C21: Monthly | D21: Ops Dir
A22: 14 | B22: Maintenance Work Order & Backlog | C22: Daily | D22: Maint Dir
A23: 15 | B23: Resident Satisfaction & NPS | C23: Monthly | D23: Ops Dir
A24: 16 | B24: Marketing Performance & CPA Dashboard | C24: Daily | D24: Mkt Dir
A25: 17 | B25: Source-to-Lease Attribution | C25: Monthly | D25: Mkt Dir
A27: DEVELOPMENT / CONSTRUCTION
A28: # | B28: Report | C28: Cadence | D28: Owner
A29: 18 | B29: Project Status & Earned Value Report | C29: Weekly | D29: Dev Dir
A30: 19 | B30: Cost to Complete / Cashflow by Project | C30: Monthly | D30: Dev Dir
A31: 20 | B31: Entitlement & Risk Register | C31: Monthly | D31: Dev Dir
A33: CAPITAL MARKETS / GOVERNANCE / ESG
A34: # | B34: Report | C34: Cadence | D34: Owner
A35: 21 | B35: Investor Quarterly Pack & Asset Highlights | C35: Quarterly | D35: IR
A36: 22 | B36: ESG / Sustainability & Safety Report | C36: Quarterly | D36: ESG Mgr
A38: SUGGESTED ADDITIONAL REPORTS
A39: # | B39: Report | C39: Cadence | D39: Division
A40: 23 | B40: Tax & 1099 Reporting Pack | C40: Annual | D40: Finance
A41: 24 | B41: Insurance Renewal & Claims Tracker | C41: Quarterly | D41: Finance
A42: 25 | B42: Utility Cost Analysis & Benchmarking | C42: Monthly | D42: Finance
A43: 26 | B43: Competitor Market Survey | C43: Weekly | D43: Leasing
A44: 27 | B44: Amenity Utilization Report | C44: Monthly | D44: Ops
A45: 28 | B45: Lease Audit & Compliance | C45: Quarterly | D45: Ops
A46: 29 | B46: Vendor Performance Scorecard | C46: Quarterly | D46: Ops
A47: 30 | B47: Staff Productivity & Training | C47: Monthly | D47: Ops
A48: 31 | B48: Reputation Management (Reviews) | C48: Daily | D48: Marketing
A49: 32 | B49: SEO & Organic Traffic Report | C49: Monthly | D49: Marketing
A50: 33 | B50: Social Media Engagement | C50: Weekly | D50: Marketing
A51: 34 | B51: Permit & Inspection Tracker | C51: Weekly | D51: Development
... A57: 40 | B57: Diversity & Inclusion Report | C57: Quarterly | D57: ESG
A59: COMBINED EXECUTIVE PACKS (Multi-Report Bundles)
A60: Pack | B60: Included Reports | C60: Audience | D60: Cadence
A61: Weekly Ops Deck | B61: #9,10,14,16 (Leasing, Funnel, Maint, Marketing) | C61: Ops Director | D61: Weekly
A62: Monthly Asset Review | B62: #2,3,4,11,12,13 (NOI, Rent Roll, Variance, Occ, Renewal, Turn) | C62: Asset Manager | D62: Monthly
A63: Quarterly Board Pack | B63: #1,2,7,21,22 (Investor, NOI, Covenant, IR, ESG) | C63: Board/Investors | D63: Quarterly
A64: Daily Leasing Flash | B64: #9,10,16 (One-Pager, Funnel, CPA) | C64: Leasing Team | D64: Daily
A65: Monthly Marketing ROI | B65: #16,17,31,32 (CPA, Attribution, Reviews, SEO) | C65: CMO | D65: Monthly
A66: Development Status Pack | B66: #18,19,20,34 (EV, Cost, Risk, Permits) | C66: Dev Director | D66: Weekly
A67: Annual Investor Report | B67: #1,21,22,37 (Financials, IR Pack, ESG, Insurance) | C67: Investors | D67: Annual

Sheet _TOC
A1: PATRY ENTERPRISE REPORTING SYSTEM - ARCHITECTURE SPECIFICATION
A2: Version 1.0 | Created: January 11, 2026 | 22 Reports | Daily Update Cadence
A4: TABLE OF CONTENTS
A6: # | B6: Sheet Name | C6: Report Title | D6: Category | E6: Cadence | F6: Owner | G6: Status
A7: 1 | B7: FIN_01_Investor_Pack | C7: Consolidated Financial Statements / Investor Pack | D7: Finance | E7: Quarterly | F7: CFO | G7: Template
A8: 2 | B8: FIN_02_NOI_Pack | C8: Monthly Portfolio NOI Pack | D8: Finance | E8: Monthly | F8: Asset Mgr | G8: Template
A9: 3 | B9: FIN_03_Rent_Roll | C9: Rent Roll & Lease Expirations | D9: Finance | E9: Monthly+Daily | F9: Ops | G9: Template
A10: 4 | B10: FIN_04_Budget_Variance | C10: Budget vs Actual / Variance Analysis | D10: Finance | E10: Monthly | F10: Finance | G10: Template
A11: 5 | B11: FIN_05_Cash_Flow | C11: 12-Month Cash Flow Forecast & Liquidity | D11: Finance | E11: Monthly | F11: CFO | G11: Template
A12: 6 | B12: FIN_06_Capex | C12: Capex Pipeline & Spend vs Budget | D12: Finance | E12: Monthly | F12: Asset Mgr | G12: Template
A13: 7 | B13: FIN_07_Debt_Covenant | C13: Debt / Covenant Compliance | D13: Finance | E13: Monthly | F13: CFO | G13: Template
A14: 8 | B14: FIN_08_AR_Bad_Debt | C14: Accounts Receivable & Bad Debt Rollup | D14: Finance | E14: Monthly | F14: Finance | G14: Template
A15: 9 | B15: OPS_09_Leasing_OnePager | C15: Property Leasing One-Pager | D15: Leasing | E15: Daily | F15: Ops Mgr | G15: Template
A16: 10 | B16: OPS_10_Leasing_Funnel | C16: Leasing Funnel & Conversion Dashboard | D16: Leasing | E16: Daily | F16: Leasing Dir | G16: Template
A17: 11 | B17: OPS_11_Occupancy_Mix | C17: Occupancy & Unit Mix / Floorplan Performance | D17: Leasing | E17: Monthly | F17: Asset Mgr | G17: Template
A18: 12 | B18: OPS_12_Renewal_Retention | C18: Renewal & Retention Report | D18: Leasing | E18: Monthly | F18: Ops Dir | G18: Template
... A28: 22 | B28: ESG_22_Sustainability | C28: ESG / Sustainability & Safety Report | D28: ESG | E28: Quarterly | F28: ESG Mgr | G28: Template
A31: SYSTEM SHEETS
A33: SYS | B33: _CSV_Templates | C33: CSV Upload Templates & Schemas | D33: Data Ingestion | E33: — | F33: Admin | G33: Template
A34: SYS | B34: _KPI_Dictionary | C34: KPI Definitions & Business Rules | D34: Reference | E34: — | F34: Admin | G34: Template
A35: SYS | B35: _Alert_Rules | C35: Alert Thresholds & Notification Rules | D35: Alerting | E35: — | F35: Admin | G35: Template
A36: SYS | B36: _Access_Matrix | C36: Role-Based Access & Distribution | D36: Governance | E36: — | F36: Admin | G36: Template
A37: SYS | B37: _Validation_Log | C37: Data Validation & Reconciliation Log | D37: Quality | E37: Daily | F37: System | G37: Template

Sheet _CSV_Templates
A1: CSV UPLOAD TEMPLATES & DATA SCHEMAS
A2: File naming: YYYYMMDD_<PropertyID>_<DataType>.csv | Example: 20260115_150Marketplace_Leasing.csv
A4: TEMPLATE 1: RentRoll.csv
A5: Field Name | B5: Data Type | C5: Required | D5: Validation Rule | E5: Example | F5: Notes
A6: property_id | B6: STRING | C6: Yes | D6: Non-empty, valid property code | E6: 150MKT | F6: Unique property identifier
A7: property_name | B7: STRING | C7: Yes | D7: Non-empty | E7: 150 Marketplace | F7: Full property name
A8: unit_id | B8: STRING | C8: Yes | D8: Unique per property | E8: 101 | F8: Unit number
A9: unit_type | B9: STRING | C9: Yes | D9: Studio|1BR|1BR+Den|2BR|3BR | E9: 1BR+Den | F9: Floorplan category
A10: sqft | B10: INTEGER | C10: Yes | D10: >0 and <10000 | E10: 875 | F10: Unit square footage
A11: floor | B11: INTEGER | C11: No | D11: >=0 | E11: 5 | F11: Floor number
A12: status | B12: STRING | C12: Yes | D12: Leased|Available|Notice|Down|Model | E12: Leased | F12: Current unit status
A13: lease_start_date | B13: DATE | C13: Cond | D13: YYYY-MM-DD, if Leased | E13: 2025-06-01 | F13: Current lease start
A14: lease_end_date | B14: DATE | C14: Cond | D14: YYYY-MM-DD, >= lease_start | E14: 2026-05-31 | F14: Current lease end
A15: contract_rent | B15: DECIMAL | C15: Cond | D15: >0 if Leased | E15: 2350 | F15: Monthly contract rent
A16: market_rent | B16: DECIMAL | C16: Yes | D16: >0 | E16: 2495 | F16: Current market/asking rent
A17: concession_monthly | B17: DECIMAL | C17: No | D17: >=0 | E17: 100 | F17: Monthly concession amount
A18: net_effective_rent | B18: DECIMAL | C18: Calc | D18: contract-(concession/term) | E18: 2266.67 | F18: NER calculation
A19: resident_id | B19: STRING | C19: Cond | D19: If Leased | E19: RES-45678 | F19: Resident identifier
A20: move_in_date | B20: DATE | C20: Cond | D20: YYYY-MM-DD if occupied | E20: 2025-06-15 | F20: Actual move-in
A21: timestamp | B21: DATETIME | C21: Yes | D21: ISO 8601 | E21: 2026-01-11T09:00:00 | F21: Extraction time
A23: TEMPLATE 2: LeasingActivity.csv
A24: Field Name | B24: Data Type | C24: Required | D24: Validation Rule | E24: Example | F24: Notes
A25: property_id | B25: STRING | C25: Yes | D25: Valid property code | E25: 150MKT | F25: Property identifier
A26: report_date | B26: DATE | C26: Yes | D26: YYYY-MM-DD | E26: 2026-01-11 | F26: Activity date
A27: new_leads | B27: INTEGER | C27: Yes | D27: >=0 | E27: 12 | F27: Guest cards created
A28: leads_contacted_1hr | B28: INTEGER | C28: Yes | D28: <=new_leads | E28: 10 | F28: Contacted within 1hr
A29: tours_scheduled | B29: INTEGER | C29: Yes | D29: >=0 | E29: 8 | F29: Tours scheduled
A30: tours_completed | B30: INTEGER | C30: Yes | D30: >=0 | E30: 6 | F30: Tours completed
A31: apps_submitted | B31: INTEGER | C31: Yes | D31: >=0 | E31: 3 | F31: Apps submitted
A32: apps_approved | B32: INTEGER | C32: Yes | D32: >=0 | E32: 2 | F32: Apps approved
A33: leases_signed | B33: INTEGER | C33: Yes | D33: >=0 | E33: 1 | F33: Leases executed
A34: followups_due | B34: INTEGER | C34: Yes | D34: >=0 | E34: 25 | F34: Follow-ups due
A35: followups_completed | B35: INTEGER | C35: Yes | D35: >=0 | E35: 23 | F35: Follow-ups done
A36: timestamp | B36: DATETIME | C36: Yes | D36: ISO 8601 | E36: 2026-01-11T18:00:00 | F36: Extraction time
A38: TEMPLATE 3: Marketing.csv
A39: Field Name | B39: Data Type | C39: Required | D39: Validation Rule | E39: Example | F39: Notes
A40: property_id | B40: STRING | C40: Yes | D40: Valid property code | E40: 150MKT | F40: Property identifier
A41: report_date | B41: DATE | C41: Yes | D41: YYYY-MM-DD | E41: 2026-01-11 | F41: Campaign date
A42: channel | B42: STRING | C42: Yes | D42: ILS|PPC|Social|Direct|Referral | E42: ILS | F42: Marketing channel
A43: campaign_id | B43: STRING | C43: No | D43: Valid campaign code | E43: APT-Q1-2026 | F43: Campaign identifier
A44: impressions | B44: INTEGER | C44: No | D44: >=0 | E44: 15000 | F44: Ad impressions
A45: clicks | B45: INTEGER | C45: No | D45: >=0 | E45: 450 | F45: Ad clicks
A46: leads | B46: INTEGER | C46: Yes | D46: >=0 | E46: 25 | F46: Leads generated
A47: tours | B47: INTEGER | C47: No | D47: >=0 | E47: 12 | F47: Tours from channel
A48: leases | B48: INTEGER | C48: No | D48: >=0 | E48: 3 | F48: Leases from channel
A49: spend | B49: DECIMAL | C49: Yes | D49: >=0 | E49: 1500 | F49: Marketing spend $
A50: timestamp | B50: DATETIME | C50: Yes | D50: ISO 8601 | E50: 2026-01-11T23:59:00 | F50: Extraction time
A52: TEMPLATE 4: Maintenance.csv
A53: Field Name | B53: Data Type | C53: Required | D53: Validation Rule | E53: Example | F53: Notes
A54: property_id | B54: STRING | C54: Yes | D54: Valid property code | E54: 150MKT | F54: Property identifier
A55: report_date | B55: DATE | C55: Yes | D55: YYYY-MM-DD | E55: 2026-01-11 | F55: Report date
A56: wo_number | B56: STRING | C56: Yes | D56: Unique WO ID | E56: WO-2026-001234 | F56: Work order number
A57: unit_id | B57: STRING | C57: No | D57: Valid unit or Common | E57: 101 | F57: Unit or common area
A58: category | B58: STRING | C58: Yes | D58: Plumbing|HVAC|Electrical|Appliance|General | E58: HVAC | F58: WO category
A59: priority | B59: STRING | C59: Yes | D59: Emergency|Urgent|Normal|Scheduled | E59: Normal | F59: Priority level
A60: status | B60: STRING | C60: Yes | D60: Open|In Progress|Complete|On Hold | E60: Complete | F60: Current status
A61: created_date | B61: DATE | C61: Yes | D61: YYYY-MM-DD | E61: 2026-01-09 | F61: WO created date
A62: completed_date | B62: DATE | C62: Cond | D62: If Complete | E62: 2026-01-11 | F62: Completion date
A63: time_to_complete_hrs | B63: DECIMAL | C63: Cond | D63: >=0 if Complete | E63: 4.5 | F63: Hours to complete
A64: cost | B64: DECIMAL | C64: No | D64: >=0 | E64: 125 | F64: Parts/labor cost
A65: timestamp | B65: DATETIME | C65: Yes | D65: ISO 8601 | E65: 2026-01-11T18:00:00 | F65: Extraction time
A67: TEMPLATE 5: Financials.csv
A68: Field Name | B68: Data Type | C68: Required | D68: Validation Rule | E68: Example | F68: Notes
A69: property_id | B69: STRING | C69: Yes | D69: Valid property code | E69: 150MKT | F69: Property identifier
A70: period | B70: STRING | C70: Yes | D70: YYYY-MM | E70: 2026-01 | F70: Reporting period
A71: gl_account | B71: STRING | C71: Yes | D71: Valid GL code | E71: 4100-001 | F71: GL account code
A72: gl_description | B72: STRING | C72: Yes | D72: Non-empty | E72: Rental Income | F72: Account description
A73: category | B73: STRING | C73: Yes | D73: Revenue|OpEx|CapEx|Other | E73: Revenue | F73: Account category
A74: actual | B74: DECIMAL | C74: Yes | D74: Any number | E74: 125000 | F74: Actual amount
A75: budget | B75: DECIMAL | C75: Yes | D75: Any number | E75: 130000 | F75: Budget amount
A76: variance | B76: DECIMAL | C76: Calc | D76: actual - budget | E76: -5000 | F76: Variance amount
A77: variance_pct | B77: DECIMAL | C77: Calc | D77: variance / budget | E77: -0.0385 | F77: Variance %
A78: ytd_actual | B78: DECIMAL | C78: No | D78: Any number | E78: 125000 | F78: YTD actual
A79: ytd_budget | B79: DECIMAL | C79: No | D79: Any number | E79: 130000 | F79: YTD budget
A80: timestamp | B80: DATETIME | C80: Yes | D80: ISO 8601 | E80: 2026-01-31T23:59:00 | F80: Extraction time

Sheet _KPI_Dictionary
A1: KPI DEFINITIONS & BUSINESS RULES
A2: Standard definitions for portfolio-wide consistency. Do not modify without Ops/Finance approval.
A4: CORE FINANCIAL KPIs
A5: KPI Name | B5: Definition | C5: Formula | D5: Data Source | E5: Cadence | F5: Owner | G5: Yellow Threshold | H5: Red Threshold | I5: Excel Formula | J5: Example Calc | K5: Units
A6: NOI | B6: Net Operating Income = Revenue - Operating Expenses | C6: Revenue - OpEx | D6: Financials.csv | E6: Monthly | F6: Asset Mgr | G6: <Budget -5% | H6: <Budget -10% | I6: =SUM(Revenue)-SUM(OpEx) -> #NAME? | J6: 500000-350000=150000 | K6: $
A7: Same-Store NOI | B7: NOI for properties owned >12 months, YoY comparison | C7: (Current NOI - Prior NOI) / Prior NOI | D7: Financials.csv | E7: Monthly | F7: Asset Mgr | G7: YoY <2% | H7: YoY <0% | I7: =(CurrentNOI-PriorNOI)/PriorNOI -> #NAME? | J7: (150000-140000)/140000=7.1% | K7: %
A8: FFO | B8: Funds From Operations (REIT standard) | C8: Net Income + D&A - Gains on Sales | D8: Financials.csv | E8: Quarterly | F8: CFO | G8: <Guidance -5% | H8: <Guidance -10% | I8: =NetIncome+Depreciation-GainOnSale -> #NAME? | J8: 100000+50000-10000=140000 | K8: $
A9: DSCR | B9: Debt Service Coverage Ratio | C9: NOI / Total Debt Service | D9: Financials.csv | E9: Monthly | F9: CFO | G9: <1.30x | H9: <1.20x | I9: =NOI/AnnualDebtService -> #NAME? | J9: 150000/100000=1.50x | K9: x
A10: Leverage Ratio | B10: Total Debt / Total Assets | C10: Debt / Assets | D10: Financials.csv | E10: Monthly | F10: CFO | G10: >60% | H10: >65% | I10: =TotalDebt/TotalAssets -> #NAME? | J10: 60000000/100000000=60% | K10: %
A11: Delinquency Rate | B11: Past due rent / Total rent billed | C11: Delinquent $ / Billed $ | D11: AR Report | E11: Monthly | F11: Finance | G11: >3% | H11: >5% | I11: =SUMIF(AR,">0")/TotalBilled -> #NAME? | J11: 15000/500000=3% | K11: %
A12: Bad Debt % | B12: Write-offs / Revenue | C12: Write-offs / Revenue | D12: Financials.csv | E12: Monthly | F12: Finance | G12: >1% | H12: >2% | I12: =WriteOffs/Revenue -> #NAME? | J12: 5000/500000=1% | K12: %
A14: LEASING & OCCUPANCY KPIs
A15: KPI Name | B15: Definition | C15: Formula | D15: Data Source | E15: Cadence | F15: Owner | G15: Yellow Threshold | H15: Red Threshold | I15: Excel Formula | J15: Example Calc | K15: Units
A16: Physical Occupancy % | B16: Occupied units / Total units | C16: Occupied / Total | D16: RentRoll.csv | E16: Daily | F16: Ops Mgr | G16: <95% | H16: <92% | I16: '=COUNTIF(Status,"Leased")/COUNTA(UnitID) | J16: 275/357=77.0% | K16: %
A17: Economic Occupancy % | B17: Collected rent / Potential rent | C17: Collected / (Units × Market) | D17: RentRoll.csv | E17: Monthly | F17: Asset Mgr | G17: <90% | H17: <85% | I17: '=SUM(CollectedRent)/SUM(MarketRent) | J17: 450000/500000=90% | K17: %
A18: Net Effective Rent (NER) | B18: Contract rent - (Concessions / Lease Term) | C18: (Contract - Concession) / Term | D18: RentRoll.csv | E18: Daily | F18: Leasing | G18: <Market -5% | H18: <Market -10% | I18: '=ContractRent-(Concession/LeaseTerm) | J18: 2400-(600/12)=2350 | K18: $
A19: Lead-to-Tour % | B19: Tours completed / New leads | C19: Tours / Leads | D19: LeasingActivity.csv | E19: Daily | F19: Leasing Dir | G19: <40% | H19: <30% | I19: '=ToursCompleted/NewLeads | J19: 6/15=40% | K19: %
A20: Tour-to-Lease % | B20: Leases signed / Tours completed | C20: Leases / Tours | D20: LeasingActivity.csv | E20: Daily | F20: Leasing Dir | G20: <25% | H20: <20% | I20: '=LeasesSigned/ToursCompleted | J20: 2/6=33% | K20: %
A21: Lead-to-Lease % | B21: Leases signed / New leads | C21: Leases / Leads | D21: LeasingActivity.csv | E21: Daily | F21: Leasing Dir | G21: <15% | H21: <10% | I21: '=LeasesSigned/NewLeads | J21: 2/15=13% | K21: %
A22: Renewal Rate | B22: Renewals / Expiring leases | C22: Renewed / Expiring | D22: RentRoll.csv | E22: Monthly | F22: Ops Dir | G22: <55% | H22: <50% | I22: '=Renewals/ExpiringLeases | J22: 45/80=56% | K22: %
A23: Days on Market | B23: Avg days unit vacant before lease | C23: Avg(Lease Date - Vacant Date) | D23: RentRoll.csv | E23: Weekly | F23: Leasing | G23: >21 days | H23: >30 days | I23: '=AVERAGE(LeaseDate-VacantDate) | J23: AVG(14,21,7)=14 | K23: days
A24: Follow-up Completion % | B24: Completed follow-ups / Due follow-ups | C24: Completed / Due | D24: LeasingActivity.csv | E24: Daily | F24: Leasing Mgr | G24: <95% | H24: <90% | I24: '=FollowupsCompleted/FollowupsDue | J24: 23/25=92% | K24: %
A26: MARKETING KPIs
A27: KPI Name | B27: Definition | C27: Formula | D27: Data Source | E27: Cadence | F27: Owner | G27: Yellow Threshold | H27: Red Threshold | I27: Excel Formula | J27: Example Calc | K27: Units
A28: Cost Per Lead (CPL) | B28: Marketing spend / Leads generated | C28: Spend / Leads | D28: Marketing.csv | E28: Weekly | F28: Mkt Dir | G28: >$75 | H28: >$100 | I28: '=MarketingSpend/Leads | J28: 1500/20=$75 | K28: $
A29: Cost Per Tour (CPT) | B29: Marketing spend / Tours from marketing | C29: Spend / Tours | D29: Marketing.csv | E29: Weekly | F29: Mkt Dir | G29: >$150 | H29: >$200 | I29: '=MarketingSpend/Tours | J29: 1500/10=$150 | K29: $
A30: Cost Per Acquisition (CPA) | B30: Marketing spend / Leases signed | C30: Spend / Leases | D30: Marketing.csv | E30: Weekly | F30: Mkt Dir | G30: >1 mo rent | H30: >1.5 mo rent | I30: '=MarketingSpend/Leases | J30: 1500/3=$500 | K30: $
A31: Customer Acquisition Cost (CAC) | B31: Total acquisition cost per new resident | C31: (Mkt + Leasing Ops) / Leases | D31: Marketing.csv | E31: Monthly | F31: Mkt Dir | G31: >$2000 | H31: >$3000 | I31: '=(MktSpend+LeasingCost)/Leases | J31: (1500+500)/3=$667 | K31: $
A32: LTV:CAC Ratio | B32: Lifetime Value / Customer Acquisition Cost | C32: LTV / CAC | D32: Calculated | E32: Monthly | F32: Mkt Dir | G32: <3:1 | H32: <2:1 | I32: '=LTV/CAC | J32: 7200/667=10.8x | K32: ratio
A33: Click-Through Rate (CTR) | B33: Clicks / Impressions | C33: Clicks / Impressions | D33: Marketing.csv | E33: Weekly | F33: Mkt Dir | G33: <1.5% | H33: <1% | I33: '=Clicks/Impressions | J33: 450/30000=1.5% | K33: %
A34: Conversion Rate (Web) | B34: Leads / Sessions | C34: Leads / Sessions | D34: GA4 | E34: Weekly | F34: Mkt Dir | G34: <3% | H34: <2% | I34: '=Leads/Sessions | J34: 20/800=2.5% | K34: %
A36: OPERATIONS & MAINTENANCE KPIs
A37: KPI Name | B37: Definition | C37: Formula | D37: Data Source | E37: Cadence | F37: Owner | G37: Yellow Threshold | H37: Red Threshold | I37: Excel Formula | J37: Example Calc | K37: Units
A38: Turnover Rate | B38: Move-outs / Total units (annualized) | C38: (Move-outs × 12) / Units | D38: RentRoll.csv | E38: Monthly | F38: Ops Dir | G38: >50% | H38: >60% | I38: '=(MoveOuts*12)/TotalUnits | J38: (30*12)/357=100.8% | K38: %
A39: Cost Per Turn | B39: Total make-ready cost / Turns | C39: Turn Cost / Turns | D39: Maintenance.csv | E39: Monthly | F39: Ops Dir | G39: >$1500 | H39: >$2000 | I39: '=SUM(TurnCost)/COUNT(Turns) | J39: 45000/30=$1500 | K39: $
A40: Days to Re-Rent | B40: Avg days from move-out to new lease | C40: Avg(New Lease - Move Out) | D40: RentRoll.csv | E40: Monthly | F40: Ops Dir | G40: >14 days | H40: >21 days | I40: '=AVG(NewLeaseDate-MoveOutDate) | J40: AVG(10,14,21)=15 | K40: days
A41: WO Completion Time | B41: Avg hours to complete work orders | C41: Avg(Complete - Created) | D41: Maintenance.csv | E41: Daily | F41: Maint Dir | G41: >48 hrs | H41: >72 hrs | I41: '=AVG(CompletedTime-CreatedTime) | J41: AVG(24,48,36)=36 | K41: hrs
A42: Emergency Response | B42: Avg hours for emergency WO response | C42: Avg(First Action - Created) | D42: Maintenance.csv | E42: Daily | F42: Maint Dir | G42: >4 hrs | H42: >8 hrs | I42: '=AVG(ResponseTime) WHERE Priority='Emergency' | J42: AVG(2,4,3)=3 | K42: hrs
A43: WO Backlog | B43: Open work orders / Total units | C43: Open WOs / Units | D43: Maintenance.csv | E43: Daily | F43: Maint Dir | G43: >0.5 | H43: >1.0 | I43: '=COUNTIF(Status,"Open")/TotalUnits | J43: 50/357=0.14 | K43: ratio
A44: NPS Score | B44: Net Promoter Score (Promoters - Detractors) | C44: (9-10 scores) - (0-6 scores) | D44: Survey Data | E44: Monthly | F44: Ops Dir | G44: <40 | H44: <20 | I44: '=(%Promoters-%Detractors)*100 | J44: (45%-15%)*100=30 | K44: score
A45: Resident Satisfaction | B45: Survey satisfaction score | C45: Avg satisfaction rating | D45: Survey Data | E45: Monthly | F45: Ops Dir | G45: <4.0 | H45: <3.5 | I45: '=AVERAGE(SatisfactionRating) | J45: AVG(4.2,3.8,4.5)=4.2 | K45: /5
A47: DEVELOPMENT & CONSTRUCTION KPIs
A48: KPI Name | B48: Definition | C48: Formula | D48: Data Source | E48: Cadence | F48: Owner | G48: Yellow Threshold | H48: Red Threshold | I48: Excel Formula | J48: Example Calc | K48: Units
A49: Schedule Variance (SV) | B49: Earned Value - Planned Value | C49: EV - PV | D49: Project Tracker | E49: Weekly | F49: Dev Dir | G49: <-5% | H49: <-10% | I49: '=EarnedValue-PlannedValue | J49: 950000-1000000=-50000 | K49: $
A50: Cost Variance (CV) | B50: Earned Value - Actual Cost | C50: EV - AC | D50: Project Tracker | E50: Weekly | F50: Dev Dir | G50: <-5% | H50: <-10% | I50: '=EarnedValue-ActualCost | J50: 950000-980000=-30000 | K50: $
A51: Schedule Performance Index | B51: Earned Value / Planned Value | C51: EV / PV | D51: Project Tracker | E51: Weekly | F51: Dev Dir | G51: <0.95 | H51: <0.90 | I51: '=EarnedValue/PlannedValue | J51: 950000/1000000=0.95 | K51: index
A52: Cost Performance Index | B52: Earned Value / Actual Cost | C52: EV / AC | D52: Project Tracker | E52: Weekly | F52: Dev Dir | G52: <0.95 | H52: <0.90 | I52: '=EarnedValue/ActualCost | J52: 950000/980000=0.97 | K52: index
A53: % Complete | B53: Work completed vs total scope | C53: Completed / Total Scope | D53: Project Tracker | E53: Weekly | F53: Dev Dir | G53: Behind schedule | H53: >2 weeks late | I53: '=CompletedWork/TotalScope | J53: 47.5/50=95% | K53: %
A54: Cost to Complete | B54: Remaining budget to finish project | C54: Budget - Spent - Committed | D54: Project Tracker | E54: Monthly | F54: Dev Dir | G54: >Budget +5% | H54: >Budget +10% | I54: '=Budget-Spent-Committed | J54: 1M-800K-150K=50K | K54: $
A55: Risk Score | B55: Weighted risk assessment | C55: Sum(Impact × Likelihood) | D55: Risk Register | E55: Monthly | F55: Dev Dir | G55: >Medium | H55: >High | I55: '=SUMPRODUCT(Impact,Likelihood) | J55: SUM(3*4,2*3,5*2)=28 | K55: score
A57: ESG & SUSTAINABILITY KPIs
A58: KPI Name | B58: Definition | C58: Formula | D58: Data Source | E58: Cadence | F58: Owner | G58: Yellow Threshold | H58: Red Threshold | I58: Excel Formula | J58: Example Calc | K58: Units
A59: Energy Intensity | B59: kWh per unit per month | C59: Total kWh / Units | D59: Utility Data | E59: Monthly | F59: ESG Mgr | G59: >Baseline +10% | H59: >Baseline +20% | I59: '=TotalkWh/TotalUnits | J59: 150000/357=420 | K59: kWh/unit
A60: Water Intensity | B60: Gallons per unit per month | C60: Total Gallons / Units | D60: Utility Data | E60: Monthly | F60: ESG Mgr | G60: >Baseline +10% | H60: >Baseline +20% | I60: '=TotalGallons/TotalUnits | J60: 1500000/357=4202 | K60: gal/unit
A61: Safety Incidents | B61: Recordable incidents per property | C61: Count of incidents | D61: Safety Log | E61: Monthly | F61: ESG Mgr | G61: >0 | H61: >2 | I61: '=COUNTIF(Type,"Recordable") | J61: COUNT=2 | K61: count
A62: GRESB Score | B62: Global Real Estate Sustainability Benchmark | C62: GRESB assessment | D62: Annual Survey | E62: Annual | F62: ESG Mgr | G62: <70 | H62: <60 | I62: '=GRESBAssessmentScore | J62: Score=72 | K62: 0-100
A64: ADDITIONAL CALCULATED KPIs
A65: KPI Name | B65: Definition | C65: Formula | D65: Data Source | E65: Cadence | F65: Owner | G65: Yellow | H65: Red | I65: Excel Formula | J65: Example | K65: Units
A66: Revenue Per Unit | B66: Total revenue / Total units | C66: Revenue/Units | D66: Financials | E66: Monthly | F66: Asset Mgr | G66: <$1800 | H66: <$1600 | I66: '=SUM(Revenue)/TotalUnits | J66: 650000/357=$1821 | K66: $/unit
A67: OpEx Ratio | B67: Operating expenses / Revenue | C67: OpEx/Revenue | D67: Financials | E67: Monthly | F67: Asset Mgr | G67: >45% | H67: >50% | I67: '=SUM(OpEx)/SUM(Revenue) | J67: 325000/650000=50% | K67: %
A68: Gross Potential Rent | B68: All units at market rent | C68: Units × Market Rent | D68: RentRoll | E68: Monthly | F68: Finance | G68: N/A | H68: N/A | I68: '=SUMPRODUCT(Units,MarketRent) | J68: 357*2500=$892,500 | K68: $
A69: Loss to Lease | B69: Market rent - Contract rent | C69: GPR - Actual Rent | D69: RentRoll | E69: Monthly | F69: Leasing | G69: >5% | H69: >8% | I69: '=(MarketRent-ContractRent)/MarketRent | J69: (2500-2350)/2500=6% | K69: %
A70: Vacancy Loss | B70: Revenue lost from vacant units | C70: Vacant × Market × Days | D70: RentRoll | E70: Monthly | F70: Ops | G70: >3% | H70: >5% | I70: '=VacantUnits*AvgRent*Days/30 | J70: 20*2400*15/30=$24,000 | K70: $
A71: Concession Impact | B71: Total concessions given | C71: Sum of concessions | D71: RentRoll | E71: Monthly | F71: Leasing | G71: >2% | H71: >4% | I71: '=SUM(Concessions)/GPR | J71: 15000/892500=1.7% | K71: %
A72: Rent Growth YoY | B72: Year-over-year rent increase | C72: (Current-Prior)/Prior | D72: RentRoll | E72: Monthly | F72: Asset Mgr | G72: <2% | H72: <0% | I72: '=(AvgRentNow-AvgRentPY)/AvgRentPY | J72: (2400-2300)/2300=4.3% | K72: %
A73: Absorption Rate | B73: Leases signed / Available units | C73: New Leases/Available | D73: Leasing | E73: Weekly | F73: Leasing Dir | G73: <15% | H73: <10% | I73: '=NewLeases/AvailableUnits | J73: 5/30=16.7% | K73: %/wk
A74: Avg Lease Term | B74: Average lease duration | C74: Avg of lease terms | D74: RentRoll | E74: Monthly | F74: Leasing | G74: <11 mo | H74: <10 mo | I74: '=AVERAGE(LeaseTerm) | J74: AVG(12,12,11,13)=12 | K74: months
A75: Resident Tenure | B75: Avg months resident stays | C75: Avg tenure all residents | D75: RentRoll | E75: Monthly | F75: Ops Dir | G75: <18 mo | H75: <12 mo | I75: '=AVERAGE(DATEDIF(MoveIn,TODAY(),"M")) | J75: AVG(24,18,36,12)=22.5 | K75: months
A77: FORMULA LOGIC & DEPENDENCIES
A78: Derived Metric | B78: Depends On | C78: Calculation Chain | D78: Refresh Order
A79: NOI Margin % | B79: NOI, Revenue | C79: 1. Calculate Revenue → 2. Calculate OpEx → 3. NOI=Rev-OpEx → 4. Margin=NOI/Rev | D79: 1
A80: Economic Occ | B80: Physical Occ, Collected Rent, GPR | C80: 1. GPR=Units×Market → 2. Collected from AR → 3. EconOcc=Collected/GPR | D80: 2
A81: LTV:CAC | B81: CAC, Avg Tenure, NER | C81: 1. CAC=MktSpend/Leases → 2. LTV=NER×Tenure → 3. Ratio=LTV/CAC | D81: 3
A82: CPA Guard | B82: CPA, Avg NER | C82: 1. CPA=Spend/Leases → 2. Threshold=1×NER → 3. Alert if CPA>Threshold | D82: 4
A83: Same-Store NOI | B83: NOI Current, NOI Prior, Property Age | C83: 1. Filter props >12mo → 2. Sum current NOI → 3. Sum prior NOI → 4. YoY% | D83: 5
A84: DSCR | B84: NOI, Debt Service | C84: 1. Annual NOI → 2. Annual P&I payments → 3. DSCR=NOI/DebtSvc | D84: 6
A85: FFO | B85: Net Income, D&A, Gains | C85: 1. Net Income from P&L → 2. Add back D&A → 3. Subtract gains → 4. FFO | D85: 7
A86: SPI/CPI | B86: EV, PV, AC | C86: 1. Calculate Planned Value → 2. Calculate Earned Value → 3. Track Actual Cost → 4. Indices | D86: 8

Sheet _Alert_Rules
A1: ALERT THRESHOLDS & NOTIFICATION RULES
A2: Automated alerts triggered when KPIs breach thresholds. Hard rules require immediate action.
A4: CRITICAL ALERTS (RED)
A5: Alert ID | B5: Alert Name | C5: Trigger Condition | D5: Severity | E5: Hard Rule? | F5: Block Action | G5: Notify (Primary) | H5: Notify (Secondary) | I5: Recommended Action | J5: Escalation
A6: ALT-001 | B6: Marketing CPA Breach | C6: CPA > 1 month net rent | D6: RED | E6: Yes | F6: Pause channel spend | G6: Head Marketing | H6: Asset Mgr, CFO | I6: Pause channel, review attribution | J6: Immediate: CFO
A7: ALT-002 | B7: Occupancy Critical Drop | C7: Occupancy < 92% | D7: RED | E7: No | F7: — | G7: Asset Manager | H7: Ops Director | I7: Emergency leasing sprint | J7: 24hr: SVP Ops
A8: ALT-003 | B8: Occupancy MoM Drop | C8: Occupancy drop > 2% MoM | D8: RED | E8: No | F8: — | G8: Asset Manager | H8: Ops Director | I8: Review pricing, concessions | J8: 24hr: SVP Ops
A9: ALT-004 | B9: Covenant Breach Risk | C9: DSCR < 1.20x | D9: RED | E9: Yes | F9: Capital review required | G9: CFO | H9: CEO, IR | I9: Prepare lender communication | J9: Immediate: CEO
A10: ALT-005 | B10: Conversion Rate Collapse | C10: Lead-to-Lease drop > 20% MoM | D10: RED | E10: No | F10: — | G10: Head Leasing | H10: Asset Manager | I10: Audit leasing process | J10: 48hr: Ops Dir
A11: ALT-006 | B11: Emergency WO Delayed | C11: Emergency WO > 8 hrs | D11: RED | E11: No | F11: — | G11: Maint Director | H11: Property Mgr | I11: Immediate dispatch | J11: 4hr: Ops Dir
A12: ALT-007 | B12: Cash Flow Critical | C12: Liquidity < 30 days opex | D12: RED | E12: Yes | F12: Capex freeze | G12: CFO | H12: CEO | I12: Draw credit facility | J12: Immediate: CEO
A14: WARNING ALERTS (YELLOW)
A15: Alert ID | B15: Alert Name | C15: Trigger Condition | D15: Severity | E15: Hard Rule? | F15: Block Action | G15: Notify (Primary) | H15: Notify (Secondary) | I15: Recommended Action | J15: Escalation
A16: ALT-101 | B16: Occupancy Warning | C16: Occupancy < 95% | D16: YELLOW | E16: No | F16: — | G16: Property Manager | H16: Asset Manager | I16: Review leasing velocity | J16: Weekly review
A17: ALT-102 | B17: Marketing CPL High | C17: CPL > $75 | D17: YELLOW | E17: No | F17: — | G17: Marketing Mgr | H17: Head Marketing | I17: Optimize campaigns | J17: Weekly review
A18: ALT-103 | B18: Follow-up Backlog | C18: Follow-up completion < 95% | D18: YELLOW | E18: No | F18: — | G18: Leasing Manager | H18: Property Manager | I18: Clear backlog same day | J18: Daily standup
A19: ALT-104 | B19: NER Below Market | C19: NER < Market rent - 5% | D19: YELLOW | E19: No | F19: — | G19: Leasing Director | H19: Asset Manager | I19: Review pricing strategy | J19: Weekly review
A20: ALT-105 | B20: WO Backlog High | C20: Open WOs > 0.5 per unit | D20: YELLOW | E20: No | F20: — | G20: Maint Supervisor | H20: Maint Director | I20: Schedule overtime/temp | J20: 48hr review
A21: ALT-106 | B21: Budget Variance | C21: Actual vs Budget > 5% | D21: YELLOW | E21: No | F21: — | G21: Property Manager | H21: Asset Manager | I21: Variance explanation | J21: Monthly review
A22: ALT-107 | B22: Delinquency Rising | C22: Delinquency > 3% | D22: YELLOW | E22: No | F22: — | G22: Property Manager | H22: Finance | I22: Increase collection efforts | J22: Weekly review
A23: ALT-108 | B23: Project Schedule Slip | C23: Schedule variance < -5% | D23: YELLOW | E23: No | F23: — | G23: Project Manager | H23: Dev Director | I23: Recovery plan required | J23: Weekly review
A24: ALT-109 | B24: Renewal Rate Low | C24: Renewal rate < 55% | D24: YELLOW | E24: No | F24: — | G24: Property Manager | H24: Ops Director | I24: Retention campaign | J24: Monthly review

Sheet _Access_Matrix
A1: ROLE-BASED ACCESS & DISTRIBUTION MATRIX
A2: Access rights by role. V=View, E=Edit, A=Approve, D=Download, N=No Access
A4: ROLE DEFINITIONS
A5: Role | B5: Description | C5: Properties | D5: Reports Access
A6: Executive (CEO/CFO) | B6: Full portfolio visibility, approval authority | C6: All | D6: All reports, sign-off
A7: Department Head | B7: Division oversight, sign-off authority | C7: Division | D7: Division reports, sign-off
A8: Asset Manager | B8: Portfolio segment management | C8: Assigned portfolio | D8: Finance, Leasing, Ops
A9: Operations Director | B9: Property operations oversight | C9: Region/portfolio | D9: Ops, Leasing, Maint
A10: Property Manager | B10: Single property management | C10: Single property | D10: Property-level only
A11: Leasing Director | B11: Leasing strategy and performance | C11: Region/portfolio | D11: Leasing, Marketing
A12: Leasing Agent | B12: Daily leasing activities | C12: Single property | D12: Leasing inputs only
A13: Marketing Director | B13: Marketing strategy and spend | C13: All properties | D13: Marketing, Attribution
A14: Finance Manager | B14: Financial reporting and AR | C14: All properties | D14: Finance reports
A15: Maintenance Director | B15: Maintenance operations | C15: Region/portfolio | D15: Maintenance, WO
A16: Development Director | B16: Construction oversight | C16: Dev projects | D16: Development reports
... A18: ESG Manager | B18: Sustainability reporting | C18: All properties | D18: ESG reports
A20: DISTRIBUTION SCHEDULE
A21: Report | B21: Frequency | C21: Format | D21: Audience | E21: Delivery | F21: Time | G21: Sign-off Required
A22: Property Leasing One-Pager | B22: Daily | C22: PDF | D22: Property Mgr, Asset Mgr | E22: Email | F22: 7:00 AM | G22: No
A23: Marketing CPA Dashboard | B23: Daily | C23: Dashboard | D23: Marketing, Asset Mgr | E23: Dashboard | F23: Real-time | G23: No
A24: Weekly Leasing Summary | B24: Weekly | C24: PDF+CSV | D24: Dept Heads, Asset Mgrs | E24: Email | F24: Mon 8:00 AM | G24: No
A25: Monthly Portfolio NOI | B25: Monthly | C25: PDF | D25: CFO, Dept Heads | E25: Email | F25: 5th business day | G25: Yes - CFO
A26: Monthly Variance Report | B26: Monthly | C26: PDF+Excel | D26: Finance, Asset Mgrs | E26: Email | F26: 5th business day | G26: Yes - Finance
A27: Investor Quarterly Pack | B27: Quarterly | C27: PDF | D27: IR, Investors | E27: Secure portal | F27: 45 days post QE | G27: Yes - CEO/CFO
A28: Rent Roll Extract | B28: Monthly | C28: CSV | D28: Capital Markets | E28: SFTP | F28: Last business day | G28: No
A29: ESG Report | B29: Quarterly | C29: PDF | D29: ESG, Investors | E29: Email+Portal | F29: 30 days post QE | G29: Yes - ESG Mgr

Sheet OPS_09_Leasing_OnePager
A1: [PROPERTY NAME] - PROPERTY LEASING ONE-PAGER
A2: Report Date: | B2: =TODAY() -> 46034 | D2: Week Start: | E2: [Enter Date]
A4: KEY METRICS
B5: Total Units | D5: Occupied | F5: Physical Occ% | H5: Available | J5: Avg NER | L5: Vacant Rent $
B6: [Units] | D6: [Occ] | F6: [%] | H6: [Avail] | J6: [$NER] | L6: [$Vacant]
A8: DAILY LEASING ACTIVITY
A9: Metric | B9: Today | C9: WTD | D9: MTD | E9: Target | F9: Variance
A10: New Leads | B10: 0 | C10: 0 | D10: 0 | E10: — | F10: —
A11: Tours Scheduled | B11: 0 | C11: 0 | D11: 0 | E11: — | F11: —
A12: Tours Completed | B12: 0 | C12: 0 | D12: 0 | E12: — | F12: —
A13: Applications Submitted | B13: 0 | C13: 0 | D13: 0 | E13: — | F13: —
A14: Applications Approved | B14: 0 | C14: 0 | D14: 0 | E14: — | F14: —
A15: Leases Signed | B15: 0 | C15: 0 | D15: 0 | E15: — | F15: —
A16: Cancellations/No-Shows | B16: 0 | C16: 0 | D16: 0 | E16: — | F16: —
A18: CONVERSION RATES
A19: Lead → Tour % | B19: — | C19: — | D19: —
A20: Tour → App % | B20: — | C20: — | D20: —
A21: App → Lease % | B21: — | C21: — | D21: —
A22: Lead → Lease % | B22: — | C22: — | D22: —
A24: FOLLOW-UP HEALTH
A25: Follow-ups Due | B25: 0
A26: Follow-ups Completed | B26: 0
A27: Completion % | B27: 0
A28: Overdue Tasks | B28: 0
A29: Uncontacted >24hr | B29: 0

Sheet MKT_16_Marketing_CPA
A1: MARKETING PERFORMANCE & CPA DASHBOARD | L1: =HYPERLINK("#Alert_Dashboard!B2","← Back to Alerts") -> ← Back to Alerts
A2: ALERT: CPA > 1 month rent triggers RED alert and channel pause
A4: PORTFOLIO MARKETING KPIs (WTD)
B5: Total Spend | C5: Leads | D5: CPL | E5: Tours | F5: CPT | G5: Leases | H5: CPA
B6: =SUM(B10:B16) -> 24000 | C6: =SUM(C10:C16) -> 1151 | D6: =IF(C6=0,0,B6/C6) -> 20.851434 | E6: =SUM(E10:E16) -> 401 | F6: =IF(E6=0,0,B6/E6) -> 59.850374 | G6: =SUM(G10:G16) -> 104 | H6: =IF(G6=0,0,B6/G6) -> 230.76923
A8: CHANNEL PERFORMANCE
A9: Channel | B9: Spend | C9: Leads | D9: CPL | E9: Tours | F9: CPT | G9: Leases | H9: CPA | I9: Status | J9: Action
A10: ILS (Apartments.com) | B10: 8500 | C10: 245 | D10: =IF(C10=0,0,B10/C10) -> 34.693878 | E10: 78 | F10: =IF(E10=0,0,B10/E10) -> 108.97436 | G10: 18 | H10: =IF(G10=0,0,B10/G10) -> 472.22222 | I10: =IF(H10>$F$18,"PAUSE",IF(H10>$F$18*0.8,"WATCH","OK")) -> OK | J10: =IF(I10="PAUSE","Pause Channel",IF(I10="WATCH","Monitor","—")) -> —
A11: ILS (Zillow) | B11: 6200 | C11: 198 | D11: =IF(C11=0,0,B11/C11) -> 31.313131 | E11: 61 | F11: =IF(E11=0,0,B11/E11) -> 101.63934 | G11: 14 | H11: =IF(G11=0,0,B11/G11) -> 442.85714 | I11: =IF(H11>$F$18,"PAUSE",IF(H11>$F$18*0.8,"WATCH","OK")) -> OK | J11: =IF(I11="PAUSE","Pause Channel",IF(I11="WATCH","Monitor","—")) -> —
A12: Google Ads (PPC) | B12: 4800 | C12: 156 | D12: =IF(C12=0,0,B12/C12) -> 30.769231 | E12: 52 | F12: =IF(E12=0,0,B12/E12) -> 92.307692 | G12: 11 | H12: =IF(G12=0,0,B12/G12) -> 436.36364 | I12: =IF(H12>$F$18,"PAUSE",IF(H12>$F$18*0.8,"WATCH","OK")) -> OK | J12: =IF(I12="PAUSE","Pause Channel",IF(I12="WATCH","Monitor","—")) -> —
A13: Facebook/Instagram | B13: 3200 | C13: 134 | D13: =IF(C13=0,0,B13/C13) -> 23.880597 | E13: 38 | F13: =IF(E13=0,0,B13/E13) -> 84.210526 | G13: 7 | H13: =IF(G13=0,0,B13/G13) -> 457.14286 | I13: =IF(H13>$F$18,"PAUSE",IF(H13>$F$18*0.8,"WATCH","OK")) -> OK | J13: =IF(I13="PAUSE","Pause Channel",IF(I13="WATCH","Monitor","—")) -> —
A14: Direct/Organic | B14: 0 | C14: 287 | D14: =IF(C14=0,0,B14/C14) -> 0 | E14: 112 | F14: =IF(E14=0,0,B14/E14) -> 0 | G14: 32 | H14: =IF(G14=0,0,B14/G14) -> 0 | I14: =IF(H14>$F$18,"PAUSE",IF(H14>$F$18*0.8,"WATCH","OK")) -> OK | J14: =IF(I14="PAUSE","Pause Channel",IF(I14="WATCH","Monitor","—")) -> —
A15: Referral | B15: 500 | C15: 89 | D15: =IF(C15=0,0,B15/C15) -> 5.6179775 | E15: 45 | F15: =IF(E15=0,0,B15/E15) -> 11.111111 | G15: 19 | H15: =IF(G15=0,0,B15/G15) -> 26.315789 | I15: =IF(H15>$F$18,"PAUSE",IF(H15>$F$18*0.8,"WATCH","OK")) -> OK | J15: =IF(I15="PAUSE","Pause Channel",IF(I15="WATCH","Monitor","—")) -> —
A16: Other | B16: 800 | C16: 42 | D16: =IF(C16=0,0,B16/C16) -> 19.047619 | E16: 15 | F16: =IF(E16=0,0,B16/E16) -> 53.333333 | G16: 3 | H16: =IF(G16=0,0,B16/G16) -> 266.66667 | I16: =IF(H16>$F$18,"PAUSE",IF(H16>$F$18*0.8,"WATCH","OK")) -> OK | J16: =IF(I16="PAUSE","Pause Channel",IF(I16="WATCH","Monitor","—")) -> —
A18: CAC PAYBACK & LTV ANALYSIS | E18: CPA Threshold: | F18: 1814
A19: Metric | B19: Value | C19: Formula/Notes
A20: Avg Monthly Rent (NER) | B20: 1814 | C20: From OPS_11 weighted avg
A21: Avg Lease Term (months) | B21: 12 | C21: Standard 12-month lease
A22: Avg Retention Rate | B22: 0.697 | C22: From OPS_12 TTM retention
A23: Blended CPA | B23: {=H6} -> 230.76923 | C23: Total spend / Total leases
A25: CAC Payback (months) | B25: =B23/B20 -> 0.12721567 | C25: CPA / Monthly Rent
A26: Avg Customer Lifespan (months) | B26: =B21/(1-B22) -> 39.60396 | C26: Lease Term / (1 - Retention)
A27: Customer LTV | B27: =B20*B26 -> 71841.584 | C27: Monthly Rent × Lifespan
A28: LTV:CAC Ratio | B28: =B27/B23 -> 311.31353 | C28: Target: >3.0x

Sheet FIN_02_NOI_Pack
A1: MONTHLY PORTFOLIO NOI PACK
A2: Period: [YYYY-MM] | Prepared: [Date] | Status: Draft/Final
A4: PORTFOLIO NOI SUMMARY
A5: Metric | B5: Current Month | C5: Prior Month | D5: MoM Change | E5: Budget | F5: Variance | G5: YTD Actual | H5: YTD Budget
A6: Total Revenue | B6: $— | C6: $— | D6: $— | E6: $— | F6: $— | G6: $— | H6: $—
A7: Rental Income | B7: $— | C7: $— | D7: $— | E7: $— | F7: $— | G7: $— | H7: $—
A8: Other Income | B8: $— | C8: $— | D8: $— | E8: $— | F8: $— | G8: $— | H8: $—
A9: Total Operating Expenses | B9: $— | C9: $— | D9: $— | E9: $— | F9: $— | G9: $— | H9: $—
A10: Payroll | B10: $— | C10: $— | D10: $— | E10: $— | F10: $— | G10: $— | H10: $—
A11: R&M | B11: $— | C11: $— | D11: $— | E11: $— | F11: $— | G11: $— | H11: $—
A12: Utilities | B12: $— | C12: $— | D12: $— | E12: $— | F12: $— | G12: $— | H12: $—
A13: Admin/Marketing | B13: $— | C13: $— | D13: $— | E13: $— | F13: $— | G13: $— | H13: $—
A14: Insurance | B14: $— | C14: $— | D14: $— | E14: $— | F14: $— | G14: $— | H14: $—
A15: Property Tax | B15: $— | C15: $— | D15: $— | E15: $— | F15: $— | G15: $— | H15: $—
A16: Net Operating Income | B16: $— | C16: $— | D16: $— | E16: $— | F16: $— | G16: $— | H16: $—
A17: NOI Margin % | B17: —% | C17: —% | D17: —% | E17: —% | F17: —% | G17: —% | H17: —%
A19: PROPERTY NOI BREAKDOWN
A20: Property | B20: Revenue | C20: OpEx | D20: NOI | E20: NOI Margin | F20: Budget | G20: Variance | H20: Variance %
A21: Property 1 | B21: $— | C21: $— | D21: $— | E21: —% | F21: $— | G21: $— | H21: —%
A22: Property 2 | B22: $— | C22: $— | D22: $— | E22: —% | F22: $— | G22: $— | H22: —%
A23: Property 3 | B23: $— | C23: $— | D23: $— | E23: —% | F23: $— | G23: $— | H23: —%
A24: Property 4 | B24: $— | C24: $— | D24: $— | E24: —% | F24: $— | G24: $— | H24: —%
A25: Property 5 | B25: $— | C25: $— | D25: $— | E25: —% | F25: $— | G25: $— | H25: —%
A26: TOTAL

Sheet FIN_01_Investor_Pack
A1: CONSOLIDATED FINANCIAL STATEMENTS / INVESTOR PACK
A3: SECTIONS: P&L | Balance Sheet | Cash Flow | FFO Reconciliation | Same-Store NOI | Covenant Compliance
A5: CONSOLIDATED P&L STATEMENT | I5: KEY METRICS SUMMARY
A6: 0 | B6: Q4 2025 | C6: Q3 2025 | D6: QoQ Chg | E6: Q4 2024 | F6: YoY Chg | G6: FY 2025 | I6: Metric | J6: Current | K6: Prior Qtr | L6: YoY
A7: REVENUE | I7: FFO | J7: {=B30} -> 7050000 | K7: {=C30} -> 7000000 | L7: {=D30} -> 0.0071428571
A8: Rental Income | B8: 12500000 | C8: 12300000 | D8: =IF(C8=0,"—",(B8-C8)/C8) -> 0.016260163 | E8: 11800000 | F8: =IF(E8=0,"—",(B8-E8)/E8) -> 0.059322034 | G8: 49100000 | I8: FFO/Share | J8: {=B40} -> 0.141 | K8: {=C40} -> 0.14 | L8: =(J8-K8)/K8 -> 0.0071428571
A9: Other Income | B9: 850000 | C9: 820000 | D9: =IF(C9=0,"—",(B9-C9)/C9) -> 0.036585366 | E9: 780000 | F9: =IF(E9=0,"—",(B9-E9)/E9) -> 0.08974359 | G9: 3290000 | I9: AFFO/Share | J9: {=B41} -> 0.1401 | K9: {=C41} -> 0.141 | L9: =(J9-K9)/K9 -> -0.0063829787
A10: Total Revenue | B10: =B8+B9 -> 13350000 | C10: =C8+C9 -> 13120000 | D10: =IF(C10=0,"—",(B10-C10)/C10) -> 0.017530488 | E10: =E8+E9 -> 12580000 | F10: =IF(E10=0,"—",(B10-E10)/E10) -> 0.061208267 | G10: =G8+G9 -> 52390000 | I10: NOI | J10: {=B21} -> 8200000 | K10: {=C21} -> 8030000 | L10: {=D21} -> 0.02117061
A11: 0 | I11: Same-Store NOI Growth | J11: {=E52} -> 0.019903912 | K11: 0 | L11: 0
A12: OPERATING EXPENSES | I12: Physical Occupancy | J12: 0.952 | K12: 0.948 | L12: =J12-K12 -> 0.004
A13: Property Operations | B13: 2100000 | C13: 2050000 | D13: =IF(C13=0,"—",(B13-C13)/C13) -> 0.024390244 | E13: 1980000 | F13: =IF(E13=0,"—",(B13-E13)/E13) -> 0.060606061 | G13: 8180000 | I13: DSCR | J13: {=C62} -> 1.52 | K13: 1.48 | L13: 0
A14: Repairs & Maintenance | B14: 650000 | C14: 620000 | D14: =IF(C14=0,"—",(B14-C14)/C14) -> 0.048387097 | E14: 600000 | F14: =IF(E14=0,"—",(B14-E14)/E14) -> 0.083333333 | G14: 2520000 | I14: Leverage | J14: {=C64} -> 0.58 | K14: 0.585 | L14: =J14-K14 -> -0.005
A15: Utilities | B15: 480000 | C15: 510000 | D15: =IF(C15=0,"—",(B15-C15)/C15) -> -0.058823529 | E15: 460000 | F15: =IF(E15=0,"—",(B15-E15)/E15) -> 0.043478261 | G15: 1940000
A16: Property Taxes | B16: 1200000 | C16: 1200000 | D16: =IF(C16=0,"—",(B16-C16)/C16) -> 0 | E16: 1150000 | F16: =IF(E16=0,"—",(B16-E16)/E16) -> 0.043478261 | G16: 4800000
A17: Insurance | B17: 320000 | C17: 320000 | D17: =IF(C17=0,"—",(B17-C17)/C17) -> 0 | E17: 300000 | F17: =IF(E17=0,"—",(B17-E17)/E17) -> 0.066666667 | G17: 1280000
A18: Property Management | B18: 400000 | C18: 390000 | D18: =IF(C18=0,"—",(B18-C18)/C18) -> 0.025641026 | E18: 375000 | F18: =IF(E18=0,"—",(B18-E18)/E18) -> 0.066666667 | G18: 1555000
A19: Total Operating Expenses | B19: =SUM(B13:B18) -> 5150000 | C19: =SUM(C13:C18) -> 5090000 | D19: =IF(C19=0,"—",(B19-C19)/C19) -> 0.011787819 | E19: =SUM(E13:E18) -> 4865000 | F19: =IF(E19=0,"—",(B19-E19)/E19) -> 0.058581706 | G19: =SUM(G13:G18) -> 20275000
A20: 0
A21: NET OPERATING INCOME | B21: =B10-B19 -> 8200000 | C21: =C10-C19 -> 8030000 | D21: =IF(C21=0,"—",(B21-C21)/C21) -> 0.02117061 | E21: =E10-E19 -> 7715000 | F21: =IF(E21=0,"—",(B21-E21)/E21) -> 0.06286455 | G21: =G10-G19 -> 32115000
A23: FFO RECONCILIATION
B24: Q4 2025 | C24: Q3 2025 | D24: QoQ Chg | E24: Q4 2024 | F24: YoY Chg | G24: FY 2025
A25: Net Income (GAAP) | B25: 4200000 | C25: 4100000 | D25: =IF(C25=0,"—",(B25-C25)/ABS(C25)) -> 0.024390244 | E25: 4000000 | F25: =IF(E25=0,"—",(B25-E25)/ABS(E25)) -> 0.05 | G25: 16400000
A26: (+) Real Estate Depreciation | B26: 2800000 | C26: 2800000 | D26: =IF(C26=0,"—",(B26-C26)/ABS(C26)) -> 0 | E26: 2700000 | F26: =IF(E26=0,"—",(B26-E26)/ABS(E26)) -> 0.037037037 | G26: 11200000
A27: (+) Amortization | B27: 150000 | C27: 150000 | D27: =IF(C27=0,"—",(B27-C27)/ABS(C27)) -> 0 | E27: 140000 | F27: =IF(E27=0,"—",(B27-E27)/ABS(E27)) -> 0.071428571 | G27: 600000
A28: (-) Gain on Sale of Properties | B28: 0 | C28: 0 | D28: =IF(C28=0,"—",(B28-C28)/ABS(C28)) -> — | E28: 250000 | F28: =IF(E28=0,"—",(B28-E28)/ABS(E28)) -> -1 | G28: 250000
A29: (-) Unrealized Gains | B29: 100000 | C29: 50000 | D29: =IF(C29=0,"—",(B29-C29)/ABS(C29)) -> 1 | E29: 0 | F29: =IF(E29=0,"—",(B29-E29)/ABS(E29)) -> — | G29: 200000
A30: FFO (NAREIT Definition) | B30: =B25+B26+B27-B28-B29 -> 7050000 | C30: =C25+C26+C27-C28-C29 -> 7000000 | D30: =IF(C30=0,"—",(B30-C30)/ABS(C30)) -> 0.0071428571 | E30: =E25+E26+E27-E28-E29 -> 6590000 | F30: =IF(E30=0,"—",(B30-E30)/ABS(E30)) -> 0.069802731 | G30: =G25+G26+G27-G28-G29 -> 27750000
A31: 0
A32: FFO Adjustments:
A33: (+) Non-cash Interest Expense | B33: 75000 | C33: 75000 | D33: =IF(C33=0,"—",(B33-C33)/ABS(C33)) -> 0 | E33: 70000 | F33: =IF(E33=0,"—",(B33-E33)/ABS(E33)) -> 0.071428571 | G33: 300000
A34: (-) Straight-line Rent Adj | B34: 120000 | C34: 110000 | D34: =IF(C34=0,"—",(B34-C34)/ABS(C34)) -> 0.090909091 | E34: 100000 | F34: =IF(E34=0,"—",(B34-E34)/ABS(E34)) -> 0.2 | G34: 450000
A35: (+) Non-recurring Items | B35: 0 | C35: 85000 | D35: =IF(C35=0,"—",(B35-C35)/ABS(C35)) -> -1 | E35: 0 | F35: =IF(E35=0,"—",(B35-E35)/ABS(E35)) -> — | G35: 85000
A36: AFFO (Adjusted FFO) | B36: =B30+B33-B34+B35 -> 7005000 | C36: =C30+C33-C34+C35 -> 7050000 | D36: =IF(C36=0,"—",(B36-C36)/ABS(C36)) -> -0.0063829787 | E36: =E30+E33-E34+E35 -> 6560000 | F36: =IF(E36=0,"—",(B36-E36)/ABS(E36)) -> 0.067835366 | G36: =G30+G33-G34+G35 -> 27685000
A38: PER SHARE METRICS
A39: Shares Outstanding (diluted) | B39: 50000000 | C39: 50000000 | E39: 49500000 | G39: 50000000
A40: FFO per Share | B40: =B30/B39 -> 0.141 | C40: =C30/C39 -> 0.14 | E40: =E30/E39 -> 0.13313131 | G40: =G30/G39 -> 0.555
A41: AFFO per Share | B41: =B36/B39 -> 0.1401 | C41: =C36/C39 -> 0.141 | E41: =E36/E39 -> 0.13252525 | G41: =G36/G39 -> 0.5537
A43: SAME-STORE NOI RECONCILIATION
B44: Q4 2025 | C44: Q4 2024 | D44: $ Change | E44: % Change | F44: Properties
A45: Total Portfolio NOI | B45: 8200000 | C45: 7715000 | D45: =B45-C45 -> 485000 | E45: =D45/C45 -> 0.06286455 | F45: 12
A46: Less: Non-Same-Store Properties
A47: Acquisitions (<12 months) | B47: 450000 | C47: 0 | F47: 2
A48: Dispositions | B48: 0 | C48: 280000 | F48: 1
A49: Development/Lease-up | B49: 320000 | C49: 150000 | F49: 1
A50: Total Non-Same-Store | B50: =B47+B48+B49 -> 770000 | C50: =C47+C48+C49 -> 430000 | F50: =F47+F48+F49 -> 4
A51: 0
A52: SAME-STORE NOI | B52: =B45-B50 -> 7430000 | C52: =C45-C50 -> 7285000 | D52: =B52-C52 -> 145000 | E52: =D52/C52 -> 0.019903912 | F52: =F45-F50 -> 8
A53: 0
A54: Same-Store NOI Bridge:
A55: Prior Period Same-Store NOI | C55: 7285000
A56: Revenue Growth | D56: 380000 | E56: =D56/C55 -> 0.052161977
A57: Expense Change | D57: -120000 | E57: =D57/C55 -> -0.016472203
A58: Current Period Same-Store NOI | B58: {=B52} -> 7430000 | D58: =D56+D57 -> 260000 | E58: =D58/C55 -> 0.035689774
A60: COVENANT COMPLIANCE TABLE
A61: Covenant | B61: Requirement | C61: Current | D61: Headroom | E61: Status | F61: Trend | G61: Next Test | H61: Lender
A62: Debt Service Coverage Ratio | B62: ≥ 1.25x | C62: 1.52 | D62: =C62-1.25 -> 0.27 | E62: PASS | F62: ↑ | G62: Mar 31, 2026 | H62: Wells Fargo
A63: Interest Coverage Ratio | B63: ≥ 2.00x | C63: 2.85 | D63: =C63-2 -> 0.85 | E63: PASS | F63: ↑ | G63: Mar 31, 2026 | H63: Wells Fargo
A64: Leverage Ratio (Debt/Assets) | B64: ≤ 65% | C64: 0.58 | D64: =0.65-C64 -> 0.07 | E64: PASS | F64: → | G64: Mar 31, 2026 | H64: JPMorgan
A65: Secured Debt Ratio | B65: ≤ 40% | C65: 0.32 | D65: =0.40-C65 -> 0.08 | E65: PASS | F65: ↓ | G65: Mar 31, 2026 | H65: JPMorgan
A66: Unencumbered Asset Coverage | B66: ≥ 150% | C66: 2.15 | D66: =C66-1.5 -> 0.65 | E66: PASS | F66: ↑ | G66: Mar 31, 2026 | H66: Unsecured
A67: Minimum Net Worth | B67: ≥ $150M | C67: $185M | E67: PASS | F67: ↑ | G67: Mar 31, 2026 | H67: All
A68: Minimum Liquidity | B68: ≥ $25M | C68: $42M | E68: PASS | F68: → | G68: Quarterly | H68: All

Sheet FIN_03_Rent_Roll
A1: RENT ROLL & LEASE EXPIRATIONS
A3: RENT ROLL SUMMARY
A4: Unit | B4: Type | C4: SqFt | D4: Status | E4: Resident | F4: Lease Start | G4: Lease End | H4: Contract Rent | I4: Market Rent | J4: NER | K4: Concession
A6: LEASE EXPIRATION SCHEDULE (24 MONTHS) | F6: Total Units: | G6: 251
A7: Month | B7: Units Expiring | C7: % of Portfolio | D7: Cumulative
A8: Feb 26 | B8: 8 | C8: =B8/$G$6 -> 0.03187251 | D8: {=B8} -> 8
A9: Mar 26 | B9: 12 | C9: =B9/$G$6 -> 0.047808765 | D9: =D8+B9 -> 20
A10: Apr 26 | B10: 15 | C10: =B10/$G$6 -> 0.059760956 | D10: =D9+B10 -> 35
A11: May 26 | B11: 18 | C11: =B11/$G$6 -> 0.071713147 | D11: =D10+B11 -> 53
A12: Jun 26 | B12: 22 | C12: =B12/$G$6 -> 0.087649402 | D12: =D11+B12 -> 75
A13: Jul 26 | B13: 25 | C13: =B13/$G$6 -> 0.099601594 | D13: =D12+B13 -> 100
A14: Aug 26 | B14: 20 | C14: =B14/$G$6 -> 0.079681275 | D14: =D13+B14 -> 120
A15: Sep 26 | B15: 18 | C15: =B15/$G$6 -> 0.071713147 | D15: =D14+B15 -> 138
A16: Oct 26 | B16: 14 | C16: =B16/$G$6 -> 0.055776892 | D16: =D15+B16 -> 152
A17: Nov 26 | B17: 10 | C17: =B17/$G$6 -> 0.039840637 | D17: =D16+B17 -> 162
A18: Dec 26 | B18: 8 | C18: =B18/$G$6 -> 0.03187251 | D18: =D17+B18 -> 170
A19: Jan 27 | B19: 6 | C19: =B19/$G$6 -> 0.023904382 | D19: =D18+B19 -> 176
A20: Feb 27 | B20: 9 | C20: =B20/$G$6 -> 0.035856574 | D20: =D19+B20 -> 185
... A31: Jan 28 | B31: 5 | C31: =B31/$G$6 -> 0.019920319 | D31: =D30+B31 -> 341

Sheet FIN_04_Budget_Variance
A1: BUDGET VS ACTUAL VARIANCE ANALYSIS | L1: =HYPERLINK("#Alert_Dashboard!B2","← Back to Alerts") -> ← Back to Alerts
A2: =TEXT(DATE(2026,1,1),"mmmm yyyy")&" | MTD and YTD Analysis by Cost Center" -> January 2026 | MTD and YTD Analysis by Cost Center
A4: SUMMARY
A6: MTD Actual | B6: MTD Budget | C6: MTD Variance | E6: YTD Actual | F6: YTD Budget | G6: YTD Variance | I6: Var % | J6: Status
A7: =SUM(C10:C22) -> 621000 | B7: =SUM(D10:D22) -> 585000 | C7: =A7-B7 -> 36000 | E7: =SUM(F10:F22) -> 621000 | F7: =SUM(G10:G22) -> 585000 | G7: =E7-F7 -> 36000 | I7: =IF(F7=0,0,(E7-F7)/F7) -> 0.061538462 | J7: =IF(I7>=-0.05,"✓",IF(I7>=-0.10,"⚠","✗")) -> ✓
A9: VARIANCE BY COST CENTER
A10: Cost Center | B10: Description | C10: MTD Actual | D10: MTD Budget | E10: MTD Var | F10: YTD Actual | G10: YTD Budget | H10: YTD Var | I10: Var % | J10: Status | K10: Commentary
A11: 4100 | B11: Rental Revenue | C11: 1125000 | D11: 1100000 | E11: =C11-D11 -> 25000 | F11: 1125000 | G11: 1100000 | H11: =F11-G11 -> 25000 | I11: =IF(G11=0,0,(F11-G11)/ABS(G11)) -> 0.022727273 | J11: =IF(I11>=-0.05,"✓",IF(I11>=-0.10,"⚠","✗")) -> ✓ | K11: Strong occupancy driving above-plan revenue
A12: 4200 | B12: Other Income | C12: 45000 | D12: 50000 | E12: =C12-D12 -> -5000 | F12: 45000 | G12: 50000 | H12: =F12-G12 -> -5000 | I12: =IF(G12=0,0,(F12-G12)/ABS(G12)) -> -0.1 | J12: =IF(I12>=-0.05,"✓",IF(I12>=-0.10,"⚠","✗")) -> ⚠ | K12: Parking revenue below target; evaluating rate increase
A13: 4300 | B13: Concessions | C13: -28000 | D13: -35000 | E13: =C13-D13 -> 7000 | F13: -28000 | G13: -35000 | H13: =F13-G13 -> 7000 | I13: =IF(G13=0,0,(F13-G13)/ABS(G13)) -> 0.2 | J13: =IF(I13>=-0.05,"✓",IF(I13>=-0.10,"⚠","✗")) -> ✓ | K13: Lower concessions needed due to strong demand
A14: 5100 | B14: Payroll & Benefits | C14: -185000 | D14: -180000 | E14: =C14-D14 -> -5000 | F14: -185000 | G14: -180000 | H14: =F14-G14 -> -5000 | I14: =IF(G14=0,0,(F14-G14)/ABS(G14)) -> -0.027777778 | J14: =IF(I14>=-0.05,"✓",IF(I14>=-0.10,"⚠","✗")) -> ✓ | K14: Overtime for maintenance backlog; expect normalization Q2
A15: 5200 | B15: Repairs & Maintenance | C15: -62000 | D15: -70000 | E15: =C15-D15 -> 8000 | F15: -62000 | G15: -70000 | H15: =F15-G15 -> 8000 | I15: =IF(G15=0,0,(F15-G15)/ABS(G15)) -> 0.11428571 | J15: =IF(I15>=-0.05,"✓",IF(I15>=-0.10,"⚠","✗")) -> ✓ | K15: Preventive maintenance program reducing reactive costs
A16: 5300 | B16: Utilities | C16: -48000 | D16: -55000 | E16: =C16-D16 -> 7000 | F16: -48000 | G16: -55000 | H16: =F16-G16 -> 7000 | I16: =IF(G16=0,0,(F16-G16)/ABS(G16)) -> 0.12727273 | J16: =IF(I16>=-0.05,"✓",IF(I16>=-0.10,"⚠","✗")) -> ✓ | K16: Mild weather and LED retrofit savings
A17: 5400 | B17: Insurance | C17: -32000 | D17: -30000 | E17: =C17-D17 -> -2000 | F17: -32000 | G17: -30000 | H17: =F17-G17 -> -2000 | I17: =IF(G17=0,0,(F17-G17)/ABS(G17)) -> -0.066666667 | J17: =IF(I17>=-0.05,"✓",IF(I17>=-0.10,"⚠","✗")) -> ⚠ | K17: Premium increase at renewal; shopping alternatives
A18: 5500 | B18: Property Taxes | C18: -85000 | D18: -85000 | E18: =C18-D18 -> 0 | F18: -85000 | G18: -85000 | H18: =F18-G18 -> 0 | I18: =IF(G18=0,0,(F18-G18)/ABS(G18)) -> 0 | J18: =IF(I18>=-0.05,"✓",IF(I18>=-0.10,"⚠","✗")) -> ✓ | K18: On budget; appeal pending for 2027
A19: 5600 | B19: Marketing | C19: -24000 | D19: -28000 | E19: =C19-D19 -> 4000 | F19: -24000 | G19: -28000 | H19: =F19-G19 -> 4000 | I19: =IF(G19=0,0,(F19-G19)/ABS(G19)) -> 0.14285714 | J19: =IF(I19>=-0.05,"✓",IF(I19>=-0.10,"⚠","✗")) -> ✓ | K19: Shifted spend to digital; higher ROI channels
A20: 5700 | B20: Professional Fees | C20: -18000 | D20: -15000 | E20: =C20-D20 -> -3000 | F20: -18000 | G20: -15000 | H20: =F20-G20 -> -3000 | I20: =IF(G20=0,0,(F20-G20)/ABS(G20)) -> -0.2 | J20: =IF(I20>=-0.05,"✓",IF(I20>=-0.10,"⚠","✗")) -> ✗ | K20: Legal fees for lease dispute; one-time
A21: 5800 | B21: Admin & General | C21: -22000 | D21: -25000 | E21: =C21-D21 -> 3000 | F21: -22000 | G21: -25000 | H21: =F21-G21 -> 3000 | I21: =IF(G21=0,0,(F21-G21)/ABS(G21)) -> 0.12 | J21: =IF(I21>=-0.05,"✓",IF(I21>=-0.10,"⚠","✗")) -> ✓ | K21: Cost control initiatives showing results
A22: 5900 | B22: Contract Services | C22: -45000 | D22: -42000 | E22: =C22-D22 -> -3000 | F22: -45000 | G22: -42000 | H22: =F22-G22 -> -3000 | I22: =IF(G22=0,0,(F22-G22)/ABS(G22)) -> -0.071428571 | J22: =IF(I22>=-0.05,"✓",IF(I22>=-0.10,"⚠","✗")) -> ⚠ | K22: Landscaping scope expansion; renegotiating for Q2
B23: TOTAL | C23: =SUM(C11:C22) -> 621000 | D23: =SUM(D11:D22) -> 585000 | E23: =C23-D23 -> 36000 | F23: =SUM(F11:F22) -> 621000 | G23: =SUM(G11:G22) -> 585000 | H23: =F23-G23 -> 36000 | I23: =IF(G23=0,0,(F23-G23)/ABS(G23)) -> 0.061538462 | J23: =IF(I23>=-0.05,"✓",IF(I23>=-0.10,"⚠","✗")) -> ✓
A25: MONTHLY VARIANCE TREND
A26: Month | B26: Actual | C26: Budget | D26: Variance $ | E26: Var % | F26: Cum Actual | G26: Cum Budget | H26: Cum Var $ | I26: Cum Var % | J26: Status | K26: Monthly Commentary
A27: Jan-26 | B27: 621000 | C27: 585000 | D27: =B27-C27 -> 36000 | E27: =IF(C27=0,0,(B27-C27)/C27) -> 0.061538462 | F27: {=IF(B27="—",0,B27)} -> 621000 | G27: {=C27} -> 585000 | H27: =F27-G27 -> 36000 | I27: =IF(G27=0,0,(F27-G27)/G27) -> 0.061538462 | J27: =IF(I27>=-0.05,"✓",IF(I27>=-0.10,"⚠","✗")) -> ✓ | K27: Strong start; revenue ahead, controlled costs
A28: Feb-26 | B28: — | C28: 590000 | D28: — | E28: — | F28: {=IF(B28="—",F27,F27+B28)} -> 621000 | G28: =G27+C28 -> 1175000 | H28: =F28-G28 -> -554000 | I28: =IF(G28=0,0,(F28-G28)/G28) -> -0.47148936 | J28: =IF(I28>=-0.05,"✓",IF(I28>=-0.10,"⚠","✗")) -> ✗ | K28: [Forecast: Expected seasonal increase in utilities]
A29: Mar-26 | B29: — | C29: 605000 | D29: — | E29: — | F29: {=IF(B29="—",F28,F28+B29)} -> 621000 | G29: =G28+C29 -> 1780000 | H29: =F29-G29 -> -1159000 | I29: =IF(G29=0,0,(F29-G29)/G29) -> -0.6511236 | J29: =IF(I29>=-0.05,"✓",IF(I29>=-0.10,"⚠","✗")) -> ✗ | K29: [Forecast: Q1 close; property tax payment]
A30: Apr-26 | B30: — | C30: 615000 | D30: — | E30: — | F30: {=IF(B30="—",F29,F29+B30)} -> 621000 | G30: =G29+C30 -> 2395000 | H30: =F30-G30 -> -1774000 | I30: =IF(G30=0,0,(F30-G30)/G30) -> -0.74070981 | J30: =IF(I30>=-0.05,"✓",IF(I30>=-0.10,"⚠","✗")) -> ✗ | K30: [Forecast: Spring leasing season begins]
A31: May-26 | B31: — | C31: 625000 | D31: — | E31: — | F31: {=IF(B31="—",F30,F30+B31)} -> 621000 | G31: =G30+C31 -> 3020000 | H31: =F31-G31 -> -2399000 | I31: =IF(G31=0,0,(F31-G31)/G31) -> -0.79437086 | J31: =IF(I31>=-0.05,"✓",IF(I31>=-0.10,"⚠","✗")) -> ✗ | K31: [Forecast: Peak leasing; marketing spend increase]
A32: Jun-26 | B32: — | C32: 620000 | D32: — | E32: — | F32: {=IF(B32="—",F31,F31+B32)} -> 621000 | G32: =G31+C32 -> 3640000 | H32: =F32-G32 -> -3019000 | I32: =IF(G32=0,0,(F32-G32)/G32) -> -0.8293956 | J32: =IF(I32>=-0.05,"✓",IF(I32>=-0.10,"⚠","✗")) -> ✗ | K32: [Forecast: Summer maintenance projects]
A33: Jul-26 | B33: — | C33: 610000 | D33: — | E33: — | F33: {=IF(B33="—",F32,F32+B33)} -> 621000 | G33: =G32+C33 -> 4250000 | H33: =F33-G33 -> -3629000 | I33: =IF(G33=0,0,(F33-G33)/G33) -> -0.85388235 | J33: =IF(I33>=-0.05,"✓",IF(I33>=-0.10,"⚠","✗")) -> ✗ | K33: [Forecast: Turnover season peak]
A34: Aug-26 | B34: — | C34: 605000 | D34: — | E34: — | F34: {=IF(B34="—",F33,F33+B34)} -> 621000 | G34: =G33+C34 -> 4855000 | H34: =F34-G34 -> -4234000 | I34: =IF(G34=0,0,(F34-G34)/G34) -> -0.87209063 | J34: =IF(I34>=-0.05,"✓",IF(I34>=-0.10,"⚠","✗")) -> ✗ | K34: [Forecast: Back-to-school move-ins]
A35: Sep-26 | B35: — | C35: 595000 | D35: — | E35: — | F35: {=IF(B35="—",F34,F34+B35)} -> 621000 | G35: =G34+C35 -> 5450000 | H35: =F35-G35 -> -4829000 | I35: =IF(G35=0,0,(F35-G35)/G35) -> -0.88605505 | J35: =IF(I35>=-0.05,"✓",IF(I35>=-0.10,"⚠","✗")) -> ✗ | K35: [Forecast: Fall stabilization]
A36: Oct-26 | B36: — | C36: 590000 | D36: — | E36: — | F36: {=IF(B36="—",F35,F35+B36)} -> 621000 | G36: =G35+C36 -> 6040000 | H36: =F36-G36 -> -5419000 | I36: =IF(G36=0,0,(F36-G36)/G36) -> -0.89718543 | J36: =IF(I36>=-0.05,"✓",IF(I36>=-0.10,"⚠","✗")) -> ✗ | K36: [Forecast: Pre-winter maintenance]
A37: Nov-26 | B37: — | C37: 580000 | D37: — | E37: — | F37: {=IF(B37="—",F36,F36+B37)} -> 621000 | G37: =G36+C37 -> 6620000 | H37: =F37-G37 -> -5999000 | I37: =IF(G37=0,0,(F37-G37)/G37) -> -0.90619335 | J37: =IF(I37>=-0.05,"✓",IF(I37>=-0.10,"⚠","✗")) -> ✗ | K37: [Forecast: Holiday slowdown]
A38: Dec-26 | B38: — | C38: 575000 | D38: — | E38: — | F38: {=IF(B38="—",F37,F37+B38)} -> 621000 | G38: =G37+C38 -> 7195000 | H38: =F38-G38 -> -6574000 | I38: =IF(G38=0,0,(F38-G38)/G38) -> -0.91369006 | J38: =IF(I38>=-0.05,"✓",IF(I38>=-0.10,"⚠","✗")) -> ✗ | K38: [Forecast: Year-end close; accruals]
A39: ANNUAL TOTAL | B39: =SUMIF(B27:B38,"<>—") -> 621000 | C39: =SUM(C27:C38) -> 7195000 | D39: =B39-C39 -> -6574000 | E39: =IF(C39=0,0,(B39-C39)/C39) -> -0.91369006 | F39: {=F38} -> 621000 | G39: {=G38} -> 7195000 | H39: =F39-G39 -> -6574000 | I39: =IF(G39=0,0,(F39-G39)/G39) -> -0.91369006 | J39: =IF(I39>=-0.05,"✓",IF(I39>=-0.10,"⚠","✗")) -> ✗ | K39: Full year projection based on current trends
A41: EXECUTIVE COMMENTARY & ACTION ITEMS
A42: Category | B42: Impact | C42: Commentary | J42: Owner | K42: Due Date
A43: ✓ Favorable | B43: 42000 | C43: Revenue: Occupancy at 95.2% vs 94% budget driving rental income above plan. | J43: Leasing Dir | K43: Ongoing
A44: ✓ Favorable | B44: 15000 | C44: Utilities: LED retrofit completed; mild January weather reduced heating costs. | J44: Ops Mgr | K44: Ongoing
A45: ⚠ Watch | B45: -5000 | C45: Payroll: Overtime for maintenance backlog. Hiring additional tech in Feb. | J45: HR Dir | K45: Feb-15
A46: ⚠ Watch | B46: -2000 | C46: Insurance: 6.7% premium increase at renewal. Obtaining competitive quotes. | J46: CFO | K46: Mar-31
A47: ✗ Risk | B47: -3000 | C47: Professional Fees: Unbudgeted legal costs for tenant dispute. | J47: Legal | K47: Feb-28
A48: Action Item | B48: N/A | C48: Prepare Q1 forecast revision incorporating actual January results. | J48: FP&A | K48: Feb-10
A50: Prepared by: | B50: [Finance Team] | E50: Last Updated: | F50: =TEXT(NOW(),"mmmm d, yyyy h:mm AM/PM") -> January 12, 2026 9:41 AM | J50: Next Review: | K50: Feb 10, 2026

Sheet FIN_05_Cash_Flow
A1: 12-MONTH CASH FLOW FORECAST & LIQUIDITY
A3: ROLLING 12-MONTH CASH FLOW FORECAST | P3: CASH FLOW SUMMARY
A4: Line Item | B4: Jan-26 | C4: Feb-26 | D4: Mar-26 | E4: Apr-26 | F4: May-26 | G4: Jun-26 | H4: Jul-26 | I4: Aug-26 | J4: Sep-26 | K4: Oct-26 | L4: Nov-26 | M4: Dec-26 | N4: TOTAL | P4: TTM NOI | Q4: {=N11} -> 3650000
A5: OPERATING CASH FLOW | P5: TTM Debt Service | Q5: {=N19} -> -2026800
A6: Gross Potential Rent | B6: 485000 | C6: 488000 | D6: 492000 | E6: 495000 | F6: 498000 | G6: 502000 | H6: 505000 | I6: 508000 | J6: 512000 | K6: 515000 | L6: 518000 | M6: 522000 | N6: =SUM(B6:M6) -> 6040000 | P6: TTM Net Cash Flow | Q6: {=N23} -> 1352200
A7: (-) Vacancy/Concessions | B7: =-B6*0.05 -> -24250 | C7: =-C6*0.05 -> -24400 | D7: =-D6*0.05 -> -24600 | E7: =-E6*0.05 -> -24750 | F7: =-F6*0.05 -> -24900 | G7: =-G6*0.05 -> -25100 | H7: =-H6*0.05 -> -25250 | I7: =-I6*0.05 -> -25400 | ... M7: =-M6*0.05 -> -26100 | N7: =SUM(B7:M7) -> -302000 | P7: Current Cash | Q7: {=B24} -> 2500000
A8: Net Rental Revenue | B8: =B6+B7 -> 460750 | C8: =C6+C7 -> 463600 | D8: =D6+D7 -> 467400 | E8: =E6+E7 -> 470250 | F8: =F6+F7 -> 473100 | G8: =G6+G7 -> 476900 | H8: =H6+H7 -> 479750 | I8: =I6+I7 -> 482600 | ... M8: =M6+M7 -> 495900 | N8: =SUM(B8:M8) -> 5738000 | P8: EOY Cash | Q8: {=N25} -> 3852200
A9: (+) Other Income | B9: 18500 | C9: 18500 | D9: 18500 | E9: 18500 | F9: 18500 | G9: 18500 | H9: 18500 | I9: 18500 | J9: 18500 | K9: 18500 | L9: 18500 | M9: 18500 | N9: =SUM(B9:M9) -> 222000 | P9: Cash Build | Q9: =Q8-Q7 -> 1352200
A10: (-) Operating Expenses | B10: -185000 | C10: -186000 | D10: -187000 | E10: -188000 | F10: -190000 | G10: -192000 | H10: -194000 | I10: -195000 | J10: -196000 | K10: -198000 | L10: -199000 | M10: -200000 | N10: =SUM(B10:M10) -> -2310000 | P10: Avg DSCR | Q10: =AVERAGE(B20:M20) -> 1.8010422
A11: Net Operating Income (NOI) | B11: =B8+B9+B10 -> 294250 | C11: =C8+C9+C10 -> 296100 | D11: =D8+D9+D10 -> 298900 | E11: =E8+E9+E10 -> 300750 | F11: =F8+F9+F10 -> 301600 | G11: =G8+G9+G10 -> 303400 | H11: =H8+H9+H10 -> 304250 | I11: =I8+I9+I10 -> 306100 | ... M11: =M8+M9+M10 -> 314400 | N11: =SUM(B11:M11) -> 3650000 | P11: Runway (months) | Q11: {=B34} -> 14.801658
A12: (-) Capital Expenditures | B12: -25000 | C12: -15000 | D12: -20000 | E12: -18000 | F12: -22000 | G12: -30000 | H12: -35000 | I12: -28000 | J12: -20000 | K12: -15000 | L12: -18000 | M12: -25000 | N12: =SUM(B12:M12) -> -271000
A13: (+/-) Working Capital Δ | B13: -5000 | C13: 3000 | D13: -2000 | E13: 4000 | F13: -3000 | G13: 2000 | H13: -4000 | I13: 3000 | J13: -2000 | K13: 5000 | L13: -3000 | M13: 2000 | N13: =SUM(B13:M13) -> 0
A14: Cash from Operations | B14: =B11+B12+B13 -> 264250 | C14: =C11+C12+C13 -> 284100 | D14: =D11+D12+D13 -> 276900 | E14: =E11+E12+E13 -> 286750 | F14: =F11+F12+F13 -> 276600 | G14: =G11+G12+G13 -> 275400 | H14: =H11+H12+H13 -> 265250 | I14: =I11+I12+I13 -> 281100 | ... M14: =M11+M12+M13 -> 291400 | N14: =SUM(B14:M14) -> 3379000
A16: DEBT SERVICE
A17: (-) Interest Expense | B17: -125000 | C17: -124800 | D17: -124600 | E17: -124400 | F17: -124200 | G17: -124000 | H17: -123800 | I17: -123600 | J17: -123400 | K17: -123200 | L17: -123000 | M17: -122800 | N17: =SUM(B17:M17) -> -1486800
A18: (-) Principal Payments | B18: -45000 | C18: -45000 | D18: -45000 | E18: -45000 | F18: -45000 | G18: -45000 | H18: -45000 | I18: -45000 | J18: -45000 | K18: -45000 | L18: -45000 | M18: -45000 | N18: =SUM(B18:M18) -> -540000
A19: Total Debt Service | B19: =B17+B18 -> -170000 | C19: =C17+C18 -> -169800 | D19: =D17+D18 -> -169600 | E19: =E17+E18 -> -169400 | F19: =F17+F18 -> -169200 | G19: =G17+G18 -> -169000 | H19: =H17+H18 -> -168800 | I19: =I17+I18 -> -168600 | ... M19: =M17+M18 -> -167800 | N19: =SUM(B19:M19) -> -2026800
A20: DSCR (Monthly) | B20: =IF(B19=0,0,B11/-B19) -> 1.7308824 | C20: =IF(C19=0,0,C11/-C19) -> 1.7438163 | D20: =IF(D19=0,0,D11/-D19) -> 1.7623821 | E20: =IF(E19=0,0,E11/-E19) -> 1.7753837 | F20: =IF(F19=0,0,F11/-F19) -> 1.7825059 | G20: =IF(G19=0,0,G11/-G19) -> 1.7952663 | H20: =IF(H19=0,0,H11/-H19) -> 1.8024289 | I20: =IF(I19=0,0,I11/-I19) -> 1.8155397 | ... N20: =IF(N19=0,0,N11/-N19) -> 1.8008684
A22: LIQUIDITY & CASH POSITION
A23: Net Cash Flow | B23: =B14+B19 -> 94250 | C23: =C14+C19 -> 114300 | D23: =D14+D19 -> 107300 | E23: =E14+E19 -> 117350 | F23: =F14+F19 -> 107400 | G23: =G14+G19 -> 106400 | H23: =H14+H19 -> 96450 | I23: =I14+I19 -> 112500 | ... M23: =M14+M19 -> 123600 | N23: =SUM(B23:M23) -> 1352200
A24: Beginning Cash | B24: 2500000 | C24: {=B25} -> 2594250 | D24: {=C25} -> 2708550 | E24: {=D25} -> 2815850 | F24: {=E25} -> 2933200 | G24: {=F25} -> 3040600 | H24: {=G25} -> 3147000 | I24: {=H25} -> 3243450 | J24: {=I25} -> 3355950 | ... M24: {=L25} -> 3728600
A25: Ending Cash | B25: =B24+B23 -> 2594250 | C25: =C24+C23 -> 2708550 | D25: =D24+D23 -> 2815850 | E25: =E24+E23 -> 2933200 | F25: =F24+F23 -> 3040600 | G25: =G24+G23 -> 3147000 | H25: =H24+H23 -> 3243450 | I25: =I24+I23 -> 3355950 | ... M25: =M24+M23 -> 3852200 | N25: {=M25} -> 3852200
A26: Minimum Cash Required | B26: 500000 | C26: 500000 | D26: 500000 | E26: 500000 | F26: 500000 | G26: 500000 | H26: 500000 | I26: 500000 | J26: 500000 | K26: 500000 | L26: 500000 | M26: 500000
A27: Cash Surplus/(Deficit) | B27: =B25-B26 -> 2094250 | C27: =C25-C26 -> 2208550 | D27: =D25-D26 -> 2315850 | E27: =E25-E26 -> 2433200 | F27: =F25-F26 -> 2540600 | G27: =G25-G26 -> 2647000 | H27: =H25-H26 -> 2743450 | I27: =I25-I26 -> 2855950 | ... M27: =M25-M26 -> 3352200 | N27: {=M27} -> 3352200
A29: LIQUIDITY RUNWAY ANALYSIS
A30: Metric | B30: Value | C30: Notes
A31: Current Cash Position | B31: {=B24} -> 2500000 | C31: As of Jan 2026
A32: Avg Monthly Burn Rate | B32: =AVERAGE(B19:M19) -> -168900 | C32: Total debt service/12
A33: Avg Monthly Net Cash | B33: =AVERAGE(B23:M23) -> 112683.33 | C33: After all obligations
A34: Runway (months @ break-even) | B34: =IF(B32=0,0,B31/-B32) -> 14.801658 | C34: Cash / Monthly burn
A35: Projected EOY Cash | B35: {=N25} -> 3852200 | C35: Dec 2026 ending balance
A36: Min DSCR (12-mo) | B36: =MIN(B20:M20) -> 1.7308824 | C36: Lowest monthly DSCR
A37: Avg DSCR (12-mo) | B37: =AVERAGE(B20:M20) -> 1.8010422 | C37: Average monthly DSCR

Sheet FIN_06_Capex
A1: CAPEX PIPELINE & SPEND VS BUDGET
A3: CAPEX PROJECT PIPELINE (2026)
A4: Project | B4: Category | C4: Budget | D4: Committed | E4: Paid | F4: Remaining | G4: ETC | H4: EAC | I4: Variance | J4: % Spent | K4: Status
A5: HVAC Replacement - Bldg A | B5: Major Systems | C5: 185000 | D5: 175000 | E5: 142000 | F5: =D5-E5 -> 33000 | G5: =MAX(0,C5-D5)+F5 -> 43000 | H5: =E5+G5 -> 185000 | I5: =C5-H5 -> 0 | J5: =IF(C5=0,0,E5/C5) -> 0.76756757 | K5: =IF(J5>=1,"Complete",IF(J5>=0.75,"In Progress",IF(D5>0,"Committed","Planned"))) -> In Progress
A6: Roof Repair - West Wing | B6: Major Systems | C6: 95000 | D6: 92000 | E6: 88000 | F6: =D6-E6 -> 4000 | G6: =MAX(0,C6-D6)+F6 -> 7000 | H6: =E6+G6 -> 95000 | I6: =C6-H6 -> 0 | J6: =IF(C6=0,0,E6/C6) -> 0.92631579 | K6: =IF(J6>=1,"Complete",IF(J6>=0.75,"In Progress",IF(D6>0,"Committed","Planned"))) -> In Progress
A7: Lobby Renovation | B7: Common Area | C7: 125000 | D7: 118000 | E7: 65000 | F7: =D7-E7 -> 53000 | G7: =MAX(0,C7-D7)+F7 -> 60000 | H7: =E7+G7 -> 125000 | I7: =C7-H7 -> 0 | J7: =IF(C7=0,0,E7/C7) -> 0.52 | K7: =IF(J7>=1,"Complete",IF(J7>=0.75,"In Progress",IF(D7>0,"Committed","Planned"))) -> Committed
A8: Elevator Modernization | B8: Major Systems | C8: 320000 | D8: 285000 | E8: 180000 | F8: =D8-E8 -> 105000 | G8: =MAX(0,C8-D8)+F8 -> 140000 | H8: =E8+G8 -> 320000 | I8: =C8-H8 -> 0 | J8: =IF(C8=0,0,E8/C8) -> 0.5625 | K8: =IF(J8>=1,"Complete",IF(J8>=0.75,"In Progress",IF(D8>0,"Committed","Planned"))) -> Committed
A9: Pool Deck Resurfacing | B9: Common Area | C9: 48000 | D9: 48000 | E9: 48000 | F9: =D9-E9 -> 0 | G9: =MAX(0,C9-D9)+F9 -> 0 | H9: =E9+G9 -> 48000 | I9: =C9-H9 -> 0 | J9: =IF(C9=0,0,E9/C9) -> 1 | K9: =IF(J9>=1,"Complete",IF(J9>=0.75,"In Progress",IF(D9>0,"Committed","Planned"))) -> Complete
A10: Unit Upgrades (15 units) | B10: Unit Turns | C10: 112500 | D10: 98000 | E10: 82500 | F10: =D10-E10 -> 15500 | G10: =MAX(0,C10-D10)+F10 -> 30000 | H10: =E10+G10 -> 112500 | I10: =C10-H10 -> 0 | J10: =IF(C10=0,0,E10/C10) -> 0.73333333 | K10: =IF(J10>=1,"Complete",IF(J10>=0.75,"In Progress",IF(D10>0,"Committed","Planned"))) -> Committed
A11: Parking Lot Repairs | B11: Site Work | C11: 65000 | D11: 58000 | E11: 45000 | F11: =D11-E11 -> 13000 | G11: =MAX(0,C11-D11)+F11 -> 20000 | H11: =E11+G11 -> 65000 | I11: =C11-H11 -> 0 | J11: =IF(C11=0,0,E11/C11) -> 0.69230769 | K11: =IF(J11>=1,"Complete",IF(J11>=0.75,"In Progress",IF(D11>0,"Committed","Planned"))) -> Committed
A12: Security System Upgrade | B12: Common Area | C12: 38000 | D12: 32000 | E12: 28000 | F12: =D12-E12 -> 4000 | G12: =MAX(0,C12-D12)+F12 -> 10000 | H12: =E12+G12 -> 38000 | I12: =C12-H12 -> 0 | J12: =IF(C12=0,0,E12/C12) -> 0.73684211 | K12: =IF(J12>=1,"Complete",IF(J12>=0.75,"In Progress",IF(D12>0,"Committed","Planned"))) -> Committed
A13: Landscaping Phase 2 | B13: Site Work | C13: 28000 | D13: 22000 | E13: 18000 | F13: =D13-E13 -> 4000 | G13: =MAX(0,C13-D13)+F13 -> 10000 | H13: =E13+G13 -> 28000 | I13: =C13-H13 -> 0 | J13: =IF(C13=0,0,E13/C13) -> 0.64285714 | K13: =IF(J13>=1,"Complete",IF(J13>=0.75,"In Progress",IF(D13>0,"Committed","Planned"))) -> Committed
A14: Contingency Reserve | B14: Contingency | C14: 75000 | D14: 0 | E14: 0 | F14: =D14-E14 -> 0 | G14: =MAX(0,C14-D14)+F14 -> 75000 | H14: =E14+G14 -> 75000 | I14: =C14-H14 -> 0 | J14: =IF(C14=0,0,E14/C14) -> 0 | K14: =IF(J14>=1,"Complete",IF(J14>=0.75,"In Progress",IF(D14>0,"Committed","Planned"))) -> Planned
A15: TOTAL | B15: 0 | C15: =SUM(C5:C14) -> 1091500 | D15: =SUM(D5:D14) -> 928000 | E15: =SUM(E5:E14) -> 696500 | F15: =SUM(F5:F14) -> 231500 | G15: =SUM(G5:G14) -> 395000 | H15: =SUM(H5:H14) -> 1091500 | I15: =SUM(I5:I14) -> 0 | J15: =IF(C15=0,0,E15/C15) -> 0.63811269 | K15: 0
A17: SPEND BY CATEGORY | H17: CAPEX SUMMARY
A18: Category | B18: Annual Budget | C18: Committed | D18: Paid YTD | E18: % Utilized | F18: Remaining | H18: Annual Budget | I18: {=C15} -> 1091500
A19: Major Systems | B19: =SUMIF($B$5:$B$14,A19,$C$5:$C$14) -> 600000 | C19: =SUMIF($B$5:$B$14,A19,$D$5:$D$14) -> 552000 | D19: =SUMIF($B$5:$B$14,A19,$E$5:$E$14) -> 410000 | E19: =IF(B19=0,0,D19/B19) -> 0.68333333 | F19: =B19-D19 -> 190000 | H19: Total Committed | I19: {=D15} -> 928000
A20: Common Area | B20: =SUMIF($B$5:$B$14,A20,$C$5:$C$14) -> 211000 | C20: =SUMIF($B$5:$B$14,A20,$D$5:$D$14) -> 198000 | D20: =SUMIF($B$5:$B$14,A20,$E$5:$E$14) -> 141000 | E20: =IF(B20=0,0,D20/B20) -> 0.66824645 | F20: =B20-D20 -> 70000 | H20: Total Paid YTD | I20: {=E15} -> 696500
A21: Unit Turns | B21: =SUMIF($B$5:$B$14,A21,$C$5:$C$14) -> 112500 | C21: =SUMIF($B$5:$B$14,A21,$D$5:$D$14) -> 98000 | D21: =SUMIF($B$5:$B$14,A21,$E$5:$E$14) -> 82500 | E21: =IF(B21=0,0,D21/B21) -> 0.73333333 | F21: =B21-D21 -> 30000 | H21: % Spent | I21: {=J15} -> 0.63811269
A22: Site Work | B22: =SUMIF($B$5:$B$14,A22,$C$5:$C$14) -> 93000 | C22: =SUMIF($B$5:$B$14,A22,$D$5:$D$14) -> 80000 | D22: =SUMIF($B$5:$B$14,A22,$E$5:$E$14) -> 63000 | E22: =IF(B22=0,0,D22/B22) -> 0.67741935 | F22: =B22-D22 -> 30000 | H22: Remaining Budget | I22: =C15-E15 -> 395000
A23: Contingency | B23: =SUMIF($B$5:$B$14,A23,$C$5:$C$14) -> 75000 | C23: =SUMIF($B$5:$B$14,A23,$D$5:$D$14) -> 0 | D23: =SUMIF($B$5:$B$14,A23,$E$5:$E$14) -> 0 | E23: =IF(B23=0,0,D23/B23) -> 0 | F23: =B23-D23 -> 75000 | H23: Uncommitted | I23: =C15-D15 -> 163500
A24: TOTAL | B24: =SUM(B19:B23) -> 1091500 | C24: =SUM(C19:C23) -> 928000 | D24: =SUM(D19:D23) -> 696500 | E24: =IF(B24=0,0,D24/B24) -> 0.63811269 | F24: =SUM(F19:F23) -> 395000 | H24: Projects Complete | I24: =COUNTIF(K5:K14,"Complete") -> 1
H25: Projects In Progress | I25: =COUNTIF(K5:K14,"In Progress")+COUNTIF(K5:K14,"Committed") -> 8

Sheet FIN_07_Debt_Covenant
A1: DEBT / COVENANT COMPLIANCE | L1: =HYPERLINK("#Alert_Dashboard!B2","← Back to Alerts") -> ← Back to Alerts
A3: DEBT COVENANT COMPLIANCE
A4: Covenant | B4: Type | C4: Threshold | D4: Current | E4: Cushion | F4: Status
A5: Debt Service Coverage Ratio | B5: Minimum | C5: 1.25 | D5: 1.52 | E5: =D5-C5 -> 0.27 | F5: =IF(D5>=C5,"✓ PASS","✗ FAIL") -> ✓ PASS
A6: Loan-to-Value | B6: Maximum | C6: 0.75 | D6: 0.58 | E6: =C6-D6 -> 0.17 | F6: =IF(D6<=C6,"✓ PASS","✗ FAIL") -> ✓ PASS
A7: Debt Yield | B7: Minimum | C7: 0.08 | D7: 0.092 | E7: =D7-C7 -> 0.012 | F7: =IF(D7>=C7,"✓ PASS","✗ FAIL") -> ✓ PASS
A8: Interest Coverage Ratio | B8: Minimum | C8: 1.5 | D8: 1.85 | E8: =D8-C8 -> 0.35 | F8: =IF(D8>=C8,"✓ PASS","✗ FAIL") -> ✓ PASS
A9: Net Worth Minimum | B9: Minimum | C9: 15000000 | D9: 22500000 | E9: =D9-C9 -> 7500000 | F9: =IF(D9>=C9,"✓ PASS","✗ FAIL") -> ✓ PASS
A10: Liquidity Requirement | B10: Minimum | C10: 2000000 | D10: 3852200 | E10: =D10-C10 -> 1852200 | F10: =IF(D10>=C10,"✓ PASS","✗ FAIL") -> ✓ PASS
A11: Occupancy Minimum | B11: Minimum | C11: 0.9 | D11: 0.952 | E11: =D11-C11 -> 0.052 | F11: =IF(D11>=C11,"✓ PASS","✗ FAIL") -> ✓ PASS

Sheet FIN_08_AR_Bad_Debt
A1: ACCOUNTS RECEIVABLE & BAD DEBT ROLLUP | L1: =HYPERLINK("#Alert_Dashboard!B2","← Back to Alerts") -> ← Back to Alerts
A3: ACCOUNTS RECEIVABLE AGING | H3: KEY METRICS
A4: Aging Bucket | B4: # Accounts | C4: Balance | D4: % of Total | E4: Reserve Rate | F4: Reserve Amt | H4: Total AR | I4: {=C10} -> 206500
A5: Current (0-30 days) | B5: 185 | C5: 125000 | D5: =IF($C$10=0,0,C5/$C$10) -> 0.60532688 | E5: 0.01 | F5: =C5*E5 -> 1250 | H5: Bad Debt Reserve | I5: {=F10} -> 16755
A6: 31-60 days | B6: 28 | C6: 42000 | D6: =IF($C$10=0,0,C6/$C$10) -> 0.20338983 | E6: 0.05 | F6: =C6*E6 -> 2100 | H6: Reserve % | I6: {=E10} -> 0.081138015
A7: 61-90 days | B7: 12 | C7: 18500 | D7: =IF($C$10=0,0,C7/$C$10) -> 0.089588378 | E7: 0.15 | F7: =C7*E7 -> 2775 | H7: Delinquency Rate | I7: =1-D5 -> 0.39467312
A8: 91-120 days | B8: 8 | C8: 12800 | D8: =IF($C$10=0,0,C8/$C$10) -> 0.061985472 | E8: 0.35 | F8: =C8*E8 -> 4480 | H8: Avg Days Outstanding | I8: 28
A9: 120+ days | B9: 5 | C9: 8200 | D9: =IF($C$10=0,0,C9/$C$10) -> 0.039709443 | E9: 0.75 | F9: =C9*E9 -> 6150
A10: TOTAL | B10: =SUM(B5:B9) -> 238 | C10: =SUM(C5:C9) -> 206500 | D10: =SUM(D5:D9) -> 1 | E10: =IF(C10=0,0,F10/C10) -> 0.081138015 | F10: =SUM(F5:F9) -> 16755

Sheet OPS_10_Leasing_Funnel
A1: LEASING FUNNEL & CONVERSION DASHBOARD
A3: FUNNEL BY LEAD SOURCE
A4: Source | B4: Leads | C4: Tours | D4: Apps | E4: Leases | F4: Lead→Tour | G4: Tour→App | H4: App→Lease | I4: Lead→Lease | J4: CPA
A5: ILS (Apartments.com) | B5: 245 | C5: 78 | D5: 42 | E5: 18 | F5: =IF(B5=0,0,C5/B5) -> 0.31836735 | G5: =IF(C5=0,0,D5/C5) -> 0.53846154 | H5: =IF(D5=0,0,E5/D5) -> 0.42857143 | I5: =IF(B5=0,0,E5/B5) -> 0.073469388 | J5: {=MKT_16_Marketing_CPA!H10} -> 472.22222
A6: ILS (Zillow) | B6: 198 | C6: 61 | D6: 35 | E6: 14 | F6: =IF(B6=0,0,C6/B6) -> 0.30808081 | G6: =IF(C6=0,0,D6/C6) -> 0.57377049 | H6: =IF(D6=0,0,E6/D6) -> 0.4 | I6: =IF(B6=0,0,E6/B6) -> 0.070707071 | J6: {=MKT_16_Marketing_CPA!H11} -> 442.85714
A7: Google Ads (PPC) | B7: 156 | C7: 52 | D7: 28 | E7: 11 | F7: =IF(B7=0,0,C7/B7) -> 0.33333333 | G7: =IF(C7=0,0,D7/C7) -> 0.53846154 | H7: =IF(D7=0,0,E7/D7) -> 0.39285714 | I7: =IF(B7=0,0,E7/B7) -> 0.070512821 | J7: {=MKT_16_Marketing_CPA!H12} -> 436.36364
A8: Facebook/Instagram | B8: 134 | C8: 38 | D8: 19 | E8: 7 | F8: =IF(B8=0,0,C8/B8) -> 0.28358209 | G8: =IF(C8=0,0,D8/C8) -> 0.5 | H8: =IF(D8=0,0,E8/D8) -> 0.36842105 | I8: =IF(B8=0,0,E8/B8) -> 0.052238806 | J8: {=MKT_16_Marketing_CPA!H13} -> 457.14286
A9: Direct/Organic | B9: 287 | C9: 112 | D9: 68 | E9: 32 | F9: =IF(B9=0,0,C9/B9) -> 0.3902439 | G9: =IF(C9=0,0,D9/C9) -> 0.60714286 | H9: =IF(D9=0,0,E9/D9) -> 0.47058824 | I9: =IF(B9=0,0,E9/B9) -> 0.11149826 | J9: {=MKT_16_Marketing_CPA!H14} -> 0
A10: Referral | B10: 89 | C10: 45 | D10: 31 | E10: 19 | F10: =IF(B10=0,0,C10/B10) -> 0.50561798 | G10: =IF(C10=0,0,D10/C10) -> 0.68888889 | H10: =IF(D10=0,0,E10/D10) -> 0.61290323 | I10: =IF(B10=0,0,E10/B10) -> 0.21348315 | J10: {=MKT_16_Marketing_CPA!H15} -> 26.315789
A11: Other | B11: 42 | C11: 15 | D11: 8 | E11: 3 | F11: =IF(B11=0,0,C11/B11) -> 0.35714286 | G11: =IF(C11=0,0,D11/C11) -> 0.53333333 | H11: =IF(D11=0,0,E11/D11) -> 0.375 | I11: =IF(B11=0,0,E11/B11) -> 0.071428571 | J11: {=MKT_16_Marketing_CPA!H16} -> 266.66667
A12: TOTAL | B12: =SUM(B5:B11) -> 1151 | C12: =SUM(C5:C11) -> 401 | D12: =SUM(D5:D11) -> 231 | E12: =SUM(E5:E11) -> 104 | F12: =IF(B12=0,0,C12/B12) -> 0.3483927 | G12: =IF(C12=0,0,D12/C12) -> 0.57605985 | H12: =IF(D12=0,0,E12/D12) -> 0.45021645 | I12: =IF(B12=0,0,E12/B12) -> 0.090356212 | J12: =AVERAGE(J5:J11) -> 300.22404
A14: CONVERSION BENCHMARKS
A15: Metric | B15: Actual | C15: Target | D15: Variance | E15: Status
A16: Lead→Tour Rate | B16: {=F12} -> 0.3483927 | C16: 0.35 | D16: =B16-C16 -> -0.001607298
A17: Tour→App Rate | B17: {=G12} -> 0.57605985 | C17: 0.55 | D17: =B17-C17 -> 0.02605985
A18: App→Lease Rate | B18: {=H12} -> 0.45021645 | C18: 0.45 | D18: =B18-C18 -> 0.00021645022
A19: Lead→Lease Rate | B19: {=I12} -> 0.090356212 | C19: 0.09 | D19: =B19-C19 -> 0.00035621199
A20: Avg CPA | B20: {=J12} -> 300.22404 | C20: 850 | D20: =B20-C20 -> -549.77596

Sheet OPS_11_Occupancy_Mix
A1: OCCUPANCY & UNIT MIX / FLOORPLAN PERFORMANCE | L1: =HYPERLINK("#Alert_Dashboard!B2","← Back to Alerts") -> ← Back to Alerts
A3: FLOORPLAN PERFORMANCE
A4: Floorplan | B4: Units | C4: Occupied | D4: Occ % | E4: Avg SqFt | F4: Market Rent | G4: Avg NER | H4: NER/SqFt | I4: Absorption
A5: Studio | B5: 24 | C5: 23 | D5: =IF(B5=0,0,C5/B5) -> 0.95833333 | E5: 485 | F5: 1295 | G5: 1265 | H5: =IF(E5=0,0,G5/E5) -> 2.6082474 | I5: 2.1
A6: 1BR / 1BA | B6: 68 | C6: 65 | D6: =IF(B6=0,0,C6/B6) -> 0.95588235 | E6: 725 | F6: 1595 | G6: 1545 | H6: =IF(E6=0,0,G6/E6) -> 2.1310345 | I6: 4.8
A7: 1BR + Den | B7: 32 | C7: 30 | D7: =IF(B7=0,0,C7/B7) -> 0.9375 | E7: 815 | F7: 1745 | G7: 1695 | H7: =IF(E7=0,0,G7/E7) -> 2.0797546 | I7: 2.4
A8: 2BR / 1BA | B8: 45 | C8: 42 | D8: =IF(B8=0,0,C8/B8) -> 0.93333333 | E8: 985 | F8: 1895 | G8: 1825 | H8: =IF(E8=0,0,G8/E8) -> 1.8527919 | I8: 3.2
A9: 2BR / 2BA | B9: 56 | C9: 54 | D9: =IF(B9=0,0,C9/B9) -> 0.96428571 | E9: 1085 | F9: 2095 | G9: 2015 | H9: =IF(E9=0,0,G9/E9) -> 1.8571429 | I9: 3.8
A10: 3BR / 2BA | B10: 18 | C10: 17 | D10: =IF(B10=0,0,C10/B10) -> 0.94444444 | E10: 1325 | F10: 2595 | G10: 2485 | H10: =IF(E10=0,0,G10/E10) -> 1.8754717 | I10: 1.2
A11: Penthouse | B11: 8 | C11: 8 | D11: =IF(B11=0,0,C11/B11) -> 1 | E11: 1650 | F11: 3295 | G11: 3195 | H11: =IF(E11=0,0,G11/E11) -> 1.9363636 | I11: 0.6
A12: TOTAL / WTD AVG | B12: =SUM(B5:B11) -> 251 | C12: =SUM(C5:C11) -> 239 | D12: =IF(B12=0,0,C12/B12) -> 0.95219124 | E12: =SUMPRODUCT(B5:B11,E5:E11)/SUM(B5:B11) -> 912.96813 | F12: =SUMPRODUCT(B5:B11,F5:F11)/SUM(B5:B11) -> 1876.6733 | G12: =SUMPRODUCT(C5:C11,G5:G11)/SUM(C5:C11) -> 1814.3724 | H12: =IF(E12=0,0,G12/E12) -> 1.9873338 | I12: =SUM(I5:I11) -> 18.1
A14: NER PERFORMANCE METRICS
A15: Metric | B15: Current | C15: Prior Month | D15: Change | E15: YoY
A16: Avg NER (Portfolio) | B16: {=G12} -> 1814.3724 | C16: 1785 | D16: =B16-C16 -> 29.372385 | E16: 0.032
A17: NER/SqFt | B17: {=H12} -> 1.9873338 | C17: 1.92 | D17: =B17-C17 -> 0.067333764 | E17: 0.028
A18: Occupancy % | B18: {=D12} -> 0.95219124 | C18: 0.948 | D18: =B18-C18 -> 0.0041912351 | E18: 0.012
A19: Absorption Rate (units/mo) | B19: {=I12} -> 18.1 | C19: 16.8 | D19: =B19-C19 -> 1.3 | E19: 0.085

Sheet OPS_12_Renewal_Retention
A1: RENEWAL & RETENTION REPORT | L1: =HYPERLINK("#Alert_Dashboard!B2","← Back to Alerts") -> ← Back to Alerts
A3: RENEWAL RATES BY COHORT (MTD)
A4: Cohort | B4: Expiring | C4: Renewed | D4: Renewal % | E4: Avg Increase | F4: Concession $ | G4: MTM | H4: NTV
A5: 1st Year Residents | B5: 28 | C5: 18 | D5: =IF(B5=0,0,C5/B5) -> 0.64285714 | E5: 0.042 | F5: 125 | G5: 4 | H5: 6
A6: 2nd Year Residents | B6: 22 | C6: 17 | D6: =IF(B6=0,0,C6/B6) -> 0.77272727 | E6: 0.038 | F6: 85 | G6: 2 | H6: 3
A7: 3+ Year Residents | B7: 15 | C7: 14 | D7: =IF(B7=0,0,C7/B7) -> 0.93333333 | E7: 0.032 | F7: 50 | G7: 0 | H7: 1
A8: Month-to-Month | B8: 8 | C8: 5 | D8: =IF(B8=0,0,C8/B8) -> 0.625 | E8: 0.025 | F8: 0 | G8: 3 | H8: 0
A9: Corporate/Short-Term | B9: 4 | C9: 2 | D9: =IF(B9=0,0,C9/B9) -> 0.5 | E9: 0.05 | F9: 150 | G9: 1 | H9: 1
A10: TOTAL | B10: =SUM(B5:B9) -> 77 | C10: =SUM(C5:C9) -> 56 | D10: =IF(B10=0,0,C10/B10) -> 0.72727273 | E10: =SUMPRODUCT(C5:C9,E5:E9)/SUM(C5:C9) -> 0.037053571 | F10: =SUMPRODUCT(C5:C9,F5:F9)/SUM(C5:C9) -> 83.839286 | G10: =SUM(G5:G9) -> 10 | H10: =SUM(H5:H9) -> 11
A12: CONCESSION ANALYSIS | G12: KEY METRICS
A13: Concession Type | B13: # Offered | C13: Avg Amount | D13: Total Value | E13: % Accepted | G13: TTM Retention Rate | H13: =AVERAGE(B22:M22) -> 0.69583333
A14: Rent Discount (1 mo free) | B14: 12 | C14: 1650 | D14: =B14*C14 -> 19800 | E14: 0.83 | G14: YoY Change | H14: 0.023
A15: Reduced Increase Cap | B15: 18 | C15: 480 | D15: =B15*C15 -> 8640 | E15: 0.89 | G15: Avg Concession Cost | H15: {=F10} -> 83.839286
A16: Waived Fees | B16: 8 | C16: 350 | D16: =B16*C16 -> 2800 | E16: 0.75 | G16: Notice to Vacate % | H16: =IF(B10=0,0,H10/B10) -> 0.14285714
A17: Upgrade/Amenity Credit | B17: 6 | C17: 500 | D17: =B17*C17 -> 3000 | E17: 0.67 | G17: MTM Conversion % | H17: =IF(B10=0,0,G10/B10) -> 0.12987013
A18: None Required | B18: 33 | C18: 0 | D18: =B18*C18 -> 0 | E18: 1
A20: RETENTION TREND (12-MONTH)
A21: Month | B21: Jan | C21: Feb | D21: Mar | E21: Apr | F21: May | G21: Jun | H21: Jul | I21: Aug | J21: Sep | K21: Oct | L21: Nov | M21: Dec
A22: Retention % | B22: 0.68 | C22: 0.71 | D22: 0.74 | E22: 0.72 | F22: 0.69 | G22: 0.65 | H22: 0.62 | I22: 0.64 | J22: 0.7 | K22: 0.73 | L22: 0.75 | M22: 0.72
A23: Expirations | B23: 18 | C23: 22 | D23: 25 | E23: 28 | F23: 32 | G23: 35 | H23: 38 | I23: 34 | J23: 28 | K23: 24 | L23: 20 | M23: 18
A24: Renewals | B24: =ROUND(B23*B22,0) -> 12 | C24: =ROUND(C23*C22,0) -> 16 | D24: =ROUND(D23*D22,0) -> 19 | E24: =ROUND(E23*E22,0) -> 20 | F24: =ROUND(F23*F22,0) -> 22 | G24: =ROUND(G23*G22,0) -> 23 | H24: =ROUND(H23*H22,0) -> 24 | I24: =ROUND(I23*I22,0) -> 22 | ... M24: =ROUND(M23*M22,0) -> 13

Sheet OPS_13_Turnover_MakeReady
A1: TURNOVER & MAKE-READY COST REPORT | L1: =HYPERLINK("#Alert_Dashboard!B2","← Back to Alerts") -> ← Back to Alerts
A3: TURNOVER BY UNIT TYPE (MTD) | J3: KEY METRICS
A4: Unit Type | B4: Units | C4: Move-Outs | D4: Turnover % | E4: Avg Cost | F4: Total Cost | G4: Days Vacant | H4: Days to Rent | J4: MTD Move-Outs | K4: {=C12} -> 19
A5: Studio | B5: 24 | C5: 2 | D5: =IF(B5=0,0,C5/B5) -> 0.083333333 | E5: 1850 | F5: =C5*E5 -> 3700 | G5: 8 | H5: 12 | J5: Turnover Rate | K5: {=D12} -> 0.075697211
A6: 1BR / 1BA | B6: 68 | C6: 5 | D6: =IF(B6=0,0,C6/B6) -> 0.073529412 | E6: 2250 | F6: =C6*E6 -> 11250 | G6: 10 | H6: 15 | J6: Avg Cost/Turn | K6: {=E12} -> 2628.9474
A7: 1BR + Den | B7: 32 | C7: 3 | D7: =IF(B7=0,0,C7/B7) -> 0.09375 | E7: 2450 | F7: =C7*E7 -> 7350 | G7: 9 | H7: 14 | J7: Total Turn Cost | K7: {=F12} -> 49950
A8: 2BR / 1BA | B8: 45 | C8: 4 | D8: =IF(B8=0,0,C8/B8) -> 0.088888889 | E8: 2850 | F8: =C8*E8 -> 11400 | G8: 12 | H8: 18 | J8: Avg Days Vacant | K8: {=G12} -> 10.473684
A9: 2BR / 2BA | B9: 56 | C9: 4 | D9: =IF(B9=0,0,C9/B9) -> 0.071428571 | E9: 3150 | F9: =C9*E9 -> 12600 | G9: 11 | H9: 16 | J9: Avg Days to Rent | K9: {=H12} -> 15.684211
A10: 3BR / 2BA | B10: 18 | C10: 1 | D10: =IF(B10=0,0,C10/B10) -> 0.055555556 | E10: 3650 | F10: =C10*E10 -> 3650 | G10: 14 | H10: 21 | J10: Make-Ready Time | K10: {=C23} -> 12.5
A11: Penthouse | B11: 8 | C11: 0 | D11: =IF(B11=0,0,C11/B11) -> 0 | E11: 4500 | F11: =C11*E11 -> 0 | G11: 0 | H11: 0 | J11: On-Time % | K11: {=E23} -> 0.86142857
A12: TOTAL / AVG | B12: =SUM(B5:B11) -> 251 | C12: =SUM(C5:C11) -> 19 | D12: =IF(B12=0,0,C12/B12) -> 0.075697211 | E12: =IF(C12=0,0,F12/C12) -> 2628.9474 | F12: =SUM(F5:F11) -> 49950 | G12: =SUMPRODUCT(C5:C11,G5:G11)/SUM(C5:C11) -> 10.473684 | H12: =SUMPRODUCT(C5:C11,H5:H11)/SUM(C5:C11) -> 15.684211
A14: MAKE-READY TIMING BREAKDOWN | G14: MAKE-READY COST BREAKDOWN
A15: Phase | B15: Target Days | C15: Actual Avg | D15: Variance | E15: % On-Time | G15: Category | H15: Avg Cost | I15: % of Total | J15: Variance
A16: Move-Out Inspection | B16: 1 | C16: 0.8 | D16: =C16-B16 -> -0.2 | E16: 0.94 | G16: Cleaning | H16: 425 | I16: =IF($H$24=0,0,H16/$H$24) -> 0.16165843 | J16: 25
A17: Cleaning | B17: 2 | C17: 2.2 | D17: =C17-B17 -> 0.2 | E17: 0.85 | G17: Paint/Touch-up | H17: 650 | I17: =IF($H$24=0,0,H17/$H$24) -> 0.2472423 | J17: -50
A18: Paint/Touch-up | B18: 2 | C18: 2.5 | D18: =C18-B18 -> 0.5 | E18: 0.78 | G18: Flooring | H18: 485 | I18: =IF($H$24=0,0,H18/$H$24) -> 0.18448079 | J18: 85
A19: Flooring (if needed) | B19: 3 | C19: 3.8 | D19: =C19-B19 -> 0.8 | E19: 0.72 | G19: Appliance Repair | H19: 320 | I19: =IF($H$24=0,0,H19/$H$24) -> 0.12171928 | J19: -15
A20: Repairs/Maintenance | B20: 2 | C20: 2.1 | D20: =C20-B20 -> 0.1 | E20: 0.88 | G20: HVAC Service | H20: 185 | I20: =IF($H$24=0,0,H20/$H$24) -> 0.070368962 | J20: 10
A21: Final Inspection | B21: 1 | C21: 0.9 | D21: =C21-B21 -> -0.1 | E21: 0.96 | G21: Plumbing | H21: 215 | I21: =IF($H$24=0,0,H21/$H$24) -> 0.081780145 | J21: 30
A22: Market-Ready | B22: 0 | C22: 0.2 | D22: =C22-B22 -> 0.2 | E22: 0.9 | G22: Electrical | H22: 125 | I22: =IF($H$24=0,0,H22/$H$24) -> 0.047546596 | J22: -5
A23: TOTAL DAYS | B23: =SUM(B16:B22) -> 11 | C23: =SUM(C16:C22) -> 12.5 | D23: =C23-B23 -> 1.5 | E23: =AVERAGE(E16:E22) -> 0.86142857 | G23: General Repairs | H23: 224 | I23: =IF($H$24=0,0,H23/$H$24) -> 0.085203499 | J23: 20
G24: TOTAL | H24: =SUM(H16:H23) -> 2629 | I24: =SUM(I16:I23) -> 1 | J24: =SUM(J16:J23) -> 100

Sheet OPS_14_Maintenance_WO
A1: MAINTENANCE WORK ORDER & BACKLOG
A3: WORK ORDER STATUS BY CATEGORY (MTD) | I3: KEY METRICS
A4: Category | B4: Open | C4: In Progress | D4: Completed | E4: Avg Time (hrs) | F4: % On-Time | G4: Backlog | I4: Total Open WOs | J4: {=B11} -> 64
A5: Plumbing | B5: 8 | C5: 4 | D5: 42 | E5: 18.5 | F5: 0.88 | G5: =B5+C5 -> 12 | I5: Total Backlog | J5: {=G11} -> 95
A6: HVAC | B6: 12 | C6: 6 | D6: 38 | E6: 24.2 | F6: 0.82 | G6: =B6+C6 -> 18 | I6: Avg Completion (hrs) | J6: {=E11} -> 19.392509
A7: Electrical | B7: 5 | C7: 2 | D7: 28 | E7: 12.4 | F7: 0.92 | G7: =B7+C7 -> 7 | I7: On-Time % | J7: {=F11} -> 0.86962547
A8: Appliances | B8: 15 | C8: 8 | D8: 56 | E8: 32.6 | F8: 0.78 | G8: =B8+C8 -> 23 | I8: Emergency SLA % | J8: {=E15} -> 0.95238095
A9: General/Other | B9: 22 | C9: 10 | D9: 85 | E9: 14.8 | F9: 0.91 | G9: =B9+C9 -> 32 | I9: 30+ Day Backlog % | J9: {=C25} -> 0.052631579
A10: Emergency | B10: 2 | C10: 1 | D10: 18 | E10: 2.8 | F10: 0.96 | G10: =B10+C10 -> 3 | I10: WOs per Unit (MTD) | J10: =D11/251 -> 1.063745
A11: TOTAL | B11: =SUM(B5:B10) -> 64 | C11: =SUM(C5:C10) -> 31 | D11: =SUM(D5:D10) -> 267 | E11: =SUMPRODUCT(D5:D10,E5:E10)/SUM(D5:D10) -> 19.392509 | F11: =SUMPRODUCT(D5:D10,F5:F10)/SUM(D5:D10) -> 0.86962547 | G11: =SUM(G5:G10) -> 95
A13: EMERGENCY RESPONSE SLA (MTD)
A14: Priority | B14: SLA Target | C14: Total WOs | D14: Met SLA | E14: SLA % | F14: Avg Response | G14: Status
A15: Emergency (<4hr) | B15: 4 hrs | C15: 21 | D15: 20 | E15: =IF(C15=0,0,D15/C15) -> 0.95238095 | F15: 2.8 | G15: =IF(E15>=0.95,"✓ PASS",IF(E15>=0.9,"⚠ WATCH","✗ FAIL")) -> ✓ PASS
A16: Urgent (<24hr) | B16: 24 hrs | C16: 48 | D16: 44 | E16: =IF(C16=0,0,D16/C16) -> 0.91666667 | F16: 16.4 | G16: =IF(E16>=0.95,"✓ PASS",IF(E16>=0.9,"⚠ WATCH","✗ FAIL")) -> ⚠ WATCH
A17: Standard (<72hr) | B17: 72 hrs | C17: 156 | D17: 142 | E17: =IF(C17=0,0,D17/C17) -> 0.91025641 | F17: 38.2 | G17: =IF(E17>=0.95,"✓ PASS",IF(E17>=0.9,"⚠ WATCH","✗ FAIL")) -> ⚠ WATCH
A18: Scheduled | B18: 7 days | C18: 42 | D18: 41 | E18: =IF(C18=0,0,D18/C18) -> 0.97619048 | F18: 4.2 | G18: =IF(E18>=0.95,"✓ PASS",IF(E18>=0.9,"⚠ WATCH","✗ FAIL")) -> ✓ PASS
A20: BACKLOG AGING ANALYSIS | F20: Total Backlog: | G20: {=G11} -> 95
A21: Age Bucket | B21: # WOs | C21: % of Backlog | D21: Risk Level | E21: Target
A22: 0-7 days | B22: 52 | C22: =IF($G$20=0,0,B22/$G$20) -> 0.54736842 | D22: Low | E22: <70%
A23: 8-14 days | B23: 24 | C23: =IF($G$20=0,0,B23/$G$20) -> 0.25263158 | D23: Medium | E23: <20%
A24: 15-30 days | B24: 14 | C24: =IF($G$20=0,0,B24/$G$20) -> 0.14736842 | D24: High | E24: <8%
A25: 30+ days | B25: 5 | C25: =IF($G$20=0,0,B25/$G$20) -> 0.052631579 | D25: Critical | E25: <2%

Sheet OPS_15_Resident_NPS
A1: RESIDENT SATISFACTION & NPS
A3: RESIDENT SATISFACTION & NPS | H3: NPS SUMMARY
A4: Category | B4: Promoters | C4: Passives | D4: Detractors | E4: Total | F4: NPS Score | H4: Overall NPS | I4: {=F5} -> 0.4789916
A5: Overall Experience | B5: 142 | C5: 68 | D5: 28 | E5: =B5+C5+D5 -> 238 | F5: =IF(E5=0,0,(B5-D5)/E5) -> 0.4789916 | H5: Total Responses | I5: {=E5} -> 238
A6: Maintenance Response | B6: 125 | C6: 78 | D6: 35 | E6: =B6+C6+D6 -> 238 | F6: =IF(E6=0,0,(B6-D6)/E6) -> 0.37815126 | H6: Response Rate | I6: 0.42
A7: Leasing Team | B7: 156 | C7: 52 | D7: 30 | E7: =B7+C7+D7 -> 238 | F7: =IF(E7=0,0,(B7-D7)/E7) -> 0.52941176 | H7: Promoter % | I7: =IF(E5=0,0,B5/E5) -> 0.59663866
A8: Community Amenities | B8: 118 | C8: 82 | D8: 38 | E8: =B8+C8+D8 -> 238 | F8: =IF(E8=0,0,(B8-D8)/E8) -> 0.33613445 | H8: Detractor % | I8: =IF(E5=0,0,D5/E5) -> 0.11764706
A9: Move-In Experience | B9: 148 | C9: 62 | D9: 28 | E9: =B9+C9+D9 -> 238 | F9: =IF(E9=0,0,(B9-D9)/E9) -> 0.50420168 | H9: YoY Change | I9: 8
A10: Communication | B10: 132 | C10: 72 | D10: 34 | E10: =B10+C10+D10 -> 238 | F10: =IF(E10=0,0,(B10-D10)/E10) -> 0.41176471

Sheet MKT_17_Attribution
A1: SOURCE-TO-LEASE ATTRIBUTION
A3: MARKETING ATTRIBUTION ANALYSIS
A4: Channel | B4: First Touch | C4: Last Touch | D4: Multi-Touch | E4: Revenue Attr | F4: ROAS
A5: ILS (Apartments.com) | B5: 0.22 | C5: 0.18 | D5: 0.2 | E5: 425000 | F5: =IF(MKT_16_Marketing_CPA!B10=0,0,E5/MKT_16_Marketing_CPA!B10) -> 50
A6: ILS (Zillow) | B6: 0.18 | C6: 0.15 | D6: 0.16 | E6: 320000 | F6: =IF(MKT_16_Marketing_CPA!B11=0,0,E6/MKT_16_Marketing_CPA!B11) -> 51.612903
A7: Google Ads (PPC) | B7: 0.15 | C7: 0.12 | D7: 0.14 | E7: 285000 | F7: =IF(MKT_16_Marketing_CPA!B12=0,0,E7/MKT_16_Marketing_CPA!B12) -> 59.375
A8: Facebook/Instagram | B8: 0.12 | C8: 0.08 | D8: 0.1 | E8: 195000 | F8: =IF(MKT_16_Marketing_CPA!B13=0,0,E8/MKT_16_Marketing_CPA!B13) -> 60.9375
A9: Direct/Organic | B9: 0.25 | C9: 0.35 | D9: 0.3 | E9: 625000 | F9: =IF(MKT_16_Marketing_CPA!B14=0,0,E9/MKT_16_Marketing_CPA!B14) -> 0
A10: Referral | B10: 0.06 | C10: 0.1 | D10: 0.08 | E10: 165000 | F10: =IF(MKT_16_Marketing_CPA!B15=0,0,E10/MKT_16_Marketing_CPA!B15) -> 330
A11: Other | B11: 0.02 | C11: 0.02 | D11: 0.02 | E11: 45000 | F11: =IF(MKT_16_Marketing_CPA!B16=0,0,E11/MKT_16_Marketing_CPA!B16) -> 56.25
A12: TOTAL | B12: =SUM(B5:B11) -> 1 | C12: =SUM(C5:C11) -> 1 | D12: =SUM(D5:D11) -> 1 | E12: =SUM(E5:E11) -> 2060000 | F12: =IF(MKT_16_Marketing_CPA!B6=0,0,E12/MKT_16_Marketing_CPA!B6) -> 85.833333

Sheet DEV_18_Project_EV
A1: PROJECT STATUS & EARNED VALUE REPORT
A3: DEVELOPMENT PROJECT ENTERPRISE VALUE
A4: Project | B4: Units | C4: Total Cost | D4: Stabilized NOI | E4: Cap Rate | F4: EV | G4: Equity | H4: ROE
A5: Parkside Phase II | B5: 180 | C5: 48500000 | D5: 3250000 | E5: 0.055 | F5: =IF(E5=0,0,D5/E5) -> 59090909 | G5: 18500000 | H5: =IF(G5=0,0,(F5-C5)/G5) -> 0.57248157
A6: Downtown Mixed-Use | B6: 225 | C6: 72000000 | D6: 4800000 | E6: 0.0525 | F6: =IF(E6=0,0,D6/E6) -> 91428571 | G6: 28000000 | H6: =IF(G6=0,0,(F6-C6)/G6) -> 0.69387755
A7: Suburban Garden | B7: 145 | C7: 38500000 | D7: 2650000 | E7: 0.058 | F7: =IF(E7=0,0,D7/E7) -> 45689655 | G7: 14500000 | H7: =IF(G7=0,0,(F7-C7)/G7) -> 0.49583829
A8: TOTAL / WTD AVG | B8: =SUM(B5:B7) -> 550 | C8: =SUM(C5:C7) -> 159000000 | D8: =SUM(D5:D7) -> 10700000 | E8: =IF(F8=0,0,D8/F8) -> 0.054533648 | F8: =SUM(F5:F7) -> 1.9620914e+08 | G8: =SUM(G5:G7) -> 61000000 | H8: =IF(G8=0,0,(F8-C8)/G8) -> 0.60998583

Sheet DEV_19_Cost_Complete
A1: COST TO COMPLETE / CASHFLOW BY PROJECT | L1: =HYPERLINK("#Alert_Dashboard!B2","← Back to Alerts") -> ← Back to Alerts
A3: DEVELOPMENT COST TO COMPLETE
A4: Category | B4: Budget | C4: Spent | D4: Committed | E4: ETC | F4: EAC | G4: Variance
A5: Land & Acquisition | B5: 28500000 | C5: 28500000 | D5: 0 | E5: =MAX(0,B5-C5-D5) -> 0 | F5: =C5+D5+E5 -> 28500000 | G5: =B5-F5 -> 0
A6: Hard Costs | B6: 95000000 | C6: 62000000 | D6: 18500000 | E6: =MAX(0,B6-C6-D6) -> 14500000 | F6: =C6+D6+E6 -> 95000000 | G6: =B6-F6 -> 0
A7: Soft Costs | B7: 18500000 | C7: 12200000 | D7: 3800000 | E7: =MAX(0,B7-C7-D7) -> 2500000 | F7: =C7+D7+E7 -> 18500000 | G7: =B7-F7 -> 0
A8: Financing Costs | B8: 8500000 | C8: 5200000 | D8: 1800000 | E8: =MAX(0,B8-C8-D8) -> 1500000 | F8: =C8+D8+E8 -> 8500000 | G8: =B8-F8 -> 0
A9: Contingency | B9: 8500000 | C9: 1200000 | D9: 0 | E9: =MAX(0,B9-C9-D9) -> 7300000 | F9: =C9+D9+E9 -> 8500000 | G9: =B9-F9 -> 0
A10: TOTAL | B10: =SUM(B5:B9) -> 159000000 | C10: =SUM(C5:C9) -> 109100000 | D10: =SUM(D5:D9) -> 24100000 | E10: =SUM(E5:E9) -> 25800000 | F10: =SUM(F5:F9) -> 159000000 | G10: =SUM(G5:G9) -> 0

Sheet DEV_20_Entitlement_Risk
A1: ENTITLEMENT & RISK REGISTER
A3: ENTITLEMENT & PERMITTING RISK TRACKER
A4: Project | B4: Permit Type | C4: Status | D4: Submit Date | E4: Target Date | F4: Days Rem | G4: Risk | H4: Mitigation
A5: Parkside II | B5: Site Plan | C5: Approved | D5: 2025-08-15 | E5: 2025-11-01 | F5: 0 | G5: Low | H5: Complete
A6: Parkside II | B6: Building Permit | C6: In Review | D6: 2025-12-01 | E6: 2026-03-15 | F6: 63 | G6: Med | H6: Weekly check-ins
A7: Downtown MU | B7: Zoning Variance | C7: Submitted | D7: 2025-11-20 | E7: 2026-02-28 | F7: 48 | G7: High | H7: Council liaison
A8: Downtown MU | B8: Site Plan | C8: Pending | D8: 2026-01-15 | E8: 2026-04-30 | F8: 109 | G8: Med | H8: Pre-app meeting
A9: Suburban Gdn | B9: Site Plan | C9: Approved | D9: 2025-09-01 | E9: 2025-12-15 | F9: 0 | G9: Low | H9: Complete
A10: Suburban Gdn | B10: Building Permit | C10: Approved | D10: 2025-12-20 | E10: 2026-01-10 | F10: 0 | G10: Low | H10: Complete

Sheet CAP_21_Investor_Quarterly
A1: QUARTERLY INVESTOR REPORT
A3: PORTFOLIO PERFORMANCE SUMMARY - Q4 2025
A4: Metric | B4: Q4 2025 | C4: Q3 2025 | D4: QoQ Δ | E4: Q4 2024 | F4: YoY Δ
A5: Total Revenue | B5: 13350000 | C5: 13100000 | D5: =IF(C5=0,0,(B5-C5)/C5) -> 0.019083969 | E5: 12800000 | F5: =IF(E5=0,0,(B5-E5)/E5) -> 0.04296875
A6: Net Operating Income | B6: 8200000 | C6: 8050000 | D6: =IF(C6=0,0,(B6-C6)/C6) -> 0.01863354 | E6: 7850000 | F6: =IF(E6=0,0,(B6-E6)/E6) -> 0.044585987
A7: NOI Margin | B7: 0.614 | C7: 0.615 | D7: =IF(C7=0,0,(B7-C7)/C7) -> -0.0016260163 | E7: 0.613 | F7: =IF(E7=0,0,(B7-E7)/E7) -> 0.0016313214
A8: Occupancy | B8: 0.952 | C8: 0.948 | D8: =IF(C8=0,0,(B8-C8)/C8) -> 0.0042194093 | E8: 0.942 | F8: =IF(E8=0,0,(B8-E8)/E8) -> 0.010615711
A9: Average NER | B9: 1814 | C9: 1785 | D9: =IF(C9=0,0,(B9-C9)/C9) -> 0.016246499 | E9: 1725 | F9: =IF(E9=0,0,(B9-E9)/E9) -> 0.051594203
A10: FFO | B10: 7050000 | C10: 6900000 | D10: =IF(C10=0,0,(B10-C10)/C10) -> 0.02173913 | E10: 6650000 | F10: =IF(E10=0,0,(B10-E10)/E10) -> 0.060150376
A11: FFO per Share | B11: 0.14 | C11: 0.138 | D11: =IF(C11=0,0,(B11-C11)/C11) -> 0.014492754 | E11: 0.133 | F11: =IF(E11=0,0,(B11-E11)/E11) -> 0.052631579
A12: DSCR | B12: 1.52 | C12: 1.48 | D12: =IF(C12=0,0,(B12-C12)/C12) -> 0.027027027 | E12: 1.45 | F12: =IF(E12=0,0,(B12-E12)/E12) -> 0.048275862

Sheet ESG_22_Sustainability
A1: ESG / SUSTAINABILITY & SAFETY REPORT
A3: ESG & SUSTAINABILITY METRICS
A4: Metric | B4: Current | C4: Prior Year | D4: Change | E4: Target | F4: Status
A5: Energy Use (kWh/sqft) | B5: 12.8 | C5: 14.2 | D5: =B5-C5 -> -1.4 | E5: 11.5 | F5: =IF(B5<=E5,"✓ On Track","⚠ Behind") -> ⚠ Behind
A6: Water Use (gal/sqft) | B6: 48.5 | C6: 52.3 | D6: =B6-C6 -> -3.8 | E6: 45 | F6: =IF(B6<=E6,"✓ On Track","⚠ Behind") -> ⚠ Behind
A7: Waste Diversion Rate | B7: 0.42 | C7: 0.38 | D7: =B7-C7 -> 0.04 | E7: 0.5 | F7: =IF(B7>=E7,"✓ On Track","⚠ Behind") -> ⚠ Behind
A8: Carbon Intensity (kg CO2/sqft) | B8: 8.2 | C8: 9.1 | D8: =B8-C8 -> -0.9 | E8: 7.5 | F8: =IF(B8<=E8,"✓ On Track","⚠ Behind") -> ⚠ Behind
A9: ENERGY STAR Score | B9: 72 | C9: 68 | D9: =B9-C9 -> 4 | E9: 75 | F9: =IF(B9>=E9,"✓ On Track","⚠ Behind") -> ⚠ Behind
A10: LED Lighting % | B10: 0.85 | C10: 0.72 | D10: =B10-C10 -> 0.13 | E10: 1 | F10: =IF(B10>=E10,"✓ On Track","⚠ Behind") -> ⚠ Behind
A11: Smart Thermostat % | B11: 0.68 | C11: 0.52 | D11: =B11-C11 -> 0.16 | E11: 0.9 | F11: =IF(B11>=E11,"✓ On Track","⚠ Behind") -> ⚠ Behind
A12: EV Charging Stations | B12: 24 | C12: 16 | D12: =B12-C12 -> 8 | E12: 40 | F12: =IF(B12>=E12,"✓ On Track","⚠ Behind") -> ⚠ Behind

Sheet Alert_Dashboard
B2: AUTOMATED ALERT DASHBOARD
B3: Real-time variance monitoring across all 22 reports | Auto-refresh: Every 15 min | Last Updated: 01/12/2026 08:00
B5: ALERT SUMMARY
B6: Total Active Alerts | D6: Critical (Red) | H6: Escalated | J6: Acknowledged
B7: =COUNTIF(J28:J49,"⚠")+COUNTIF(J28:J49,"✗") -> 8 | D7: =COUNTIF(J28:J49,"✗") -> 2 | F7: =_xlfn.IFERROR(COUNTIF(J28:J49,"⚠"),0) -> 6 | H7: 1 | J7: 3
B10: 🔴 CRITICAL ALERTS - IMMEDIATE ACTION REQUIRED
B11: Report | C11: Metric | D11: Threshold | E11: Current | F11: Variance | G11: Status | H11: Owner | I11: Escalate To | J11: Time Open | K11: Action
B12: =HYPERLINK("#FIN_07_Debt_Covenant!A1","FIN_07 →") -> FIN_07 → | C12: DSCR Covenant | D12: ≥ 1.20x | F12: =_xlfn.IFERROR(-1.7%,0) -> -0.017 | H12: CFO | I12: CEO | J12: 2 hrs | K12: Lender call scheduled
B13: =HYPERLINK("#OPS_11_Occupancy_Mix!A1","OPS_11 →") -> OPS_11 → | C13: Portfolio Occupancy | D13: ≥ 92% | F13: =_xlfn.IFERROR(-0.9%,0) -> -0.009 | H13: Asset Mgr | I13: SVP Ops | J13: 18 hrs | K13: Emergency leasing sprint
B16: 🟡 WARNING ALERTS - MONITOR & ACTION WITHIN 48 HRS
B17: Report | C17: Metric | D17: Threshold | E17: Current | F17: Variance | G17: Status | H17: Owner | I17: Escalate To | J17: Time Open | K17: Action
B18: =HYPERLINK("#FIN_04_Budget_Variance!A1","FIN_04 →") -> FIN_04 → | C18: Budget Variance | D18: ≤ 5% | F18: =_xlfn.IFERROR(+1.2%,0) -> 0.012 | H18: Prop Mgr | I18: Asset Mgr | J18: 5 days | K18: Variance memo due
B19: =HYPERLINK("#MKT_16_Marketing_CPA!A1","MKT_16 →") -> MKT_16 → | C19: Cost Per Lead | D19: ≤ $75 | F19: =_xlfn.IFERROR(+9.3%,0) -> 0.093 | H19: Mktg Mgr | I19: Head Mktg | J19: 3 days | K19: Campaign review
B20: =HYPERLINK("#OPS_13_Turnover_MakeReady!A1","OPS_13 →") -> OPS_13 → | C20: Make-Ready Days | D20: ≤ 7 days | F20: =_xlfn.IFERROR(+31%,0) -> 0.31 | H20: Maint Dir | I20: Ops Dir | J20: 1 day | K20: Staff overtime
B21: =HYPERLINK("#OPS_12_Renewal_Retention!A1","OPS_12 →") -> OPS_12 → | C21: Renewal Rate | D21: ≥ 55% | F21: =_xlfn.IFERROR(-5.5%,0) -> -0.055 | H21: Prop Mgr | I21: Asset Mgr | J21: 7 days | K21: Retention outreach
B22: =HYPERLINK("#FIN_08_AR_Bad_Debt!A1","FIN_08 →") -> FIN_08 → | C22: Delinquency Rate | D22: ≤ 3% | F22: =_xlfn.IFERROR(+26%,0) -> 0.26 | H22: Prop Mgr | I22: Finance | J22: 4 days | K22: Collection calls
B23: =HYPERLINK("#DEV_19_Cost_Complete!A1","DEV_19 →") -> DEV_19 → | C23: Cost Variance | D23: ≤ 5% | F23: =_xlfn.IFERROR(+2.2%,0) -> 0.022 | H23: Proj Mgr | I23: Dev Dir | J23: 2 days | K23: Change order review
B26: REPORT HEALTH MATRIX - ALL 22 REPORTS
B27: # | C27: Report ID | D27: Report Name | E27: Category | F27: Key Metric | G27: Target | H27: Actual | I27: Var % | J27: Status | K27: Last Check
B28: 1 | C28: =HYPERLINK("#FIN_01_Investor_Pack!A1","FIN_01 →") -> FIN_01 → | D28: Investor Pack | E28: Financial | F28: NOI | G28: $485K | H28: $492K | I28: =+1.4% -> 0.014 | J28: ✓ | K28: 08:00
B29: 2 | C29: =HYPERLINK("#FIN_02_NOI_Pack!A1","FIN_02 →") -> FIN_02 → | D29: NOI Pack | E29: Financial | F29: NOI Margin | G29: 62% | H29: 63.1% | I29: =+1.8% -> 0.018 | J29: ✓ | K29: 08:00
B30: 3 | C30: =HYPERLINK("#FIN_03_Rent_Roll!A1","FIN_03 →") -> FIN_03 → | D30: Rent Roll | E30: Financial | F30: Gross Rent | G30: $580K | H30: $578K | I30: =-0.3% -> -0.003 | J30: ✓ | K30: 08:00
B31: 4 | C31: =HYPERLINK("#FIN_04_Budget_Variance!A1","FIN_04 →") -> FIN_04 → | D31: Budget Variance | E31: Financial | F31: Var % | G31: ≤5% | H31: 6.2% | I31: =+1.2% -> 0.012 | J31: ⚠ | K31: 08:00
B32: 5 | C32: =HYPERLINK("#FIN_05_Cash_Flow!A1","FIN_05 →") -> FIN_05 → | D32: Cash Flow | E32: Financial | F32: Net CF | G32: $125K | H32: $131K | I32: =+4.8% -> 0.048 | J32: ✓ | K32: 08:00
B33: 6 | C33: =HYPERLINK("#FIN_06_Capex!A1","FIN_06 →") -> FIN_06 → | D33: Capex | E33: Financial | F33: Budget Used | G33: 8.3% | H33: 7.9% | I33: =-4.8% -> -0.048 | J33: ✓ | K33: 08:00
B34: 7 | C34: =HYPERLINK("#FIN_07_Debt_Covenant!A1","FIN_07 →") -> FIN_07 → | D34: Debt Covenant | E34: Financial | F34: DSCR | G34: 1.20x | H34: 1.18x | I34: =-1.7% -> -0.017 | J34: ✗ | K34: 08:00
B35: 8 | C35: =HYPERLINK("#FIN_08_AR_Bad_Debt!A1","FIN_08 →") -> FIN_08 → | D35: AR/Bad Debt | E35: Financial | F35: Delinquency | G35: ≤3% | H35: 3.8% | I35: =+26% -> 0.26 | J35: ⚠ | K35: 08:00
B36: 9 | C36: =HYPERLINK("#OPS_09_Leasing_OnePager!A1","OPS_09 →") -> OPS_09 → | D36: Leasing OnePager | E36: Operations | F36: Leases MTD | G36: 15 | H36: 14 | I36: =-6.7% -> -0.067 | J36: ✓ | K36: 08:00
B37: 10 | C37: =HYPERLINK("#OPS_10_Leasing_Funnel!A1","OPS_10 →") -> OPS_10 → | D37: Leasing Funnel | E37: Operations | F37: Conversion | G37: 25% | H37: 23% | I37: =-8% -> -0.08 | J37: ✓ | K37: 08:00
B38: 11 | C38: =HYPERLINK("#OPS_11_Occupancy_Mix!A1","OPS_11 →") -> OPS_11 → | D38: Occupancy Mix | E38: Operations | F38: Occupancy | G38: 92% | H38: 91.2% | I38: =-0.9% -> -0.009 | J38: ✗ | K38: 08:00
B39: 12 | C39: =HYPERLINK("#OPS_12_Renewal_Retention!A1","OPS_12 →") -> OPS_12 → | D39: Renewal Retention | E39: Operations | F39: Renewal % | G39: 55% | H39: 52% | I39: =-5.5% -> -0.055 | J39: ⚠ | K39: 08:00
B40: 13 | C40: =HYPERLINK("#OPS_13_Turnover_MakeReady!A1","OPS_13 →") -> OPS_13 → | D40: Turnover MakeReady | E40: Operations | F40: Days | G40: ≤7 | H40: 9.2 | I40: =+31% -> 0.31 | J40: ⚠ | K40: 08:00
B41: 14 | C41: =HYPERLINK("#OPS_14_Maintenance_WO!A1","OPS_14 →") -> OPS_14 → | D41: Maintenance WO | E41: Operations | F41: Completion | G41: 95% | H41: 94% | I41: =-1.1% -> -0.011 | J41: ✓ | K41: 08:00
B42: 15 | C42: =HYPERLINK("#OPS_15_Resident_NPS!A1","OPS_15 →") -> OPS_15 → | D42: Resident NPS | E42: Operations | F42: NPS Score | G42: 50 | H42: 48 | I42: =-4% -> -0.04 | J42: ✓ | K42: 08:00
B43: 16 | C43: =HYPERLINK("#MKT_16_Marketing_CPA!A1","MKT_16 →") -> MKT_16 → | D43: Marketing CPA | E43: Marketing | F43: CPL | G43: ≤$75 | H43: $82 | I43: =+9.3% -> 0.093 | J43: ⚠ | K43: 08:00
B44: 17 | C44: =HYPERLINK("#MKT_17_Attribution!A1","MKT_17 →") -> MKT_17 → | D44: Attribution | E44: Marketing | F44: Attributed % | G44: 80% | H44: 78% | I44: =-2.5% -> -0.025 | J44: ✓ | K44: 08:00
B45: 18 | C45: =HYPERLINK("#DEV_18_Project_EV!A1","DEV_18 →") -> DEV_18 → | D45: Project EV | E45: Development | F45: IRR | G45: 15% | H45: 14.2% | I45: =-5.3% -> -0.053 | J45: ✓ | K45: 08:00
B46: 19 | C46: =HYPERLINK("#DEV_19_Cost_Complete!A1","DEV_19 →") -> DEV_19 → | D46: Cost Complete | E46: Development | F46: Cost Var | G46: ≤5% | H46: 7.2% | I46: =+2.2% -> 0.022 | J46: ⚠ | K46: 08:00
B47: 20 | C47: =HYPERLINK("#DEV_20_Entitlement_Risk!A1","DEV_20 →") -> DEV_20 → | D47: Entitlement Risk | E47: Development | F47: Risk Score | G47: Low | H47: Med | I47: — | J47: ✓ | K47: 08:00
B48: 21 | C48: =HYPERLINK("#CAP_21_Investor_Quarterly!A1","CAP_21 →") -> CAP_21 → | D48: Investor Quarterly | E48: Capital Mkts | F48: NAV Growth | G48: 5% | H48: 4.8% | I48: =-4% -> -0.04 | J48: ✓ | K48: 08:00
B49: 22 | C49: =HYPERLINK("#ESG_22_Sustainability!A1","ESG_22 →") -> ESG_22 → | D49: Sustainability | E49: ESG | F49: Energy Use | G49: =-5% -> -0.05 | H49: =-3.2% -> -0.032 | I49: =+36% -> 0.36 | J49: ✓ | K49: 08:00
B52: ESCALATION RULES & RESPONSE TIMES
B53: Level | C53: Trigger | D53: Response Time | E53: Notify | F53: Action Required | G53: Auto-Escalate | H53: 0 | I53: 0 | J53: 0 | K53: 0
B54: L1 - Monitor | C54: Var 0-5% | D54: 24 hrs | E54: Report Owner | F54: Acknowledge & document | G54: After 24 hrs → L2
B55: L2 - Warning | C55: Var 5-10% | D55: 8 hrs | E55: Manager + Asset Mgr | F55: Root cause + action plan | G55: After 48 hrs → L3
B56: L3 - Critical | C56: Var >10% or Hard Rule | D56: 2 hrs | E56: Director + VP | F56: Immediate remediation | G56: After 4 hrs → L4
B57: L4 - Executive | C57: Covenant breach | D57: Immediate | E57: C-Suite + Board | F57: Crisis response | G57: Board notification
B60: VARIANCE THRESHOLD CONFIGURATION
B61: Category | C61: Green (OK) | D61: Yellow (Warn) | E61: Red (Critical) | F61: Hard Rule? | G61: Block Action
B62: Financial Variance | C62: ≤ 3% | D62: 3-7% | E62: > 7% | F62: No | G62: —
B63: Occupancy | C63: ≥ 95% | D63: 92-95% | E63: < 92% | F63: No | G63: —
B64: DSCR Covenant | C64: ≥ 1.25x | D64: 1.20-1.25x | E64: < 1.20x | F64: Yes | G64: Capital freeze
B65: Delinquency | C65: ≤ 2% | D65: 2-4% | E65: > 4% | F65: No | G65: —
B66: Marketing CPA | C66: ≤ 0.8x rent | D66: 0.8-1.0x rent | E66: > 1.0x rent | F66: Yes | G66: Pause spend
B67: Make-Ready Days | C67: ≤ 5 days | D67: 5-10 days | E67: > 10 days | F67: No | G67: —
B68: Renewal Rate | C68: ≥ 60% | D68: 50-60% | E68: < 50% | F68: No | G68: —
B69: Cost Overrun (Dev) | C69: ≤ 3% | D69: 3-8% | E69: > 8% | F69: No | G69: —
B72: RECENT ALERT LOG
B73: Timestamp | C73: Alert ID | D73: Report | E73: Metric | F73: Severity | G73: Status | H73: Owner | I73: Resolution | J73: 0 | K73: 0
B74: 01/12 08:00 | C74: ALT-004 | D74: FIN_07 | E74: DSCR < 1.20x | F74: 🔴 CRIT | G74: ACTIVE | H74: CFO | I74: Lender call 10am
B75: 01/12 07:45 | C75: ALT-002 | D75: OPS_11 | E75: Occupancy < 92% | F75: 🔴 CRIT | G75: ACTIVE | H75: Asset Mgr | I75: Leasing sprint started
B76: 01/11 16:30 | C76: ALT-106 | D76: FIN_04 | E76: Budget Var > 5% | F76: 🟡 WARN | G76: ACK | H76: Prop Mgr | I76: Memo submitted
B77: 01/11 14:00 | C77: ALT-102 | D77: MKT_16 | E77: CPL > $75 | F77: 🟡 WARN | G77: ACK | H77: Mktg Mgr | I77: Campaign paused
B78: 01/10 09:15 | C78: ALT-109 | D78: OPS_12 | E78: Renewal < 55% | F78: 🟡 WARN | G78: RESOLVED | H78: Prop Mgr | I78: Retention calls complete
B79: 01/09 11:00 | C79: ALT-103 | D79: OPS_10 | E79: Follow-up < 95% | F79: 🟡 WARN | G79: RESOLVED | H79: Leasing Mgr | I79: Backlog cleared
B82: 📧 EMAIL DISTRIBUTION LIST - ESCALATION NOTIFICATIONS
B83: Configure recipients for automated alert notifications by escalation level
B85: Role | C85: Name | D85: Email | E85: L1 Monitor | F85: L2 Warning | G85: L3 Critical | H85: L4 Executive | I85: SMS? | J85: Frequency | K85: Notes
B86: CEO | C86: Michael Chen | D86: mchen@company.com | E86: 0 | F86: 0 | G86: ✓ | H86: ✓ | I86: Yes | J86: Immediate | K86: All L4 + covenant breaches
B87: CFO | C87: Sarah Williams | D87: swilliams@company.com | E87: 0 | F87: ✓ | G87: ✓ | H87: ✓ | I87: Yes | J87: Immediate | K87: Financial alerts only
B88: COO | C88: David Park | D88: dpark@company.com | E88: 0 | F88: ✓ | G88: ✓ | H88: ✓ | I88: Yes | J88: Immediate | K88: Operations alerts
B89: VP Operations | C89: Jennifer Martinez | D89: jmartinez@company.com | E89: ✓ | F89: ✓ | G89: ✓ | H89: 0 | I89: No | J89: 4 hrs | K89: Ops & maintenance
B90: VP Development | C90: Robert Kim | D90: rkim@company.com | E90: 0 | F90: ✓ | G90: ✓ | H90: 0 | I90: No | J90: 4 hrs | K90: Dev projects only
B91: Director Finance | C91: Amy Thompson | D91: athompson@company.com | E91: ✓ | F91: ✓ | G91: ✓ | H91: 0 | I91: No | J91: Daily | K91: All financial reports
B92: Asset Manager | C92: Lisa Wong | D92: lwong@company.com | E92: ✓ | F92: ✓ | G92: ✓ | H92: 0 | I92: No | J92: Real-time | K92: Primary escalation contact
B93: Property Manager | C93: Tom Richards | D93: trichards@company.com | E93: ✓ | F93: ✓ | G93: 0 | H93: 0 | I93: No | J93: Real-time | K93: Site-level alerts
B94: Leasing Manager | C94: Nicole Davis | D94: ndavis@company.com | E94: ✓ | F94: ✓ | G94: 0 | H94: 0 | I94: No | J94: Daily | K94: Leasing & occupancy
B95: Maintenance Dir | C95: James Wilson | D95: jwilson@company.com | E95: ✓ | F95: ✓ | G95: 0 | H95: 0 | I95: Yes | J95: Real-time | K95: Work orders & emergencies
B96: Marketing Mgr | C96: Emily Santos | D96: esantos@company.com | E96: ✓ | F96: ✓ | G96: 0 | H96: 0 | I96: No | J96: Daily | K96: Marketing KPIs
B99: ⚙️ NOTIFICATION SETTINGS
B100: Alert Frequency: | C100: Real-time for L3-L4, Digest for L1-L2
B101: Digest Schedule: | C101: Daily 8:00 AM, Weekly Monday 8:00 AM
B102: SMS Gateway: | C102: Twilio (+1-555-ALERT)
B103: Email Template: | C103: Standard (includes metric, threshold, current, action)
B104: Auto-Acknowledge: | C104: L1 alerts auto-close after 48 hrs if no action
B107: QUICK ACTIONS
B108: =HYPERLINK("mailto:mchen@company.com;swilliams@company.com;dpark@company.com?subject=URGENT: Executive Alert Escalation&body=Alert requires immediate executive attention.","📧 Email All Executives") -> 📧 Email All Executives | D108: =HYPERLINK("mailto:jmartinez@company.com;rkim@company.com;athompson@company.com?subject=Alert Escalation - Director Review&body=Please review the attached alert.","📧 Email All Directors") -> 📧 Email All Directors | F108: =HYPERLINK("mailto:lwong@company.com;trichards@company.com;ndavis@company.com;jwilson@company.com;esantos@company.com?subject=Alert Notification&body=New alert requires attention.","📧 Email All Managers") -> 📧 Email All Managers
B110: =HYPERLINK("mailto:swilliams@company.com;athompson@company.com?subject=CRITICAL: DSCR Covenant Alert&body=DSCR has breached 1.20x threshold. Current: 1.18x. Immediate lender communication required.","📧 DSCR Breach → CFO") -> 📧 DSCR Breach → CFO | D110: =HYPERLINK("mailto:jmartinez@company.com;lwong@company.com?subject=CRITICAL: Occupancy Alert&body=Portfolio occupancy below 92%. Current: 91.2%. Emergency leasing sprint required.","📧 Occupancy Alert → Ops") -> 📧 Occupancy Alert → Ops
B113: ESCALATION MATRIX SUMMARY
B114: Level | C114: Recipients | D114: Response SLA | E114: Auto-Escalate
B115: L1 - Monitor | C115: Property Mgr, Leasing Mgr, Maint Dir, Mktg Mgr | D115: 24 hrs | E115: → L2 after 24 hrs
B116: L2 - Warning | C116: Asset Mgr + Directors | D116: 8 hrs | E116: → L3 after 48 hrs
B117: L3 - Critical | C117: VP Ops, VP Dev, Dir Finance | D117: 2 hrs | E117: → L4 after 4 hrs
B118: L4 - Executive | C118: CEO, CFO, COO + Board | D118: Immediate | E118: Board notification
B121: 📋 EMAIL TEMPLATES BY ESCALATION LEVEL
B122: Click template buttons to generate pre-populated emails with current metric data
B124: LEVEL 1 - MONITOR TEMPLATE
B125: Subject: | C125: [L1 MONITOR] Daily Alert Digest - {{DATE}} | J125: =HYPERLINK("mailto:trichards@company.com;ndavis@company.com?subject=[L1 MONITOR] Daily Alert Digest - 01/12/2026&body=Daily Performance Alert Summary%0A%0AThe following metrics require monitoring:%0A• Budget Variance: 6.2%25 (Threshold: ≤5%25)%0A• Marketing CPL: $82 (Threshold: ≤$75)%0A• Make-Ready Days: 9.2 (Threshold: ≤7)%0A%0AACTION: Review and acknowledge within 24 hours.","📧 Generate L1 Email") -> 📧 Generate L1 Email
B126: To: | C126: Property Managers, Leasing Managers, Department Heads
B127: Body:
...

Sheet Lease_Expiration_Matrix
B2: LEASE EXPIRATION MATRIX
B3: 12-Month Rolling Lease Expiration Calendar | Portfolio: Sunrise Properties | As of: January 2026
B5: EXPIRATION SUMMARY
B6: Total Units | D6: Expiring (12 mo) | F6: At Risk | H6: Renewed | J6: Pending | L6: Renewal Rate
B7: 248 | D7: 156 | F7: 23 | H7: 42 | J7: 91 | L7: 52%
B10: EXPIRATIONS BY FLOORPLAN & MONTH
B11: Floorplan | C11: Jan-26 | D11: Feb-26 | E11: Mar-26 | F11: Apr-26 | G11: May-26 | H11: Jun-26 | I11: Jul-26 | J11: Aug-26 | K11: Sep-26 | L11: Oct-26 | M11: Nov-26 | N11: Dec-26 | O11: Total | P11: % of Type
B12: Studio | C12: 3 | D12: 2 | E12: 4 | F12: 3 | G12: 2 | H12: 3 | I12: 2 | J12: 4 | K12: 3 | L12: 2 | M12: 3 | N12: 2 | O12: =SUM(C12:N12) -> 33 | P12: 0.72
B13: 1BR/1BA | C13: 5 | D13: 4 | E13: 6 | F13: 5 | G13: 4 | H13: 5 | I13: 4 | J13: 6 | K13: 5 | L13: 4 | M13: 5 | N13: 4 | O13: =SUM(C13:N13) -> 57 | P13: 0.68
B14: 1BR/1BA+Den | C14: 2 | D14: 1 | E14: 2 | F14: 2 | G14: 1 | H14: 2 | I14: 1 | J14: 2 | K14: 2 | L14: 1 | M14: 2 | N14: 1 | O14: =SUM(C14:N14) -> 19 | P14: 0.59
B15: 2BR/1BA | C15: 3 | D15: 2 | E15: 3 | F15: 2 | G15: 3 | H15: 2 | I15: 3 | J15: 2 | K15: 3 | L15: 2 | M15: 3 | N15: 2 | O15: =SUM(C15:N15) -> 30 | P15: 0.63
B16: 2BR/2BA | C16: 2 | D16: 2 | E16: 1 | F16: 2 | G16: 2 | H16: 1 | I16: 2 | J16: 2 | K16: 1 | L16: 2 | M16: 2 | N16: 1 | O16: =SUM(C16:N16) -> 20 | P16: 0.56
B17: 3BR/2BA | C17: 1 | D17: 1 | E17: 0 | F17: 1 | G17: 1 | H17: 1 | I17: 0 | J17: 1 | K17: 1 | L17: 1 | M17: 0 | N17: 1 | O17: =SUM(C17:N17) -> 9 | P17: 0.45
B18: Townhome | C18: 0 | D18: 1 | E18: 1 | F18: 0 | G18: 1 | H18: 1 | I18: 0 | J18: 1 | K18: 1 | L18: 0 | M18: 1 | N18: 1 | O18: =SUM(C18:N18) -> 8 | P18: 0.5
B19: TOTAL | C19: =SUM(C12:C18) -> 16 | D19: =SUM(D12:D18) -> 13 | E19: =SUM(E12:E18) -> 17 | F19: =SUM(F12:F18) -> 15 | G19: =SUM(G12:G18) -> 14 | H19: =SUM(H12:H18) -> 15 | I19: =SUM(I12:I18) -> 12 | J19: =SUM(J12:J18) -> 18 | ... O19: =SUM(O12:O18) -> 176 | P19: =O19/248 -> 0.70967742
B22: RENEWAL STATUS BY MONTH
B23: Status | C23: Jan-26 | D23: Feb-26 | E23: Mar-26 | F23: Apr-26 | G23: May-26 | H23: Jun-26 | I23: Jul-26 | J23: Aug-26 | K23: Sep-26 | L23: Oct-26 | M23: Nov-26 | N23: Dec-26 | O23: Total
B24: ✓ Renewed | C24: 8 | D24: 6 | E24: 0 | F24: 0 | G24: 0 | H24: 0 | I24: 0 | J24: 0 | K24: 0 | L24: 0 | M24: 0 | N24: 0 | O24: =SUM(C24:N24) -> 14
B25: ⏳ Pending | C25: 5 | D25: 4 | E25: 12 | F25: 10 | G25: 9 | H25: 8 | I25: 7 | J25: 12 | K25: 10 | L25: 7 | M25: 9 | N25: 7 | O25: =SUM(C25:N25) -> 100
B26: ⚠ At Risk | C26: 2 | D26: 2 | E26: 3 | F26: 3 | G26: 2 | H26: 3 | I26: 2 | J26: 3 | K26: 2 | L26: 2 | M26: 1 | N26: 1 | O26: =SUM(C26:N26) -> 26
B27: ✗ NTV Given | C27: 1 | D27: 1 | E27: 2 | F27: 2 | G27: 2 | H27: 3 | I27: 1 | J27: 3 | K27: 3 | L27: 2 | M27: 2 | N27: 0 | O27: =SUM(C27:N27) -> 22
B30: UPCOMING EXPIRATIONS - NEXT 90 DAYS (Detail View)
B31: Unit | C31: Bldg | D31: Floorplan | E31: Resident | F31: Lease End | G31: Current Rent | H31: Market Rent | I31: Gap % | J31: Status | K31: Last Contact | L31: Renewal Prob | M31: Notes
B32: 101 | C32: A | D32: 1BR/1BA | E32: Johnson, M. | F32: 01/31/26 | G32: 1450 | H32: 1525 | I32: =1-G32/H32 -> 0.049180328 | J32: ⚠ At Risk | K32: 01/08/26 | L32: 35% | M32: Price sensitive
B33: 205 | C33: A | D33: 2BR/2BA | E33: Williams, S. | F33: 01/31/26 | G33: 1850 | H33: 1875 | I33: =1-G33/H33 -> 0.013333333 | J33: ✓ Renewed | K33: 01/10/26 | L33: 100% | M33: Signed 12-mo
B34: 312 | C34: B | D34: Studio | E34: Chen, L. | F34: 02/15/26 | G34: 1150 | H34: 1200 | I34: =1-G34/H34 -> 0.041666667 | J34: ⏳ Pending | K34: 01/05/26 | L34: 70% | M34: Waiting on decision
B35: 118 | C35: A | D35: 1BR/1BA+Den | E35: Garcia, R. | F35: 02/28/26 | G35: 1625 | H35: 1700 | I35: =1-G35/H35 -> 0.044117647 | J35: ⏳ Pending | K35: 01/09/26 | L35: 65% | M35: Requested lower rent
B36: 421 | C36: C | D36: 2BR/1BA | E36: Thompson, J. | F36: 02/28/26 | G36: 1550 | H36: 1600 | I36: =1-G36/H36 -> 0.03125 | J36: ✗ NTV Given | K36: 01/02/26 | L36: 0% | M36: Relocating for work
B37: 203 | C37: A | D37: 1BR/1BA | E37: Martinez, A. | F37: 03/15/26 | G37: 1475 | H37: 1525 | I37: =1-G37/H37 -> 0.032786885 | J37: ⏳ Pending | K37: 12/28/25 | L37: 75% | M37: Happy resident
B38: 509 | C38: C | D38: 3BR/2BA | E38: Brown, K. | F38: 03/31/26 | G38: 2100 | H38: 2200 | I38: =1-G38/H38 -> 0.045454545 | J38: ⚠ At Risk | K38: 01/06/26 | L38: 40% | M38: Noise complaints
B39: 115 | C39: A | D39: Studio | E39: Lee, D. | F39: 03/31/26 | G39: 1125 | H39: 1200 | I39: =1-G39/H39 -> 0.0625 | J39: ⏳ Pending | K39: 01/11/26 | L39: 80% | M39: Long-term resident
B42: RISK HEAT MAP - REVENUE AT RISK BY MONTH
B43: Risk Level | C43: Jan-26 | D43: Feb-26 | E43: Mar-26 | F43: Apr-26 | G43: May-26 | H43: Jun-26 | I43: Jul-26 | J43: Aug-26 | K43: Sep-26 | L43: Oct-26 | M43: Nov-26 | N43: Dec-26 | O43: Total
B44: High Risk (>$3K) | C44: 4500 | D44: 3200 | E44: 5100 | F44: 4800 | G44: 3600 | H44: 4200 | I44: 3100 | J44: 4900 | K44: 3800 | L44: 3400 | M44: 2800 | N44: 2200 | O44: =SUM(C44:N44) -> 45600
B45: Medium Risk ($1-3K) | C45: 2800 | D45: 2100 | E45: 3200 | F45: 2900 | G45: 2400 | H45: 2700 | I45: 2200 | J45: 3100 | K45: 2600 | L45: 2200 | M45: 2400 | N45: 1800 | O45: =SUM(C45:N45) -> 30400
B46: Low Risk (<$1K) | C46: 800 | D46: 600 | E46: 1100 | F46: 900 | G46: 700 | H46: 800 | I46: 600 | J46: 1000 | K46: 800 | L46: 700 | M46: 600 | N46: 500 | O46: =SUM(C46:N46) -> 9100
B47: TOTAL AT RISK | C47: =SUM(C44:C46) -> 8100 | D47: =SUM(D44:D46) -> 5900 | E47: =SUM(E44:E46) -> 9400 | F47: =SUM(F44:F46) -> 8600 | G47: =SUM(G44:G46) -> 6700 | H47: =SUM(H44:H46) -> 7700 | I47: =SUM(I44:I46) -> 5900 | J47: =SUM(J44:J46) -> 9000 | ... O47: =SUM(O44:O46) -> 85100
B50: PRIORITY ACTIONS | J50: STATUS LEGEND
B51: # | C51: Action Item | F51: Owner | G51: Due Date | J51: ✓ Renewed | K51: Lease signed for renewal term
B52: 1 | C52: Contact at-risk residents (23 units) within 48 hours | F52: Leasing Team | G52: 01/14/26 | J52: ⏳ Pending | K52: Contacted, awaiting decision
B53: 2 | C53: Prepare competitive renewal offers for Q1 expirations | F53: Asset Manager | G53: 01/15/26 | J53: ⚠ At Risk | K53: May not renew (price/issues)
B54: 3 | C54: Review pricing strategy for 2BR units (lowest renewal %) | F54: Revenue Mgr | G54: 01/20/26 | J54: ✗ NTV Given | K54: Notice to vacate received
B55: 4 | C55: Schedule retention calls for Building C residents | F55: Property Mgr | G55: 01/13/26

Sheet Rolling_12M_Forecast
B2: ROLLING 12-MONTH FORECAST
B3: Automatically updates with actuals | Forecast Period: Jan 2026 - Dec 2026
B5: CONTROL PANEL
B6: Current Month: | C6: 1 | D6: Last Actual: | E6: Jan-26
B7: Forecast Version: | C7: RF2 - Jan 2026
B10: Line Item | C10: Jan-26 | D10: Feb-26 | E10: Mar-26 | F10: Apr-26 | G10: May-26 | H10: Jun-26 | I10: Jul-26 | J10: Aug-26 | K10: Sep-26 | L10: Oct-26 | M10: Nov-26 | N10: Dec-26 | O10: FY Total | P10: YoY %
B11: Data Type → | C11: =_xlfn.IFERROR(IF(1<=$C$6,"A","F"),0) -> A | D11: =_xlfn.IFERROR(IF(2<=$C$6,"A","F"),0) -> F | E11: =_xlfn.IFERROR(IF(3<=$C$6,"A","F"),0) -> F | F11: =_xlfn.IFERROR(IF(4<=$C$6,"A","F"),0) -> F | G11: =_xlfn.IFERROR(IF(5<=$C$6,"A","F"),0) -> F | H11: =_xlfn.IFERROR(IF(6<=$C$6,"A","F"),0) -> F | I11: =_xlfn.IFERROR(IF(7<=$C$6,"A","F"),0) -> F | J11: =_xlfn.IFERROR(IF(8<=$C$6,"A","F"),0) -> F | K11: =_xlfn.IFERROR(IF(9<=$C$6,"A","F"),0) -> F | L11: =_xlfn.IFERROR(IF(10<=$C$6,"A","F"),0) -> F | M11: =_xlfn.IFERROR(IF(11<=$C$6,"A","F"),0) -> F | N11: =_xlfn.IFERROR(IF(12<=$C$6,"A","F"),0) -> F
B13: REVENUE
B14: Rental Income | C14: =IF(1<=$C$6,452000,450000) -> 452000 | D14: =IF(2<=$C$6,455000,455000) -> 455000 | E14: =IF(3<=$C$6,458000,458000) -> 458000 | F14: =IF(4<=$C$6,462000,462000) -> 462000 | G14: =IF(5<=$C$6,465000,465000) -> 465000 | H14: =IF(6<=$C$6,470000,470000) -> 470000 | I14: =IF(7<=$C$6,472000,472000) -> 472000 | J14: =IF(8<=$C$6,475000,475000) -> 475000 | K14: =IF(9<=$C$6,478000,478000) -> 478000 | L14: =IF(10<=$C$6,480000,480000) -> 480000 | M14: =IF(11<=$C$6,482000,482000) -> 482000 | N14: =IF(12<=$C$6,485000,485000) -> 485000 | O14: =SUM(C14:N14) -> 5634000 | P14: 0.032
B15: Other Income | C15: =IF(1<=$C$6,19200,18000) -> 19200 | D15: =IF(2<=$C$6,18500,18500) -> 18500 | E15: =IF(3<=$C$6,19000,19000) -> 19000 | F15: =IF(4<=$C$6,19200,19200) -> 19200 | G15: =IF(5<=$C$6,19500,19500) -> 19500 | H15: =IF(6<=$C$6,20000,20000) -> 20000 | I15: =IF(7<=$C$6,20200,20200) -> 20200 | J15: =IF(8<=$C$6,20500,20500) -> 20500 | K15: =IF(9<=$C$6,20800,20800) -> 20800 | L15: =IF(10<=$C$6,21000,21000) -> 21000 | M15: =IF(11<=$C$6,21200,21200) -> 21200 | N15: =IF(12<=$C$6,21500,21500) -> 21500 | O15: =SUM(C15:N15) -> 240600 | P15: 0.045
B16: Total Revenue | C16: =_xlfn.IFERROR(C14+C15,0) -> 471200 | D16: =_xlfn.IFERROR(D14+D15,0) -> 473500 | E16: =_xlfn.IFERROR(E14+E15,0) -> 477000 | F16: =_xlfn.IFERROR(F14+F15,0) -> 481200 | G16: =_xlfn.IFERROR(G14+G15,0) -> 484500 | H16: =_xlfn.IFERROR(H14+H15,0) -> 490000 | I16: =_xlfn.IFERROR(I14+I15,0) -> 492200 | J16: =_xlfn.IFERROR(J14+J15,0) -> 495500 | ... N16: =_xlfn.IFERROR(N14+N15,0) -> 506500 | O16: =_xlfn.IFERROR(SUM(C16:N16),0) -> 5874600 | P16: =_xlfn.IFERROR(AVERAGE(C14:N14)/450000-1,0) -> 0.043333333
B18: OPERATING EXPENSES
B19: Payroll & Benefits | C19: =IF(1<=$C$6,88000,85000) -> 88000 | D19: =IF(2<=$C$6,85500,85500) -> 85500 | E19: =IF(3<=$C$6,86000,86000) -> 86000 | F19: =IF(4<=$C$6,86500,86500) -> 86500 | G19: =IF(5<=$C$6,87000,87000) -> 87000 | H19: =IF(6<=$C$6,87500,87500) -> 87500 | I19: =IF(7<=$C$6,88000,88000) -> 88000 | J19: =IF(8<=$C$6,88500,88500) -> 88500 | K19: =IF(9<=$C$6,89000,89000) -> 89000 | L19: =IF(10<=$C$6,89500,89500) -> 89500 | M19: =IF(11<=$C$6,90000,90000) -> 90000 | N19: =IF(12<=$C$6,90500,90500) -> 90500 | O19: =SUM(C19:N19) -> 1056000
B20: Repairs & Maintenance | C20: =IF(1<=$C$6,29500,28000) -> 29500 | D20: =IF(2<=$C$6,30000,30000) -> 30000 | E20: =IF(3<=$C$6,32000,32000) -> 32000 | F20: =IF(4<=$C$6,35000,35000) -> 35000 | G20: =IF(5<=$C$6,33000,33000) -> 33000 | H20: =IF(6<=$C$6,31000,31000) -> 31000 | I20: =IF(7<=$C$6,29000,29000) -> 29000 | J20: =IF(8<=$C$6,32000,32000) -> 32000 | K20: =IF(9<=$C$6,34000,34000) -> 34000 | L20: =IF(10<=$C$6,30000,30000) -> 30000 | M20: =IF(11<=$C$6,28000,28000) -> 28000 | N20: =IF(12<=$C$6,26000,26000) -> 26000 | O20: =SUM(C20:N20) -> 369500
B21: Utilities | C21: =IF(1<=$C$6,23800,24000) -> 23800 | D21: =IF(2<=$C$6,23000,23000) -> 23000 | E21: =IF(3<=$C$6,22000,22000) -> 22000 | F21: =IF(4<=$C$6,21000,21000) -> 21000 | G21: =IF(5<=$C$6,23000,23000) -> 23000 | H21: =IF(6<=$C$6,26000,26000) -> 26000 | I21: =IF(7<=$C$6,28000,28000) -> 28000 | J21: =IF(8<=$C$6,27000,27000) -> 27000 | K21: =IF(9<=$C$6,25000,25000) -> 25000 | L21: =IF(10<=$C$6,23000,23000) -> 23000 | M21: =IF(11<=$C$6,22000,22000) -> 22000 | N21: =IF(12<=$C$6,24000,24000) -> 24000 | O21: =SUM(C21:N21) -> 287800
B22: Property Management | C22: =_xlfn.IFERROR(IF(1<=$C$6,22000,22000),0) -> 22000 | D22: =_xlfn.IFERROR(IF(2<=$C$6,22000,22000),0) -> 22000 | E22: =_xlfn.IFERROR(IF(3<=$C$6,22000,22000),0) -> 22000 | F22: =_xlfn.IFERROR(IF(4<=$C$6,22000,22000),0) -> 22000 | G22: =_xlfn.IFERROR(IF(5<=$C$6,22500,22500),0) -> 22500 | H22: =_xlfn.IFERROR(IF(6<=$C$6,22500,22500),0) -> 22500 | I22: =_xlfn.IFERROR(IF(7<=$C$6,22500,22500),0) -> 22500 | J22: =_xlfn.IFERROR(IF(8<=$C$6,22500,22500),0) -> 22500 | K22: =_xlfn.IFERROR(IF(9<=$C$6,23000,23000),0) -> 23000 | L22: =_xlfn.IFERROR(IF(10<=$C$6,23000,23000),0) -> 23000 | M22: =_xlfn.IFERROR(IF(11<=$C$6,23000,23000),0) -> 23000 | N22: =_xlfn.IFERROR(IF(12<=$C$6,23000,23000),0) -> 23000 | O22: =_xlfn.IFERROR(SUM(C22:N22),0) -> 270000
B23: Marketing | C23: =IF(1<=$C$6,16500,15000) -> 16500 | D23: =IF(2<=$C$6,18000,18000) -> 18000 | E23: =IF(3<=$C$6,20000,20000) -> 20000 | F23: =IF(4<=$C$6,22000,22000) -> 22000 | G23: =IF(5<=$C$6,20000,20000) -> 20000 | H23: =IF(6<=$C$6,18000,18000) -> 18000 | I23: =IF(7<=$C$6,16000,16000) -> 16000 | J23: =IF(8<=$C$6,18000,18000) -> 18000 | K23: =IF(9<=$C$6,20000,20000) -> 20000 | L23: =IF(10<=$C$6,18000,18000) -> 18000 | M23: =IF(11<=$C$6,16000,16000) -> 16000 | N23: =IF(12<=$C$6,14000,14000) -> 14000 | O23: =SUM(C23:N23) -> 216500
B24: Insurance | C24: =IF(1<=$C$6,12000,12000) -> 12000 | D24: =IF(2<=$C$6,12000,12000) -> 12000 | E24: =IF(3<=$C$6,12000,12000) -> 12000 | F24: =IF(4<=$C$6,12000,12000) -> 12000 | G24: =IF(5<=$C$6,12000,12000) -> 12000 | H24: =IF(6<=$C$6,12000,12000) -> 12000 | I24: =IF(7<=$C$6,12500,12500) -> 12500 | J24: =IF(8<=$C$6,12500,12500) -> 12500 | K24: =IF(9<=$C$6,12500,12500) -> 12500 | L24: =IF(10<=$C$6,12500,12500) -> 12500 | M24: =IF(11<=$C$6,12500,12500) -> 12500 | N24: =IF(12<=$C$6,12500,12500) -> 12500 | O24: =SUM(C24:N24) -> 147000
B25: Property Taxes | C25: =IF(1<=$C$6,38000,38000) -> 38000 | D25: =IF(2<=$C$6,38000,38000) -> 38000 | E25: =IF(3<=$C$6,38000,38000) -> 38000 | F25: =IF(4<=$C$6,38000,38000) -> 38000 | G25: =IF(5<=$C$6,38000,38000) -> 38000 | H25: =IF(6<=$C$6,38000,38000) -> 38000 | I25: =IF(7<=$C$6,38500,38500) -> 38500 | J25: =IF(8<=$C$6,38500,38500) -> 38500 | K25: =IF(9<=$C$6,38500,38500) -> 38500 | L25: =IF(10<=$C$6,38500,38500) -> 38500 | M25: =IF(11<=$C$6,38500,38500) -> 38500 | N25: =IF(12<=$C$6,38500,38500) -> 38500 | O25: =SUM(C25:N25) -> 459000
B26: Admin & G&A | C26: =IF(1<=$C$6,8500,8000) -> 8500 | D26: =IF(2<=$C$6,8200,8200) -> 8200 | E26: =IF(3<=$C$6,8400,8400) -> 8400 | F26: =IF(4<=$C$6,8600,8600) -> 8600 | G26: =IF(5<=$C$6,8800,8800) -> 8800 | H26: =IF(6<=$C$6,9000,9000) -> 9000 | I26: =IF(7<=$C$6,9000,9000) -> 9000 | J26: =IF(8<=$C$6,9200,9200) -> 9200 | K26: =IF(9<=$C$6,9400,9400) -> 9400 | L26: =IF(10<=$C$6,9600,9600) -> 9600 | M26: =IF(11<=$C$6,9800,9800) -> 9800 | N26: =IF(12<=$C$6,10000,10000) -> 10000 | O26: =SUM(C26:N26) -> 108500
B27: Total Operating Expenses | C27: =SUM(C19:C26) -> 238300 | D27: =SUM(D19:D26) -> 236700 | E27: =SUM(E19:E26) -> 240400 | F27: =SUM(F19:F26) -> 245100 | G27: =SUM(G19:G26) -> 244300 | H27: =SUM(H19:H26) -> 244000 | I27: =SUM(I19:I26) -> 243500 | J27: =SUM(J19:J26) -> 248200 | ... N27: =SUM(N19:N26) -> 238500 | O27: =SUM(C27:N27) -> 2914300
B29: NET OPERATING INCOME
B30: NOI | C30: =_xlfn.IFERROR(C16-C27,0) -> 232900 | D30: =_xlfn.IFERROR(D16-D27,0) -> 236800 | E30: =_xlfn.IFERROR(E16-E27,0) -> 236600 | F30: =_xlfn.IFERROR(F16-F27,0) -> 236100 | G30: =_xlfn.IFERROR(G16-G27,0) -> 240200 | H30: =_xlfn.IFERROR(H16-H27,0) -> 246000 | I30: =_xlfn.IFERROR(I16-I27,0) -> 248700 | J30: =_xlfn.IFERROR(J16-J27,0) -> 247300 | ... N30: =_xlfn.IFERROR(N16-N27,0) -> 268000 | O30: =_xlfn.IFERROR(SUM(C30:N30),0) -> 2960300 | P30: =_xlfn.IFERROR(O30/O16,0) -> 0.50391516
B32: CAPITAL & DEBT SERVICE
B33: Capital Expenditures | C33: 15000 | D33: 12000 | E33: 18000 | F33: 25000 | G33: 20000 | H33: 15000 | I33: 12000 | J33: 22000 | K33: 18000 | L33: 15000 | M33: 12000 | N33: 10000 | O33: =SUM(C33:N33) -> 194000
B34: Debt Service | C34: 125000 | D34: 125000 | E34: 125000 | F34: 125000 | G34: 125000 | H34: 125000 | I34: 125000 | J34: 125000 | K34: 125000 | L34: 125000 | M34: 125000 | N34: 125000 | O34: =SUM(C34:N34) -> 1500000
B35: Total Capital & Debt | C35: =_xlfn.IFERROR(C33+C34,0) -> 140000 | D35: =_xlfn.IFERROR(D33+D34,0) -> 137000 | E35: =_xlfn.IFERROR(E33+E34,0) -> 143000 | F35: =_xlfn.IFERROR(F33+F34,0) -> 150000 | G35: =_xlfn.IFERROR(G33+G34,0) -> 145000 | H35: =_xlfn.IFERROR(H33+H34,0) -> 140000 | I35: =_xlfn.IFERROR(I33+I34,0) -> 137000 | J35: =_xlfn.IFERROR(J33+J34,0) -> 147000 | ... N35: =_xlfn.IFERROR(N33+N34,0) -> 135000 | O35: =_xlfn.IFERROR(SUM(C35:N35),0) -> 1694000
B37: NET CASH FLOW
B38: Net Cash Flow | C38: =_xlfn.IFERROR(C30-C35,0) -> 92900 | D38: =_xlfn.IFERROR(D30-D35,0) -> 99800 | E38: =_xlfn.IFERROR(E30-E35,0) -> 93600 | F38: =_xlfn.IFERROR(F30-F35,0) -> 86100 | G38: =_xlfn.IFERROR(G30-G35,0) -> 95200 | H38: =_xlfn.IFERROR(H30-H35,0) -> 106000 | I38: =_xlfn.IFERROR(I30-I35,0) -> 111700 | J38: =_xlfn.IFERROR(J30-J35,0) -> 100300 | ... N38: =_xlfn.IFERROR(N30-N35,0) -> 133000 | O38: =_xlfn.IFERROR(SUM(C38:N38),0) -> 1266300
B41: FORECAST ACCURACY TRACKING
B42: Metric | C42: Original Budget | D42: Current Forecast | E42: YTD Actual | F42: Variance | G42: Accuracy
B43: Total Revenue | C43: 5650000 | D43: {=O16} -> 5874600 | E43: {=C16} -> 471200 | F43: =E43-C43 -> -5178800 | G43: =1-ABS(F43/C43) -> 0.08339823
B44: Operating Expenses | C44: 2850000 | D44: {=O27} -> 2914300 | E44: {=C27} -> 238300 | F44: =E44-C44 -> -2611700 | G44: =1-ABS(F44/C44) -> 0.083614035
B45: NOI | C45: 2800000 | D45: {=O30} -> 2960300 | E45: {=C30} -> 232900 | F45: =E45-C45 -> -2567100 | G45: =1-ABS(F45/C45) -> 0.083178571
B46: Net Cash Flow | C46: 1200000 | D46: {=O38} -> 1266300 | E46: {=C38} -> 92900 | F46: =E46-C46 -> -1107100 | G46: =1-ABS(F46/C46) -> 0.077416667
B49: KEY ASSUMPTIONS
B50: Assumption | C50: Value | D50: Notes
B51: Rent Growth Rate | C51: 3.2% | D51: Annual escalation on renewals
B52: Occupancy Target | C52: 95% | D52: Stabilized occupancy assumption
B53: Expense Inflation | C53: 2.5% | D53: General operating expense growth
B54: CapEx Reserve | C54: $194K | D54: Annual capital reserve budget
B55: Debt Service | C55: $125K/mo | D55: Fixed P&I on term loan
B57: HOW TO USE THIS MODEL
B58: 1. Update Current Month (C6) when closing the books each month (1=Jan, 2=Feb, etc.)
B59: 2. Months ≤ Current Month show ACTUALS (marked 'A'), future months show FORECAST (marked 'F')
B60: 3. Replace forecast values with actuals as they become available
B61: 4. Review Forecast Accuracy section to track budget vs actual performance
B62: 5. Update assumptions in Key Assumptions section when reforecasting

Sheet Sensitivity_Analysis
B2: SENSITIVITY ANALYSIS MODEL
B3: What-If Scenario Analysis | Base Case vs Upside vs Downside | FY 2026
B5: INPUT ASSUMPTIONS (Edit Yellow Cells)
B6: Assumption | C6: Downside | D6: Base Case | E6: Upside | F6: Current | G6: Notes
B7: Annual Rent Growth | C7: -0.01 | D7: 0.03 | E7: 0.05 | F7: 0.032 | G7: % change in rental rates
B8: Occupancy Rate | C8: 0.9 | D8: 0.95 | E8: 0.97 | F8: 0.952 | G8: Average occupancy
B9: Expense Growth | C9: 0.05 | D9: 0.025 | E9: 0.015 | F9: 0.025 | G9: OpEx inflation rate
B10: Bad Debt % | C10: 0.04 | D10: 0.02 | E10: 0.01 | F10: 0.025 | G10: % of revenue
B11: CapEx ($/unit) | C11: 1200 | D11: 800 | E11: 600 | F11: 780 | G11: Annual per unit
B14: BASE FINANCIAL INPUTS
B15: Total Units | C15: 248 | D15: units
B16: Base Monthly Rent | C16: 1800 | D16: $/unit
B17: Other Income (% of Rent) | C17: 0.04 | D17: %
B18: Base OpEx ($/unit/year) | C18: 11750 | D18: $/unit
B19: Debt Service (Annual) | C19: 1500000 | D19: $
B22: SCENARIO COMPARISON - ANNUAL PROJECTIONS
B23: Metric | C23: Downside | D23: Base Case | E23: Upside | F23: Δ Down vs Base | G23: Δ Up vs Base
B24: Gross Potential Rent | C24: =_xlfn.IFERROR($C$15*$C$16*12*(1+C7),0) -> 5303232 | D24: =_xlfn.IFERROR($C$15*$C$16*12*(1+D7),0) -> 5517504 | E24: =_xlfn.IFERROR($C$15*$C$16*12*(1+E7),0) -> 5624640 | F24: =_xlfn.IFERROR(C24-D24,0) -> -214272 | G24: =_xlfn.IFERROR(E24-D24,0) -> 107136
B25: Effective Rental Revenue | C25: =_xlfn.IFERROR(C24*C8,0) -> 4772908.8 | D25: =_xlfn.IFERROR(D24*D8,0) -> 5241628.8 | E25: =_xlfn.IFERROR(E24*E8,0) -> 5455900.8 | F25: =_xlfn.IFERROR(C25-D25,0) -> -468720 | G25: =_xlfn.IFERROR(E25-D25,0) -> 214272
B26: Other Income | C26: =_xlfn.IFERROR(C25*$C$17,0) -> 190916.35 | D26: =_xlfn.IFERROR(D25*$C$17,0) -> 209665.15 | E26: =_xlfn.IFERROR(E25*$C$17,0) -> 218236.03 | F26: =_xlfn.IFERROR(C26-D26,0) -> -18748.8 | G26: =_xlfn.IFERROR(E26-D26,0) -> 8570.88
B27: Less: Bad Debt | C27: =_xlfn.IFERROR(-C25*C10,0) -> -190916.35 | D27: =_xlfn.IFERROR(-D25*D10,0) -> -104832.58 | E27: =_xlfn.IFERROR(-E25*E10,0) -> -54559.008 | F27: =_xlfn.IFERROR(C27-D27,0) -> -86083.776 | G27: =_xlfn.IFERROR(E27-D27,0) -> 50273.568
B28: Total Revenue | C28: =_xlfn.IFERROR(C25+C26+C27,0) -> 4772908.8 | D28: =_xlfn.IFERROR(D25+D26+D27,0) -> 5346461.4 | E28: =_xlfn.IFERROR(E25+E26+E27,0) -> 5619577.8 | F28: =_xlfn.IFERROR(C28-D28,0) -> -573552.58 | G28: =_xlfn.IFERROR(E28-D28,0) -> 273116.45
B30: Operating Expenses | C30: =_xlfn.IFERROR($C$18*$C$15*(1+C9),0) -> 3059700 | D30: =_xlfn.IFERROR($C$18*$C$15*(1+D9),0) -> 2986850 | E30: =_xlfn.IFERROR($C$18*$C$15*(1+E9),0) -> 2957710 | F30: =_xlfn.IFERROR(C30-D30,0) -> 72850 | G30: =_xlfn.IFERROR(E30-D30,0) -> -29140
B31: Capital Expenditures | C31: =_xlfn.IFERROR(C11*$C$15,0) -> 297600 | D31: =_xlfn.IFERROR(D11*$C$15,0) -> 198400 | E31: =_xlfn.IFERROR(E11*$C$15,0) -> 148800 | F31: =_xlfn.IFERROR(C31-D31,0) -> 99200 | G31: =_xlfn.IFERROR(E31-D31,0) -> -49600
B33: Net Operating Income (NOI) | C33: =_xlfn.IFERROR(C28-C30,0) -> 1713208.8 | D33: =_xlfn.IFERROR(D28-D30,0) -> 2359611.4 | E33: =_xlfn.IFERROR(E28-E30,0) -> 2661867.8 | F33: =_xlfn.IFERROR(C33-D33,0) -> -646402.58 | G33: =_xlfn.IFERROR(E33-D33,0) -> 302256.45
B34: NOI Margin | C34: =_xlfn.IFERROR(C33/C28,0) -> 0.35894438 | D34: =_xlfn.IFERROR(D33/D28,0) -> 0.44134077 | E34: =_xlfn.IFERROR(E33/E28,0) -> 0.47367754 | F34: =_xlfn.IFERROR(C34-D34,0) -> -0.082396387 | G34: =_xlfn.IFERROR(E34-D34,0) -> 0.032336775
B36: Debt Service | C36: =_xlfn.IFERROR($C$19,0) -> 1500000 | D36: =_xlfn.IFERROR($C$19,0) -> 1500000 | E36: =_xlfn.IFERROR($C$19,0) -> 1500000 | F36: =_xlfn.IFERROR(C36-D36,0) -> 0 | G36: =_xlfn.IFERROR(E36-D36,0) -> 0
B37: Net Cash Flow | C37: =_xlfn.IFERROR(C33-C31-C36,0) -> -84391.2 | D37: =_xlfn.IFERROR(D33-D31-D36,0) -> 661211.38 | E37: =_xlfn.IFERROR(E33-E31-E36,0) -> 1013067.8 | F37: =_xlfn.IFERROR(C37-D37,0) -> -745602.58 | G37: =_xlfn.IFERROR(E37-D37,0) -> 351856.45
B38: DSCR | C38: =_xlfn.IFERROR(C33/C36,0) -> 1.1421392 | D38: =_xlfn.IFERROR(D33/D36,0) -> 1.5730743 | E38: =_xlfn.IFERROR(E33/E36,0) -> 1.7745785 | F38: =_xlfn.IFERROR(C38-D38,0) -> -0.43093505 | G38: =_xlfn.IFERROR(E38-D38,0) -> 0.2015043
B39: Cash-on-Cash Return | C39: =_xlfn.IFERROR(C37/20000000,0) -> -0.00421956 | D39: =_xlfn.IFERROR(D37/20000000,0) -> 0.033060569 | E39: =_xlfn.IFERROR(E37/20000000,0) -> 0.050653391 | F39: =_xlfn.IFERROR(C39-D39,0) -> -0.037280129 | G39: =_xlfn.IFERROR(E39-D39,0) -> 0.017592822
B42: SINGLE VARIABLE SENSITIVITY - NOI IMPACT
B44: Rent Growth Impact on NOI
B45: Rent Growth | C45: -0.02 | D45: 0 | E45: 0.02 | F45: 0.03 | G45: 0.04 | H45: 0.05
B46: NOI ($) | C46: 2096084.7 | D46: 2199818 | E46: 2303551.4 | F46: 2355418.1 | G46: 2407284.8 | H46: 2459151.4
B47: Δ vs Base | C47: =C46-E46 -> -207466.72 | D47: =D46-E46 -> -103733.36 | E47: =E46-E46 -> 0 | F47: =F46-E46 -> 51866.68 | G47: =G46-E46 -> 103733.36 | H47: =H46-E46 -> 155600.04
B49: Occupancy Impact on NOI
B50: Occupancy | C50: 0.88 | D50: 0.9 | E50: 0.93 | F50: 0.95 | G50: 0.97 | H50: 0.99
B51: NOI ($) | C51: 1961777.3 | D51: 2074246.1 | E51: 2242949.3 | F51: 2355418.1 | G51: 2467886.9 | H51: 2580355.7
B52: Δ vs Base | C52: =C51-F51 -> -393640.81 | D52: =D51-F51 -> -281172 | E52: =E51-F51 -> -112468.8 | F52: =F51-F51 -> 0 | G52: =G51-F51 -> 112468.8 | H52: =H51-F51 -> 224937.6
B55: TWO-WAY SENSITIVITY: NOI by Rent Growth × Occupancy
B56: NOI ($000s) | C56: 0 | D56: 0.02 | E56: 0.03 | F56: 0.04 | G56: 0.05
B57: 0.9 | C57: 1926.8355 | D57: 2025.1092 | E57: 2074.2461 | F57: 2123.3829 | G57: 2172.5198
B58: 0.92 | C58: 2036.0285 | D58: 2136.4861 | E58: 2186.7149 | F58: 2236.9437 | G58: 2287.1724
B59: 0.94 | C59: 2145.2215 | D59: 2247.863 | E59: 2299.1837 | F59: 2350.5044 | G59: 2401.8251
B60: 0.95 | C60: 2199.818 | D60: 2303.5514 | E60: 2355.4181 | F60: 2407.2848 | G60: 2459.1514
B61: 0.96 | C61: 2254.4145 | D61: 2359.2398 | E61: 2411.6525 | F61: 2464.0651 | G61: 2516.4778
B62: 0.98 | C62: 2363.6075 | D62: 2470.6167 | E62: 2524.1213 | F62: 2577.6259 | G62: 2631.1304
B65: KEY INSIGHTS & RISK ASSESSMENT | F65: SCENARIO VERDICT
B66: Metric | C66: Value | D66: Interpretation | F66: Downside: | G66: ⚠ HIGH RISK
B67: Breakeven Occupancy (at Base Rent) | C67: =($C$18*$C$15+$C$19)/($C$15*$C$16*12*1.03*1.04*0.98) -> 0.78492879 | D67: Minimum occupancy to cover OpEx + Debt | F67: Base Case: | G67: ✓ VIABLE
B68: Revenue per 1% Occupancy | C68: =$C$15*$C$16*12*1.03*1.04*0.98*0.01 -> 56234.401 | D68: $/year per 1% occupancy change | F68: Upside: | G68: ✓ STRONG
B69: Revenue per 1% Rent Growth | C69: =$C$15*$C$16*12*0.95*1.04*0.98*0.01 -> 51866.68 | D69: $/year per 1% rent change | F69: Probability: | G69: 20% / 60% / 20%
B70: DSCR Cushion (Base) | C70: =D38-1.2 -> 0.37307425 | D70: Buffer above 1.20x covenant
B71: Downside DSCR Risk | C71: =IF(C38<1.2,"⚠ COVENANT BREACH","✓ OK") -> ⚠ COVENANT BREACH | D71: Covenant check

Sheet Scenario_Comparison
B2: SCENARIO COMPARISON TOOL
B3: Side-by-Side Base vs Upside vs Downside Analysis | FY 2026 Projections
B5: SCENARIO DEFINITIONS
B6: Parameter | C6: 🔴 Downside | D6: 📊 Base Case | E6: 🟢 Upside | F6: Probability
B7: Rent Growth | C7: =-1.0% -> -0.01 | D7: 3.0% | E7: 5.0% | F7: 0
B8: Occupancy | C8: 90.0% | D8: 95.0% | E8: 97.0% | F8: 0
B9: Expense Growth | C9: 5.0% | D9: 2.5% | E9: 1.5% | F9: 0
B10: Bad Debt | C10: 4.0% | D10: 2.0% | E10: 1.0% | F10: 0
B11: Probability Weight | C11: 20% | D11: 60% | E11: 20% | F11: 100%
B14: FINANCIAL PROJECTIONS
B15: Metric | C15: 🔴 Downside | D15: 📊 Base Case | E15: 🟢 Upside | F15: Down vs Base | G15: Up vs Base | H15: Prob-Wtd Value
B16: Gross Potential Rent | C16: =_xlfn.IFERROR(Sensitivity_Analysis!C24,0) -> 5303232 | D16: =_xlfn.IFERROR(Sensitivity_Analysis!D24,0) -> 5517504 | E16: =_xlfn.IFERROR(Sensitivity_Analysis!E24,0) -> 5624640 | F16: =_xlfn.IFERROR(C16-D16,0) -> -214272 | G16: =_xlfn.IFERROR(E16-D16,0) -> 107136 | H16: =_xlfn.IFERROR(C16*0.2+D16*0.6+E16*0.2,0) -> 5496076.8
B17: Effective Revenue | C17: =_xlfn.IFERROR(Sensitivity_Analysis!C25,0) -> 4772908.8 | D17: =_xlfn.IFERROR(Sensitivity_Analysis!D25,0) -> 5241628.8 | E17: =_xlfn.IFERROR(Sensitivity_Analysis!E25,0) -> 5455900.8 | F17: =_xlfn.IFERROR(C17-D17,0) -> -468720 | G17: =_xlfn.IFERROR(E17-D17,0) -> 214272 | H17: =_xlfn.IFERROR(C17*0.2+D17*0.6+E17*0.2,0) -> 5190739.2
B18: Other Income | C18: =_xlfn.IFERROR(Sensitivity_Analysis!C26,0) -> 190916.35 | D18: =_xlfn.IFERROR(Sensitivity_Analysis!D26,0) -> 209665.15 | E18: =_xlfn.IFERROR(Sensitivity_Analysis!E26,0) -> 218236.03 | F18: =_xlfn.IFERROR(C18-D18,0) -> -18748.8 | G18: =_xlfn.IFERROR(E18-D18,0) -> 8570.88 | H18: =_xlfn.IFERROR(C18*0.2+D18*0.6+E18*0.2,0) -> 207629.57
B19: Less: Bad Debt | C19: =_xlfn.IFERROR(Sensitivity_Analysis!C27,0) -> -190916.35 | D19: =_xlfn.IFERROR(Sensitivity_Analysis!D27,0) -> -104832.58 | E19: =_xlfn.IFERROR(Sensitivity_Analysis!E27,0) -> -54559.008 | F19: =_xlfn.IFERROR(C19-D19,0) -> -86083.776 | G19: =_xlfn.IFERROR(E19-D19,0) -> 50273.568 | H19: =_xlfn.IFERROR(C19*0.2+D19*0.6+E19*0.2,0) -> -111994.62
B20: Total Revenue | C20: =_xlfn.IFERROR(Sensitivity_Analysis!C28,0) -> 4772908.8 | D20: =_xlfn.IFERROR(Sensitivity_Analysis!D28,0) -> 5346461.4 | E20: =_xlfn.IFERROR(Sensitivity_Analysis!E28,0) -> 5619577.8 | F20: =_xlfn.IFERROR(C20-D20,0) -> -573552.58 | G20: =_xlfn.IFERROR(E20-D20,0) -> 273116.45 | H20: =_xlfn.IFERROR(C20*0.2+D20*0.6+E20*0.2,0) -> 5286374.2
B21: Operating Expenses | C21: =_xlfn.IFERROR(Sensitivity_Analysis!C30,0) -> 3059700 | D21: =_xlfn.IFERROR(Sensitivity_Analysis!D30,0) -> 2986850 | E21: =_xlfn.IFERROR(Sensitivity_Analysis!E30,0) -> 2957710 | F21: =_xlfn.IFERROR(C21-D21,0) -> 72850 | G21: =_xlfn.IFERROR(E21-D21,0) -> -29140 | H21: =_xlfn.IFERROR(C21*0.2+D21*0.6+E21*0.2,0) -> 2995592
B22: Net Operating Income | C22: =_xlfn.IFERROR(Sensitivity_Analysis!C33,0) -> 1713208.8 | D22: =_xlfn.IFERROR(Sensitivity_Analysis!D33,0) -> 2359611.4 | E22: =_xlfn.IFERROR(Sensitivity_Analysis!E33,0) -> 2661867.8 | F22: =_xlfn.IFERROR(C22-D22,0) -> -646402.58 | G22: =_xlfn.IFERROR(E22-D22,0) -> 302256.45 | H22: =_xlfn.IFERROR(C22*0.2+D22*0.6+E22*0.2,0) -> 2290782.2
B23: Capital Expenditures | C23: =_xlfn.IFERROR(Sensitivity_Analysis!C31,0) -> 297600 | D23: =_xlfn.IFERROR(Sensitivity_Analysis!D31,0) -> 198400 | E23: =_xlfn.IFERROR(Sensitivity_Analysis!E31,0) -> 148800 | F23: =_xlfn.IFERROR(C23-D23,0) -> 99200 | G23: =_xlfn.IFERROR(E23-D23,0) -> -49600 | H23: =_xlfn.IFERROR(C23*0.2+D23*0.6+E23*0.2,0) -> 208320
B24: Debt Service | C24: =_xlfn.IFERROR(Sensitivity_Analysis!C36,0) -> 1500000 | D24: =_xlfn.IFERROR(Sensitivity_Analysis!D36,0) -> 1500000 | E24: =_xlfn.IFERROR(Sensitivity_Analysis!E36,0) -> 1500000 | F24: =_xlfn.IFERROR(C24-D24,0) -> 0 | G24: =_xlfn.IFERROR(E24-D24,0) -> 0 | H24: =_xlfn.IFERROR(C24*0.2+D24*0.6+E24*0.2,0) -> 1500000
B25: Net Cash Flow | C25: =_xlfn.IFERROR(Sensitivity_Analysis!C37,0) -> -84391.2 | D25: =_xlfn.IFERROR(Sensitivity_Analysis!D37,0) -> 661211.38 | E25: =_xlfn.IFERROR(Sensitivity_Analysis!E37,0) -> 1013067.8 | F25: =_xlfn.IFERROR(C25-D25,0) -> -745602.58 | G25: =_xlfn.IFERROR(E25-D25,0) -> 351856.45 | H25: =_xlfn.IFERROR(C25*0.2+D25*0.6+E25*0.2,0) -> 582462.15
B28: KEY PERFORMANCE METRICS
B29: Metric | C29: 🔴 Downside | D29: 📊 Base Case | E29: 🟢 Upside | F29: Covenant/Target | G29: Status
B30: NOI Margin | C30: =_xlfn.IFERROR(C22/C20,0) -> 0.35894438 | D30: =_xlfn.IFERROR(D22/D20,0) -> 0.44134077 | E30: =_xlfn.IFERROR(E22/E20,0) -> 0.47367754 | G30: =_xlfn.IFERROR(IF(D30>=0.45,"✓ Pass","✗ Below"),0) -> ✗ Below
B31: DSCR | C31: =_xlfn.IFERROR(Sensitivity_Analysis!C38,0) -> 1.1421392 | D31: =_xlfn.IFERROR(Sensitivity_Analysis!D38,0) -> 1.5730743 | E31: =_xlfn.IFERROR(Sensitivity_Analysis!E38,0) -> 1.7745785 | G31: =_xlfn.IFERROR(IF(D31>=1.2,"✓ Pass","✗ BREACH"),0) -> ✓ Pass
B32: Cash-on-Cash Return | C32: =_xlfn.IFERROR(Sensitivity_Analysis!C39,0) -> -0.00421956 | D32: =_xlfn.IFERROR(Sensitivity_Analysis!D39,0) -> 0.033060569 | E32: =_xlfn.IFERROR(Sensitivity_Analysis!E39,0) -> 0.050653391 | G32: =_xlfn.IFERROR(IF(D32>=0.05,"✓ Target","⚠ Below"),0) -> ⚠ Below
B33: Yield on Cost | C33: =_xlfn.IFERROR(C22/50000000,0) -> 0.034264176 | D33: =_xlfn.IFERROR(D22/50000000,0) -> 0.047192228 | E33: =_xlfn.IFERROR(E22/50000000,0) -> 0.053237356 | G33: =_xlfn.IFERROR(IF(D33>=0.05,"✓ Target","⚠ Below"),0) -> ⚠ Below
B34: Breakeven Occupancy | C34: =_xlfn.IFERROR(Sensitivity_Analysis!C67,0) -> 0.78492879 | D34: =_xlfn.IFERROR(Sensitivity_Analysis!C67,0) -> 0.78492879 | E34: =_xlfn.IFERROR(Sensitivity_Analysis!C67,0) -> 0.78492879 | G34: =_xlfn.IFERROR(IF(D34<0.85,"✓ OK","⚠ High"),0) -> ✓ OK
B37: VARIANCE ANALYSIS - DOWNSIDE VS BASE
B38: Driver | C38: $ Impact | D38: % Impact | E38: Root Cause
B39: Revenue Impact | C39: =C20-D20 -> -573552.58 | D39: =F20/D20 -> -0.10727704 | E39: Rent decline + higher vacancy
B40: Expense Impact | C40: =C21-D21 -> 72850 | D40: =F21/D21 -> 0.024390244 | E40: Higher inflation on OpEx
B41: NOI Impact | C41: =C22-D22 -> -646402.58 | D41: =F22/D22 -> -0.27394451 | E41: Combined revenue/expense effect
B42: Cash Flow Impact | C42: =C25-D25 -> -745602.58 | D42: =F25/D25 -> -1.1276312 | E42: After debt service
B44: VARIANCE ANALYSIS - UPSIDE VS BASE
B45: Driver | C45: $ Impact | D45: % Impact | E45: Root Cause
B46: Revenue Impact | C46: =E20-D20 -> 273116.45 | D46: =G20/D20 -> 0.051083591 | E46: Rent growth + higher occupancy
B47: Expense Impact | C47: =E21-D21 -> -29140 | D47: =G21/D21 -> -0.0097560976 | E47: Lower inflation + efficiencies
B48: NOI Impact | C48: =E22-D22 -> 302256.45 | D48: =G22/D22 -> 0.12809586 | E48: Combined favorable effects
B49: Cash Flow Impact | C49: =E25-D25 -> 351856.45 | D49: =G25/D25 -> 0.53213913 | E49: After lower CapEx
B52: EXECUTIVE SUMMARY & RECOMMENDATION
B54: SCENARIO VERDICTS | E54: RISK MITIGATION STRATEGIES
B55: Downside: | C55: ⚠ HIGH RISK - Negative cash flow, near-breach DSCR | E55: 1. Maintain 95% occupancy through proactive leasing
B56: Base Case: | C56: ✓ VIABLE - Positive returns, comfortable DSCR cushion | E56: 2. Lock in multi-year vendor contracts to control OpEx
B57: Upside: | C57: ✓ STRONG - Exceeds all targets, attractive returns | E57: 3. Build 6-month debt service reserve ($750K)
E58: 4. Monitor leading indicators weekly (traffic, apps)
B60: INVESTMENT DECISION MATRIX
B61: If Scenario → | C61: Then Action
B62: Downside materializes | C62: Reduce CapEx, defer non-critical projects, tighten collections
B63: Base Case tracking | C63: Proceed with planned investments, maintain reserves
B64: Upside materializes | C64: Accelerate value-add CapEx, consider acquisition opportunities
B66: RECOMMENDATION: | C66: PROCEED with Base Case assumptions. Probability-weighted NOI of $2.29M supports investment thesis. Monitor occupancy and rent trends monthly.

Sheet Variance_Trends
B2: VARIANCE TREND ANALYSIS
B3: 12-Month History: Actual vs Budget vs Forecast by Cost Center | Feb 2025 - Jan 2026
B5: TOTAL REVENUE TREND
B6: Series | C6: Feb-25 | D6: Mar-25 | E6: Apr-25 | F6: May-25 | G6: Jun-25 | H6: Jul-25 | I6: Aug-25 | J6: Sep-25 | K6: Oct-25 | L6: Nov-25 | M6: Dec-25 | N6: Jan-26 | O6: YTD
B7: Actual | C7: 458000 | D7: 462000 | E7: 468000 | F7: 472000 | G7: 475000 | H7: 478000 | I7: 480000 | J7: 482000 | K7: 485000 | L7: 488000 | M7: 490000 | N7: 471200 | O7: =SUM(C7:N7) -> 5709200
B8: Budget | C8: 455000 | D8: 458000 | E8: 462000 | F8: 465000 | G8: 468000 | H8: 472000 | I8: 475000 | J8: 478000 | K8: 480000 | L8: 482000 | M8: 485000 | N8: 470000 | O8: =SUM(C8:N8) -> 5650000
B9: Forecast | C9: 456000 | D9: 460000 | E9: 465000 | F9: 470000 | G9: 473000 | H9: 476000 | I9: 479000 | J9: 481000 | K9: 484000 | L9: 487000 | M9: 489000 | N9: 471000 | O9: =SUM(C9:N9) -> 5691000
B10: Var % (A vs B) | C10: =_xlfn.IFERROR((C7-C8)/C8,0) -> 0.0065934066 | D10: =_xlfn.IFERROR((D7-D8)/D8,0) -> 0.0087336245 | E10: =_xlfn.IFERROR((E7-E8)/E8,0) -> 0.012987013 | F10: =_xlfn.IFERROR((F7-F8)/F8,0) -> 0.015053763 | G10: =_xlfn.IFERROR((G7-G8)/G8,0) -> 0.014957265 | H10: =_xlfn.IFERROR((H7-H8)/H8,0) -> 0.012711864 | I10: =_xlfn.IFERROR((I7-I8)/I8,0) -> 0.010526316 | J10: =_xlfn.IFERROR((J7-J8)/J8,0) -> 0.0083682008 | ... O10: =_xlfn.IFERROR((O7-O8)/O8,0) -> 0.010477876
B13: OPERATING EXPENSES TREND
B14: Series | C14: Feb-25 | D14: Mar-25 | E14: Apr-25 | F14: May-25 | G14: Jun-25 | H14: Jul-25 | I14: Aug-25 | J14: Sep-25 | K14: Oct-25 | L14: Nov-25 | M14: Dec-25 | N14: Jan-26 | O14: YTD
B15: Actual | C15: 235000 | D15: 238000 | E15: 242000 | F15: 240000 | G15: 245000 | H15: 248000 | I15: 252000 | J15: 250000 | K15: 248000 | L15: 245000 | M15: 242000 | N15: 238300 | O15: =SUM(C15:N15) -> 2923300
B16: Budget | C16: 240000 | D16: 242000 | E16: 245000 | F16: 248000 | G16: 250000 | H16: 252000 | I16: 255000 | J16: 258000 | K16: 260000 | L16: 262000 | M16: 265000 | N16: 248000 | O16: =SUM(C16:N16) -> 3025000
B17: Forecast | C17: 238000 | D17: 240000 | E17: 243000 | F17: 245000 | G17: 248000 | H17: 250000 | I17: 253000 | J17: 255000 | K17: 257000 | L17: 259000 | M17: 261000 | N17: 245000 | O17: =SUM(C17:N17) -> 2994000
B18: Var % (A vs B) | C18: =_xlfn.IFERROR((C15-C16)/C16,0) -> -0.020833333 | D18: =_xlfn.IFERROR((D15-D16)/D16,0) -> -0.016528926 | E18: =_xlfn.IFERROR((E15-E16)/E16,0) -> -0.012244898 | F18: =_xlfn.IFERROR((F15-F16)/F16,0) -> -0.032258065 | G18: =_xlfn.IFERROR((G15-G16)/G16,0) -> -0.02 | H18: =_xlfn.IFERROR((H15-H16)/H16,0) -> -0.015873016 | I18: =_xlfn.IFERROR((I15-I16)/I16,0) -> -0.011764706 | J18: =_xlfn.IFERROR((J15-J16)/J16,0) -> -0.031007752 | ... O18: =_xlfn.IFERROR((O15-O16)/O16,0) -> -0.033619835
B21: NET OPERATING INCOME TREND
B22: Series | C22: Feb-25 | D22: Mar-25 | E22: Apr-25 | F22: May-25 | G22: Jun-25 | H22: Jul-25 | I22: Aug-25 | J22: Sep-25 | K22: Oct-25 | L22: Nov-25 | M22: Dec-25 | N22: Jan-26 | O22: YTD
